Workbook

Sheet Dashboard
A1: FAMOUS BRANDS LIMITED — DUE DILIGENCE TRACKER
A3: Growth Equity | Deal Size: R13.0bn | South Africa / Pan-Africa | Date: 17 Mar 2026
A5: WORKSTREAM PROGRESS SUMMARY
A6: Workstream | B6: Sheet | C6: Total Items | D6: Not Started | E6: In Progress | F6: Complete | G6: Red Flags | H6: % Complete | I6: P0 Outstanding | J6: Status
A7: Financial DD | B7: Financial DD | C7: =COUNTA('Financial DD'!$A$3:$A$100) -> 24 | D7: =COUNTIF('Financial DD'!$F$3:$F$100,"Not Started") -> 20 | E7: =COUNTIF('Financial DD'!$F$3:$F$100,"Requested")+COUNTIF('Financial DD'!$F$3:$F$100,"Received")+COUNTIF('Financial DD'!$F$3:$F$100,"In Review") -> 0 | F7: =COUNTIF('Financial DD'!$F$3:$F$100,"Complete") -> 0 | G7: =COUNTIF('Financial DD'!$F$3:$F$100,"Red Flag") -> 0 | H7: =IF(C7=0,0,F7/C7) -> 0 | I7: =COUNTIFS('Financial DD'!$E$3:$E$100,"P0 - Gating",'Financial DD'!$F$3:$F$100,"<>Complete",'Financial DD'!$F$3:$F$100,"<>Red Flag") -> 11 | J7: =IF(G7>0,"🚩 Red Flag",IF(H7=1,"✅ Complete",IF(H7>=0.5,"🔄 In Progress","⬜ Not Started"))) -> ⬜ Not Started
A8: Commercial DD | B8: Commercial DD | C8: =COUNTA('Commercial DD'!$A$3:$A$100) -> 22 | D8: =COUNTIF('Commercial DD'!$F$3:$F$100,"Not Started") -> 18 | E8: =COUNTIF('Commercial DD'!$F$3:$F$100,"Requested")+COUNTIF('Commercial DD'!$F$3:$F$100,"Received")+COUNTIF('Commercial DD'!$F$3:$F$100,"In Review") -> 0 | F8: =COUNTIF('Commercial DD'!$F$3:$F$100,"Complete") -> 0 | G8: =COUNTIF('Commercial DD'!$F$3:$F$100,"Red Flag") -> 0 | H8: =IF(C8=0,0,F8/C8) -> 0 | I8: =COUNTIFS('Commercial DD'!$E$3:$E$100,"P0 - Gating",'Commercial DD'!$F$3:$F$100,"<>Complete",'Commercial DD'!$F$3:$F$100,"<>Red Flag") -> 8 | J8: =IF(G8>0,"🚩 Red Flag",IF(H8=1,"✅ Complete",IF(H8>=0.5,"🔄 In Progress","⬜ Not Started"))) -> ⬜ Not Started
A9: Legal DD | B9: Legal DD | C9: =COUNTA('Legal DD'!$A$3:$A$100) -> 18 | D9: =COUNTIF('Legal DD'!$F$3:$F$100,"Not Started") -> 15 | E9: =COUNTIF('Legal DD'!$F$3:$F$100,"Requested")+COUNTIF('Legal DD'!$F$3:$F$100,"Received")+COUNTIF('Legal DD'!$F$3:$F$100,"In Review") -> 0 | F9: =COUNTIF('Legal DD'!$F$3:$F$100,"Complete") -> 0 | G9: =COUNTIF('Legal DD'!$F$3:$F$100,"Red Flag") -> 0 | H9: =IF(C9=0,0,F9/C9) -> 0 | I9: =COUNTIFS('Legal DD'!$E$3:$E$100,"P0 - Gating",'Legal DD'!$F$3:$F$100,"<>Complete",'Legal DD'!$F$3:$F$100,"<>Red Flag") -> 8 | J9: =IF(G9>0,"🚩 Red Flag",IF(H9=1,"✅ Complete",IF(H9>=0.5,"🔄 In Progress","⬜ Not Started"))) -> ⬜ Not Started
A10: Operational DD | B10: Operational DD | C10: =COUNTA('Operational DD'!$A$3:$A$100) -> 16 | D10: =COUNTIF('Operational DD'!$F$3:$F$100,"Not Started") -> 13 | E10: =COUNTIF('Operational DD'!$F$3:$F$100,"Requested")+COUNTIF('Operational DD'!$F$3:$F$100,"Received")+COUNTIF('Operational DD'!$F$3:$F$100,"In Review") -> 0 | F10: =COUNTIF('Operational DD'!$F$3:$F$100,"Complete") -> 0 | G10: =COUNTIF('Operational DD'!$F$3:$F$100,"Red Flag") -> 0 | H10: =IF(C10=0,0,F10/C10) -> 0 | I10: =COUNTIFS('Operational DD'!$E$3:$E$100,"P0 - Gating",'Operational DD'!$F$3:$F$100,"<>Complete",'Operational DD'!$F$3:$F$100,"<>Red Flag") -> 4 | J10: =IF(G10>0,"🚩 Red Flag",IF(H10=1,"✅ Complete",IF(H10>=0.5,"🔄 In Progress","⬜ Not Started"))) -> ⬜ Not Started
A11: HR & People DD | B11: HR & People DD | C11: =COUNTA('HR & People DD'!$A$3:$A$100) -> 13 | D11: =COUNTIF('HR & People DD'!$F$3:$F$100,"Not Started") -> 10 | E11: =COUNTIF('HR & People DD'!$F$3:$F$100,"Requested")+COUNTIF('HR & People DD'!$F$3:$F$100,"Received")+COUNTIF('HR & People DD'!$F$3:$F$100,"In Review") -> 0 | F11: =COUNTIF('HR & People DD'!$F$3:$F$100,"Complete") -> 0 | G11: =COUNTIF('HR & People DD'!$F$3:$F$100,"Red Flag") -> 0 | H11: =IF(C11=0,0,F11/C11) -> 0 | I11: =COUNTIFS('HR & People DD'!$E$3:$E$100,"P0 - Gating",'HR & People DD'!$F$3:$F$100,"<>Complete",'HR & People DD'!$F$3:$F$100,"<>Red Flag") -> 2 | J11: =IF(G11>0,"🚩 Red Flag",IF(H11=1,"✅ Complete",IF(H11>=0.5,"🔄 In Progress","⬜ Not Started"))) -> ⬜ Not Started
A12: IT & Technology DD | B12: IT & Tech DD | C12: =COUNTA('IT & Tech DD'!$A$3:$A$100) -> 15 | D12: =COUNTIF('IT & Tech DD'!$F$3:$F$100,"Not Started") -> 12 | E12: =COUNTIF('IT & Tech DD'!$F$3:$F$100,"Requested")+COUNTIF('IT & Tech DD'!$F$3:$F$100,"Received")+COUNTIF('IT & Tech DD'!$F$3:$F$100,"In Review") -> 0 | F12: =COUNTIF('IT & Tech DD'!$F$3:$F$100,"Complete") -> 0 | G12: =COUNTIF('IT & Tech DD'!$F$3:$F$100,"Red Flag") -> 0 | H12: =IF(C12=0,0,F12/C12) -> 0 | I12: =COUNTIFS('IT & Tech DD'!$E$3:$E$100,"P0 - Gating",'IT & Tech DD'!$F$3:$F$100,"<>Complete",'IT & Tech DD'!$F$3:$F$100,"<>Red Flag") -> 1 | J12: =IF(G12>0,"🚩 Red Flag",IF(H12=1,"✅ Complete",IF(H12>=0.5,"🔄 In Progress","⬜ Not Started"))) -> ⬜ Not Started
A13: ESG & Regulatory | B13: ESG DD | C13: =COUNTA('ESG DD'!$A$3:$A$100) -> 16 | D13: =COUNTIF('ESG DD'!$F$3:$F$100,"Not Started") -> 13 | E13: =COUNTIF('ESG DD'!$F$3:$F$100,"Requested")+COUNTIF('ESG DD'!$F$3:$F$100,"Received")+COUNTIF('ESG DD'!$F$3:$F$100,"In Review") -> 0 | F13: =COUNTIF('ESG DD'!$F$3:$F$100,"Complete") -> 0 | G13: =COUNTIF('ESG DD'!$F$3:$F$100,"Red Flag") -> 0 | H13: =IF(C13=0,0,F13/C13) -> 0 | I13: =COUNTIFS('ESG DD'!$E$3:$E$100,"P0 - Gating",'ESG DD'!$F$3:$F$100,"<>Complete",'ESG DD'!$F$3:$F$100,"<>Red Flag") -> 3 | J13: =IF(G13>0,"🚩 Red Flag",IF(H13=1,"✅ Complete",IF(H13>=0.5,"🔄 In Progress","⬜ Not Started"))) -> ⬜ Not Started
A14: Consumer / Franchise | B14: Consumer DD | C14: =COUNTA('Consumer DD'!$A$3:$A$100) -> 19 | D14: =COUNTIF('Consumer DD'!$F$3:$F$100,"Not Started") -> 15 | E14: =COUNTIF('Consumer DD'!$F$3:$F$100,"Requested")+COUNTIF('Consumer DD'!$F$3:$F$100,"Received")+COUNTIF('Consumer DD'!$F$3:$F$100,"In Review") -> 0 | F14: =COUNTIF('Consumer DD'!$F$3:$F$100,"Complete") -> 0 | G14: =COUNTIF('Consumer DD'!$F$3:$F$100,"Red Flag") -> 0 | H14: =IF(C14=0,0,F14/C14) -> 0 | I14: =COUNTIFS('Consumer DD'!$E$3:$E$100,"P0 - Gating",'Consumer DD'!$F$3:$F$100,"<>Complete",'Consumer DD'!$F$3:$F$100,"<>Red Flag") -> 5 | J14: =IF(G14>0,"🚩 Red Flag",IF(H14=1,"✅ Complete",IF(H14>=0.5,"🔄 In Progress","⬜ Not Started"))) -> ⬜ Not Started
A15: TOTAL | C15: =SUM(C7:C14) -> 143 | D15: =SUM(D7:D14) -> 116 | E15: =SUM(E7:E14) -> 0 | F15: =SUM(F7:F14) -> 0 | G15: =SUM(G7:G14) -> 0 | H15: =IF(C15=0,0,F15/C15) -> 0 | I15: =SUM(I7:I14) -> 42
A17: KEY DEAL PARAMETERS
A18: Target Company | B18: Famous Brands Limited (JSE: FBR)
A19: Sector | B19: Consumer / QSR & Casual Dining Franchisor
A20: Deal Type | B20: Growth Equity (Minority Stake)
A21: Deal Size | B21: R13.0bn
A22: Geography | B22: South Africa (primary), Sub-Saharan Africa, Middle East
A23: Key Concern | B23: Customer / Franchisee Concentration; Brand Concentration
A24: LOI Target | B24: TBC
A25: Close Target | B25: TBC
A26: Lead Advisor | B26: TBC
A27: DD Status | B27: Initiated

Sheet Financial DD
A1: Famous Brands — Financial DD
A2: # | B2: Due Diligence Item | C2: Description / Request | D2: Data Room Ref | E2: Priority | F2: Status | G2: Owner | H2: Due Date | I2: Notes / Red Flag Detail
A3: QUALITY OF EARNINGS (QOE)
A4: 1 | B4: QoE Report — Management Accounts | C4: Obtain FY2022–FY2025 audited financials + management accounts. IFRS-compliant. Focus on recurring vs. non-recurring items. | E4: P0 - Gating | F4: Not Started
A5: 2 | B5: Revenue Bridge — Organic vs. Inorganic | C5: Decompose revenue growth by: new restaurant openings, same-store sales growth (SSSG), royalty rate changes, manufacturing volumes. | E5: P0 - Gating | F5: Not Started
A6: 3 | B6: EBITDA Adjustments & Normalisation | C6: Identify one-off costs (GBK write-down residuals, restructuring, COVID relief, IFRS 16 lease reclassifications), management add-backs. | E6: P0 - Gating | F6: Not Started
A7: 4 | B7: IFRS 16 Lease Analysis | C7: Quantify right-of-use assets and lease liabilities. Understand impact on reported EBITDA vs. EBITDAL. Key given franchise model. | E7: P1 - High | F7: Not Started
A8: 5 | B8: Manufacturing Division P&L | C8: Separate Logistical Services (manufacturing, distribution) P&L from franchise segment. Assess intercompany pricing / transfer pricing. | E8: P0 - Gating | F8: Not Started
A9: 6 | B9: Royalty & Franchise Fee Revenue Quality | C9: Validate royalty rate structures by brand. Identify fixed vs. % of turnover fees. Confirm royalty collection history and bad debts. | E9: P0 - Gating | F9: Not Started
A10: 7 | B10: Supply Chain Revenue Concentration | C10: Assess revenue concentration by brand and franchisee group within manufacturing segment. | E10: P0 - Gating | F10: Not Started
A11: WORKING CAPITAL & CASH FLOW
A12: 8 | B12: Normalised Working Capital Analysis | C12: 12-month trailing working capital. Identify seasonal peaks (December trading). Peg for SPA locked-box / completion accounts. | E12: P0 - Gating | F12: Not Started
A13: 9 | B13: Capex — Maintenance vs. Growth | C13: Split capex between: company-owned restaurant refurbs, manufacturing plant, IT systems, and growth (new territories). | E13: P1 - High | F13: Not Started
A14: 10 | B14: Free Cash Flow Conversion | C14: FCF = EBITDA – capex – working capital movements – tax paid. Target >75% conversion vs. EBITDA. | E14: P1 - High | F14: Not Started
A15: 11 | B15: Dividend History & Capital Allocation | C15: Review JSE dividend announcements, special dividends, and share buyback history (FY2019–FY2025). | E15: P2 - Medium | F15: Not Started
A16: DEBT, TAX & BALANCE SHEET
A17: 12 | B17: Net Debt & Debt-Like Items | C17: Full net debt schedule including: borrowings, IFRS 16 lease liabilities, deferred consideration, contingent liabilities. | E17: P0 - Gating | F17: Not Started
A18: 13 | B18: Pension / Retirement Fund Obligations | C18: South African pension fund actuarial surplus/deficit. Any defined benefit exposure. | E18: P1 - High | F18: Not Started
A19: 14 | B19: Tax Compliance — SARS | C19: Confirm SARS compliance: PAYE, VAT, income tax. Any outstanding assessments or disputes. Section 45 / group restructuring history. | E19: P0 - Gating | F19: Not Started
A20: 15 | B20: Deferred Tax & Tax Losses | C20: Identify any unused tax losses (carry-forward). Understand temporary differences from accelerated depreciation. | E20: P1 - High | F20: Not Started
A21: 16 | B21: Currency Exposure — Sub-Saharan Africa | C21: Quantify revenues and EBITDA in non-ZAR currencies (Namibia, Botswana, Zambia, Ghana, Nigeria, Middle East). | E21: P1 - High | F21: Not Started
A22: 17 | B22: Audit History & Accounting Policies | C22: Review last 3 audit reports (PwC / Deloitte). Any qualified opinions, emphasis of matter, or restatements. | E22: P0 - Gating | F22: Not Started
A23: PRO FORMA & PROJECTIONS
A24: 18 | B24: Management Case Financial Projections (FY2025–FY2029) | C24: Obtain management's 5-year plan. Stress-test SSSG assumptions, new restaurant rollout plan, and margin targets. | E24: P0 - Gating | F24: Not Started
A25: 19 | B25: Run-Rate & Synergy Adjustments | C25: Identify any cost-out opportunities or synergies relevant to the equity story (efficiency, supply chain leverage, digital). | E25: P2 - Medium | F25: Not Started
A26: 20 | B26: Sensitivity Analysis — ZAR/Consumer | C26: Model downside scenarios: consumer spending contraction, load-shedding impact, rand depreciation. | E26: P1 - High | F26: Not Started

Sheet Commercial DD
A1: Famous Brands — Commercial DD
A2: # | B2: Due Diligence Item | C2: Description / Request | D2: Data Room Ref | E2: Priority | F2: Status | G2: Owner | H2: Due Date | I2: Notes / Red Flag Detail
A3: MARKET & INDUSTRY
A4: 1 | B4: South African QSR Market Size & Growth | C4: TAM for SA QSR and casual dining. Historical growth (2018–2025). Impact of load-shedding on foot traffic and delivery volumes. | E4: P0 - Gating | F4: Not Started
A5: 2 | B5: Consumer Spending Outlook | C5: SA consumer confidence, disposable income trends, unemployment (35%+). Impact on trading in key LSM segments. | E5: P1 - High | F5: Not Started
A6: 3 | B6: Delivery & Digital Market Shift | C6: Assessment of third-party delivery (Uber Eats, Mr D) as % of brand revenue. Competitive dynamics vs. pure-play digital players. | E6: P1 - High | F6: Not Started
A7: 4 | B7: Pan-African & Middle East Growth Opportunity | C7: TAM for SSA expansion. Current footprint: Ghana, Nigeria, Kenya, Mauritius, Namibia, Botswana, Middle East. Growth pipeline. | E7: P1 - High | F7: Not Started
A8: COMPETITIVE POSITIONING
A9: 5 | B9: Brand Portfolio Competitive Map | C9: Map Wimpy, Steers, Debonairs, Mugg & Bean, Fishaways, Tashas against competitors: McDonald's, KFC, Nando's, Spur, RCL Foods. | E9: P0 - Gating | F9: Not Started
A10: 6 | B10: Market Share by Brand & Segment | C10: Estimated market share by: burger QSR, pizza, fish, chicken, casual dining. Source: Euromonitor / NPD / internal data. | E10: P1 - High | F10: Not Started
A11: 7 | B11: Franchisee Satisfaction Survey | C11: Obtain or commission franchisee NPS survey. Red flag: franchisee grievances, non-renewals, system exits. | E11: P0 - Gating | F11: Not Started
A12: 8 | B12: Brand Health Tracking | C12: Consumer brand awareness, consideration, preference metrics by brand. Key vs. Nando's and McDonald's. | E12: P1 - High | F12: Not Started
A13: CUSTOMER & FRANCHISEE CONCENTRATION (KEY RISK)
A14: 9 | B14: Top 20 Franchisee Concentration Analysis | C14: PRIORITY: Identify top 20 franchisees by number of restaurants and revenue contribution. Concentration risk if top 3-5 represent >20% of system. | E14: P0 - Gating | F14: Not Started
A15: 10 | B15: Multi-Unit Franchisee (MUF) Agreements | C15: Review terms for multi-unit operators. Rights of first refusal, territory exclusivity, performance covenants. | E15: P0 - Gating | F15: Not Started
A16: 11 | B16: Franchisee Financial Health | C16: Request anonymised franchisee P&L data. Assess viability (4-wall EBITDA margins). Red flag: franchisee distress could accelerate exits. | E16: P0 - Gating | F16: Not Started
A17: 12 | B17: Brand Concentration by Revenue | C17: What % of total system sales does Steers + Wimpy + Debonairs represent? Risk if legacy brands decline vs. premium (Tashas). | E17: P0 - Gating | F17: Not Started
A18: 13 | B18: Contract Renewal & Retention Rate | C18: Franchisee renewal rate over last 5 years, by brand. Non-renewal reasons. | E18: P1 - High | F18: Not Started
A19: 14 | B19: New Franchisee Pipeline | C19: Number of signed franchise agreements not yet open. Geographic split. Pipeline coverage ratio. | E19: P1 - High | F19: Not Started
A20: PRICING, SALES & PIPELINE
A21: 15 | B21: Menu Price Inflation History | C21: Annual menu price increases vs. CPI, vs. SARB food inflation. Elasticity analysis. | E21: P1 - High | F21: Not Started
A22: 16 | B22: Same-Store Sales Growth (SSSG) by Brand | C22: Monthly SSSG for last 36 months by brand. Red flag: sustained negative SSSG in legacy QSR brands. | E22: P0 - Gating | F22: Not Started
A23: 17 | B23: Restaurant Development Pipeline | C23: New restaurant pipeline: signed, under construction, planned (12M / 24M). Split: South Africa vs. international. | E23: P1 - High | F23: Not Started
A24: 18 | B24: Go-to-Market & Advertising Fund | C24: Review National Advertising Fund (NAF) contributions, spend allocation, and franchisee disputes. | E24: P2 - Medium | F24: Not Started

Sheet Legal DD
A1: Famous Brands — Legal DD
A2: # | B2: Due Diligence Item | C2: Description / Request | D2: Data Room Ref | E2: Priority | F2: Status | G2: Owner | H2: Due Date | I2: Notes / Red Flag Detail
A3: CORPORATE STRUCTURE
A4: 1 | B4: Group Corporate Structure Chart | C4: Full legal entity map: holding company (Famous Brands Ltd), SA operating subsidiaries, international JV/franchise structures. | E4: P0 - Gating | F4: Not Started
A5: 2 | B5: JSE Listing & Shareholder Register | C5: Major shareholders (>5%), concert parties, institutional holders. Confirm no change-of-control provisions triggered. | E5: P0 - Gating | F5: Not Started
A6: 3 | B6: Subsidiaries & Joint Ventures | C6: List all subsidiaries, JVs, and associates. Focus on international structures (Middle East JV, African master franchise holders). | E6: P1 - High | F6: Not Started
A7: MATERIAL CONTRACTS
A8: 4 | B8: Master Franchise Agreements — International | C8: Review all international master franchise agreements. Terms: territory rights, royalty rates, development obligations, renewal options. | E8: P0 - Gating | F8: Not Started
A9: 5 | B9: SA Franchise Disclosure Documents (FDD) | C9: Compliance with SA Consumer Protection Act (CPA) franchise disclosure requirements. Last update date. | E9: P0 - Gating | F9: Not Started
A10: 6 | B10: Manufacturing Supply Agreements | C10: Key supply agreements between manufacturing division and franchisees. Transfer pricing, exclusivity, and price escalation clauses. | E10: P0 - Gating | F10: Not Started
A11: 7 | B11: Key Supplier Agreements | C11: Review top 10 supplier contracts (packaging, proteins, buns). Single-source risk, pricing mechanisms. | E11: P1 - High | F11: Not Started
A12: 8 | B12: Lease Portfolio Review | C12: Corporate-leased properties (manufacturing, support office). Remaining lease terms, break clauses, renewal options. | E12: P1 - High | F12: Not Started
A13: 9 | B13: Technology & Licensing Agreements | C13: POS system licenses, loyalty programme (Famous Rewards) IP, digital ordering platform agreements. | E13: P2 - Medium | F13: Not Started
A14: IP, COMPLIANCE & LITIGATION
A15: 10 | B15: Trademark Portfolio | C15: All brand trademarks registered in SA and key international markets. Any disputed marks (esp. Wimpy in UK/EU contexts). | E15: P0 - Gating | F15: Not Started
A16: 11 | B16: Litigation History | C16: All pending or threatened litigation. Focus on: franchisee disputes, employment claims, product liability, competition law. | E16: P1 - High | F16: Not Started
A17: 12 | B17: Competition Commission History | C17: Any prior investigations, settlements, or behavioural remedies under SA Competition Act. Sector has history of scrutiny. | E17: P0 - Gating | F17: Not Started
A18: 13 | B18: Consumer Protection Act (CPA) Compliance | C18: Review franchise disclosure compliance, cooling-off periods, food safety regulations (R638 Foodstuffs Regulations). | E18: P1 - High | F18: Not Started
A19: 14 | B19: Employment & Labour Law | C19: CCMA disputes, unfair dismissal claims. Compliance with BCEA, LRA, EEA. | E19: P1 - High | F19: Not Started
A20: 15 | B20: BBBEE Compliance | C20: Current BBBEE scorecard level and certificate. Ownership, management control, skills dev, enterprise/supplier dev components. | E20: P0 - Gating | F20: Not Started

Sheet Operational DD
A1: Famous Brands — Operational DD
A2: # | B2: Due Diligence Item | C2: Description / Request | D2: Data Room Ref | E2: Priority | F2: Status | G2: Owner | H2: Due Date | I2: Notes / Red Flag Detail
A3: MANAGEMENT & ORGANISATION
A4: 1 | B4: Executive Team Assessment | C4: CEO (Darren Hele or successor), CFO, COO, Brand MDs. Tenure, succession, contractual protections. | E4: P0 - Gating | F4: Not Started
A5: 2 | B5: Key Person Risk | C5: Identify top 5–10 key employees. Review notice periods, restraint of trade, retention incentives. | E5: P1 - High | F5: Not Started
A6: 3 | B6: Organisational Structure | C6: Headcount by function: brand management, marketing, operations support, manufacturing, finance, IT. | E6: P1 - High | F6: Not Started
A7: 4 | B7: Management Incentive Plan (MIP) | C7: Review LTI/STI structures. JSE-listed equity-settled share plan terms. Alignment with growth equity investor. | E7: P0 - Gating | F7: Not Started
A8: MANUFACTURING & SUPPLY CHAIN
A9: 5 | B9: Manufacturing Plant Assessment | C9: Review Midrand and other production facilities. Capacity utilisation, maintenance capex requirements, regulatory compliance. | E9: P0 - Gating | F9: Not Started
A10: 6 | B10: Load-Shedding Resilience | C10: Generator capacity at manufacturing plants. Impact of Eskom load-shedding on production schedules and uptime. | E10: P1 - High | F10: Not Started
A11: 7 | B11: Distribution Network | C11: Cold-chain and ambient distribution network. 3PL vs. owned fleet. Route-to-market efficiency. | E11: P1 - High | F11: Not Started
A12: 8 | B12: Food Safety & Quality Systems | C12: FSSC 22000 / HACCP certification status. Last audit results. Product recall history. | E12: P0 - Gating | F12: Not Started
A13: 9 | B13: Supplier Concentration Risk | C13: Single-source ingredient risk. Top 5 suppliers as % of COGS. Alternative sourcing options. | E13: P1 - High | F13: Not Started
A14: OPERATIONS & FRANCHISEE SUPPORT
A15: 10 | B15: Franchisee Operations Manual & Standards | C15: Review mystery shopper scores, QSC audit results by brand over last 3 years. | E15: P1 - High | F15: Not Started
A16: 11 | B16: Restaurant Technology (POS & Digital) | C16: POS system coverage and age. Integration with third-party delivery, loyalty (Famous Rewards), and back-office reporting. | E16: P2 - Medium | F16: Not Started
A17: 12 | B17: Training & Development Infrastructure | C17: Famous Brands Academy: capacity, franchisee training compliance rates, online vs. in-person capability. | E17: P2 - Medium | F17: Not Started
A18: 13 | B18: Insurance Coverage | C18: Product liability, property, business interruption, D&O, cyber. Adequacy of cover. | E18: P2 - Medium | F18: Not Started

Sheet HR & People DD
A1: Famous Brands — HR & People DD
A2: # | B2: Due Diligence Item | C2: Description / Request | D2: Data Room Ref | E2: Priority | F2: Status | G2: Owner | H2: Due Date | I2: Notes / Red Flag Detail
A3: WORKFORCE OVERVIEW
A4: 1 | B4: Headcount & FTE Analysis | C4: Corporate headcount (Famous Brands Ltd employees, not franchisees). By department and geography. Trend FY2021–FY2025. | E4: P1 - High | F4: Not Started
A5: 2 | B5: Employment Equity (EE) Report | C5: EEA2 / EEA4 reports. Top management and senior management transformation targets vs. actual. | E5: P0 - Gating | F5: Not Started
A6: 3 | B6: Remuneration Benchmarking | C6: Executive and management pay vs. SA market (Payscale / Remchannel data). Incentive structures. | E6: P1 - High | F6: Not Started
A7: RETENTION & CULTURE
A8: 4 | B8: Staff Turnover Rate | C8: Annual voluntary attrition by band. Red flag: >20% corporate attrition may indicate cultural issues. | E8: P1 - High | F8: Not Started
A9: 5 | B9: Employee Engagement Survey | C9: Most recent engagement/culture survey results. eNPS score. | E9: P2 - Medium | F9: Not Started
A10: 6 | B10: Key Employee Retention Risk | C10: Identify C-suite and brand MD departure risk. Any recent departures or announced exits. | E10: P0 - Gating | F10: Not Started
A11: BENEFITS & OBLIGATIONS
A12: 7 | B12: Provident Fund / Retirement Funding | C12: Defined contribution provident fund details. Any defined benefit legacy obligations. | E12: P1 - High | F12: Not Started
A13: 8 | B13: Medical Aid & Benefits | C13: Group life, disability, medical aid arrangements. Cost per employee trends. | E13: P2 - Medium | F13: Not Started
A14: 9 | B14: Union & Labour Agreements | C14: Any union recognition agreements. Sector bargaining council membership (SACCAWU/HORECASA). Past strike history. | E14: P1 - High | F14: Not Started
A15: 10 | B15: CCMA & Labour Court Claims | C15: Outstanding or settled unfair dismissal / retrenchment claims. Exposure quantum. | E15: P1 - High | F15: Not Started

Sheet IT & Tech DD
A1: Famous Brands — IT & Tech DD
A2: # | B2: Due Diligence Item | C2: Description / Request | D2: Data Room Ref | E2: Priority | F2: Status | G2: Owner | H2: Due Date | I2: Notes / Red Flag Detail
A3: TECHNOLOGY STACK
A4: 1 | B4: ERP & Financial Systems | C4: Core ERP (SAP, Sage, Oracle?). Integration with manufacturing, franchise billing, and reporting. Age and upgrade risk. | E4: P1 - High | F4: Not Started
A5: 2 | B5: POS Systems — Brand Coverage | C5: POS provider(s) by brand (e.g., Lightspeed, Oracle MICROS, custom). Age, cloud vs. on-premise. Integration to loyalty. | E5: P1 - High | F5: Not Started
A6: 3 | B6: Loyalty Platform — Famous Rewards | C6: Member base size, active users, redemption rates, data analytics capability. White-label vs. proprietary. | E6: P1 - High | F6: Not Started
A7: 4 | B7: Digital Ordering & Delivery Integration | C7: Own app capability. API integrations with Uber Eats, Mr D, etc. Revenue from digital channels as % of total. | E7: P1 - High | F7: Not Started
A8: 5 | B8: Manufacturing IT Systems | C8: MES / WMS systems in manufacturing plants. Automation level. Maintenance scheduling systems. | E8: P2 - Medium | F8: Not Started
A9: CYBERSECURITY & DATA
A10: 6 | B10: Cybersecurity Posture Assessment | C10: Penetration testing history, SOC monitoring, endpoint protection, incident response plan. | E10: P1 - High | F10: Not Started
A11: 7 | B11: Data Privacy — POPIA Compliance | C11: SA Protection of Personal Information Act (POPIA) compliance: data mapping, consent management, POPIA officer appointment. | E11: P0 - Gating | F11: Not Started
A12: 8 | B12: GDPR Exposure | C12: Any EU customer / franchisee data held? GDPR compliance if applicable to international operations. | E12: P2 - Medium | F12: Not Started
A13: 9 | B13: Cyber Incident History | C13: Any prior breaches, ransomware events, or data leaks. Customer notification history. | E13: P1 - High | F13: Not Started
A14: 10 | B14: IT Disaster Recovery (DR) Plan | C14: RTO / RPO targets, DR testing frequency, cloud backup strategy. | E14: P2 - Medium | F14: Not Started
A15: TECH ROADMAP
A16: 11 | B16: 3-Year IT Investment Plan | C16: Planned spend on IT and digital transformation. POS rollout, ERP upgrade, loyalty platform investment. | E16: P1 - High | F16: Not Started
A17: 12 | B17: AI / Data Analytics Capability | C17: Use of data analytics in menu engineering, franchisee performance, supply forecasting. | E17: P2 - Medium | F17: Not Started

Sheet ESG DD
A1: Famous Brands — ESG DD
A2: # | B2: Due Diligence Item | C2: Description / Request | D2: Data Room Ref | E2: Priority | F2: Status | G2: Owner | H2: Due Date | I2: Notes / Red Flag Detail
A3: ENVIRONMENTAL
A4: 1 | B4: Integrated Report / Sustainability Report | C4: Review Famous Brands Integrated Annual Report (IAR). GRI / TCFD disclosures. | E4: P1 - High | F4: Not Started
A5: 2 | B5: Carbon Footprint & Scope 1/2/3 Emissions | C5: Manufacturing emissions. Fleet emissions. Franchisee Scope 3 emissions strategy. | E5: P2 - Medium | F5: Not Started
A6: 3 | B6: Water Usage — Manufacturing | C6: SA water scarcity risk. Water consumption data for Midrand manufacturing facility. | E6: P1 - High | F6: Not Started
A7: 4 | B7: Packaging & Waste Reduction | C7: Single-use plastics compliance with SA regulations. EPR (Extended Producer Responsibility) scheme membership. | E7: P1 - High | F7: Not Started
A8: 5 | B8: Energy & Load-Shedding Mitigation | C8: Solar PV or generator capex at manufacturing plants. Renewable energy procurement. | E8: P2 - Medium | F8: Not Started
A9: SOCIAL & GOVERNANCE
A10: 6 | B10: BBBEE Scorecard — Full Detail | C10: Level 4+ BBBEE required for major retail/government procurement. Ownership element critical if black shareholders. | E10: P0 - Gating | F10: Not Started
A11: 7 | B11: Social Impact — Enterprise Development | C11: Franchisee development programmes for black-owned franchisees. 51%+ black-owned franchise targets. | E11: P1 - High | F11: Not Started
A12: 8 | B12: Food Nutrition & Health Obligations | C12: Compliance with SA R429 food labelling regulations. Calorie disclosure, allergen labelling. Menu transformation risk. | E12: P1 - High | F12: Not Started
A13: 9 | B13: Corporate Governance (King IV) | C13: JSE-listed: King IV compliance. Board composition, independent non-executives, audit committee independence. | E13: P0 - Gating | F13: Not Started
A14: 10 | B14: Related Party Transactions | C14: Any material RPTs: director-linked franchisee interests, family connections. JSE Related Party Transaction rules. | E14: P1 - High | F14: Not Started
A15: REGULATORY
A16: 11 | B16: JSE Listings Requirements Compliance | C16: History of JSE censures, cautionary announcements, major/category 1 transaction compliance. | E16: P0 - Gating | F16: Not Started
A17: 12 | B17: Competition Commission — Market Inquiry | C17: Monitor SA Competition Commission's Grocery Retail Market Inquiry and any food sector follow-on investigations. | E17: P1 - High | F17: Not Started
A18: 13 | B18: International Franchise Regulations | C18: Regulatory requirements in key markets: Nigeria (FIRS), Ghana, Kenya (CA), UAE (franchise law). Compliance status. | E18: P1 - High | F18: Not Started

Sheet Consumer DD
A1: Famous Brands — Consumer DD
A2: # | B2: Due Diligence Item | C2: Description / Request | D2: Data Room Ref | E2: Priority | F2: Status | G2: Owner | H2: Due Date | I2: Notes / Red Flag Detail
A3: BRAND PORTFOLIO ANALYSIS
A4: 1 | B4: Brand P&L by Brand | C4: Revenue, royalties, EBITDA contribution per brand. Identify any structurally declining brands (Milky Lane, Panarottis?). | E4: P0 - Gating | F4: Not Started
A5: 2 | B5: Premium vs. Value Brand Mix | C5: Segment brand portfolio by consumer segment. LSM 5-7 (value: Steers/Wimpy) vs. LSM 8-10 (premium: Tashas/Mugg & Bean). | E5: P1 - High | F5: Not Started
A6: 3 | B6: Brand Refresh / Remodelling Capex | C6: Scheduled brand revamps (e.g., Wimpy remodel programme). Franchisee capex commitment and Famous Brands co-investment. | E6: P1 - High | F6: Not Started
A7: 4 | B7: Brand Sunset / Exit Risk | C7: Identify brands where franchise agreement non-renewals have accelerated. Any brands being phased out. | E7: P1 - High | F7: Not Started
A8: FRANCHISE SYSTEM HEALTH
A9: 5 | B9: Total Restaurant Count Trend | C9: System restaurant count by brand over FY2019–FY2025. Net new openings vs. closures. COVID recovery trajectory. | E9: P0 - Gating | F9: Not Started
A10: 6 | B10: Franchisee 4-Wall Economics | C10: Average franchisee revenue and 4-wall EBITDA margin. Payback period on investment. Comparison vs. competing systems. | E10: P0 - Gating | F10: Not Started
A11: 7 | B11: Franchisee Application Pipeline | C11: Number of qualified applicants. Approval rate. Financial requirements. Geographic target areas. | E11: P1 - High | F11: Not Started
A12: 8 | B12: Corporate vs. Franchised Restaurants | C12: Number of company-owned restaurants (direct exposure). Strategy — are they converting to franchise or holding? | E12: P1 - High | F12: Not Started
A13: 9 | B13: International Master Franchisee Performance | C13: Restaurant count and SSSG in SSA (Nigeria, Ghana, Kenya, Mauritius). Middle East performance. | E13: P1 - High | F13: Not Started
A14: CONSUMER & DIGITAL
A15: 10 | B15: Famous Rewards Loyalty Programme | C15: Active member count, annual transaction volume, digital engagement rate. Monetisation of data. | E15: P1 - High | F15: Not Started
A16: 11 | B16: Digital Sales Mix | C16: App orders + third-party delivery as % of system sales by brand. Trajectory 2021–2025. | E16: P1 - High | F16: Not Started
A17: 12 | B17: Consumer NPS by Brand | C17: Brand Net Promoter Score (NPS) trend. Key detractor themes. | E17: P1 - High | F17: Not Started
A18: 13 | B18: Social Media & Brand Sentiment | C18: Share of voice vs. KFC, McDonald's, Nando's. Crisis history (social media boycotts, food safety incidents). | E18: P2 - Medium | F18: Not Started
A19: GBK POST-DISPOSAL LIABILITIES
A20: 14 | B20: GBK Residual Liabilities | C20: Confirm no residual exposure from 2020 GBK (Gourmet Burger Kitchen UK) disposal / CVA process. | E20: P0 - Gating | F20: Not Started
A21: 15 | B21: UK Creditor / Lease Claims | C21: Any continuing obligations under GBK property leases or creditor claims in the UK that may still be outstanding. | E21: P0 - Gating | F21: Not Started

Sheet Red Flag Log
A1: Famous Brands — Red Flag Log
A2: # | B2: Workstream | C2: Red Flag Description | D2: Date Identified | E2: Severity | F2: Mitigant / Path to Resolution | G2: Valuation / Deal Impact | H2: Owner | I2: Status
A3: 1 | B3: Financial DD | C3: Validate if any GBK-related residual losses remain in P&L | E3: Deal-Breaker | G3: Potential restatement risk | I3: Open
A4: 2 | B4: Commercial DD | C4: Customer / franchisee concentration — top 20 franchisees to be quantified | E4: Significant | G4: May require contractual protections / MFO agreements | I4: Open
A5: 3 | B5: Legal DD | C5: Competition Commission prior dealings — confirm no remedies attached to current operations | E5: Significant | G5: Seek clean bill from competition counsel | I5: Open
A6: 4 | B6: ESG DD | C6: BBBEE level — growth equity structure must not dilute ownership component | E6: Significant | G6: Restructure deal to preserve BBBEE compliance | I6: Open
