Workbook
Name central_anc_access_rate: Assumptions!$D$5
Name central_anc_access_rate_growth: Assumptions!$E$5
Name central_anc_access_rate_positive: Assumptions!$F$5
Name central_anc_access_rate_positive_growth: Assumptions!$G$5
Name central_launch_budget: Assumptions!$D$117
Name central_launch_budget_growth: Assumptions!$E$117
Name central_launch_budget_positive: Assumptions!$F$117
Name central_launch_budget_positive_growth: Assumptions!$G$117
Name central_private_acceptance_rate: Assumptions!$D$46
Name central_private_acceptance_rate_growth: Assumptions!$E$46
Name central_private_acceptance_rate_positive: Assumptions!$F$46
Name central_private_acceptance_rate_positive_growth: Assumptions!$G$46
Name central_private_coverage_additions: Assumptions!$D$48
Name central_private_coverage_additions_growth: Assumptions!$E$48
Name central_private_coverage_additions_positive: Assumptions!$F$48
Name central_private_coverage_additions_positive_growth: Assumptions!$G$48
Name central_private_coverage_churn: Assumptions!$D$49
Name central_private_coverage_churn_growth: Assumptions!$E$49
Name central_private_coverage_churn_positive: Assumptions!$F$49
Name central_private_coverage_churn_positive_growth: Assumptions!$G$49
Name central_private_distribution_cost_per_dose: Assumptions!$D$80
Name central_private_distribution_cost_per_dose_growth: Assumptions!$E$80
Name central_private_distribution_cost_per_dose_positive: Assumptions!$F$80
Name central_private_distribution_cost_per_dose_positive_growth: Assumptions!$G$80
Name central_private_eligibility_rate: Assumptions!$D$44
Name central_private_eligibility_rate_growth: Assumptions!$E$44
Name central_private_eligibility_rate_positive: Assumptions!$F$44
Name central_private_eligibility_rate_positive_growth: Assumptions!$G$44
Name central_private_net_price_per_dose: Assumptions!$D$50
Name central_private_net_price_per_dose_growth: Assumptions!$E$50
Name central_private_net_price_per_dose_positive: Assumptions!$F$50
Name central_private_net_price_per_dose_positive_growth: Assumptions!$G$50
Name central_private_provider_recommendation_rate: Assumptions!$D$45
Name central_private_provider_recommendation_rate_growth: Assumptions!$E$45
Name central_private_provider_recommendation_rate_positive: Assumptions!$F$45
Name central_private_provider_recommendation_rate_positive_growth: Assumptions!$G$45
Name central_private_stock_availability_rate: Assumptions!$D$47
Name central_private_stock_availability_rate_growth: Assumptions!$E$47
Name central_private_stock_availability_rate_positive: Assumptions!$F$47
Name central_private_stock_availability_rate_positive_growth: Assumptions!$G$47
Name central_private_trade_support_per_dose: Assumptions!$D$92
Name central_private_trade_support_per_dose_growth: Assumptions!$E$92
Name central_private_trade_support_per_dose_positive: Assumptions!$F$92
Name central_private_trade_support_per_dose_positive_growth: Assumptions!$G$92
Name central_private_wastage_rate: Assumptions!$D$88
Name central_private_wastage_rate_growth: Assumptions!$E$88
Name central_private_wastage_rate_positive: Assumptions!$F$88
Name central_private_wastage_rate_positive_growth: Assumptions!$G$88
Name central_public_acceptance_rate: Assumptions!$D$9
Name central_public_acceptance_rate_growth: Assumptions!$E$9
Name central_public_acceptance_rate_positive: Assumptions!$F$9
Name central_public_acceptance_rate_positive_growth: Assumptions!$G$9
Name central_public_coverage_additions: Assumptions!$D$11
Name central_public_coverage_additions_growth: Assumptions!$E$11
Name central_public_coverage_additions_positive: Assumptions!$F$11
Name central_public_coverage_additions_positive_growth: Assumptions!$G$11
Name central_public_coverage_churn: Assumptions!$D$12
Name central_public_coverage_churn_growth: Assumptions!$E$12
Name central_public_coverage_churn_positive: Assumptions!$F$12
Name central_public_coverage_churn_positive_growth: Assumptions!$G$12

Sheet Assumptions
A1: Input label | B1: Named range name | C1: Unit / note | D1: Base starting value | E1: Base annual growth | F1: Positive starting value | G1: Positive annual growth
A2: Revenue inputs
A3: National Live Births Per Month | B3: national_live_births_per_month | C3: births/month | Directionally consistent with roughly 1.75 million births per year | D3: 145833 | E3: 0.018 | F3: 145833 | G3: 0.018
A4: Central Regional Opportunity Weight | B4: central_regional_opportunity_weight | C4: % of national opportunity | D4: 0.28 | E4: 0 | F4: 0.28 | G4: 0
A5: Central ANC Access Rate | B5: central_anc_access_rate | C5: % | ANC channel reach | D5: 0.72 | E5: 0.003 | F5: 0.72 | G5: 0.003
A6: Central Third Trimester Window Rate | B6: central_third_trimester_window_rate | C6: % | Share reached in relevant gestational window | D6: 0.62 | E6: 0.006 | F6: 0.62 | G6: 0.006
A7: Central Public Eligibility Rate | B7: central_public_eligibility_rate | C7: % | Funded or affordable share of reachable pregnancies | D7: 0.28 | E7: 0.08 | F7: 0.35 | G7: 0.1
A8: Central Public Provider Recommendation Rate | B8: central_public_provider_recommendation_rate | C8: % | D8: 0.56 | E8: 0.04 | F8: 0.6272 | G8: 0.05
A9: Central Public Acceptance Rate | B9: central_public_acceptance_rate | C9: % | D9: 0.78 | E9: 0.02 | F9: 0.819 | G9: 0.025
A10: Central Public Stock Availability Rate | B10: central_public_stock_availability_rate | C10: % | D10: 0.9 | E10: 0.015 | F10: 0.954 | G10: 0.02
A11: Central Public Coverage Additions | B11: central_public_coverage_additions | C11: % pts/month | Monthly rollout gain from onboarding, awareness, and funded expansion | D11: 0.025 | E11: 0.03 | F11: 0.03375 | G11: 0.04
A12: Central Public Coverage Churn | B12: central_public_coverage_churn | C12: % pts/month | Loss of active coverage due to drop-off, stock issues, and execution leakage | D12: 0.004 | E12: 0 | F12: 0.003 | G12: 0
A13: Central Public Net Realised Price Per Dose | B13: central_public_net_price_per_dose | C13: UGX/dose | D13: 35500 | E13: 0.03 | F13: 38340 | G13: 0.03
A14: Western Regional Opportunity Weight | B14: western_regional_opportunity_weight | C14: % of national opportunity | D14: 0.25 | E14: 0 | F14: 0.25 | G14: 0
... A71: Northern Private Net Realised Price Per Dose | B71: northern_private_net_price_per_dose | C71: UGX/dose | D71: 76000 | E71: 0.035 | F71: 79800 | G71: 0.035
A72: Variable cost inputs
A73: Landed Vaccine Cost Per Dose | B73: landed_vaccine_cost_per_dose | C73: UGX/dose | Leaner transfer price assumption | D73: 20500 | E73: 0.035 | F73: 19475 | G73: 0.035
A74: Import and Clearance Cost Per Dose | B74: import_clearance_cost_per_dose | C74: UGX/dose | International freight and import handling | D74: 850 | E74: 0.04 | F74: 824.5 | G74: 0.04
A75: Cold-Chain Warehousing Cost Per Dose | B75: cold_chain_warehousing_cost_per_dose | C75: UGX/dose | National warehousing and cold-chain holding | D75: 950 | E75: 0.04 | F75: 921.5 | G75: 0.04
A76: Central Public Distribution Cost Per Dose | B76: central_public_distribution_cost_per_dose | C76: UGX/dose | D76: 2500 | E76: 0.04 | F76: 2400 | G76: 0.04
A77: Western Public Distribution Cost Per Dose | B77: western_public_distribution_cost_per_dose | C77: UGX/dose | D77: 3400 | E77: 0.04 | F77: 3264 | G77: 0.04
A78: Eastern Public Distribution Cost Per Dose | B78: eastern_public_distribution_cost_per_dose | C78: UGX/dose | D78: 4200 | E78: 0.04 | F78: 4032 | G78: 0.04
A79: Northern Public Distribution Cost Per Dose | B79: northern_public_distribution_cost_per_dose | C79: UGX/dose | D79: 5600 | E79: 0.04 | F79: 5376 | G79: 0.04
A80: Central Private Distribution Cost Per Dose | B80: central_private_distribution_cost_per_dose | C80: UGX/dose | D80: 3200 | E80: 0.04 | F80: 3072 | G80: 0.04
A81: Western Private Distribution Cost Per Dose | B81: western_private_distribution_cost_per_dose | C81: UGX/dose | D81: 4300 | E81: 0.04 | F81: 4128 | G81: 0.04
A82: Eastern Private Distribution Cost Per Dose | B82: eastern_private_distribution_cost_per_dose | C82: UGX/dose | D82: 5100 | E82: 0.04 | F82: 4896 | G82: 0.04
A83: Northern Private Distribution Cost Per Dose | B83: northern_private_distribution_cost_per_dose | C83: UGX/dose | D83: 6600 | E83: 0.04 | F83: 6336 | G83: 0.04
A84: Central Public Wastage Rate | B84: central_public_wastage_rate | C84: % | D84: 0.035 | E84: 0 | F84: 0.0315 | G84: 0
... A95: Northern Private Trade Support Per Dose | B95: northern_private_trade_support_per_dose | C95: UGX/dose | D95: 1200 | E95: 0.03 | F95: 1140 | G95: 0.03
A96: Fixed cost inputs
A97: Regulatory Headcount | B97: regulatory_headcount | C97: FTE | D97: 1 | E97: 0 | F97: 1 | G97: 0
A98: Regulatory Cost Per FTE | B98: regulatory_cost_per_fte | C98: UGX/FTE/month | D98: 8500000 | E98: 0.05 | F98: 7480000 | G98: 0.05
A99: Regulatory Fees and Compliance | B99: regulatory_fees_and_compliance | C99: UGX/month | D99: 4500000 | E99: 0.04 | F99: 3960000 | G99: 0.04
A100: Market Access Headcount | B100: market_access_headcount | C100: FTE | D100: 2 | E100: 0 | F100: 2 | G100: 0
A101: Market Access Cost Per FTE | B101: market_access_cost_per_fte | C101: UGX/FTE/month | D101: 8000000 | E101: 0.05 | F101: 7040000 | G101: 0.05
A102: Tender Support Budget | B102: tender_support_budget | C102: UGX/month | D102: 5000000 | E102: 0.04 | F102: 4400000 | G102: 0.04
A103: Medical Headcount | B103: medical_headcount | C103: FTE | D103: 1 | E103: 0 | F103: 1 | G103: 0
A104: Medical Cost Per FTE | B104: medical_cost_per_fte | C104: UGX/FTE/month | D104: 9500000 | E104: 0.05 | F104: 8360000 | G104: 0.05
A105: KOL and Medical Program Budget | B105: kol_and_medical_program_budget | C105: UGX/month | D105: 6000000 | E105: 0.04 | F105: 5280000 | G105: 0.04
A106: Central Training Budget | B106: central_training_budget | C106: UGX/month | D106: 8000000 | E106: 0.03 | F106: 6000000 | G106: 0.03
A107: Western Training Budget | B107: western_training_budget | C107: UGX/month | D107: 5000000 | E107: 0.03 | F107: 3750000 | G107: 0.03
A108: Eastern Training Budget | B108: eastern_training_budget | C108: UGX/month | D108: 3500000 | E108: 0.03 | F108: 2625000 | G108: 0.03
... A120: Northern Launch Budget | B120: northern_launch_budget | C120: UGX/month | D120: 2500000 | E120: 0.03 | F120: 1875000 | G120: 0.03

Sheet Model - Positive
H1: Month 1 | I1: Month 2 | J1: Month 3 | K1: Month 4 | L1: Month 5 | M1: Month 6 | N1: Month 7 | O1: Month 8 | P1: Month 9 | Q1: Month 10 | R1: Month 11 | S1: Month 12 | T1: Month 13 | U1: Month 14 | V1: Month 15 | W1: Month 16 | X1: Month 17 | Y1: Month 18 | Z1: Month 19 | AA1: Month 20 | AB1: Month 21 | AC1: Month 22 | AD1: Month 23 | AE1: Month 24 | AF1: Month 25 | AG1: Month 26 | AH1: Month 27 | AI1: Month 28 | AJ1: Month 29 | AK1: Month 30 | AL1: Month 31 | AM1: Month 32 | AN1: Month 33 | AO1: Month 34 | AP1: Month 35 | AQ1: Month 36
A2: Net Profit | H2: =(H3-H110) -> -92794715 | I2: =(I3-I110) -> -88112219 | J2: =(J3-J110) -> -83219907 | K2: =(K3-K110) -> -78111037 | L2: =(L3-L110) -> -72778670 | M2: =(M3-M110) -> -67215672 | N2: =(N3-N110) -> -61414705 | O2: =(O3-O110) -> -55368223 | ... AQ2: =(AQ3-AQ110) -> 2.5207607e+08
B3: Revenue | H3: =(H4+H65) -> 26728497 | I3: =(I4+I65) -> 36784643 | J3: =(J4+J65) -> 47272383 | K3: =(K4+K65) -> 58205907 | L3: =(L4+L65) -> 69599826 | M3: =(M4+M65) -> 81469177 | N3: =(N4+N65) -> 93829439 | O3: =(O4+O65) -> 1.0669655e+08 | ... AQ3: =(AQ4+AQ65) -> 7.5455306e+08
C4: Public / Donor Revenue | H4: =(((H5+H20)+H35)+H50) -> 18362493 | I4: =(((I5+I20)+I35)+I50) -> 24539385 | J4: =(((J5+J20)+J35)+J50) -> 30984973 | K4: =(((K5+K20)+K35)+K50) -> 37708235 | L4: =(((L5+L20)+L35)+L50) -> 44718415 | M4: =(((M5+M20)+M35)+M50) -> 52025034 | N4: =(((N5+N20)+N35)+N50) -> 59637897 | O4: =(((O5+O20)+O35)+O50) -> 67567100 | ... AQ4: =(((AQ5+AQ20)+AQ35)+AQ50) -> 4.7005926e+08
D5: Central Public Revenue | H5: =(H6*H19) -> 9589290.9 | I5: =(I6*I19) -> 13562480 | J5: =(J6*J19) -> 17709319 | K5: =(K6*K19) -> 22035611 | L5: =(L6*L19) -> 26547335 | M5: =(M6*M19) -> 31250647 | N5: =(N6*N19) -> 36151886 | O5: =(O6*O19) -> 41257581 | ... AQ5: =(AQ6*AQ19) -> 3.0087064e+08
E6: Central Public Administered Doses | H6: =(((((H7*H12)*H13)*H14)*H15)*H16) -> 250.11192 | I6: =(((((I7*I12)*I13)*I14)*I15)*I16) -> 352.87204 | J6: =(((((J7*J12)*J13)*J14)*J15)*J16) -> 459.63196 | K6: =(((((K7*K12)*K13)*K14)*K15)*K16) -> 570.51056 | L6: =(((((L7*L12)*L13)*L14)*L15)*L16) -> 685.6299 | M6: =(((((M7*M12)*M13)*M14)*M15)*M16) -> 805.11526 | N6: =(((((N7*N12)*N13)*N14)*N15)*N16) -> 929.09524 | O6: =(((((O7*O12)*O13)*O14)*O15)*O16) -> 1057.7019 | ... AQ6: =(((((AQ7*AQ12)*AQ13)*AQ14)*AQ15)*AQ16) -> 7199.2257
F7: Central Reachable Pregnancies | H7: =(((H8*H9)*H10)*H11) -> 18227.958 | I7: =(((I8*I9)*I10)*I11) -> 18268.74 | J7: =(((J8*J9)*J10)*J11) -> 18309.612 | K7: =(((K8*K9)*K10)*K11) -> 18350.576 | L7: =(((L8*L9)*L10)*L11) -> 18391.632 | M7: =(((M8*M9)*M10)*M11) -> 18432.779 | N7: =(((N8*N9)*N10)*N11) -> 18474.018 | O7: =(((O8*O9)*O10)*O11) -> 18515.35 | ... AQ7: =(((AQ8*AQ9)*AQ10)*AQ11) -> 19710.949
G8: National Live Births Per Month | H8: =national_live_births_per_month_positive*(1+national_live_births_per_month_positive_growth)^((COLUMN()-8)/12) -> 145833 | I8: =national_live_births_per_month_positive*(1+national_live_births_per_month_positive_growth)^((COLUMN()-8)/12) -> 146049.97 | J8: =national_live_births_per_month_positive*(1+national_live_births_per_month_positive_growth)^((COLUMN()-8)/12) -> 146267.25 | K8: =national_live_births_per_month_positive*(1+national_live_births_per_month_positive_growth)^((COLUMN()-8)/12) -> 146484.86 | L8: =national_live_births_per_month_positive*(1+national_live_births_per_month_positive_growth)^((COLUMN()-8)/12) -> 146702.8 | M8: =national_live_births_per_month_positive*(1+national_live_births_per_month_positive_growth)^((COLUMN()-8)/12) -> 146921.06 | N8: =national_live_births_per_month_positive*(1+national_live_births_per_month_positive_growth)^((COLUMN()-8)/12) -> 147139.64 | O8: =national_live_births_per_month_positive*(1+national_live_births_per_month_positive_growth)^((COLUMN()-8)/12) -> 147358.55 | ... AQ8: =national_live_births_per_month_positive*(1+national_live_births_per_month_positive_growth)^((COLUMN()-8)/12) -> 153622.03
G9: times Central Regional Opportunity Weight | H9: =central_regional_opportunity_weight_positive*(1+central_regional_opportunity_weight_positive_growth)^((COLUMN()-8)/12) -> 0.28 | I9: =central_regional_opportunity_weight_positive*(1+central_regional_opportunity_weight_positive_growth)^((COLUMN()-8)/12) -> 0.28 | J9: =central_regional_opportunity_weight_positive*(1+central_regional_opportunity_weight_positive_growth)^((COLUMN()-8)/12) -> 0.28 | K9: =central_regional_opportunity_weight_positive*(1+central_regional_opportunity_weight_positive_growth)^((COLUMN()-8)/12) -> 0.28 | L9: =central_regional_opportunity_weight_positive*(1+central_regional_opportunity_weight_positive_growth)^((COLUMN()-8)/12) -> 0.28 | M9: =central_regional_opportunity_weight_positive*(1+central_regional_opportunity_weight_positive_growth)^((COLUMN()-8)/12) -> 0.28 | N9: =central_regional_opportunity_weight_positive*(1+central_regional_opportunity_weight_positive_growth)^((COLUMN()-8)/12) -> 0.28 | O9: =central_regional_opportunity_weight_positive*(1+central_regional_opportunity_weight_positive_growth)^((COLUMN()-8)/12) -> 0.28 | ... AQ9: =central_regional_opportunity_weight_positive*(1+central_regional_opportunity_weight_positive_growth)^((COLUMN()-8)/12) -> 0.28
G10: times Central ANC Access Rate | H10: =central_anc_access_rate_positive*(1+central_anc_access_rate_positive_growth)^((COLUMN()-8)/12) -> 0.72 | I10: =central_anc_access_rate_positive*(1+central_anc_access_rate_positive_growth)^((COLUMN()-8)/12) -> 0.72017975 | J10: =central_anc_access_rate_positive*(1+central_anc_access_rate_positive_growth)^((COLUMN()-8)/12) -> 0.72035955 | K10: =central_anc_access_rate_positive*(1+central_anc_access_rate_positive_growth)^((COLUMN()-8)/12) -> 0.72053939 | L10: =central_anc_access_rate_positive*(1+central_anc_access_rate_positive_growth)^((COLUMN()-8)/12) -> 0.72071928 | M10: =central_anc_access_rate_positive*(1+central_anc_access_rate_positive_growth)^((COLUMN()-8)/12) -> 0.72089921 | N10: =central_anc_access_rate_positive*(1+central_anc_access_rate_positive_growth)^((COLUMN()-8)/12) -> 0.72107919 | O10: =central_anc_access_rate_positive*(1+central_anc_access_rate_positive_growth)^((COLUMN()-8)/12) -> 0.72125921 | ... AQ10: =central_anc_access_rate_positive*(1+central_anc_access_rate_positive_growth)^((COLUMN()-8)/12) -> 0.72631813
G11: times Central Third Trimester Window Rate | H11: =central_third_trimester_window_rate_positive*(1+central_third_trimester_window_rate_positive_growth)^((COLUMN()-8)/12) -> 0.62 | I11: =central_third_trimester_window_rate_positive*(1+central_third_trimester_window_rate_positive_growth)^((COLUMN()-8)/12) -> 0.62030915 | J11: =central_third_trimester_window_rate_positive*(1+central_third_trimester_window_rate_positive_growth)^((COLUMN()-8)/12) -> 0.62061846 | K11: =central_third_trimester_window_rate_positive*(1+central_third_trimester_window_rate_positive_growth)^((COLUMN()-8)/12) -> 0.62092791 | L11: =central_third_trimester_window_rate_positive*(1+central_third_trimester_window_rate_positive_growth)^((COLUMN()-8)/12) -> 0.62123753 | M11: =central_third_trimester_window_rate_positive*(1+central_third_trimester_window_rate_positive_growth)^((COLUMN()-8)/12) -> 0.6215473 | N11: =central_third_trimester_window_rate_positive*(1+central_third_trimester_window_rate_positive_growth)^((COLUMN()-8)/12) -> 0.62185722 | O11: =central_third_trimester_window_rate_positive*(1+central_third_trimester_window_rate_positive_growth)^((COLUMN()-8)/12) -> 0.6221673 | ... AQ11: =central_third_trimester_window_rate_positive*(1+central_third_trimester_window_rate_positive_growth)^((COLUMN()-8)/12) -> 0.6309125
F12: times Central Public Eligibility Rate | H12: =central_public_eligibility_rate_positive*(1+central_public_eligibility_rate_positive_growth)^((COLUMN()-8)/12) -> 0.35 | I12: =central_public_eligibility_rate_positive*(1+central_public_eligibility_rate_positive_growth)^((COLUMN()-8)/12) -> 0.35279095 | J12: =central_public_eligibility_rate_positive*(1+central_public_eligibility_rate_positive_growth)^((COLUMN()-8)/12) -> 0.35560415 | K12: =central_public_eligibility_rate_positive*(1+central_public_eligibility_rate_positive_growth)^((COLUMN()-8)/12) -> 0.35843979 | L12: =central_public_eligibility_rate_positive*(1+central_public_eligibility_rate_positive_growth)^((COLUMN()-8)/12) -> 0.36129804 | M12: =central_public_eligibility_rate_positive*(1+central_public_eligibility_rate_positive_growth)^((COLUMN()-8)/12) -> 0.36417908 | N12: =central_public_eligibility_rate_positive*(1+central_public_eligibility_rate_positive_growth)^((COLUMN()-8)/12) -> 0.3670831 | O12: =central_public_eligibility_rate_positive*(1+central_public_eligibility_rate_positive_growth)^((COLUMN()-8)/12) -> 0.37001027 | ... AQ12: =central_public_eligibility_rate_positive*(1+central_public_eligibility_rate_positive_growth)^((COLUMN()-8)/12) -> 0.46216463
F13: times Central Public Provider Recommendation Rate | H13: =central_public_provider_recommendation_rate_positive*(1+central_public_provider_recommendation_rate_positive_growth)^((COLUMN()-8)/12) -> 0.6272 | I13: =central_public_provider_recommendation_rate_positive*(1+central_public_provider_recommendation_rate_positive_growth)^((COLUMN()-8)/12) -> 0.62975529 | J13: =central_public_provider_recommendation_rate_positive*(1+central_public_provider_recommendation_rate_positive_growth)^((COLUMN()-8)/12) -> 0.63232099 | K13: =central_public_provider_recommendation_rate_positive*(1+central_public_provider_recommendation_rate_positive_growth)^((COLUMN()-8)/12) -> 0.63489715 | L13: =central_public_provider_recommendation_rate_positive*(1+central_public_provider_recommendation_rate_positive_growth)^((COLUMN()-8)/12) -> 0.63748379 | M13: =central_public_provider_recommendation_rate_positive*(1+central_public_provider_recommendation_rate_positive_growth)^((COLUMN()-8)/12) -> 0.64008098 | N13: =central_public_provider_recommendation_rate_positive*(1+central_public_provider_recommendation_rate_positive_growth)^((COLUMN()-8)/12) -> 0.64268875 | O13: =central_public_provider_recommendation_rate_positive*(1+central_public_provider_recommendation_rate_positive_growth)^((COLUMN()-8)/12) -> 0.64530715 | ... AQ13: =central_public_provider_recommendation_rate_positive*(1+central_public_provider_recommendation_rate_positive_growth)^((COLUMN()-8)/12) -> 0.72311633
F14: times Central Public Acceptance Rate | H14: =central_public_acceptance_rate_positive*(1+central_public_acceptance_rate_positive_growth)^((COLUMN()-8)/12) -> 0.819 | I14: =central_public_acceptance_rate_positive*(1+central_public_acceptance_rate_positive_growth)^((COLUMN()-8)/12) -> 0.82068701 | J14: =central_public_acceptance_rate_positive*(1+central_public_acceptance_rate_positive_growth)^((COLUMN()-8)/12) -> 0.82237749 | K14: =central_public_acceptance_rate_positive*(1+central_public_acceptance_rate_positive_growth)^((COLUMN()-8)/12) -> 0.82407145 | L14: =central_public_acceptance_rate_positive*(1+central_public_acceptance_rate_positive_growth)^((COLUMN()-8)/12) -> 0.8257689 | M14: =central_public_acceptance_rate_positive*(1+central_public_acceptance_rate_positive_growth)^((COLUMN()-8)/12) -> 0.82746985 | N14: =central_public_acceptance_rate_positive*(1+central_public_acceptance_rate_positive_growth)^((COLUMN()-8)/12) -> 0.8291743 | O14: =central_public_acceptance_rate_positive*(1+central_public_acceptance_rate_positive_growth)^((COLUMN()-8)/12) -> 0.83088227 | ... AQ14: =central_public_acceptance_rate_positive*(1+central_public_acceptance_rate_positive_growth)^((COLUMN()-8)/12) -> 0.88016044
F15: times Central Public Stock Availability Rate | H15: =central_public_stock_availability_rate_positive*(1+central_public_stock_availability_rate_positive_growth)^((COLUMN()-8)/12) -> 0.954 | I15: =central_public_stock_availability_rate_positive*(1+central_public_stock_availability_rate_positive_growth)^((COLUMN()-8)/12) -> 0.95557561 | J15: =central_public_stock_availability_rate_positive*(1+central_public_stock_availability_rate_positive_growth)^((COLUMN()-8)/12) -> 0.95715382 | K15: =central_public_stock_availability_rate_positive*(1+central_public_stock_availability_rate_positive_growth)^((COLUMN()-8)/12) -> 0.95873464 | L15: =central_public_stock_availability_rate_positive*(1+central_public_stock_availability_rate_positive_growth)^((COLUMN()-8)/12) -> 0.96031806 | M15: =central_public_stock_availability_rate_positive*(1+central_public_stock_availability_rate_positive_growth)^((COLUMN()-8)/12) -> 0.96190411 | N15: =central_public_stock_availability_rate_positive*(1+central_public_stock_availability_rate_positive_growth)^((COLUMN()-8)/12) -> 0.96349277 | O15: =central_public_stock_availability_rate_positive*(1+central_public_stock_availability_rate_positive_growth)^((COLUMN()-8)/12) -> 0.96508406 | ... AQ15: =central_public_stock_availability_rate_positive*(1+central_public_stock_availability_rate_positive_growth)^((COLUMN()-8)/12) -> 1.0107231
F16: times Central Public Active Coverage State | H16: =0.08 -> 0.08 | I16: =H16+I17-I18 -> 0.11086049 | J16: =I16+J17-J18 -> 0.14183183 | K16: =J16+K17-K18 -> 0.17291438 | L16: =K16+L17-L18 -> 0.20410851 | M16: =L16+M17-M18 -> 0.23541458 | N16: =M16+N17-N18 -> 0.26683296 | O16: =N16+O17-O18 -> 0.29836402 | P16: =O16+P17-P18 -> 0.33000813 | ... AQ16: =AP16+AQ17-AQ18 -> 1.2285117
G17: Central Public Coverage Additions | H17: =central_public_coverage_additions_positive*(1+central_public_coverage_additions_positive_growth)^((COLUMN()-8)/12) -> 0.03375 | I17: =central_public_coverage_additions_positive*(1+central_public_coverage_additions_positive_growth)^((COLUMN()-8)/12) -> 0.033860489 | J17: =central_public_coverage_additions_positive*(1+central_public_coverage_additions_positive_growth)^((COLUMN()-8)/12) -> 0.033971339 | K17: =central_public_coverage_additions_positive*(1+central_public_coverage_additions_positive_growth)^((COLUMN()-8)/12) -> 0.034082552 | L17: =central_public_coverage_additions_positive*(1+central_public_coverage_additions_positive_growth)^((COLUMN()-8)/12) -> 0.03419413 | M17: =central_public_coverage_additions_positive*(1+central_public_coverage_additions_positive_growth)^((COLUMN()-8)/12) -> 0.034306073 | N17: =central_public_coverage_additions_positive*(1+central_public_coverage_additions_positive_growth)^((COLUMN()-8)/12) -> 0.034418382 | O17: =central_public_coverage_additions_positive*(1+central_public_coverage_additions_positive_growth)^((COLUMN()-8)/12) -> 0.034531059 | ... AQ17: =central_public_coverage_additions_positive*(1+central_public_coverage_additions_positive_growth)^((COLUMN()-8)/12) -> 0.037840281
G18: plus Central Public Coverage Churn | H18: =central_public_coverage_churn_positive*(1+central_public_coverage_churn_positive_growth)^((COLUMN()-8)/12) -> 0.003 | I18: =central_public_coverage_churn_positive*(1+central_public_coverage_churn_positive_growth)^((COLUMN()-8)/12) -> 0.003 | J18: =central_public_coverage_churn_positive*(1+central_public_coverage_churn_positive_growth)^((COLUMN()-8)/12) -> 0.003 | K18: =central_public_coverage_churn_positive*(1+central_public_coverage_churn_positive_growth)^((COLUMN()-8)/12) -> 0.003 | L18: =central_public_coverage_churn_positive*(1+central_public_coverage_churn_positive_growth)^((COLUMN()-8)/12) -> 0.003 | M18: =central_public_coverage_churn_positive*(1+central_public_coverage_churn_positive_growth)^((COLUMN()-8)/12) -> 0.003 | N18: =central_public_coverage_churn_positive*(1+central_public_coverage_churn_positive_growth)^((COLUMN()-8)/12) -> 0.003 | O18: =central_public_coverage_churn_positive*(1+central_public_coverage_churn_positive_growth)^((COLUMN()-8)/12) -> 0.003 | ... AQ18: =central_public_coverage_churn_positive*(1+central_public_coverage_churn_positive_growth)^((COLUMN()-8)/12) -> 0.003
E19: times Central Public Net Realised Price Per Dose | H19: =central_public_net_price_per_dose_positive*(1+central_public_net_price_per_dose_positive_growth)^((COLUMN()-8)/12) -> 38340 | I19: =central_public_net_price_per_dose_positive*(1+central_public_net_price_per_dose_positive_growth)^((COLUMN()-8)/12) -> 38434.557 | J19: =central_public_net_price_per_dose_positive*(1+central_public_net_price_per_dose_positive_growth)^((COLUMN()-8)/12) -> 38529.347 | K19: =central_public_net_price_per_dose_positive*(1+central_public_net_price_per_dose_positive_growth)^((COLUMN()-8)/12) -> 38624.371 | L19: =central_public_net_price_per_dose_positive*(1+central_public_net_price_per_dose_positive_growth)^((COLUMN()-8)/12) -> 38719.629 | M19: =central_public_net_price_per_dose_positive*(1+central_public_net_price_per_dose_positive_growth)^((COLUMN()-8)/12) -> 38815.122 | N19: =central_public_net_price_per_dose_positive*(1+central_public_net_price_per_dose_positive_growth)^((COLUMN()-8)/12) -> 38910.85 | O19: =central_public_net_price_per_dose_positive*(1+central_public_net_price_per_dose_positive_growth)^((COLUMN()-8)/12) -> 39006.815 | ... AQ19: =central_public_net_price_per_dose_positive*(1+central_public_net_price_per_dose_positive_growth)^((COLUMN()-8)/12) -> 41792.083
D20: plus Western Public Revenue | H20: =(H21*H34) -> 4525802.9 | I20: =(I21*I34) -> 5853583.8 | J20: =(J21*J34) -> 7238911.7 | K20: =(K21*K34) -> 8683708.1 | L20: =(L21*L34) -> 10189952 | M20: =(M21*M34) -> 11759682 | N20: =(N21*N34) -> 13394997 | O20: =(O21*O34) -> 15098059 | ... AQ20: =(AQ21*AQ34) -> 1.0143103e+08
E21: Western Public Administered Doses | H21: =(((((H22*H27)*H28)*H29)*H30)*H31) -> 121.46546 | I21: =(((((I22*I27)*I28)*I29)*I30)*I31) -> 156.71451 | J21: =(((((J22*J27)*J28)*J29)*J30)*J31) -> 193.32628 | K21: =(((((K22*K27)*K28)*K29)*K30)*K31) -> 231.34124 | L21: =(((((L22*L27)*L28)*L29)*L30)*L31) -> 270.80097 | M21: =(((((M22*M27)*M28)*M29)*M30)*M31) -> 311.74816 | N21: =(((((N22*N27)*N28)*N29)*N30)*N31) -> 354.2266 | O21: =(((((O22*O27)*O28)*O29)*O30)*O31) -> 398.28127 | ... AQ21: =(((((AQ22*AQ27)*AQ28)*AQ29)*AQ30)*AQ31) -> 2497.3884
F22: Western Reachable Pregnancies | H22: =(((H23*H24)*H25)*H26) -> 13474.969 | I22: =(((I23*I24)*I25)*I26) -> 13505.117 | J22: =(((J23*J24)*J25)*J26) -> 13535.331 | K22: =(((K23*K24)*K25)*K26) -> 13565.614 | L22: =(((L23*L24)*L25)*L26) -> 13595.964 | M22: =(((M23*M24)*M25)*M26) -> 13626.382 | N22: =(((N23*N24)*N25)*N26) -> 13656.868 | O22: =(((O23*O24)*O25)*O26) -> 13687.423 | ... AQ22: =(((AQ23*AQ24)*AQ25)*AQ26) -> 14571.266
G23: National Live Births Per Month | H23: =H8 -> 145833 | I23: =I8 -> 146049.97 | J23: =J8 -> 146267.25 | K23: =K8 -> 146484.86 | L23: =L8 -> 146702.8 | M23: =M8 -> 146921.06 | N23: =N8 -> 147139.64 | O23: =O8 -> 147358.55 | ... AQ23: =AQ8 -> 153622.03
G24: times Western Regional Opportunity Weight | H24: =western_regional_opportunity_weight_positive*(1+western_regional_opportunity_weight_positive_growth)^((COLUMN()-8)/12) -> 0.25 | I24: =western_regional_opportunity_weight_positive*(1+western_regional_opportunity_weight_positive_growth)^((COLUMN()-8)/12) -> 0.25 | J24: =western_regional_opportunity_weight_positive*(1+western_regional_opportunity_weight_positive_growth)^((COLUMN()-8)/12) -> 0.25 | K24: =western_regional_opportunity_weight_positive*(1+western_regional_opportunity_weight_positive_growth)^((COLUMN()-8)/12) -> 0.25 | L24: =western_regional_opportunity_weight_positive*(1+western_regional_opportunity_weight_positive_growth)^((COLUMN()-8)/12) -> 0.25 | M24: =western_regional_opportunity_weight_positive*(1+western_regional_opportunity_weight_positive_growth)^((COLUMN()-8)/12) -> 0.25 | N24: =western_regional_opportunity_weight_positive*(1+western_regional_opportunity_weight_positive_growth)^((COLUMN()-8)/12) -> 0.25 | O24: =western_regional_opportunity_weight_positive*(1+western_regional_opportunity_weight_positive_growth)^((COLUMN()-8)/12) -> 0.25 | ... AQ24: =western_regional_opportunity_weight_positive*(1+western_regional_opportunity_weight_positive_growth)^((COLUMN()-8)/12) -> 0.25
G25: times Western ANC Access Rate | H25: =western_anc_access_rate_positive*(1+western_anc_access_rate_positive_growth)^((COLUMN()-8)/12) -> 0.66 | I25: =western_anc_access_rate_positive*(1+western_anc_access_rate_positive_growth)^((COLUMN()-8)/12) -> 0.66016477 | J25: =western_anc_access_rate_positive*(1+western_anc_access_rate_positive_growth)^((COLUMN()-8)/12) -> 0.66032959 | K25: =western_anc_access_rate_positive*(1+western_anc_access_rate_positive_growth)^((COLUMN()-8)/12) -> 0.66049444 | L25: =western_anc_access_rate_positive*(1+western_anc_access_rate_positive_growth)^((COLUMN()-8)/12) -> 0.66065934 | M25: =western_anc_access_rate_positive*(1+western_anc_access_rate_positive_growth)^((COLUMN()-8)/12) -> 0.66082428 | N25: =western_anc_access_rate_positive*(1+western_anc_access_rate_positive_growth)^((COLUMN()-8)/12) -> 0.66098926 | O25: =western_anc_access_rate_positive*(1+western_anc_access_rate_positive_growth)^((COLUMN()-8)/12) -> 0.66115428 | ... AQ25: =western_anc_access_rate_positive*(1+western_anc_access_rate_positive_growth)^((COLUMN()-8)/12) -> 0.66579162
G26: times Western Third Trimester Window Rate | H26: =western_third_trimester_window_rate_positive*(1+western_third_trimester_window_rate_positive_growth)^((COLUMN()-8)/12) -> 0.56 | I26: =western_third_trimester_window_rate_positive*(1+western_third_trimester_window_rate_positive_growth)^((COLUMN()-8)/12) -> 0.56027923 | J26: =western_third_trimester_window_rate_positive*(1+western_third_trimester_window_rate_positive_growth)^((COLUMN()-8)/12) -> 0.56055861 | K26: =western_third_trimester_window_rate_positive*(1+western_third_trimester_window_rate_positive_growth)^((COLUMN()-8)/12) -> 0.56083812 | L26: =western_third_trimester_window_rate_positive*(1+western_third_trimester_window_rate_positive_growth)^((COLUMN()-8)/12) -> 0.56111777 | M26: =western_third_trimester_window_rate_positive*(1+western_third_trimester_window_rate_positive_growth)^((COLUMN()-8)/12) -> 0.56139756 | N26: =western_third_trimester_window_rate_positive*(1+western_third_trimester_window_rate_positive_growth)^((COLUMN()-8)/12) -> 0.56167749 | O26: =western_third_trimester_window_rate_positive*(1+western_third_trimester_window_rate_positive_growth)^((COLUMN()-8)/12) -> 0.56195756 | ... AQ26: =western_third_trimester_window_rate_positive*(1+western_third_trimester_window_rate_positive_growth)^((COLUMN()-8)/12) -> 0.56985645
F27: times Western Public Eligibility Rate | H27: =western_public_eligibility_rate_positive*(1+western_public_eligibility_rate_positive_growth)^((COLUMN()-8)/12) -> 0.275 | I27: =western_public_eligibility_rate_positive*(1+western_public_eligibility_rate_positive_growth)^((COLUMN()-8)/12) -> 0.27719289 | J27: =western_public_eligibility_rate_positive*(1+western_public_eligibility_rate_positive_growth)^((COLUMN()-8)/12) -> 0.27940326 | K27: =western_public_eligibility_rate_positive*(1+western_public_eligibility_rate_positive_growth)^((COLUMN()-8)/12) -> 0.28163126 | L27: =western_public_eligibility_rate_positive*(1+western_public_eligibility_rate_positive_growth)^((COLUMN()-8)/12) -> 0.28387703 | M27: =western_public_eligibility_rate_positive*(1+western_public_eligibility_rate_positive_growth)^((COLUMN()-8)/12) -> 0.28614071 | N27: =western_public_eligibility_rate_positive*(1+western_public_eligibility_rate_positive_growth)^((COLUMN()-8)/12) -> 0.28842243 | O27: =western_public_eligibility_rate_positive*(1+western_public_eligibility_rate_positive_growth)^((COLUMN()-8)/12) -> 0.29072235 | ... AQ27: =western_public_eligibility_rate_positive*(1+western_public_eligibility_rate_positive_growth)^((COLUMN()-8)/12) -> 0.36312936
F28: times Western Public Provider Recommendation Rate | H28: =western_public_provider_recommendation_rate_positive*(1+western_public_provider_recommendation_rate_positive_growth)^((COLUMN()-8)/12) -> 0.5488 | I28: =western_public_provider_recommendation_rate_positive*(1+western_public_provider_recommendation_rate_positive_growth)^((COLUMN()-8)/12) -> 0.55103588 | J28: =western_public_provider_recommendation_rate_positive*(1+western_public_provider_recommendation_rate_positive_growth)^((COLUMN()-8)/12) -> 0.55328087 | K28: =western_public_provider_recommendation_rate_positive*(1+western_public_provider_recommendation_rate_positive_growth)^((COLUMN()-8)/12) -> 0.555535 | L28: =western_public_provider_recommendation_rate_positive*(1+western_public_provider_recommendation_rate_positive_growth)^((COLUMN()-8)/12) -> 0.55779832 | M28: =western_public_provider_recommendation_rate_positive*(1+western_public_provider_recommendation_rate_positive_growth)^((COLUMN()-8)/12) -> 0.56007086 | N28: =western_public_provider_recommendation_rate_positive*(1+western_public_provider_recommendation_rate_positive_growth)^((COLUMN()-8)/12) -> 0.56235266 | O28: =western_public_provider_recommendation_rate_positive*(1+western_public_provider_recommendation_rate_positive_growth)^((COLUMN()-8)/12) -> 0.56464375 | ... AQ28: =western_public_provider_recommendation_rate_positive*(1+western_public_provider_recommendation_rate_positive_growth)^((COLUMN()-8)/12) -> 0.63272679
F29: times Western Public Acceptance Rate | H29: =western_public_acceptance_rate_positive*(1+western_public_acceptance_rate_positive_growth)^((COLUMN()-8)/12) -> 0.819 | I29: =western_public_acceptance_rate_positive*(1+western_public_acceptance_rate_positive_growth)^((COLUMN()-8)/12) -> 0.82068701 | J29: =western_public_acceptance_rate_positive*(1+western_public_acceptance_rate_positive_growth)^((COLUMN()-8)/12) -> 0.82237749 | K29: =western_public_acceptance_rate_positive*(1+western_public_acceptance_rate_positive_growth)^((COLUMN()-8)/12) -> 0.82407145 | L29: =western_public_acceptance_rate_positive*(1+western_public_acceptance_rate_positive_growth)^((COLUMN()-8)/12) -> 0.8257689 | M29: =western_public_acceptance_rate_positive*(1+western_public_acceptance_rate_positive_growth)^((COLUMN()-8)/12) -> 0.82746985 | N29: =western_public_acceptance_rate_positive*(1+western_public_acceptance_rate_positive_growth)^((COLUMN()-8)/12) -> 0.8291743 | O29: =western_public_acceptance_rate_positive*(1+western_public_acceptance_rate_positive_growth)^((COLUMN()-8)/12) -> 0.83088227 | ... AQ29: =western_public_acceptance_rate_positive*(1+western_public_acceptance_rate_positive_growth)^((COLUMN()-8)/12) -> 0.88016044
F30: times Western Public Stock Availability Rate | H30: =western_public_stock_availability_rate_positive*(1+western_public_stock_availability_rate_positive_growth)^((COLUMN()-8)/12) -> 0.9116 | I30: =western_public_stock_availability_rate_positive*(1+western_public_stock_availability_rate_positive_growth)^((COLUMN()-8)/12) -> 0.91310558 | J30: =western_public_stock_availability_rate_positive*(1+western_public_stock_availability_rate_positive_growth)^((COLUMN()-8)/12) -> 0.91461365 | K30: =western_public_stock_availability_rate_positive*(1+western_public_stock_availability_rate_positive_growth)^((COLUMN()-8)/12) -> 0.91612421 | L30: =western_public_stock_availability_rate_positive*(1+western_public_stock_availability_rate_positive_growth)^((COLUMN()-8)/12) -> 0.91763726 | M30: =western_public_stock_availability_rate_positive*(1+western_public_stock_availability_rate_positive_growth)^((COLUMN()-8)/12) -> 0.91915281 | N30: =western_public_stock_availability_rate_positive*(1+western_public_stock_availability_rate_positive_growth)^((COLUMN()-8)/12) -> 0.92067087 | O30: =western_public_stock_availability_rate_positive*(1+western_public_stock_availability_rate_positive_growth)^((COLUMN()-8)/12) -> 0.92219143 | ... AQ30: =western_public_stock_availability_rate_positive*(1+western_public_stock_availability_rate_positive_growth)^((COLUMN()-8)/12) -> 0.96580211
F31: times Western Public Active Coverage State | H31: =0.08 -> 0.08 | I31: =H31+I32-I33 -> 0.10137955 | J31: =I31+J32-J33 -> 0.12283892 | K31: =J31+K32-K33 -> 0.14437835 | L31: =K31+L32-L33 -> 0.16599813 | M31: =L31+M32-M33 -> 0.1876985 | N31: =M31+N32-N33 -> 0.20947973 | O31: =N31+O32-O33 -> 0.2313421 | P31: =O31+P32-P33 -> 0.25328585 | ... AQ31: =AP31+AQ32-AQ33 -> 0.87752846
G32: Western Public Coverage Additions | H32: =western_public_coverage_additions_positive*(1+western_public_coverage_additions_positive_growth)^((COLUMN()-8)/12) -> 0.0243 | I32: =western_public_coverage_additions_positive*(1+western_public_coverage_additions_positive_growth)^((COLUMN()-8)/12) -> 0.024379552 | J32: =western_public_coverage_additions_positive*(1+western_public_coverage_additions_positive_growth)^((COLUMN()-8)/12) -> 0.024459364 | K32: =western_public_coverage_additions_positive*(1+western_public_coverage_additions_positive_growth)^((COLUMN()-8)/12) -> 0.024539438 | L32: =western_public_coverage_additions_positive*(1+western_public_coverage_additions_positive_growth)^((COLUMN()-8)/12) -> 0.024619774 | M32: =western_public_coverage_additions_positive*(1+western_public_coverage_additions_positive_growth)^((COLUMN()-8)/12) -> 0.024700372 | N32: =western_public_coverage_additions_positive*(1+western_public_coverage_additions_positive_growth)^((COLUMN()-8)/12) -> 0.024781235 | O32: =western_public_coverage_additions_positive*(1+western_public_coverage_additions_positive_growth)^((COLUMN()-8)/12) -> 0.024862362 | ... AQ32: =western_public_coverage_additions_positive*(1+western_public_coverage_additions_positive_growth)^((COLUMN()-8)/12) -> 0.027245002
G33: plus Western Public Coverage Churn | H33: =western_public_coverage_churn_positive*(1+western_public_coverage_churn_positive_growth)^((COLUMN()-8)/12) -> 0.003 | I33: =western_public_coverage_churn_positive*(1+western_public_coverage_churn_positive_growth)^((COLUMN()-8)/12) -> 0.003 | J33: =western_public_coverage_churn_positive*(1+western_public_coverage_churn_positive_growth)^((COLUMN()-8)/12) -> 0.003 | K33: =western_public_coverage_churn_positive*(1+western_public_coverage_churn_positive_growth)^((COLUMN()-8)/12) -> 0.003 | L33: =western_public_coverage_churn_positive*(1+western_public_coverage_churn_positive_growth)^((COLUMN()-8)/12) -> 0.003 | M33: =western_public_coverage_churn_positive*(1+western_public_coverage_churn_positive_growth)^((COLUMN()-8)/12) -> 0.003 | N33: =western_public_coverage_churn_positive*(1+western_public_coverage_churn_positive_growth)^((COLUMN()-8)/12) -> 0.003 | O33: =western_public_coverage_churn_positive*(1+western_public_coverage_churn_positive_growth)^((COLUMN()-8)/12) -> 0.003 | ... AQ33: =western_public_coverage_churn_positive*(1+western_public_coverage_churn_positive_growth)^((COLUMN()-8)/12) -> 0.003
E34: times Western Public Net Realised Price Per Dose | H34: =western_public_net_price_per_dose_positive*(1+western_public_net_price_per_dose_positive_growth)^((COLUMN()-8)/12) -> 37260 | I34: =western_public_net_price_per_dose_positive*(1+western_public_net_price_per_dose_positive_growth)^((COLUMN()-8)/12) -> 37351.893 | J34: =western_public_net_price_per_dose_positive*(1+western_public_net_price_per_dose_positive_growth)^((COLUMN()-8)/12) -> 37444.013 | K34: =western_public_net_price_per_dose_positive*(1+western_public_net_price_per_dose_positive_growth)^((COLUMN()-8)/12) -> 37536.36 | L34: =western_public_net_price_per_dose_positive*(1+western_public_net_price_per_dose_positive_growth)^((COLUMN()-8)/12) -> 37628.935 | M34: =western_public_net_price_per_dose_positive*(1+western_public_net_price_per_dose_positive_growth)^((COLUMN()-8)/12) -> 37721.738 | N34: =western_public_net_price_per_dose_positive*(1+western_public_net_price_per_dose_positive_growth)^((COLUMN()-8)/12) -> 37814.77 | O34: =western_public_net_price_per_dose_positive*(1+western_public_net_price_per_dose_positive_growth)^((COLUMN()-8)/12) -> 37908.031 | ... AQ34: =western_public_net_price_per_dose_positive*(1+western_public_net_price_per_dose_positive_growth)^((COLUMN()-8)/12) -> 40614.841
D35: plus Eastern Public Revenue | H35: =(H36*H49) -> 2769509.5 | I35: =(I36*I49) -> 3390606.7 | J35: =(J36*J49) -> 4038383.6 | K35: =(K36*K49) -> 4713730.2 | L35: =(L36*L49) -> 5417563.1 | M35: =(M36*M49) -> 6150826.2 | N35: =(N36*N49) -> 6914491.8 | O35: =(O36*O49) -> 7709560.9 | ... AQ35: =(AQ36*AQ49) -> 47883301
E36: Eastern Public Administered Doses | H36: =(((((H37*H42)*H43)*H44)*H45)*H46) -> 76.548078 | I36: =(((((I37*I42)*I43)*I44)*I45)*I46) -> 93.484387 | J36: =(((((J37*J42)*J43)*J44)*J45)*J46) -> 111.07069 | K36: =(((((K37*K42)*K43)*K44)*K45)*K46) -> 129.3263 | L36: =(((((L37*L42)*L43)*L44)*L45)*L46) -> 148.27104 | M36: =(((((M37*M42)*M43)*M44)*M45)*M46) -> 167.92527 | N36: =(((((N37*N42)*N43)*N44)*N45)*N46) -> 188.30987 | O36: =(((((O37*O42)*O43)*O44)*O45)*O46) -> 209.4463 | ... AQ36: =(((((AQ37*AQ42)*AQ43)*AQ44)*AQ45)*AQ46) -> 1214.1536
F37: Eastern Reachable Pregnancies | H37: =(((H38*H39)*H40)*H41) -> 11484.349 | I37: =(((I38*I39)*I40)*I41) -> 11510.043 | J37: =(((J38*J39)*J40)*J41) -> 11535.794 | K37: =(((K38*K39)*K40)*K41) -> 11561.603 | L37: =(((L38*L39)*L40)*L41) -> 11587.469 | M37: =(((M38*M39)*M40)*M41) -> 11613.394 | N37: =(((N38*N39)*N40)*N41) -> 11639.377 | O37: =(((O38*O39)*O40)*O41) -> 11665.417 | ... AQ37: =(((AQ38*AQ39)*AQ40)*AQ41) -> 12418.693
G38: National Live Births Per Month | H38: =H8 -> 145833 | I38: =I8 -> 146049.97 | J38: =J8 -> 146267.25 | K38: =K8 -> 146484.86 | L38: =L8 -> 146702.8 | M38: =M8 -> 146921.06 | N38: =N8 -> 147139.64 | O38: =O8 -> 147358.55 | ... AQ38: =AQ8 -> 153622.03
G39: times Eastern Regional Opportunity Weight | H39: =eastern_regional_opportunity_weight_positive*(1+eastern_regional_opportunity_weight_positive_growth)^((COLUMN()-8)/12) -> 0.25 | I39: =eastern_regional_opportunity_weight_positive*(1+eastern_regional_opportunity_weight_positive_growth)^((COLUMN()-8)/12) -> 0.25 | J39: =eastern_regional_opportunity_weight_positive*(1+eastern_regional_opportunity_weight_positive_growth)^((COLUMN()-8)/12) -> 0.25 | K39: =eastern_regional_opportunity_weight_positive*(1+eastern_regional_opportunity_weight_positive_growth)^((COLUMN()-8)/12) -> 0.25 | L39: =eastern_regional_opportunity_weight_positive*(1+eastern_regional_opportunity_weight_positive_growth)^((COLUMN()-8)/12) -> 0.25 | M39: =eastern_regional_opportunity_weight_positive*(1+eastern_regional_opportunity_weight_positive_growth)^((COLUMN()-8)/12) -> 0.25 | N39: =eastern_regional_opportunity_weight_positive*(1+eastern_regional_opportunity_weight_positive_growth)^((COLUMN()-8)/12) -> 0.25 | O39: =eastern_regional_opportunity_weight_positive*(1+eastern_regional_opportunity_weight_positive_growth)^((COLUMN()-8)/12) -> 0.25 | ... AQ39: =eastern_regional_opportunity_weight_positive*(1+eastern_regional_opportunity_weight_positive_growth)^((COLUMN()-8)/12) -> 0.25
G40: times Eastern ANC Access Rate | H40: =eastern_anc_access_rate_positive*(1+eastern_anc_access_rate_positive_growth)^((COLUMN()-8)/12) -> 0.63 | I40: =eastern_anc_access_rate_positive*(1+eastern_anc_access_rate_positive_growth)^((COLUMN()-8)/12) -> 0.63015728 | J40: =eastern_anc_access_rate_positive*(1+eastern_anc_access_rate_positive_growth)^((COLUMN()-8)/12) -> 0.63031461 | K40: =eastern_anc_access_rate_positive*(1+eastern_anc_access_rate_positive_growth)^((COLUMN()-8)/12) -> 0.63047197 | L40: =eastern_anc_access_rate_positive*(1+eastern_anc_access_rate_positive_growth)^((COLUMN()-8)/12) -> 0.63062937 | M40: =eastern_anc_access_rate_positive*(1+eastern_anc_access_rate_positive_growth)^((COLUMN()-8)/12) -> 0.63078681 | N40: =eastern_anc_access_rate_positive*(1+eastern_anc_access_rate_positive_growth)^((COLUMN()-8)/12) -> 0.63094429 | O40: =eastern_anc_access_rate_positive*(1+eastern_anc_access_rate_positive_growth)^((COLUMN()-8)/12) -> 0.63110181 | ... AQ40: =eastern_anc_access_rate_positive*(1+eastern_anc_access_rate_positive_growth)^((COLUMN()-8)/12) -> 0.63552836
G41: times Eastern Third Trimester Window Rate | H41: =eastern_third_trimester_window_rate_positive*(1+eastern_third_trimester_window_rate_positive_growth)^((COLUMN()-8)/12) -> 0.5 | I41: =eastern_third_trimester_window_rate_positive*(1+eastern_third_trimester_window_rate_positive_growth)^((COLUMN()-8)/12) -> 0.50024932 | J41: =eastern_third_trimester_window_rate_positive*(1+eastern_third_trimester_window_rate_positive_growth)^((COLUMN()-8)/12) -> 0.50049875 | K41: =eastern_third_trimester_window_rate_positive*(1+eastern_third_trimester_window_rate_positive_growth)^((COLUMN()-8)/12) -> 0.50074832 | L41: =eastern_third_trimester_window_rate_positive*(1+eastern_third_trimester_window_rate_positive_growth)^((COLUMN()-8)/12) -> 0.50099801 | M41: =eastern_third_trimester_window_rate_positive*(1+eastern_third_trimester_window_rate_positive_growth)^((COLUMN()-8)/12) -> 0.50124782 | N41: =eastern_third_trimester_window_rate_positive*(1+eastern_third_trimester_window_rate_positive_growth)^((COLUMN()-8)/12) -> 0.50149776 | O41: =eastern_third_trimester_window_rate_positive*(1+eastern_third_trimester_window_rate_positive_growth)^((COLUMN()-8)/12) -> 0.50174782 | ... AQ41: =eastern_third_trimester_window_rate_positive*(1+eastern_third_trimester_window_rate_positive_growth)^((COLUMN()-8)/12) -> 0.5088004
F42: times Eastern Public Eligibility Rate | H42: =eastern_public_eligibility_rate_positive*(1+eastern_public_eligibility_rate_positive_growth)^((COLUMN()-8)/12) -> 0.2375 | I42: =eastern_public_eligibility_rate_positive*(1+eastern_public_eligibility_rate_positive_growth)^((COLUMN()-8)/12) -> 0.23939386 | J42: =eastern_public_eligibility_rate_positive*(1+eastern_public_eligibility_rate_positive_growth)^((COLUMN()-8)/12) -> 0.24130282 | K42: =eastern_public_eligibility_rate_positive*(1+eastern_public_eligibility_rate_positive_growth)^((COLUMN()-8)/12) -> 0.243227 | L42: =eastern_public_eligibility_rate_positive*(1+eastern_public_eligibility_rate_positive_growth)^((COLUMN()-8)/12) -> 0.24516653 | M42: =eastern_public_eligibility_rate_positive*(1+eastern_public_eligibility_rate_positive_growth)^((COLUMN()-8)/12) -> 0.24712152 | N42: =eastern_public_eligibility_rate_positive*(1+eastern_public_eligibility_rate_positive_growth)^((COLUMN()-8)/12) -> 0.2490921 | O42: =eastern_public_eligibility_rate_positive*(1+eastern_public_eligibility_rate_positive_growth)^((COLUMN()-8)/12) -> 0.2510784 | ... AQ42: =eastern_public_eligibility_rate_positive*(1+eastern_public_eligibility_rate_positive_growth)^((COLUMN()-8)/12) -> 0.31361172
F43: times Eastern Public Provider Recommendation Rate | H43: =eastern_public_provider_recommendation_rate_positive*(1+eastern_public_provider_recommendation_rate_positive_growth)^((COLUMN()-8)/12) -> 0.4928 | I43: =eastern_public_provider_recommendation_rate_positive*(1+eastern_public_provider_recommendation_rate_positive_growth)^((COLUMN()-8)/12) -> 0.49480773 | J43: =eastern_public_provider_recommendation_rate_positive*(1+eastern_public_provider_recommendation_rate_positive_growth)^((COLUMN()-8)/12) -> 0.49682364 | K43: =eastern_public_provider_recommendation_rate_positive*(1+eastern_public_provider_recommendation_rate_positive_growth)^((COLUMN()-8)/12) -> 0.49884776 | L43: =eastern_public_provider_recommendation_rate_positive*(1+eastern_public_provider_recommendation_rate_positive_growth)^((COLUMN()-8)/12) -> 0.50088012 | M43: =eastern_public_provider_recommendation_rate_positive*(1+eastern_public_provider_recommendation_rate_positive_growth)^((COLUMN()-8)/12) -> 0.50292077 | N43: =eastern_public_provider_recommendation_rate_positive*(1+eastern_public_provider_recommendation_rate_positive_growth)^((COLUMN()-8)/12) -> 0.50496973 | O43: =eastern_public_provider_recommendation_rate_positive*(1+eastern_public_provider_recommendation_rate_positive_growth)^((COLUMN()-8)/12) -> 0.50702704 | ... AQ43: =eastern_public_provider_recommendation_rate_positive*(1+eastern_public_provider_recommendation_rate_positive_growth)^((COLUMN()-8)/12) -> 0.56816283
F44: times Eastern Public Acceptance Rate | H44: =eastern_public_acceptance_rate_positive*(1+eastern_public_acceptance_rate_positive_growth)^((COLUMN()-8)/12) -> 0.819 | I44: =eastern_public_acceptance_rate_positive*(1+eastern_public_acceptance_rate_positive_growth)^((COLUMN()-8)/12) -> 0.82068701 | J44: =eastern_public_acceptance_rate_positive*(1+eastern_public_acceptance_rate_positive_growth)^((COLUMN()-8)/12) -> 0.82237749 | K44: =eastern_public_acceptance_rate_positive*(1+eastern_public_acceptance_rate_positive_growth)^((COLUMN()-8)/12) -> 0.82407145 | L44: =eastern_public_acceptance_rate_positive*(1+eastern_public_acceptance_rate_positive_growth)^((COLUMN()-8)/12) -> 0.8257689 | M44: =eastern_public_acceptance_rate_positive*(1+eastern_public_acceptance_rate_positive_growth)^((COLUMN()-8)/12) -> 0.82746985 | N44: =eastern_public_acceptance_rate_positive*(1+eastern_public_acceptance_rate_positive_growth)^((COLUMN()-8)/12) -> 0.8291743 | O44: =eastern_public_acceptance_rate_positive*(1+eastern_public_acceptance_rate_positive_growth)^((COLUMN()-8)/12) -> 0.83088227 | ... AQ44: =eastern_public_acceptance_rate_positive*(1+eastern_public_acceptance_rate_positive_growth)^((COLUMN()-8)/12) -> 0.88016044
F45: times Eastern Public Stock Availability Rate | H45: =eastern_public_stock_availability_rate_positive*(1+eastern_public_stock_availability_rate_positive_growth)^((COLUMN()-8)/12) -> 0.8692 | I45: =eastern_public_stock_availability_rate_positive*(1+eastern_public_stock_availability_rate_positive_growth)^((COLUMN()-8)/12) -> 0.87063555 | J45: =eastern_public_stock_availability_rate_positive*(1+eastern_public_stock_availability_rate_positive_growth)^((COLUMN()-8)/12) -> 0.87207348 | K45: =eastern_public_stock_availability_rate_positive*(1+eastern_public_stock_availability_rate_positive_growth)^((COLUMN()-8)/12) -> 0.87351378 | L45: =eastern_public_stock_availability_rate_positive*(1+eastern_public_stock_availability_rate_positive_growth)^((COLUMN()-8)/12) -> 0.87495646 | M45: =eastern_public_stock_availability_rate_positive*(1+eastern_public_stock_availability_rate_positive_growth)^((COLUMN()-8)/12) -> 0.87640152 | N45: =eastern_public_stock_availability_rate_positive*(1+eastern_public_stock_availability_rate_positive_growth)^((COLUMN()-8)/12) -> 0.87784897 | O45: =eastern_public_stock_availability_rate_positive*(1+eastern_public_stock_availability_rate_positive_growth)^((COLUMN()-8)/12) -> 0.87929881 | ... AQ45: =eastern_public_stock_availability_rate_positive*(1+eastern_public_stock_availability_rate_positive_growth)^((COLUMN()-8)/12) -> 0.92088108
F46: times Eastern Public Active Coverage State | H46: =0.08 -> 0.08 | I46: =H46+I47-I48 -> 0.095961874 | J46: =I46+J47-J48 -> 0.11198582 | K46: =J46+K47-K48 -> 0.12807205 | L46: =K46+L47-L48 -> 0.14422077 | M46: =L46+M47-M48 -> 0.16043217 | N46: =M46+N47-N48 -> 0.17670646 | O46: =N46+O47-O48 -> 0.19304385 | P46: =O46+P47-P48 -> 0.20944455 | ... AQ46: =AP46+AQ47-AQ48 -> 0.67696658
G47: Eastern Public Coverage Additions | H47: =eastern_public_coverage_additions_positive*(1+eastern_public_coverage_additions_positive_growth)^((COLUMN()-8)/12) -> 0.0189 | I47: =eastern_public_coverage_additions_positive*(1+eastern_public_coverage_additions_positive_growth)^((COLUMN()-8)/12) -> 0.018961874 | J47: =eastern_public_coverage_additions_positive*(1+eastern_public_coverage_additions_positive_growth)^((COLUMN()-8)/12) -> 0.01902395 | K47: =eastern_public_coverage_additions_positive*(1+eastern_public_coverage_additions_positive_growth)^((COLUMN()-8)/12) -> 0.019086229 | L47: =eastern_public_coverage_additions_positive*(1+eastern_public_coverage_additions_positive_growth)^((COLUMN()-8)/12) -> 0.019148713 | M47: =eastern_public_coverage_additions_positive*(1+eastern_public_coverage_additions_positive_growth)^((COLUMN()-8)/12) -> 0.019211401 | N47: =eastern_public_coverage_additions_positive*(1+eastern_public_coverage_additions_positive_growth)^((COLUMN()-8)/12) -> 0.019274294 | O47: =eastern_public_coverage_additions_positive*(1+eastern_public_coverage_additions_positive_growth)^((COLUMN()-8)/12) -> 0.019337393 | ... AQ47: =eastern_public_coverage_additions_positive*(1+eastern_public_coverage_additions_positive_growth)^((COLUMN()-8)/12) -> 0.021190557
G48: plus Eastern Public Coverage Churn | H48: =eastern_public_coverage_churn_positive*(1+eastern_public_coverage_churn_positive_growth)^((COLUMN()-8)/12) -> 0.003 | I48: =eastern_public_coverage_churn_positive*(1+eastern_public_coverage_churn_positive_growth)^((COLUMN()-8)/12) -> 0.003 | J48: =eastern_public_coverage_churn_positive*(1+eastern_public_coverage_churn_positive_growth)^((COLUMN()-8)/12) -> 0.003 | K48: =eastern_public_coverage_churn_positive*(1+eastern_public_coverage_churn_positive_growth)^((COLUMN()-8)/12) -> 0.003 | L48: =eastern_public_coverage_churn_positive*(1+eastern_public_coverage_churn_positive_growth)^((COLUMN()-8)/12) -> 0.003 | M48: =eastern_public_coverage_churn_positive*(1+eastern_public_coverage_churn_positive_growth)^((COLUMN()-8)/12) -> 0.003 | N48: =eastern_public_coverage_churn_positive*(1+eastern_public_coverage_churn_positive_growth)^((COLUMN()-8)/12) -> 0.003 | O48: =eastern_public_coverage_churn_positive*(1+eastern_public_coverage_churn_positive_growth)^((COLUMN()-8)/12) -> 0.003 | ... AQ48: =eastern_public_coverage_churn_positive*(1+eastern_public_coverage_churn_positive_growth)^((COLUMN()-8)/12) -> 0.003
E49: times Eastern Public Net Realised Price Per Dose | H49: =eastern_public_net_price_per_dose_positive*(1+eastern_public_net_price_per_dose_positive_growth)^((COLUMN()-8)/12) -> 36180 | I49: =eastern_public_net_price_per_dose_positive*(1+eastern_public_net_price_per_dose_positive_growth)^((COLUMN()-8)/12) -> 36269.23 | J49: =eastern_public_net_price_per_dose_positive*(1+eastern_public_net_price_per_dose_positive_growth)^((COLUMN()-8)/12) -> 36358.679 | K49: =eastern_public_net_price_per_dose_positive*(1+eastern_public_net_price_per_dose_positive_growth)^((COLUMN()-8)/12) -> 36448.35 | L49: =eastern_public_net_price_per_dose_positive*(1+eastern_public_net_price_per_dose_positive_growth)^((COLUMN()-8)/12) -> 36538.241 | M49: =eastern_public_net_price_per_dose_positive*(1+eastern_public_net_price_per_dose_positive_growth)^((COLUMN()-8)/12) -> 36628.354 | N49: =eastern_public_net_price_per_dose_positive*(1+eastern_public_net_price_per_dose_positive_growth)^((COLUMN()-8)/12) -> 36718.69 | O49: =eastern_public_net_price_per_dose_positive*(1+eastern_public_net_price_per_dose_positive_growth)^((COLUMN()-8)/12) -> 36809.248 | ... AQ49: =eastern_public_net_price_per_dose_positive*(1+eastern_public_net_price_per_dose_positive_growth)^((COLUMN()-8)/12) -> 39437.599
D50: plus Northern Public Revenue | H50: =(H51*H64) -> 1477889.7 | I50: =(I51*I64) -> 1732713.8 | J50: =(J51*J64) -> 1998358.9 | K50: =(K51*K64) -> 2275185.5 | L50: =(L51*L64) -> 2563564.7 | M50: =(M51*M64) -> 2863879.1 | N50: =(N51*N64) -> 3176522.3 | O50: =(O51*O64) -> 3501899.8 | ... AQ50: =(AQ51*AQ64) -> 19874292
E51: Northern Public Administered Doses | H51: =(((((H52*H57)*H58)*H59)*H60)*H61) -> 42.105121 | I51: =(((((I52*I57)*I58)*I59)*I60)*I61) -> 49.243618 | J51: =(((((J52*J57)*J58)*J59)*J60)*J61) -> 56.653513 | K51: =(((((K52*K57)*K58)*K59)*K60)*K61) -> 64.342863 | L51: =(((((L52*L57)*L58)*L59)*L60)*L61) -> 72.319947 | M51: =(((((M52*M57)*M58)*M59)*M60)*M61) -> 80.593258 | N51: =(((((N52*N57)*N58)*N59)*N60)*N61) -> 89.171521 | O51: =(((((O52*O57)*O58)*O59)*O60)*O61) -> 98.063688 | ... AQ51: =(((((AQ52*AQ57)*AQ58)*AQ59)*AQ60)*AQ61) -> 519.44868
F52: Northern Reachable Pregnancies | H52: =(((H53*H54)*H55)*H56) -> 8373.7309 | I52: =(((I53*I54)*I55)*I56) -> 8392.4653 | J52: =(((J53*J54)*J55)*J56) -> 8411.2417 | K52: =(((K53*K54)*K55)*K56) -> 8430.0601 | L52: =(((L53*L54)*L55)*L56) -> 8448.9206 | M52: =(((M53*M54)*M55)*M56) -> 8467.8233 | N52: =(((N53*N54)*N55)*N56) -> 8486.7683 | O52: =(((O53*O54)*O55)*O56) -> 8505.7556 | ... AQ52: =(((AQ53*AQ54)*AQ55)*AQ56) -> 9055.0013
G53: National Live Births Per Month | H53: =H8 -> 145833 | I53: =I8 -> 146049.97 | J53: =J8 -> 146267.25 | K53: =K8 -> 146484.86 | L53: =L8 -> 146702.8 | M53: =M8 -> 146921.06 | N53: =N8 -> 147139.64 | O53: =O8 -> 147358.55 | ... AQ53: =AQ8 -> 153622.03
G54: times Northern Regional Opportunity Weight | H54: =northern_regional_opportunity_weight_positive*(1+northern_regional_opportunity_weight_positive_growth)^((COLUMN()-8)/12) -> 0.22 | I54: =northern_regional_opportunity_weight_positive*(1+northern_regional_opportunity_weight_positive_growth)^((COLUMN()-8)/12) -> 0.22 | J54: =northern_regional_opportunity_weight_positive*(1+northern_regional_opportunity_weight_positive_growth)^((COLUMN()-8)/12) -> 0.22 | K54: =northern_regional_opportunity_weight_positive*(1+northern_regional_opportunity_weight_positive_growth)^((COLUMN()-8)/12) -> 0.22 | L54: =northern_regional_opportunity_weight_positive*(1+northern_regional_opportunity_weight_positive_growth)^((COLUMN()-8)/12) -> 0.22 | M54: =northern_regional_opportunity_weight_positive*(1+northern_regional_opportunity_weight_positive_growth)^((COLUMN()-8)/12) -> 0.22 | N54: =northern_regional_opportunity_weight_positive*(1+northern_regional_opportunity_weight_positive_growth)^((COLUMN()-8)/12) -> 0.22 | O54: =northern_regional_opportunity_weight_positive*(1+northern_regional_opportunity_weight_positive_growth)^((COLUMN()-8)/12) -> 0.22 | ... AQ54: =northern_regional_opportunity_weight_positive*(1+northern_regional_opportunity_weight_positive_growth)^((COLUMN()-8)/12) -> 0.22
G55: times Northern ANC Access Rate | H55: =northern_anc_access_rate_positive*(1+northern_anc_access_rate_positive_growth)^((COLUMN()-8)/12) -> 0.58 | I55: =northern_anc_access_rate_positive*(1+northern_anc_access_rate_positive_growth)^((COLUMN()-8)/12) -> 0.5801448 | J55: =northern_anc_access_rate_positive*(1+northern_anc_access_rate_positive_growth)^((COLUMN()-8)/12) -> 0.58028964 | K55: =northern_anc_access_rate_positive*(1+northern_anc_access_rate_positive_growth)^((COLUMN()-8)/12) -> 0.58043451 | L55: =northern_anc_access_rate_positive*(1+northern_anc_access_rate_positive_growth)^((COLUMN()-8)/12) -> 0.58057942 | M55: =northern_anc_access_rate_positive*(1+northern_anc_access_rate_positive_growth)^((COLUMN()-8)/12) -> 0.58072437 | N55: =northern_anc_access_rate_positive*(1+northern_anc_access_rate_positive_growth)^((COLUMN()-8)/12) -> 0.58086935 | O55: =northern_anc_access_rate_positive*(1+northern_anc_access_rate_positive_growth)^((COLUMN()-8)/12) -> 0.58101437 | ... AQ55: =northern_anc_access_rate_positive*(1+northern_anc_access_rate_positive_growth)^((COLUMN()-8)/12) -> 0.5850896
G56: times Northern Third Trimester Window Rate | H56: =northern_third_trimester_window_rate_positive*(1+northern_third_trimester_window_rate_positive_growth)^((COLUMN()-8)/12) -> 0.45 | I56: =northern_third_trimester_window_rate_positive*(1+northern_third_trimester_window_rate_positive_growth)^((COLUMN()-8)/12) -> 0.45022438 | J56: =northern_third_trimester_window_rate_positive*(1+northern_third_trimester_window_rate_positive_growth)^((COLUMN()-8)/12) -> 0.45044888 | K56: =northern_third_trimester_window_rate_positive*(1+northern_third_trimester_window_rate_positive_growth)^((COLUMN()-8)/12) -> 0.45067349 | L56: =northern_third_trimester_window_rate_positive*(1+northern_third_trimester_window_rate_positive_growth)^((COLUMN()-8)/12) -> 0.45089821 | M56: =northern_third_trimester_window_rate_positive*(1+northern_third_trimester_window_rate_positive_growth)^((COLUMN()-8)/12) -> 0.45112304 | N56: =northern_third_trimester_window_rate_positive*(1+northern_third_trimester_window_rate_positive_growth)^((COLUMN()-8)/12) -> 0.45134798 | O56: =northern_third_trimester_window_rate_positive*(1+northern_third_trimester_window_rate_positive_growth)^((COLUMN()-8)/12) -> 0.45157304 | ... AQ56: =northern_third_trimester_window_rate_positive*(1+northern_third_trimester_window_rate_positive_growth)^((COLUMN()-8)/12) -> 0.45792036
F57: times Northern Public Eligibility Rate | H57: =northern_public_eligibility_rate_positive*(1+northern_public_eligibility_rate_positive_growth)^((COLUMN()-8)/12) -> 0.2125 | I57: =northern_public_eligibility_rate_positive*(1+northern_public_eligibility_rate_positive_growth)^((COLUMN()-8)/12) -> 0.2141945 | J57: =northern_public_eligibility_rate_positive*(1+northern_public_eligibility_rate_positive_growth)^((COLUMN()-8)/12) -> 0.21590252 | K57: =northern_public_eligibility_rate_positive*(1+northern_public_eligibility_rate_positive_growth)^((COLUMN()-8)/12) -> 0.21762416 | L57: =northern_public_eligibility_rate_positive*(1+northern_public_eligibility_rate_positive_growth)^((COLUMN()-8)/12) -> 0.21935952 | M57: =northern_public_eligibility_rate_positive*(1+northern_public_eligibility_rate_positive_growth)^((COLUMN()-8)/12) -> 0.22110873 | N57: =northern_public_eligibility_rate_positive*(1+northern_public_eligibility_rate_positive_growth)^((COLUMN()-8)/12) -> 0.22287188 | O57: =northern_public_eligibility_rate_positive*(1+northern_public_eligibility_rate_positive_growth)^((COLUMN()-8)/12) -> 0.22464909 | ... AQ57: =northern_public_eligibility_rate_positive*(1+northern_public_eligibility_rate_positive_growth)^((COLUMN()-8)/12) -> 0.28059996
F58: times Northern Public Provider Recommendation Rate | H58: =northern_public_provider_recommendation_rate_positive*(1+northern_public_provider_recommendation_rate_positive_growth)^((COLUMN()-8)/12) -> 0.4368 | I58: =northern_public_provider_recommendation_rate_positive*(1+northern_public_provider_recommendation_rate_positive_growth)^((COLUMN()-8)/12) -> 0.43857958 | J58: =northern_public_provider_recommendation_rate_positive*(1+northern_public_provider_recommendation_rate_positive_growth)^((COLUMN()-8)/12) -> 0.4403664 | K58: =northern_public_provider_recommendation_rate_positive*(1+northern_public_provider_recommendation_rate_positive_growth)^((COLUMN()-8)/12) -> 0.44216051 | L58: =northern_public_provider_recommendation_rate_positive*(1+northern_public_provider_recommendation_rate_positive_growth)^((COLUMN()-8)/12) -> 0.44396193 | M58: =northern_public_provider_recommendation_rate_positive*(1+northern_public_provider_recommendation_rate_positive_growth)^((COLUMN()-8)/12) -> 0.44577068 | N58: =northern_public_provider_recommendation_rate_positive*(1+northern_public_provider_recommendation_rate_positive_growth)^((COLUMN()-8)/12) -> 0.44758681 | O58: =northern_public_provider_recommendation_rate_positive*(1+northern_public_provider_recommendation_rate_positive_growth)^((COLUMN()-8)/12) -> 0.44941033 | ... AQ58: =northern_public_provider_recommendation_rate_positive*(1+northern_public_provider_recommendation_rate_positive_growth)^((COLUMN()-8)/12) -> 0.50359888
F59: times Northern Public Acceptance Rate | H59: =northern_public_acceptance_rate_positive*(1+northern_public_acceptance_rate_positive_growth)^((COLUMN()-8)/12) -> 0.819 | I59: =northern_public_acceptance_rate_positive*(1+northern_public_acceptance_rate_positive_growth)^((COLUMN()-8)/12) -> 0.82068701 | J59: =northern_public_acceptance_rate_positive*(1+northern_public_acceptance_rate_positive_growth)^((COLUMN()-8)/12) -> 0.82237749 | K59: =northern_public_acceptance_rate_positive*(1+northern_public_acceptance_rate_positive_growth)^((COLUMN()-8)/12) -> 0.82407145 | L59: =northern_public_acceptance_rate_positive*(1+northern_public_acceptance_rate_positive_growth)^((COLUMN()-8)/12) -> 0.8257689 | M59: =northern_public_acceptance_rate_positive*(1+northern_public_acceptance_rate_positive_growth)^((COLUMN()-8)/12) -> 0.82746985 | N59: =northern_public_acceptance_rate_positive*(1+northern_public_acceptance_rate_positive_growth)^((COLUMN()-8)/12) -> 0.8291743 | O59: =northern_public_acceptance_rate_positive*(1+northern_public_acceptance_rate_positive_growth)^((COLUMN()-8)/12) -> 0.83088227 | ... AQ59: =northern_public_acceptance_rate_positive*(1+northern_public_acceptance_rate_positive_growth)^((COLUMN()-8)/12) -> 0.88016044
F60: times Northern Public Stock Availability Rate | H60: =northern_public_stock_availability_rate_positive*(1+northern_public_stock_availability_rate_positive_growth)^((COLUMN()-8)/12) -> 0.8268 | I60: =northern_public_stock_availability_rate_positive*(1+northern_public_stock_availability_rate_positive_growth)^((COLUMN()-8)/12) -> 0.82816553 | J60: =northern_public_stock_availability_rate_positive*(1+northern_public_stock_availability_rate_positive_growth)^((COLUMN()-8)/12) -> 0.82953331 | K60: =northern_public_stock_availability_rate_positive*(1+northern_public_stock_availability_rate_positive_growth)^((COLUMN()-8)/12) -> 0.83090335 | L60: =northern_public_stock_availability_rate_positive*(1+northern_public_stock_availability_rate_positive_growth)^((COLUMN()-8)/12) -> 0.83227566 | M60: =northern_public_stock_availability_rate_positive*(1+northern_public_stock_availability_rate_positive_growth)^((COLUMN()-8)/12) -> 0.83365023 | N60: =northern_public_stock_availability_rate_positive*(1+northern_public_stock_availability_rate_positive_growth)^((COLUMN()-8)/12) -> 0.83502707 | O60: =northern_public_stock_availability_rate_positive*(1+northern_public_stock_availability_rate_positive_growth)^((COLUMN()-8)/12) -> 0.83640618 | ... AQ60: =northern_public_stock_availability_rate_positive*(1+northern_public_stock_availability_rate_positive_growth)^((COLUMN()-8)/12) -> 0.87596006
F61: times Northern Public Active Coverage State | H61: =0.08 -> 0.08 | I61: =H61+I62-I63 -> 0.091898615 | J61: =I61+J62-J63 -> 0.103846 | K61: =J61+K62-K63 -> 0.11584233 | L61: =K61+L62-L63 -> 0.12788774 | M61: =L61+M62-M63 -> 0.13998242 | N61: =M61+N62-N63 -> 0.1521265 | O61: =N61+O62-O63 -> 0.16432017 | P61: =O61+P62-P63 -> 0.17656358 | ... AQ61: =AP61+AQ62-AQ63 -> 0.52654517
G62: Northern Public Coverage Additions | H62: =northern_public_coverage_additions_positive*(1+northern_public_coverage_additions_positive_growth)^((COLUMN()-8)/12) -> 0.01485 | I62: =northern_public_coverage_additions_positive*(1+northern_public_coverage_additions_positive_growth)^((COLUMN()-8)/12) -> 0.014898615 | J62: =northern_public_coverage_additions_positive*(1+northern_public_coverage_additions_positive_growth)^((COLUMN()-8)/12) -> 0.014947389 | K62: =northern_public_coverage_additions_positive*(1+northern_public_coverage_additions_positive_growth)^((COLUMN()-8)/12) -> 0.014996323 | L62: =northern_public_coverage_additions_positive*(1+northern_public_coverage_additions_positive_growth)^((COLUMN()-8)/12) -> 0.015045417 | M62: =northern_public_coverage_additions_positive*(1+northern_public_coverage_additions_positive_growth)^((COLUMN()-8)/12) -> 0.015094672 | N62: =northern_public_coverage_additions_positive*(1+northern_public_coverage_additions_positive_growth)^((COLUMN()-8)/12) -> 0.015144088 | O62: =northern_public_coverage_additions_positive*(1+northern_public_coverage_additions_positive_growth)^((COLUMN()-8)/12) -> 0.015193666 | ... AQ62: =northern_public_coverage_additions_positive*(1+northern_public_coverage_additions_positive_growth)^((COLUMN()-8)/12) -> 0.016649724
G63: plus Northern Public Coverage Churn | H63: =northern_public_coverage_churn_positive*(1+northern_public_coverage_churn_positive_growth)^((COLUMN()-8)/12) -> 0.003 | I63: =northern_public_coverage_churn_positive*(1+northern_public_coverage_churn_positive_growth)^((COLUMN()-8)/12) -> 0.003 | J63: =northern_public_coverage_churn_positive*(1+northern_public_coverage_churn_positive_growth)^((COLUMN()-8)/12) -> 0.003 | K63: =northern_public_coverage_churn_positive*(1+northern_public_coverage_churn_positive_growth)^((COLUMN()-8)/12) -> 0.003 | L63: =northern_public_coverage_churn_positive*(1+northern_public_coverage_churn_positive_growth)^((COLUMN()-8)/12) -> 0.003 | M63: =northern_public_coverage_churn_positive*(1+northern_public_coverage_churn_positive_growth)^((COLUMN()-8)/12) -> 0.003 | N63: =northern_public_coverage_churn_positive*(1+northern_public_coverage_churn_positive_growth)^((COLUMN()-8)/12) -> 0.003 | O63: =northern_public_coverage_churn_positive*(1+northern_public_coverage_churn_positive_growth)^((COLUMN()-8)/12) -> 0.003 | ... AQ63: =northern_public_coverage_churn_positive*(1+northern_public_coverage_churn_positive_growth)^((COLUMN()-8)/12) -> 0.003
E64: times Northern Public Net Realised Price Per Dose | H64: =northern_public_net_price_per_dose_positive*(1+northern_public_net_price_per_dose_positive_growth)^((COLUMN()-8)/12) -> 35100 | I64: =northern_public_net_price_per_dose_positive*(1+northern_public_net_price_per_dose_positive_growth)^((COLUMN()-8)/12) -> 35186.566 | J64: =northern_public_net_price_per_dose_positive*(1+northern_public_net_price_per_dose_positive_growth)^((COLUMN()-8)/12) -> 35273.346 | K64: =northern_public_net_price_per_dose_positive*(1+northern_public_net_price_per_dose_positive_growth)^((COLUMN()-8)/12) -> 35360.339 | L64: =northern_public_net_price_per_dose_positive*(1+northern_public_net_price_per_dose_positive_growth)^((COLUMN()-8)/12) -> 35447.547 | M64: =northern_public_net_price_per_dose_positive*(1+northern_public_net_price_per_dose_positive_growth)^((COLUMN()-8)/12) -> 35534.971 | N64: =northern_public_net_price_per_dose_positive*(1+northern_public_net_price_per_dose_positive_growth)^((COLUMN()-8)/12) -> 35622.609 | O64: =northern_public_net_price_per_dose_positive*(1+northern_public_net_price_per_dose_positive_growth)^((COLUMN()-8)/12) -> 35710.464 | ... AQ64: =northern_public_net_price_per_dose_positive*(1+northern_public_net_price_per_dose_positive_growth)^((COLUMN()-8)/12) -> 38260.357
C65: plus Private Revenue | H65: =(((H66+H77)+H88)+H99) -> 8366003.6 | I65: =(((I66+I77)+I88)+I99) -> 12245258 | J65: =(((J66+J77)+J88)+J99) -> 16287409 | K65: =(((K66+K77)+K88)+K99) -> 20497672 | L65: =(((L66+L77)+L88)+L99) -> 24881411 | M65: =(((M66+M77)+M88)+M99) -> 29444143 | N65: =(((N66+N77)+N88)+N99) -> 34191542 | O65: =(((O66+O77)+O88)+O99) -> 39129446 | ... AQ65: =(((AQ66+AQ77)+AQ88)+AQ99) -> 2.844938e+08
D66: Central Private Revenue | H66: =(H67*H76) -> 6179888.1 | I66: =(I67*I76) -> 9359826.3 | J66: =(J67*J76) -> 12673389 | K66: =(K67*K76) -> 16124852 | L66: =(L67*L76) -> 19718611 | M66: =(M67*M76) -> 23459188 | N66: =(N67*N76) -> 27351237 | O66: =(O67*O76) -> 31399538 | ... AQ66: =(AQ67*AQ76) -> 2.3257589e+08
E67: Central Private Administered Doses | H67: =(((((H68*H69)*H70)*H71)*H72)*H73) -> 49.878031 | I67: =(((((I68*I69)*I70)*I71)*I72)*I73) -> 75.327135 | J67: =(((((J68*J69)*J70)*J71)*J72)*J73) -> 101.70245 | K67: =(((((K68*K69)*K70)*K71)*K72)*K73) -> 129.02959 | L67: =(((((L68*L69)*L70)*L71)*L72)*L73) -> 157.33483 | M67: =(((((M68*M69)*M70)*M71)*M72)*M73) -> 186.64507 | N67: =(((((N68*N69)*N70)*N71)*N72)*N73) -> 216.98788 | O67: =(((((O68*O69)*O70)*O71)*O72)*O73) -> 248.39151 | ... AQ67: =(((((AQ68*AQ69)*AQ70)*AQ71)*AQ72)*AQ73) -> 1697.9206
F68: Central Reachable Pregnancies | H68: =H7 -> 18227.958 | I68: =I7 -> 18268.74 | J68: =J7 -> 18309.612 | K68: =K7 -> 18350.576 | L68: =L7 -> 18391.632 | M68: =M7 -> 18432.779 | N68: =N7 -> 18474.018 | O68: =O7 -> 18515.35 | ... AQ68: =AQ7 -> 19710.949
F69: times Central Private Eligibility Rate | H69: =central_private_eligibility_rate_positive*(1+central_private_eligibility_rate_positive_growth)^((COLUMN()-8)/12) -> 0.0875 | I69: =central_private_eligibility_rate_positive*(1+central_private_eligibility_rate_positive_growth)^((COLUMN()-8)/12) -> 0.088062978 | J69: =central_private_eligibility_rate_positive*(1+central_private_eligibility_rate_positive_growth)^((COLUMN()-8)/12) -> 0.088629577 | K69: =central_private_eligibility_rate_positive*(1+central_private_eligibility_rate_positive_growth)^((COLUMN()-8)/12) -> 0.089199823 | L69: =central_private_eligibility_rate_positive*(1+central_private_eligibility_rate_positive_growth)^((COLUMN()-8)/12) -> 0.089773737 | M69: =central_private_eligibility_rate_positive*(1+central_private_eligibility_rate_positive_growth)^((COLUMN()-8)/12) -> 0.090351344 | N69: =central_private_eligibility_rate_positive*(1+central_private_eligibility_rate_positive_growth)^((COLUMN()-8)/12) -> 0.090932667 | O69: =central_private_eligibility_rate_positive*(1+central_private_eligibility_rate_positive_growth)^((COLUMN()-8)/12) -> 0.091517731 | ... AQ69: =central_private_eligibility_rate_positive*(1+central_private_eligibility_rate_positive_growth)^((COLUMN()-8)/12) -> 0.10952014
F70: times Central Private Provider Recommendation Rate | H70: =central_private_provider_recommendation_rate_positive*(1+central_private_provider_recommendation_rate_positive_growth)^((COLUMN()-8)/12) -> 0.7504 | I70: =central_private_provider_recommendation_rate_positive*(1+central_private_provider_recommendation_rate_positive_growth)^((COLUMN()-8)/12) -> 0.75345722 | J70: =central_private_provider_recommendation_rate_positive*(1+central_private_provider_recommendation_rate_positive_growth)^((COLUMN()-8)/12) -> 0.7565269 | K70: =central_private_provider_recommendation_rate_positive*(1+central_private_provider_recommendation_rate_positive_growth)^((COLUMN()-8)/12) -> 0.75960908 | L70: =central_private_provider_recommendation_rate_positive*(1+central_private_provider_recommendation_rate_positive_growth)^((COLUMN()-8)/12) -> 0.76270383 | M70: =central_private_provider_recommendation_rate_positive*(1+central_private_provider_recommendation_rate_positive_growth)^((COLUMN()-8)/12) -> 0.76581118 | N70: =central_private_provider_recommendation_rate_positive*(1+central_private_provider_recommendation_rate_positive_growth)^((COLUMN()-8)/12) -> 0.76893119 | O70: =central_private_provider_recommendation_rate_positive*(1+central_private_provider_recommendation_rate_positive_growth)^((COLUMN()-8)/12) -> 0.77206391 | ... AQ70: =central_private_provider_recommendation_rate_positive*(1+central_private_provider_recommendation_rate_positive_growth)^((COLUMN()-8)/12) -> 0.86515704
F71: times Central Private Acceptance Rate | H71: =central_private_acceptance_rate_positive*(1+central_private_acceptance_rate_positive_growth)^((COLUMN()-8)/12) -> 0.8505 | I71: =central_private_acceptance_rate_positive*(1+central_private_acceptance_rate_positive_growth)^((COLUMN()-8)/12) -> 0.85225189 | J71: =central_private_acceptance_rate_positive*(1+central_private_acceptance_rate_positive_growth)^((COLUMN()-8)/12) -> 0.85400739 | K71: =central_private_acceptance_rate_positive*(1+central_private_acceptance_rate_positive_growth)^((COLUMN()-8)/12) -> 0.85576651 | L71: =central_private_acceptance_rate_positive*(1+central_private_acceptance_rate_positive_growth)^((COLUMN()-8)/12) -> 0.85752924 | M71: =central_private_acceptance_rate_positive*(1+central_private_acceptance_rate_positive_growth)^((COLUMN()-8)/12) -> 0.85929561 | N71: =central_private_acceptance_rate_positive*(1+central_private_acceptance_rate_positive_growth)^((COLUMN()-8)/12) -> 0.86106562 | O71: =central_private_acceptance_rate_positive*(1+central_private_acceptance_rate_positive_growth)^((COLUMN()-8)/12) -> 0.86283928 | ... AQ71: =central_private_acceptance_rate_positive*(1+central_private_acceptance_rate_positive_growth)^((COLUMN()-8)/12) -> 0.91401276
F72: times Central Private Stock Availability Rate | H72: =central_private_stock_availability_rate_positive*(1+central_private_stock_availability_rate_positive_growth)^((COLUMN()-8)/12) -> 0.98 | I72: =central_private_stock_availability_rate_positive*(1+central_private_stock_availability_rate_positive_growth)^((COLUMN()-8)/12) -> 0.98161855 | J72: =central_private_stock_availability_rate_positive*(1+central_private_stock_availability_rate_positive_growth)^((COLUMN()-8)/12) -> 0.98323977 | K72: =central_private_stock_availability_rate_positive*(1+central_private_stock_availability_rate_positive_growth)^((COLUMN()-8)/12) -> 0.98486367 | L72: =central_private_stock_availability_rate_positive*(1+central_private_stock_availability_rate_positive_growth)^((COLUMN()-8)/12) -> 0.98649026 | M72: =central_private_stock_availability_rate_positive*(1+central_private_stock_availability_rate_positive_growth)^((COLUMN()-8)/12) -> 0.98811952 | N72: =central_private_stock_availability_rate_positive*(1+central_private_stock_availability_rate_positive_growth)^((COLUMN()-8)/12) -> 0.98975148 | O72: =central_private_stock_availability_rate_positive*(1+central_private_stock_availability_rate_positive_growth)^((COLUMN()-8)/12) -> 0.99138614 | ... AQ72: =central_private_stock_availability_rate_positive*(1+central_private_stock_availability_rate_positive_growth)^((COLUMN()-8)/12) -> 1.0382691
F73: times Central Private Active Coverage State | H73: =0.05 -> 0.05 | I73: =H73+I74-I75 -> 0.074281415 | J73: =I73+J74-J75 -> 0.098657054 | K73: =J73+K74-K75 -> 0.12312722 | L73: =K73+L74-L75 -> 0.14769223 | M73: =L73+M74-M75 -> 0.1723524 | N73: =M73+N74-N75 -> 0.19710802 | O73: =N73+O74-O75 -> 0.22195942 | P73: =O73+P74-P75 -> 0.24690691 | ... AQ73: =AP73+AQ74-AQ75 -> 0.95798499
G74: Central Private Coverage Additions | H74: =central_private_coverage_additions_positive*(1+central_private_coverage_additions_positive_growth)^((COLUMN()-8)/12) -> 0.0286875 | I74: =central_private_coverage_additions_positive*(1+central_private_coverage_additions_positive_growth)^((COLUMN()-8)/12) -> 0.028781415 | J74: =central_private_coverage_additions_positive*(1+central_private_coverage_additions_positive_growth)^((COLUMN()-8)/12) -> 0.028875638 | K74: =central_private_coverage_additions_positive*(1+central_private_coverage_additions_positive_growth)^((COLUMN()-8)/12) -> 0.02897017 | L74: =central_private_coverage_additions_positive*(1+central_private_coverage_additions_positive_growth)^((COLUMN()-8)/12) -> 0.02906501 | M74: =central_private_coverage_additions_positive*(1+central_private_coverage_additions_positive_growth)^((COLUMN()-8)/12) -> 0.029160162 | N74: =central_private_coverage_additions_positive*(1+central_private_coverage_additions_positive_growth)^((COLUMN()-8)/12) -> 0.029255624 | O74: =central_private_coverage_additions_positive*(1+central_private_coverage_additions_positive_growth)^((COLUMN()-8)/12) -> 0.0293514 | ... AQ74: =central_private_coverage_additions_positive*(1+central_private_coverage_additions_positive_growth)^((COLUMN()-8)/12) -> 0.032164239
G75: plus Central Private Coverage Churn | H75: =central_private_coverage_churn_positive*(1+central_private_coverage_churn_positive_growth)^((COLUMN()-8)/12) -> 0.0045 | I75: =central_private_coverage_churn_positive*(1+central_private_coverage_churn_positive_growth)^((COLUMN()-8)/12) -> 0.0045 | J75: =central_private_coverage_churn_positive*(1+central_private_coverage_churn_positive_growth)^((COLUMN()-8)/12) -> 0.0045 | K75: =central_private_coverage_churn_positive*(1+central_private_coverage_churn_positive_growth)^((COLUMN()-8)/12) -> 0.0045 | L75: =central_private_coverage_churn_positive*(1+central_private_coverage_churn_positive_growth)^((COLUMN()-8)/12) -> 0.0045 | M75: =central_private_coverage_churn_positive*(1+central_private_coverage_churn_positive_growth)^((COLUMN()-8)/12) -> 0.0045 | N75: =central_private_coverage_churn_positive*(1+central_private_coverage_churn_positive_growth)^((COLUMN()-8)/12) -> 0.0045 | O75: =central_private_coverage_churn_positive*(1+central_private_coverage_churn_positive_growth)^((COLUMN()-8)/12) -> 0.0045 | ... AQ75: =central_private_coverage_churn_positive*(1+central_private_coverage_churn_positive_growth)^((COLUMN()-8)/12) -> 0.0045
E76: times Central Private Net Realised Price Per Dose | H76: =central_private_net_price_per_dose_positive*(1+central_private_net_price_per_dose_positive_growth)^((COLUMN()-8)/12) -> 123900 | I76: =central_private_net_price_per_dose_positive*(1+central_private_net_price_per_dose_positive_growth)^((COLUMN()-8)/12) -> 124255.7 | J76: =central_private_net_price_per_dose_positive*(1+central_private_net_price_per_dose_positive_growth)^((COLUMN()-8)/12) -> 124612.43 | K76: =central_private_net_price_per_dose_positive*(1+central_private_net_price_per_dose_positive_growth)^((COLUMN()-8)/12) -> 124970.18 | L76: =central_private_net_price_per_dose_positive*(1+central_private_net_price_per_dose_positive_growth)^((COLUMN()-8)/12) -> 125328.96 | M76: =central_private_net_price_per_dose_positive*(1+central_private_net_price_per_dose_positive_growth)^((COLUMN()-8)/12) -> 125688.76 | N76: =central_private_net_price_per_dose_positive*(1+central_private_net_price_per_dose_positive_growth)^((COLUMN()-8)/12) -> 126049.6 | O76: =central_private_net_price_per_dose_positive*(1+central_private_net_price_per_dose_positive_growth)^((COLUMN()-8)/12) -> 126411.48 | ... AQ76: =central_private_net_price_per_dose_positive*(1+central_private_net_price_per_dose_positive_growth)^((COLUMN()-8)/12) -> 136976.9
D77: plus Western Private Revenue | H77: =(H78*H87) -> 1577860.9 | I77: =(I78*I87) -> 2130502.6 | J77: =(J78*J87) -> 2706297.4 | K77: =(K78*K87) -> 3305988.3 | L77: =(L78*L87) -> 3930339.5 | M77: =(M78*M87) -> 4580137.3 | N77: =(N78*N87) -> 5256190.4 | O77: =(O78*O87) -> 5959330.5 | ... AQ77: =(AQ78*AQ87) -> 40889061
E78: Western Private Administered Doses | H78: =(((((H79*H80)*H81)*H82)*H83)*H84) -> 14.732595 | I78: =(((((I79*I80)*I81)*I82)*I83)*I84) -> 19.835702 | J78: =(((((J79*J80)*J81)*J82)*J83)*J84) -> 25.124417 | K78: =(((((K79*K80)*K81)*K82)*K83)*K84) -> 30.603899 | L78: =(((((L79*L80)*L81)*L82)*L83)*L84) -> 36.279432 | M78: =(((((M79*M80)*M81)*M82)*M83)*M84) -> 42.156436 | N78: =(((((N79*N80)*N81)*N82)*N83)*N84) -> 48.24046 | O78: =(((((O79*O80)*O81)*O82)*O83)*O84) -> 54.537195 | ... AQ78: =(((((AQ79*AQ80)*AQ81)*AQ82)*AQ83)*AQ84) -> 345.33583
F79: Western Reachable Pregnancies | H79: =H22 -> 13474.969 | I79: =I22 -> 13505.117 | J79: =J22 -> 13535.331 | K79: =K22 -> 13565.614 | L79: =L22 -> 13595.964 | M79: =M22 -> 13626.382 | N79: =N22 -> 13656.868 | O79: =O22 -> 13687.423 | ... AQ79: =AQ22 -> 14571.266
F80: times Western Private Eligibility Rate | H80: =western_private_eligibility_rate_positive*(1+western_private_eligibility_rate_positive_growth)^((COLUMN()-8)/12) -> 0.04375 | I80: =western_private_eligibility_rate_positive*(1+western_private_eligibility_rate_positive_growth)^((COLUMN()-8)/12) -> 0.044031489 | J80: =western_private_eligibility_rate_positive*(1+western_private_eligibility_rate_positive_growth)^((COLUMN()-8)/12) -> 0.044314789 | K80: =western_private_eligibility_rate_positive*(1+western_private_eligibility_rate_positive_growth)^((COLUMN()-8)/12) -> 0.044599911 | L80: =western_private_eligibility_rate_positive*(1+western_private_eligibility_rate_positive_growth)^((COLUMN()-8)/12) -> 0.044886869 | M80: =western_private_eligibility_rate_positive*(1+western_private_eligibility_rate_positive_growth)^((COLUMN()-8)/12) -> 0.045175672 | N80: =western_private_eligibility_rate_positive*(1+western_private_eligibility_rate_positive_growth)^((COLUMN()-8)/12) -> 0.045466334 | O80: =western_private_eligibility_rate_positive*(1+western_private_eligibility_rate_positive_growth)^((COLUMN()-8)/12) -> 0.045758865 | ... AQ80: =western_private_eligibility_rate_positive*(1+western_private_eligibility_rate_positive_growth)^((COLUMN()-8)/12) -> 0.054760072
F81: times Western Private Provider Recommendation Rate | H81: =western_private_provider_recommendation_rate_positive*(1+western_private_provider_recommendation_rate_positive_growth)^((COLUMN()-8)/12) -> 0.616 | I81: =western_private_provider_recommendation_rate_positive*(1+western_private_provider_recommendation_rate_positive_growth)^((COLUMN()-8)/12) -> 0.61850966 | J81: =western_private_provider_recommendation_rate_positive*(1+western_private_provider_recommendation_rate_positive_growth)^((COLUMN()-8)/12) -> 0.62102955 | K81: =western_private_provider_recommendation_rate_positive*(1+western_private_provider_recommendation_rate_positive_growth)^((COLUMN()-8)/12) -> 0.6235597 | L81: =western_private_provider_recommendation_rate_positive*(1+western_private_provider_recommendation_rate_positive_growth)^((COLUMN()-8)/12) -> 0.62610016 | M81: =western_private_provider_recommendation_rate_positive*(1+western_private_provider_recommendation_rate_positive_growth)^((COLUMN()-8)/12) -> 0.62865097 | N81: =western_private_provider_recommendation_rate_positive*(1+western_private_provider_recommendation_rate_positive_growth)^((COLUMN()-8)/12) -> 0.63121217 | O81: =western_private_provider_recommendation_rate_positive*(1+western_private_provider_recommendation_rate_positive_growth)^((COLUMN()-8)/12) -> 0.6337838 | ... AQ81: =western_private_provider_recommendation_rate_positive*(1+western_private_provider_recommendation_rate_positive_growth)^((COLUMN()-8)/12) -> 0.71020354
F82: times Western Private Acceptance Rate | H82: =western_private_acceptance_rate_positive*(1+western_private_acceptance_rate_positive_growth)^((COLUMN()-8)/12) -> 0.8505 | I82: =western_private_acceptance_rate_positive*(1+western_private_acceptance_rate_positive_growth)^((COLUMN()-8)/12) -> 0.85225189 | J82: =western_private_acceptance_rate_positive*(1+western_private_acceptance_rate_positive_growth)^((COLUMN()-8)/12) -> 0.85400739 | K82: =western_private_acceptance_rate_positive*(1+western_private_acceptance_rate_positive_growth)^((COLUMN()-8)/12) -> 0.85576651 | L82: =western_private_acceptance_rate_positive*(1+western_private_acceptance_rate_positive_growth)^((COLUMN()-8)/12) -> 0.85752924 | M82: =western_private_acceptance_rate_positive*(1+western_private_acceptance_rate_positive_growth)^((COLUMN()-8)/12) -> 0.85929561 | N82: =western_private_acceptance_rate_positive*(1+western_private_acceptance_rate_positive_growth)^((COLUMN()-8)/12) -> 0.86106562 | O82: =western_private_acceptance_rate_positive*(1+western_private_acceptance_rate_positive_growth)^((COLUMN()-8)/12) -> 0.86283928 | ... AQ82: =western_private_acceptance_rate_positive*(1+western_private_acceptance_rate_positive_growth)^((COLUMN()-8)/12) -> 0.91401276
F83: times Western Private Stock Availability Rate | H83: =western_private_stock_availability_rate_positive*(1+western_private_stock_availability_rate_positive_growth)^((COLUMN()-8)/12) -> 0.954 | I83: =western_private_stock_availability_rate_positive*(1+western_private_stock_availability_rate_positive_growth)^((COLUMN()-8)/12) -> 0.95557561 | J83: =western_private_stock_availability_rate_positive*(1+western_private_stock_availability_rate_positive_growth)^((COLUMN()-8)/12) -> 0.95715382 | K83: =western_private_stock_availability_rate_positive*(1+western_private_stock_availability_rate_positive_growth)^((COLUMN()-8)/12) -> 0.95873464 | L83: =western_private_stock_availability_rate_positive*(1+western_private_stock_availability_rate_positive_growth)^((COLUMN()-8)/12) -> 0.96031806 | M83: =western_private_stock_availability_rate_positive*(1+western_private_stock_availability_rate_positive_growth)^((COLUMN()-8)/12) -> 0.96190411 | N83: =western_private_stock_availability_rate_positive*(1+western_private_stock_availability_rate_positive_growth)^((COLUMN()-8)/12) -> 0.96349277 | O83: =western_private_stock_availability_rate_positive*(1+western_private_stock_availability_rate_positive_growth)^((COLUMN()-8)/12) -> 0.96508406 | ... AQ83: =western_private_stock_availability_rate_positive*(1+western_private_stock_availability_rate_positive_growth)^((COLUMN()-8)/12) -> 1.0107231
F84: times Western Private Active Coverage State | H84: =0.05 -> 0.05 | I84: =H84+I85-I86 -> 0.066222619 | J84: =I84+J85-J86 -> 0.082513079 | K84: =J84+K85-K86 -> 0.098871601 | L84: =K84+L85-L86 -> 0.11529841 | M84: =L84+M85-M86 -> 0.13179372 | N84: =M84+N85-N86 -> 0.14835777 | O84: =N84+O85-O86 -> 0.16499078 | P84: =O84+P85-P86 -> 0.18169297 | ... AQ84: =AP84+AQ85-AQ86 -> 0.65964919
G85: Western Private Coverage Additions | H85: =western_private_coverage_additions_positive*(1+western_private_coverage_additions_positive_growth)^((COLUMN()-8)/12) -> 0.020655 | I85: =western_private_coverage_additions_positive*(1+western_private_coverage_additions_positive_growth)^((COLUMN()-8)/12) -> 0.020722619 | J85: =western_private_coverage_additions_positive*(1+western_private_coverage_additions_positive_growth)^((COLUMN()-8)/12) -> 0.02079046 | K85: =western_private_coverage_additions_positive*(1+western_private_coverage_additions_positive_growth)^((COLUMN()-8)/12) -> 0.020858522 | L85: =western_private_coverage_additions_positive*(1+western_private_coverage_additions_positive_growth)^((COLUMN()-8)/12) -> 0.020926807 | M85: =western_private_coverage_additions_positive*(1+western_private_coverage_additions_positive_growth)^((COLUMN()-8)/12) -> 0.020995316 | N85: =western_private_coverage_additions_positive*(1+western_private_coverage_additions_positive_growth)^((COLUMN()-8)/12) -> 0.02106405 | O85: =western_private_coverage_additions_positive*(1+western_private_coverage_additions_positive_growth)^((COLUMN()-8)/12) -> 0.021133008 | ... AQ85: =western_private_coverage_additions_positive*(1+western_private_coverage_additions_positive_growth)^((COLUMN()-8)/12) -> 0.023158252
G86: plus Western Private Coverage Churn | H86: =western_private_coverage_churn_positive*(1+western_private_coverage_churn_positive_growth)^((COLUMN()-8)/12) -> 0.0045 | I86: =western_private_coverage_churn_positive*(1+western_private_coverage_churn_positive_growth)^((COLUMN()-8)/12) -> 0.0045 | J86: =western_private_coverage_churn_positive*(1+western_private_coverage_churn_positive_growth)^((COLUMN()-8)/12) -> 0.0045 | K86: =western_private_coverage_churn_positive*(1+western_private_coverage_churn_positive_growth)^((COLUMN()-8)/12) -> 0.0045 | L86: =western_private_coverage_churn_positive*(1+western_private_coverage_churn_positive_growth)^((COLUMN()-8)/12) -> 0.0045 | M86: =western_private_coverage_churn_positive*(1+western_private_coverage_churn_positive_growth)^((COLUMN()-8)/12) -> 0.0045 | N86: =western_private_coverage_churn_positive*(1+western_private_coverage_churn_positive_growth)^((COLUMN()-8)/12) -> 0.0045 | O86: =western_private_coverage_churn_positive*(1+western_private_coverage_churn_positive_growth)^((COLUMN()-8)/12) -> 0.0045 | ... AQ86: =western_private_coverage_churn_positive*(1+western_private_coverage_churn_positive_growth)^((COLUMN()-8)/12) -> 0.0045
E87: times Western Private Net Realised Price Per Dose | H87: =western_private_net_price_per_dose_positive*(1+western_private_net_price_per_dose_positive_growth)^((COLUMN()-8)/12) -> 107100 | I87: =western_private_net_price_per_dose_positive*(1+western_private_net_price_per_dose_positive_growth)^((COLUMN()-8)/12) -> 107407.47 | J87: =western_private_net_price_per_dose_positive*(1+western_private_net_price_per_dose_positive_growth)^((COLUMN()-8)/12) -> 107715.83 | K87: =western_private_net_price_per_dose_positive*(1+western_private_net_price_per_dose_positive_growth)^((COLUMN()-8)/12) -> 108025.07 | L87: =western_private_net_price_per_dose_positive*(1+western_private_net_price_per_dose_positive_growth)^((COLUMN()-8)/12) -> 108335.2 | M87: =western_private_net_price_per_dose_positive*(1+western_private_net_price_per_dose_positive_growth)^((COLUMN()-8)/12) -> 108646.22 | N87: =western_private_net_price_per_dose_positive*(1+western_private_net_price_per_dose_positive_growth)^((COLUMN()-8)/12) -> 108958.13 | O87: =western_private_net_price_per_dose_positive*(1+western_private_net_price_per_dose_positive_growth)^((COLUMN()-8)/12) -> 109270.94 | ... AQ87: =western_private_net_price_per_dose_positive*(1+western_private_net_price_per_dose_positive_growth)^((COLUMN()-8)/12) -> 118403.76
D88: plus Eastern Private Revenue | H88: =(H89*H98) -> 476853.92 | I88: =(I89*I98) -> 599096.92 | J88: =(J89*J98) -> 726443.68 | K88: =(K89*K98) -> 859058.54 | L88: =(L89*L98) -> 997110.63 | M88: =(M89*M98) -> 1140773.9 | N88: =(N89*N98) -> 1290227.3 | O88: =(O89*O98) -> 1445655 | ... AQ88: =(AQ89*AQ98) -> 9163723.3
E89: Eastern Private Administered Doses | H89: =(((((H90*H91)*H92)*H93)*H94)*H95) -> 5.1607567 | I89: =(((((I90*I91)*I92)*I93)*I94)*I95) -> 6.4651721 | J89: =(((((J90*J91)*J92)*J93)*J94)*J95) -> 7.8169965 | K89: =(((((K90*K91)*K92)*K93)*K94)*K95) -> 9.2175542 | L89: =(((((L90*L91)*L92)*L93)*L94)*L95) -> 10.668203 | M89: =(((((M90*M91)*M92)*M93)*M94)*M95) -> 12.170333 | N89: =(((((N90*N91)*N92)*N93)*N94)*N95) -> 13.725371 | O89: =(((((O90*O91)*O92)*O93)*O94)*O95) -> 15.334778 | ... AQ89: =(((((AQ90*AQ91)*AQ92)*AQ93)*AQ94)*AQ95) -> 89.706513
F90: Eastern Reachable Pregnancies | H90: =H37 -> 11484.349 | I90: =I37 -> 11510.043 | J90: =J37 -> 11535.794 | K90: =K37 -> 11561.603 | L90: =L37 -> 11587.469 | M90: =M37 -> 11613.394 | N90: =N37 -> 11639.377 | O90: =O37 -> 11665.417 | ... AQ90: =AQ37 -> 12418.693
F91: times Eastern Private Eligibility Rate | H91: =eastern_private_eligibility_rate_positive*(1+eastern_private_eligibility_rate_positive_growth)^((COLUMN()-8)/12) -> 0.0225 | I91: =eastern_private_eligibility_rate_positive*(1+eastern_private_eligibility_rate_positive_growth)^((COLUMN()-8)/12) -> 0.022644766 | J91: =eastern_private_eligibility_rate_positive*(1+eastern_private_eligibility_rate_positive_growth)^((COLUMN()-8)/12) -> 0.022790463 | K91: =eastern_private_eligibility_rate_positive*(1+eastern_private_eligibility_rate_positive_growth)^((COLUMN()-8)/12) -> 0.022937097 | L91: =eastern_private_eligibility_rate_positive*(1+eastern_private_eligibility_rate_positive_growth)^((COLUMN()-8)/12) -> 0.023084675 | M91: =eastern_private_eligibility_rate_positive*(1+eastern_private_eligibility_rate_positive_growth)^((COLUMN()-8)/12) -> 0.023233203 | N91: =eastern_private_eligibility_rate_positive*(1+eastern_private_eligibility_rate_positive_growth)^((COLUMN()-8)/12) -> 0.023382686 | O91: =eastern_private_eligibility_rate_positive*(1+eastern_private_eligibility_rate_positive_growth)^((COLUMN()-8)/12) -> 0.023533131 | ... AQ91: =eastern_private_eligibility_rate_positive*(1+eastern_private_eligibility_rate_positive_growth)^((COLUMN()-8)/12) -> 0.028162323
F92: times Eastern Private Provider Recommendation Rate | H92: =eastern_private_provider_recommendation_rate_positive*(1+eastern_private_provider_recommendation_rate_positive_growth)^((COLUMN()-8)/12) -> 0.5152 | I92: =eastern_private_provider_recommendation_rate_positive*(1+eastern_private_provider_recommendation_rate_positive_growth)^((COLUMN()-8)/12) -> 0.51729899 | J92: =eastern_private_provider_recommendation_rate_positive*(1+eastern_private_provider_recommendation_rate_positive_growth)^((COLUMN()-8)/12) -> 0.51940653 | K92: =eastern_private_provider_recommendation_rate_positive*(1+eastern_private_provider_recommendation_rate_positive_growth)^((COLUMN()-8)/12) -> 0.52152266 | L92: =eastern_private_provider_recommendation_rate_positive*(1+eastern_private_provider_recommendation_rate_positive_growth)^((COLUMN()-8)/12) -> 0.5236474 | M92: =eastern_private_provider_recommendation_rate_positive*(1+eastern_private_provider_recommendation_rate_positive_growth)^((COLUMN()-8)/12) -> 0.52578081 | N92: =eastern_private_provider_recommendation_rate_positive*(1+eastern_private_provider_recommendation_rate_positive_growth)^((COLUMN()-8)/12) -> 0.5279229 | O92: =eastern_private_provider_recommendation_rate_positive*(1+eastern_private_provider_recommendation_rate_positive_growth)^((COLUMN()-8)/12) -> 0.53007373 | ... AQ92: =eastern_private_provider_recommendation_rate_positive*(1+eastern_private_provider_recommendation_rate_positive_growth)^((COLUMN()-8)/12) -> 0.59398842
F93: times Eastern Private Acceptance Rate | H93: =eastern_private_acceptance_rate_positive*(1+eastern_private_acceptance_rate_positive_growth)^((COLUMN()-8)/12) -> 0.8505 | I93: =eastern_private_acceptance_rate_positive*(1+eastern_private_acceptance_rate_positive_growth)^((COLUMN()-8)/12) -> 0.85225189 | J93: =eastern_private_acceptance_rate_positive*(1+eastern_private_acceptance_rate_positive_growth)^((COLUMN()-8)/12) -> 0.85400739 | K93: =eastern_private_acceptance_rate_positive*(1+eastern_private_acceptance_rate_positive_growth)^((COLUMN()-8)/12) -> 0.85576651 | L93: =eastern_private_acceptance_rate_positive*(1+eastern_private_acceptance_rate_positive_growth)^((COLUMN()-8)/12) -> 0.85752924 | M93: =eastern_private_acceptance_rate_positive*(1+eastern_private_acceptance_rate_positive_growth)^((COLUMN()-8)/12) -> 0.85929561 | N93: =eastern_private_acceptance_rate_positive*(1+eastern_private_acceptance_rate_positive_growth)^((COLUMN()-8)/12) -> 0.86106562 | O93: =eastern_private_acceptance_rate_positive*(1+eastern_private_acceptance_rate_positive_growth)^((COLUMN()-8)/12) -> 0.86283928 | ... AQ93: =eastern_private_acceptance_rate_positive*(1+eastern_private_acceptance_rate_positive_growth)^((COLUMN()-8)/12) -> 0.91401276
F94: times Eastern Private Stock Availability Rate | H94: =eastern_private_stock_availability_rate_positive*(1+eastern_private_stock_availability_rate_positive_growth)^((COLUMN()-8)/12) -> 0.9116 | I94: =eastern_private_stock_availability_rate_positive*(1+eastern_private_stock_availability_rate_positive_growth)^((COLUMN()-8)/12) -> 0.91310558 | J94: =eastern_private_stock_availability_rate_positive*(1+eastern_private_stock_availability_rate_positive_growth)^((COLUMN()-8)/12) -> 0.91461365 | K94: =eastern_private_stock_availability_rate_positive*(1+eastern_private_stock_availability_rate_positive_growth)^((COLUMN()-8)/12) -> 0.91612421 | L94: =eastern_private_stock_availability_rate_positive*(1+eastern_private_stock_availability_rate_positive_growth)^((COLUMN()-8)/12) -> 0.91763726 | M94: =eastern_private_stock_availability_rate_positive*(1+eastern_private_stock_availability_rate_positive_growth)^((COLUMN()-8)/12) -> 0.91915281 | N94: =eastern_private_stock_availability_rate_positive*(1+eastern_private_stock_availability_rate_positive_growth)^((COLUMN()-8)/12) -> 0.92067087 | O94: =eastern_private_stock_availability_rate_positive*(1+eastern_private_stock_availability_rate_positive_growth)^((COLUMN()-8)/12) -> 0.92219143 | ... AQ94: =eastern_private_stock_availability_rate_positive*(1+eastern_private_stock_availability_rate_positive_growth)^((COLUMN()-8)/12) -> 0.96580211
F95: times Eastern Private Active Coverage State | H95: =0.05 -> 0.05 | I95: =H95+I96-I97 -> 0.061617593 | J95: =I95+J96-J97 -> 0.07328795 | K95: =J95+K96-K97 -> 0.085011245 | L95: =K95+L96-L97 -> 0.096787651 | M95: =L95+M96-M97 -> 0.10861734 | N95: =M95+N96-N97 -> 0.12050049 | O95: =N95+O96-O97 -> 0.13243727 | P95: =O95+P96-P97 -> 0.14442787 | ... AQ95: =AP95+AQ96-AQ97 -> 0.48917159
G96: Eastern Private Coverage Additions | H96: =eastern_private_coverage_additions_positive*(1+eastern_private_coverage_additions_positive_growth)^((COLUMN()-8)/12) -> 0.016065 | I96: =eastern_private_coverage_additions_positive*(1+eastern_private_coverage_additions_positive_growth)^((COLUMN()-8)/12) -> 0.016117593 | J96: =eastern_private_coverage_additions_positive*(1+eastern_private_coverage_additions_positive_growth)^((COLUMN()-8)/12) -> 0.016170357 | K96: =eastern_private_coverage_additions_positive*(1+eastern_private_coverage_additions_positive_growth)^((COLUMN()-8)/12) -> 0.016223295 | L96: =eastern_private_coverage_additions_positive*(1+eastern_private_coverage_additions_positive_growth)^((COLUMN()-8)/12) -> 0.016276406 | M96: =eastern_private_coverage_additions_positive*(1+eastern_private_coverage_additions_positive_growth)^((COLUMN()-8)/12) -> 0.016329691 | N96: =eastern_private_coverage_additions_positive*(1+eastern_private_coverage_additions_positive_growth)^((COLUMN()-8)/12) -> 0.01638315 | O96: =eastern_private_coverage_additions_positive*(1+eastern_private_coverage_additions_positive_growth)^((COLUMN()-8)/12) -> 0.016436784 | ... AQ96: =eastern_private_coverage_additions_positive*(1+eastern_private_coverage_additions_positive_growth)^((COLUMN()-8)/12) -> 0.018011974
G97: plus Eastern Private Coverage Churn | H97: =eastern_private_coverage_churn_positive*(1+eastern_private_coverage_churn_positive_growth)^((COLUMN()-8)/12) -> 0.0045 | I97: =eastern_private_coverage_churn_positive*(1+eastern_private_coverage_churn_positive_growth)^((COLUMN()-8)/12) -> 0.0045 | J97: =eastern_private_coverage_churn_positive*(1+eastern_private_coverage_churn_positive_growth)^((COLUMN()-8)/12) -> 0.0045 | K97: =eastern_private_coverage_churn_positive*(1+eastern_private_coverage_churn_positive_growth)^((COLUMN()-8)/12) -> 0.0045 | L97: =eastern_private_coverage_churn_positive*(1+eastern_private_coverage_churn_positive_growth)^((COLUMN()-8)/12) -> 0.0045 | M97: =eastern_private_coverage_churn_positive*(1+eastern_private_coverage_churn_positive_growth)^((COLUMN()-8)/12) -> 0.0045 | N97: =eastern_private_coverage_churn_positive*(1+eastern_private_coverage_churn_positive_growth)^((COLUMN()-8)/12) -> 0.0045 | O97: =eastern_private_coverage_churn_positive*(1+eastern_private_coverage_churn_positive_growth)^((COLUMN()-8)/12) -> 0.0045 | ... AQ97: =eastern_private_coverage_churn_positive*(1+eastern_private_coverage_churn_positive_growth)^((COLUMN()-8)/12) -> 0.0045
E98: times Eastern Private Net Realised Price Per Dose | H98: =eastern_private_net_price_per_dose_positive*(1+eastern_private_net_price_per_dose_positive_growth)^((COLUMN()-8)/12) -> 92400 | I98: =eastern_private_net_price_per_dose_positive*(1+eastern_private_net_price_per_dose_positive_growth)^((COLUMN()-8)/12) -> 92665.271 | J98: =eastern_private_net_price_per_dose_positive*(1+eastern_private_net_price_per_dose_positive_growth)^((COLUMN()-8)/12) -> 92931.304 | K98: =eastern_private_net_price_per_dose_positive*(1+eastern_private_net_price_per_dose_positive_growth)^((COLUMN()-8)/12) -> 93198.1 | L98: =eastern_private_net_price_per_dose_positive*(1+eastern_private_net_price_per_dose_positive_growth)^((COLUMN()-8)/12) -> 93465.662 | M98: =eastern_private_net_price_per_dose_positive*(1+eastern_private_net_price_per_dose_positive_growth)^((COLUMN()-8)/12) -> 93733.993 | N98: =eastern_private_net_price_per_dose_positive*(1+eastern_private_net_price_per_dose_positive_growth)^((COLUMN()-8)/12) -> 94003.094 | O98: =eastern_private_net_price_per_dose_positive*(1+eastern_private_net_price_per_dose_positive_growth)^((COLUMN()-8)/12) -> 94272.967 | ... AQ98: =eastern_private_net_price_per_dose_positive*(1+eastern_private_net_price_per_dose_positive_growth)^((COLUMN()-8)/12) -> 102152.26
D99: plus Northern Private Revenue | H99: =(H100*H109) -> 131400.66 | I99: =(I100*I109) -> 155832.31 | J99: =(J100*J109) -> 181279.01 | K99: =(K100*K109) -> 207773.63 | L99: =(L100*L109) -> 235349.97 | M99: =(M100*M109) -> 264042.81 | N99: =(N100*N109) -> 293887.96 | O99: =(O100*O109) -> 324922.23 | ... AQ99: =(AQ100*AQ109) -> 1865121
E100: Northern Private Administered Doses | H100: =(((((H101*H102)*H103)*H104)*H105)*H106) -> 1.6466249 | I100: =(((((I101*I102)*I103)*I104)*I105)*I106) -> 1.9471956 | J100: =(((((J101*J102)*J103)*J104)*J105)*J106) -> 2.2586794 | K100: =(((((K101*K102)*K103)*K104)*K105)*K106) -> 2.581383 | L100: =(((((L101*L102)*L103)*L104)*L105)*L106) -> 2.9156214 | M100: =(((((M101*M102)*M103)*M104)*M105)*M106) -> 3.2617172 | N100: =(((((N101*N102)*N103)*N104)*N105)*N106) -> 3.6200013 | O100: =(((((O101*O102)*O103)*O104)*O105)*O106) -> 3.9908126 | ... AQ100: =(((((AQ101*AQ102)*AQ103)*AQ104)*AQ105)*AQ106) -> 21.141125
...

Sheet Model - Base
H1: Month 1 | I1: Month 2 | J1: Month 3 | K1: Month 4 | L1: Month 5 | M1: Month 6 | N1: Month 7 | O1: Month 8 | P1: Month 9 | Q1: Month 10 | R1: Month 11 | S1: Month 12 | T1: Month 13 | U1: Month 14 | V1: Month 15 | W1: Month 16 | X1: Month 17 | Y1: Month 18 | Z1: Month 19 | AA1: Month 20 | AB1: Month 21 | AC1: Month 22 | AD1: Month 23 | AE1: Month 24 | AF1: Month 25 | AG1: Month 26 | AH1: Month 27 | AI1: Month 28 | AJ1: Month 29 | AK1: Month 30 | AL1: Month 31 | AM1: Month 32 | AN1: Month 33 | AO1: Month 34 | AP1: Month 35 | AQ1: Month 36
A2: Net Profit | H2: =(H3-H110) -> -1.189574e+08 | I2: =(I3-I110) -> -1.1765295e+08 | J2: =(J3-J110) -> -1.1629043e+08 | K2: =(K3-K110) -> -1.1486827e+08 | L2: =(L3-L110) -> -1.1338486e+08 | M2: =(M3-M110) -> -1.1183857e+08 | N2: =(N3-N110) -> -1.1022772e+08 | O2: =(O3-O110) -> -1.0855058e+08 | ... AQ2: =(AQ3-AQ110) -> -26265851
B3: Revenue | H3: =(H4+H65) -> 16088066 | I3: =(I4+I65) -> 20075532 | J3: =(J4+J65) -> 24206013 | K3: =(K4+K65) -> 28483455 | L3: =(L4+L65) -> 32911903 | M3: =(M4+M65) -> 37495503 | N3: =(N4+N65) -> 42238502 | O3: =(O4+O65) -> 47145251 | ... AQ3: =(AQ4+AQ65) -> 2.7251377e+08
C4: Public / Donor Revenue | H4: =(((H5+H20)+H35)+H50) -> 10911506 | I4: =(((I5+I20)+I35)+I50) -> 13396763 | J4: =(((J5+J20)+J35)+J50) -> 15972451 | K4: =(((K5+K20)+K35)+K50) -> 18641109 | L4: =(((L5+L20)+L35)+L50) -> 21405340 | M4: =(((M5+M20)+M35)+M50) -> 24267811 | N4: =(((N5+N20)+N35)+N50) -> 27231259 | O4: =(((O5+O20)+O35)+O50) -> 30298487 | ... AQ4: =(((AQ5+AQ20)+AQ35)+AQ50) -> 1.7221555e+08
D5: Central Public Revenue | H5: =(H6*H19) -> 5698224.3 | I5: =(I6*I19) -> 7323801.5 | J5: =(J6*J19) -> 9008844.3 | K5: =(K6*K19) -> 10755022 | L5: =(L6*L19) -> 12564046 | M5: =(M6*M19) -> 14437670 | N5: =(N6*N19) -> 16377693 | O5: =(O6*O19) -> 18385958 | ... AQ5: =(AQ6*AQ19) -> 1.1145827e+08
E6: Central Public Administered Doses | H6: =(((((H7*H12)*H13)*H14)*H15)*H16) -> 160.51336 | I6: =(((((I7*I12)*I13)*I14)*I15)*I16) -> 205.79672 | J6: =(((((J7*J12)*J13)*J14)*J15)*J16) -> 252.52315 | K6: =(((((K7*K12)*K13)*K14)*K15)*K16) -> 300.72785 | L6: =(((((L7*L12)*L13)*L14)*L15)*L16) -> 350.44679 | M6: =(((((M7*M12)*M13)*M14)*M15)*M16) -> 401.71673 | N6: =(((((N7*N12)*N13)*N14)*N15)*N16) -> 454.57523 | O6: =(((((O7*O12)*O13)*O14)*O15)*O16) -> 509.06064 | ... AQ6: =(((((AQ7*AQ12)*AQ13)*AQ14)*AQ15)*AQ16) -> 2880.3287
F7: Central Reachable Pregnancies | H7: =(((H8*H9)*H10)*H11) -> 18227.958 | I7: =(((I8*I9)*I10)*I11) -> 18268.74 | J7: =(((J8*J9)*J10)*J11) -> 18309.612 | K7: =(((K8*K9)*K10)*K11) -> 18350.576 | L7: =(((L8*L9)*L10)*L11) -> 18391.632 | M7: =(((M8*M9)*M10)*M11) -> 18432.779 | N7: =(((N8*N9)*N10)*N11) -> 18474.018 | O7: =(((O8*O9)*O10)*O11) -> 18515.35 | ... AQ7: =(((AQ8*AQ9)*AQ10)*AQ11) -> 19710.949
G8: National Live Births Per Month | H8: =national_live_births_per_month*(1+national_live_births_per_month_growth)^((COLUMN()-8)/12) -> 145833 | I8: =national_live_births_per_month*(1+national_live_births_per_month_growth)^((COLUMN()-8)/12) -> 146049.97 | J8: =national_live_births_per_month*(1+national_live_births_per_month_growth)^((COLUMN()-8)/12) -> 146267.25 | K8: =national_live_births_per_month*(1+national_live_births_per_month_growth)^((COLUMN()-8)/12) -> 146484.86 | L8: =national_live_births_per_month*(1+national_live_births_per_month_growth)^((COLUMN()-8)/12) -> 146702.8 | M8: =national_live_births_per_month*(1+national_live_births_per_month_growth)^((COLUMN()-8)/12) -> 146921.06 | N8: =national_live_births_per_month*(1+national_live_births_per_month_growth)^((COLUMN()-8)/12) -> 147139.64 | O8: =national_live_births_per_month*(1+national_live_births_per_month_growth)^((COLUMN()-8)/12) -> 147358.55 | ... AQ8: =national_live_births_per_month*(1+national_live_births_per_month_growth)^((COLUMN()-8)/12) -> 153622.03
G9: times Central Regional Opportunity Weight | H9: =central_regional_opportunity_weight*(1+central_regional_opportunity_weight_growth)^((COLUMN()-8)/12) -> 0.28 | I9: =central_regional_opportunity_weight*(1+central_regional_opportunity_weight_growth)^((COLUMN()-8)/12) -> 0.28 | J9: =central_regional_opportunity_weight*(1+central_regional_opportunity_weight_growth)^((COLUMN()-8)/12) -> 0.28 | K9: =central_regional_opportunity_weight*(1+central_regional_opportunity_weight_growth)^((COLUMN()-8)/12) -> 0.28 | L9: =central_regional_opportunity_weight*(1+central_regional_opportunity_weight_growth)^((COLUMN()-8)/12) -> 0.28 | M9: =central_regional_opportunity_weight*(1+central_regional_opportunity_weight_growth)^((COLUMN()-8)/12) -> 0.28 | N9: =central_regional_opportunity_weight*(1+central_regional_opportunity_weight_growth)^((COLUMN()-8)/12) -> 0.28 | O9: =central_regional_opportunity_weight*(1+central_regional_opportunity_weight_growth)^((COLUMN()-8)/12) -> 0.28 | ... AQ9: =central_regional_opportunity_weight*(1+central_regional_opportunity_weight_growth)^((COLUMN()-8)/12) -> 0.28
G10: times Central ANC Access Rate | H10: =central_anc_access_rate*(1+central_anc_access_rate_growth)^((COLUMN()-8)/12) -> 0.72 | I10: =central_anc_access_rate*(1+central_anc_access_rate_growth)^((COLUMN()-8)/12) -> 0.72017975 | J10: =central_anc_access_rate*(1+central_anc_access_rate_growth)^((COLUMN()-8)/12) -> 0.72035955 | K10: =central_anc_access_rate*(1+central_anc_access_rate_growth)^((COLUMN()-8)/12) -> 0.72053939 | L10: =central_anc_access_rate*(1+central_anc_access_rate_growth)^((COLUMN()-8)/12) -> 0.72071928 | M10: =central_anc_access_rate*(1+central_anc_access_rate_growth)^((COLUMN()-8)/12) -> 0.72089921 | N10: =central_anc_access_rate*(1+central_anc_access_rate_growth)^((COLUMN()-8)/12) -> 0.72107919 | O10: =central_anc_access_rate*(1+central_anc_access_rate_growth)^((COLUMN()-8)/12) -> 0.72125921 | ... AQ10: =central_anc_access_rate*(1+central_anc_access_rate_growth)^((COLUMN()-8)/12) -> 0.72631813
G11: times Central Third Trimester Window Rate | H11: =central_third_trimester_window_rate*(1+central_third_trimester_window_rate_growth)^((COLUMN()-8)/12) -> 0.62 | I11: =central_third_trimester_window_rate*(1+central_third_trimester_window_rate_growth)^((COLUMN()-8)/12) -> 0.62030915 | J11: =central_third_trimester_window_rate*(1+central_third_trimester_window_rate_growth)^((COLUMN()-8)/12) -> 0.62061846 | K11: =central_third_trimester_window_rate*(1+central_third_trimester_window_rate_growth)^((COLUMN()-8)/12) -> 0.62092791 | L11: =central_third_trimester_window_rate*(1+central_third_trimester_window_rate_growth)^((COLUMN()-8)/12) -> 0.62123753 | M11: =central_third_trimester_window_rate*(1+central_third_trimester_window_rate_growth)^((COLUMN()-8)/12) -> 0.6215473 | N11: =central_third_trimester_window_rate*(1+central_third_trimester_window_rate_growth)^((COLUMN()-8)/12) -> 0.62185722 | O11: =central_third_trimester_window_rate*(1+central_third_trimester_window_rate_growth)^((COLUMN()-8)/12) -> 0.6221673 | ... AQ11: =central_third_trimester_window_rate*(1+central_third_trimester_window_rate_growth)^((COLUMN()-8)/12) -> 0.6309125
F12: times Central Public Eligibility Rate | H12: =central_public_eligibility_rate*(1+central_public_eligibility_rate_growth)^((COLUMN()-8)/12) -> 0.28 | I12: =central_public_eligibility_rate*(1+central_public_eligibility_rate_growth)^((COLUMN()-8)/12) -> 0.28180153 | J12: =central_public_eligibility_rate*(1+central_public_eligibility_rate_growth)^((COLUMN()-8)/12) -> 0.28361465 | K12: =central_public_eligibility_rate*(1+central_public_eligibility_rate_growth)^((COLUMN()-8)/12) -> 0.28543943 | L12: =central_public_eligibility_rate*(1+central_public_eligibility_rate_growth)^((COLUMN()-8)/12) -> 0.28727596 | M12: =central_public_eligibility_rate*(1+central_public_eligibility_rate_growth)^((COLUMN()-8)/12) -> 0.2891243 | N12: =central_public_eligibility_rate*(1+central_public_eligibility_rate_growth)^((COLUMN()-8)/12) -> 0.29098454 | O12: =central_public_eligibility_rate*(1+central_public_eligibility_rate_growth)^((COLUMN()-8)/12) -> 0.29285674 | ... AQ12: =central_public_eligibility_rate*(1+central_public_eligibility_rate_growth)^((COLUMN()-8)/12) -> 0.35046446
F13: times Central Public Provider Recommendation Rate | H13: =central_public_provider_recommendation_rate*(1+central_public_provider_recommendation_rate_growth)^((COLUMN()-8)/12) -> 0.56 | I13: =central_public_provider_recommendation_rate*(1+central_public_provider_recommendation_rate_growth)^((COLUMN()-8)/12) -> 0.56183329 | J13: =central_public_provider_recommendation_rate*(1+central_public_provider_recommendation_rate_growth)^((COLUMN()-8)/12) -> 0.56367259 | K13: =central_public_provider_recommendation_rate*(1+central_public_provider_recommendation_rate_growth)^((COLUMN()-8)/12) -> 0.56551791 | L13: =central_public_provider_recommendation_rate*(1+central_public_provider_recommendation_rate_growth)^((COLUMN()-8)/12) -> 0.56736927 | M13: =central_public_provider_recommendation_rate*(1+central_public_provider_recommendation_rate_growth)^((COLUMN()-8)/12) -> 0.56922669 | N13: =central_public_provider_recommendation_rate*(1+central_public_provider_recommendation_rate_growth)^((COLUMN()-8)/12) -> 0.57109019 | O13: =central_public_provider_recommendation_rate*(1+central_public_provider_recommendation_rate_growth)^((COLUMN()-8)/12) -> 0.57295979 | ... AQ13: =central_public_provider_recommendation_rate*(1+central_public_provider_recommendation_rate_growth)^((COLUMN()-8)/12) -> 0.62786836
F14: times Central Public Acceptance Rate | H14: =central_public_acceptance_rate*(1+central_public_acceptance_rate_growth)^((COLUMN()-8)/12) -> 0.78 | I14: =central_public_acceptance_rate*(1+central_public_acceptance_rate_growth)^((COLUMN()-8)/12) -> 0.78128823 | J14: =central_public_acceptance_rate*(1+central_public_acceptance_rate_growth)^((COLUMN()-8)/12) -> 0.78257859 | K14: =central_public_acceptance_rate*(1+central_public_acceptance_rate_growth)^((COLUMN()-8)/12) -> 0.78387109 | L14: =central_public_acceptance_rate*(1+central_public_acceptance_rate_growth)^((COLUMN()-8)/12) -> 0.78516571 | M14: =central_public_acceptance_rate*(1+central_public_acceptance_rate_growth)^((COLUMN()-8)/12) -> 0.78646248 | N14: =central_public_acceptance_rate*(1+central_public_acceptance_rate_growth)^((COLUMN()-8)/12) -> 0.78776139 | O14: =central_public_acceptance_rate*(1+central_public_acceptance_rate_growth)^((COLUMN()-8)/12) -> 0.78906244 | ... AQ14: =central_public_acceptance_rate*(1+central_public_acceptance_rate_growth)^((COLUMN()-8)/12) -> 0.82637741
F15: times Central Public Stock Availability Rate | H15: =central_public_stock_availability_rate*(1+central_public_stock_availability_rate_growth)^((COLUMN()-8)/12) -> 0.9 | I15: =central_public_stock_availability_rate*(1+central_public_stock_availability_rate_growth)^((COLUMN()-8)/12) -> 0.90111734 | J15: =central_public_stock_availability_rate*(1+central_public_stock_availability_rate_growth)^((COLUMN()-8)/12) -> 0.90223607 | K15: =central_public_stock_availability_rate*(1+central_public_stock_availability_rate_growth)^((COLUMN()-8)/12) -> 0.90335618 | L15: =central_public_stock_availability_rate*(1+central_public_stock_availability_rate_growth)^((COLUMN()-8)/12) -> 0.90447769 | M15: =central_public_stock_availability_rate*(1+central_public_stock_availability_rate_growth)^((COLUMN()-8)/12) -> 0.90560058 | N15: =central_public_stock_availability_rate*(1+central_public_stock_availability_rate_growth)^((COLUMN()-8)/12) -> 0.90672488 | O15: =central_public_stock_availability_rate*(1+central_public_stock_availability_rate_growth)^((COLUMN()-8)/12) -> 0.90785056 | ... AQ15: =central_public_stock_availability_rate*(1+central_public_stock_availability_rate_growth)^((COLUMN()-8)/12) -> 0.93994361
F16: times Central Public Active Coverage State | H16: =0.08 -> 0.08 | I16: =H16+I17-I18 -> 0.10106166 | J16: =I16+J17-J18 -> 0.12218512 | K16: =J16+K17-K18 -> 0.14337055 | L16: =K16+L17-L18 -> 0.16461809 | M16: =L16+M17-M18 -> 0.1859279 | N16: =M16+N17-N18 -> 0.20730013 | O16: =N16+O17-O18 -> 0.22873493 | P16: =O16+P17-P18 -> 0.25023246 | ... AQ16: =AP16+AQ17-AQ18 -> 0.85495192
G17: Central Public Coverage Additions | H17: =central_public_coverage_additions*(1+central_public_coverage_additions_growth)^((COLUMN()-8)/12) -> 0.025 | I17: =central_public_coverage_additions*(1+central_public_coverage_additions_growth)^((COLUMN()-8)/12) -> 0.025061657 | J17: =central_public_coverage_additions*(1+central_public_coverage_additions_growth)^((COLUMN()-8)/12) -> 0.025123466 | K17: =central_public_coverage_additions*(1+central_public_coverage_additions_growth)^((COLUMN()-8)/12) -> 0.025185427 | L17: =central_public_coverage_additions*(1+central_public_coverage_additions_growth)^((COLUMN()-8)/12) -> 0.025247541 | M17: =central_public_coverage_additions*(1+central_public_coverage_additions_growth)^((COLUMN()-8)/12) -> 0.025309808 | N17: =central_public_coverage_additions*(1+central_public_coverage_additions_growth)^((COLUMN()-8)/12) -> 0.025372229 | O17: =central_public_coverage_additions*(1+central_public_coverage_additions_growth)^((COLUMN()-8)/12) -> 0.025434804 | ... AQ17: =central_public_coverage_additions*(1+central_public_coverage_additions_growth)^((COLUMN()-8)/12) -> 0.027250967
G18: plus Central Public Coverage Churn | H18: =central_public_coverage_churn*(1+central_public_coverage_churn_growth)^((COLUMN()-8)/12) -> 0.004 | I18: =central_public_coverage_churn*(1+central_public_coverage_churn_growth)^((COLUMN()-8)/12) -> 0.004 | J18: =central_public_coverage_churn*(1+central_public_coverage_churn_growth)^((COLUMN()-8)/12) -> 0.004 | K18: =central_public_coverage_churn*(1+central_public_coverage_churn_growth)^((COLUMN()-8)/12) -> 0.004 | L18: =central_public_coverage_churn*(1+central_public_coverage_churn_growth)^((COLUMN()-8)/12) -> 0.004 | M18: =central_public_coverage_churn*(1+central_public_coverage_churn_growth)^((COLUMN()-8)/12) -> 0.004 | N18: =central_public_coverage_churn*(1+central_public_coverage_churn_growth)^((COLUMN()-8)/12) -> 0.004 | O18: =central_public_coverage_churn*(1+central_public_coverage_churn_growth)^((COLUMN()-8)/12) -> 0.004 | ... AQ18: =central_public_coverage_churn*(1+central_public_coverage_churn_growth)^((COLUMN()-8)/12) -> 0.004
E19: times Central Public Net Realised Price Per Dose | H19: =central_public_net_price_per_dose*(1+central_public_net_price_per_dose_growth)^((COLUMN()-8)/12) -> 35500 | I19: =central_public_net_price_per_dose*(1+central_public_net_price_per_dose_growth)^((COLUMN()-8)/12) -> 35587.553 | J19: =central_public_net_price_per_dose*(1+central_public_net_price_per_dose_growth)^((COLUMN()-8)/12) -> 35675.321 | K19: =central_public_net_price_per_dose*(1+central_public_net_price_per_dose_growth)^((COLUMN()-8)/12) -> 35763.306 | L19: =central_public_net_price_per_dose*(1+central_public_net_price_per_dose_growth)^((COLUMN()-8)/12) -> 35851.508 | M19: =central_public_net_price_per_dose*(1+central_public_net_price_per_dose_growth)^((COLUMN()-8)/12) -> 35939.927 | N19: =central_public_net_price_per_dose*(1+central_public_net_price_per_dose_growth)^((COLUMN()-8)/12) -> 36028.565 | O19: =central_public_net_price_per_dose*(1+central_public_net_price_per_dose_growth)^((COLUMN()-8)/12) -> 36117.421 | ... AQ19: =central_public_net_price_per_dose*(1+central_public_net_price_per_dose_growth)^((COLUMN()-8)/12) -> 38696.373
D20: plus Western Public Revenue | H20: =(H21*H34) -> 2689358.4 | I20: =(I21*I34) -> 3216564 | J20: =(J21*J34) -> 3762870.8 | K20: =(K21*K34) -> 4328815 | L20: =(L21*L34) -> 4914946.6 | M20: =(M21*M34) -> 5521829.3 | N20: =(N21*N34) -> 6150040.9 | O20: =(O21*O34) -> 6800173.8 | ... AQ20: =(AQ21*AQ34) -> 36841427
E21: Western Public Administered Doses | H21: =(((((H22*H27)*H28)*H29)*H30)*H31) -> 77.952417 | I21: =(((((I22*I27)*I28)*I29)*I30)*I31) -> 93.004366 | J21: =(((((J22*J27)*J28)*J29)*J30)*J31) -> 108.53272 | K21: =(((((K22*K27)*K28)*K29)*K30)*K31) -> 124.54911 | L21: =(((((L22*L27)*L28)*L29)*L30)*L31) -> 141.06544 | M21: =(((((M22*M27)*M28)*M29)*M30)*M31) -> 158.09387 | N21: =(((((N22*N27)*N28)*N29)*N30)*N31) -> 175.64682 | O21: =(((((O22*O27)*O28)*O29)*O30)*O31) -> 193.73698 | ... AQ21: =(((((AQ22*AQ27)*AQ28)*AQ29)*AQ30)*AQ31) -> 979.66016
F22: Western Reachable Pregnancies | H22: =(((H23*H24)*H25)*H26) -> 13474.969 | I22: =(((I23*I24)*I25)*I26) -> 13505.117 | J22: =(((J23*J24)*J25)*J26) -> 13535.331 | K22: =(((K23*K24)*K25)*K26) -> 13565.614 | L22: =(((L23*L24)*L25)*L26) -> 13595.964 | M22: =(((M23*M24)*M25)*M26) -> 13626.382 | N22: =(((N23*N24)*N25)*N26) -> 13656.868 | O22: =(((O23*O24)*O25)*O26) -> 13687.423 | ... AQ22: =(((AQ23*AQ24)*AQ25)*AQ26) -> 14571.266
G23: National Live Births Per Month | H23: =H8 -> 145833 | I23: =I8 -> 146049.97 | J23: =J8 -> 146267.25 | K23: =K8 -> 146484.86 | L23: =L8 -> 146702.8 | M23: =M8 -> 146921.06 | N23: =N8 -> 147139.64 | O23: =O8 -> 147358.55 | ... AQ23: =AQ8 -> 153622.03
G24: times Western Regional Opportunity Weight | H24: =western_regional_opportunity_weight*(1+western_regional_opportunity_weight_growth)^((COLUMN()-8)/12) -> 0.25 | I24: =western_regional_opportunity_weight*(1+western_regional_opportunity_weight_growth)^((COLUMN()-8)/12) -> 0.25 | J24: =western_regional_opportunity_weight*(1+western_regional_opportunity_weight_growth)^((COLUMN()-8)/12) -> 0.25 | K24: =western_regional_opportunity_weight*(1+western_regional_opportunity_weight_growth)^((COLUMN()-8)/12) -> 0.25 | L24: =western_regional_opportunity_weight*(1+western_regional_opportunity_weight_growth)^((COLUMN()-8)/12) -> 0.25 | M24: =western_regional_opportunity_weight*(1+western_regional_opportunity_weight_growth)^((COLUMN()-8)/12) -> 0.25 | N24: =western_regional_opportunity_weight*(1+western_regional_opportunity_weight_growth)^((COLUMN()-8)/12) -> 0.25 | O24: =western_regional_opportunity_weight*(1+western_regional_opportunity_weight_growth)^((COLUMN()-8)/12) -> 0.25 | ... AQ24: =western_regional_opportunity_weight*(1+western_regional_opportunity_weight_growth)^((COLUMN()-8)/12) -> 0.25
G25: times Western ANC Access Rate | H25: =western_anc_access_rate*(1+western_anc_access_rate_growth)^((COLUMN()-8)/12) -> 0.66 | I25: =western_anc_access_rate*(1+western_anc_access_rate_growth)^((COLUMN()-8)/12) -> 0.66016477 | J25: =western_anc_access_rate*(1+western_anc_access_rate_growth)^((COLUMN()-8)/12) -> 0.66032959 | K25: =western_anc_access_rate*(1+western_anc_access_rate_growth)^((COLUMN()-8)/12) -> 0.66049444 | L25: =western_anc_access_rate*(1+western_anc_access_rate_growth)^((COLUMN()-8)/12) -> 0.66065934 | M25: =western_anc_access_rate*(1+western_anc_access_rate_growth)^((COLUMN()-8)/12) -> 0.66082428 | N25: =western_anc_access_rate*(1+western_anc_access_rate_growth)^((COLUMN()-8)/12) -> 0.66098926 | O25: =western_anc_access_rate*(1+western_anc_access_rate_growth)^((COLUMN()-8)/12) -> 0.66115428 | ... AQ25: =western_anc_access_rate*(1+western_anc_access_rate_growth)^((COLUMN()-8)/12) -> 0.66579162
G26: times Western Third Trimester Window Rate | H26: =western_third_trimester_window_rate*(1+western_third_trimester_window_rate_growth)^((COLUMN()-8)/12) -> 0.56 | I26: =western_third_trimester_window_rate*(1+western_third_trimester_window_rate_growth)^((COLUMN()-8)/12) -> 0.56027923 | J26: =western_third_trimester_window_rate*(1+western_third_trimester_window_rate_growth)^((COLUMN()-8)/12) -> 0.56055861 | K26: =western_third_trimester_window_rate*(1+western_third_trimester_window_rate_growth)^((COLUMN()-8)/12) -> 0.56083812 | L26: =western_third_trimester_window_rate*(1+western_third_trimester_window_rate_growth)^((COLUMN()-8)/12) -> 0.56111777 | M26: =western_third_trimester_window_rate*(1+western_third_trimester_window_rate_growth)^((COLUMN()-8)/12) -> 0.56139756 | N26: =western_third_trimester_window_rate*(1+western_third_trimester_window_rate_growth)^((COLUMN()-8)/12) -> 0.56167749 | O26: =western_third_trimester_window_rate*(1+western_third_trimester_window_rate_growth)^((COLUMN()-8)/12) -> 0.56195756 | ... AQ26: =western_third_trimester_window_rate*(1+western_third_trimester_window_rate_growth)^((COLUMN()-8)/12) -> 0.56985645
F27: times Western Public Eligibility Rate | H27: =western_public_eligibility_rate*(1+western_public_eligibility_rate_growth)^((COLUMN()-8)/12) -> 0.22 | I27: =western_public_eligibility_rate*(1+western_public_eligibility_rate_growth)^((COLUMN()-8)/12) -> 0.22141549 | J27: =western_public_eligibility_rate*(1+western_public_eligibility_rate_growth)^((COLUMN()-8)/12) -> 0.22284008 | K27: =western_public_eligibility_rate*(1+western_public_eligibility_rate_growth)^((COLUMN()-8)/12) -> 0.22427384 | L27: =western_public_eligibility_rate*(1+western_public_eligibility_rate_growth)^((COLUMN()-8)/12) -> 0.22571682 | M27: =western_public_eligibility_rate*(1+western_public_eligibility_rate_growth)^((COLUMN()-8)/12) -> 0.22716909 | N27: =western_public_eligibility_rate*(1+western_public_eligibility_rate_growth)^((COLUMN()-8)/12) -> 0.22863071 | O27: =western_public_eligibility_rate*(1+western_public_eligibility_rate_growth)^((COLUMN()-8)/12) -> 0.23010172 | ... AQ27: =western_public_eligibility_rate*(1+western_public_eligibility_rate_growth)^((COLUMN()-8)/12) -> 0.27536493
F28: times Western Public Provider Recommendation Rate | H28: =western_public_provider_recommendation_rate*(1+western_public_provider_recommendation_rate_growth)^((COLUMN()-8)/12) -> 0.49 | I28: =western_public_provider_recommendation_rate*(1+western_public_provider_recommendation_rate_growth)^((COLUMN()-8)/12) -> 0.49160413 | J28: =western_public_provider_recommendation_rate*(1+western_public_provider_recommendation_rate_growth)^((COLUMN()-8)/12) -> 0.49321352 | K28: =western_public_provider_recommendation_rate*(1+western_public_provider_recommendation_rate_growth)^((COLUMN()-8)/12) -> 0.49482817 | L28: =western_public_provider_recommendation_rate*(1+western_public_provider_recommendation_rate_growth)^((COLUMN()-8)/12) -> 0.49644811 | M28: =western_public_provider_recommendation_rate*(1+western_public_provider_recommendation_rate_growth)^((COLUMN()-8)/12) -> 0.49807335 | N28: =western_public_provider_recommendation_rate*(1+western_public_provider_recommendation_rate_growth)^((COLUMN()-8)/12) -> 0.49970391 | O28: =western_public_provider_recommendation_rate*(1+western_public_provider_recommendation_rate_growth)^((COLUMN()-8)/12) -> 0.50133981 | ... AQ28: =western_public_provider_recommendation_rate*(1+western_public_provider_recommendation_rate_growth)^((COLUMN()-8)/12) -> 0.54938482
F29: times Western Public Acceptance Rate | H29: =western_public_acceptance_rate*(1+western_public_acceptance_rate_growth)^((COLUMN()-8)/12) -> 0.78 | I29: =western_public_acceptance_rate*(1+western_public_acceptance_rate_growth)^((COLUMN()-8)/12) -> 0.78128823 | J29: =western_public_acceptance_rate*(1+western_public_acceptance_rate_growth)^((COLUMN()-8)/12) -> 0.78257859 | K29: =western_public_acceptance_rate*(1+western_public_acceptance_rate_growth)^((COLUMN()-8)/12) -> 0.78387109 | L29: =western_public_acceptance_rate*(1+western_public_acceptance_rate_growth)^((COLUMN()-8)/12) -> 0.78516571 | M29: =western_public_acceptance_rate*(1+western_public_acceptance_rate_growth)^((COLUMN()-8)/12) -> 0.78646248 | N29: =western_public_acceptance_rate*(1+western_public_acceptance_rate_growth)^((COLUMN()-8)/12) -> 0.78776139 | O29: =western_public_acceptance_rate*(1+western_public_acceptance_rate_growth)^((COLUMN()-8)/12) -> 0.78906244 | ... AQ29: =western_public_acceptance_rate*(1+western_public_acceptance_rate_growth)^((COLUMN()-8)/12) -> 0.82637741
F30: times Western Public Stock Availability Rate | H30: =western_public_stock_availability_rate*(1+western_public_stock_availability_rate_growth)^((COLUMN()-8)/12) -> 0.86 | I30: =western_public_stock_availability_rate*(1+western_public_stock_availability_rate_growth)^((COLUMN()-8)/12) -> 0.86106768 | J30: =western_public_stock_availability_rate*(1+western_public_stock_availability_rate_growth)^((COLUMN()-8)/12) -> 0.86213668 | K30: =western_public_stock_availability_rate*(1+western_public_stock_availability_rate_growth)^((COLUMN()-8)/12) -> 0.86320702 | L30: =western_public_stock_availability_rate*(1+western_public_stock_availability_rate_growth)^((COLUMN()-8)/12) -> 0.86427868 | M30: =western_public_stock_availability_rate*(1+western_public_stock_availability_rate_growth)^((COLUMN()-8)/12) -> 0.86535167 | N30: =western_public_stock_availability_rate*(1+western_public_stock_availability_rate_growth)^((COLUMN()-8)/12) -> 0.86642599 | O30: =western_public_stock_availability_rate*(1+western_public_stock_availability_rate_growth)^((COLUMN()-8)/12) -> 0.86750165 | ... AQ30: =western_public_stock_availability_rate*(1+western_public_stock_availability_rate_growth)^((COLUMN()-8)/12) -> 0.89816834
F31: times Western Public Active Coverage State | H31: =0.08 -> 0.08 | I31: =H31+I32-I33 -> 0.094044393 | J31: =I31+J32-J33 -> 0.10813329 | K31: =J31+K32-K33 -> 0.1222668 | L31: =K31+L32-L33 -> 0.13644502 | M31: =L31+M32-M33 -> 0.15066809 | N31: =M31+N32-N33 -> 0.16493609 | O31: =N31+O32-O33 -> 0.17924915 | P31: =O31+P32-P33 -> 0.19360737 | ... AQ31: =AP31+AQ32-AQ33 -> 0.59876538
G32: Western Public Coverage Additions | H32: =western_public_coverage_additions*(1+western_public_coverage_additions_growth)^((COLUMN()-8)/12) -> 0.018 | I32: =western_public_coverage_additions*(1+western_public_coverage_additions_growth)^((COLUMN()-8)/12) -> 0.018044393 | J32: =western_public_coverage_additions*(1+western_public_coverage_additions_growth)^((COLUMN()-8)/12) -> 0.018088895 | K32: =western_public_coverage_additions*(1+western_public_coverage_additions_growth)^((COLUMN()-8)/12) -> 0.018133507 | L32: =western_public_coverage_additions*(1+western_public_coverage_additions_growth)^((COLUMN()-8)/12) -> 0.018178229 | M32: =western_public_coverage_additions*(1+western_public_coverage_additions_growth)^((COLUMN()-8)/12) -> 0.018223062 | N32: =western_public_coverage_additions*(1+western_public_coverage_additions_growth)^((COLUMN()-8)/12) -> 0.018268005 | O32: =western_public_coverage_additions*(1+western_public_coverage_additions_growth)^((COLUMN()-8)/12) -> 0.018313059 | ... AQ32: =western_public_coverage_additions*(1+western_public_coverage_additions_growth)^((COLUMN()-8)/12) -> 0.019620696
G33: plus Western Public Coverage Churn | H33: =western_public_coverage_churn*(1+western_public_coverage_churn_growth)^((COLUMN()-8)/12) -> 0.004 | I33: =western_public_coverage_churn*(1+western_public_coverage_churn_growth)^((COLUMN()-8)/12) -> 0.004 | J33: =western_public_coverage_churn*(1+western_public_coverage_churn_growth)^((COLUMN()-8)/12) -> 0.004 | K33: =western_public_coverage_churn*(1+western_public_coverage_churn_growth)^((COLUMN()-8)/12) -> 0.004 | L33: =western_public_coverage_churn*(1+western_public_coverage_churn_growth)^((COLUMN()-8)/12) -> 0.004 | M33: =western_public_coverage_churn*(1+western_public_coverage_churn_growth)^((COLUMN()-8)/12) -> 0.004 | N33: =western_public_coverage_churn*(1+western_public_coverage_churn_growth)^((COLUMN()-8)/12) -> 0.004 | O33: =western_public_coverage_churn*(1+western_public_coverage_churn_growth)^((COLUMN()-8)/12) -> 0.004 | ... AQ33: =western_public_coverage_churn*(1+western_public_coverage_churn_growth)^((COLUMN()-8)/12) -> 0.004
E34: times Western Public Net Realised Price Per Dose | H34: =western_public_net_price_per_dose*(1+western_public_net_price_per_dose_growth)^((COLUMN()-8)/12) -> 34500 | I34: =western_public_net_price_per_dose*(1+western_public_net_price_per_dose_growth)^((COLUMN()-8)/12) -> 34585.086 | J34: =western_public_net_price_per_dose*(1+western_public_net_price_per_dose_growth)^((COLUMN()-8)/12) -> 34670.382 | K34: =western_public_net_price_per_dose*(1+western_public_net_price_per_dose_growth)^((COLUMN()-8)/12) -> 34755.889 | L34: =western_public_net_price_per_dose*(1+western_public_net_price_per_dose_growth)^((COLUMN()-8)/12) -> 34841.606 | M34: =western_public_net_price_per_dose*(1+western_public_net_price_per_dose_growth)^((COLUMN()-8)/12) -> 34927.535 | N34: =western_public_net_price_per_dose*(1+western_public_net_price_per_dose_growth)^((COLUMN()-8)/12) -> 35013.676 | O34: =western_public_net_price_per_dose*(1+western_public_net_price_per_dose_growth)^((COLUMN()-8)/12) -> 35100.029 | ... AQ34: =western_public_net_price_per_dose*(1+western_public_net_price_per_dose_growth)^((COLUMN()-8)/12) -> 37606.334
D35: plus Eastern Public Revenue | H35: =(H36*H49) -> 1645719.8 | I35: =(I36*I49) -> 1884410.9 | J35: =(J36*J49) -> 2131655.9 | K35: =(K36*K49) -> 2387695.3 | L35: =(L36*L49) -> 2652775.2 | M35: =(M36*M49) -> 2927148.3 | N35: =(N36*N49) -> 3211073.6 | O35: =(O36*O49) -> 3504816.4 | ... AQ35: =(AQ36*AQ49) -> 17032709
E36: Eastern Public Administered Doses | H36: =(((((H37*H42)*H43)*H44)*H45)*H46) -> 49.125965 | I36: =(((((I37*I42)*I43)*I44)*I45)*I46) -> 56.112682 | J36: =(((((J37*J42)*J43)*J44)*J45)*J46) -> 63.318813 | K36: =(((((K37*K42)*K43)*K44)*K45)*K46) -> 70.74973 | L36: =(((((L37*L42)*L43)*L44)*L45)*L46) -> 78.410924 | M36: =(((((M37*M42)*M43)*M44)*M45)*M46) -> 86.308006 | N36: =(((((N37*N42)*N43)*N44)*N45)*N46) -> 94.446711 | O36: =(((((O37*O42)*O43)*O44)*O45)*O46) -> 102.8329 | ... AQ36: =(((((AQ37*AQ42)*AQ43)*AQ44)*AQ45)*AQ46) -> 466.44132
F37: Eastern Reachable Pregnancies | H37: =(((H38*H39)*H40)*H41) -> 11484.349 | I37: =(((I38*I39)*I40)*I41) -> 11510.043 | J37: =(((J38*J39)*J40)*J41) -> 11535.794 | K37: =(((K38*K39)*K40)*K41) -> 11561.603 | L37: =(((L38*L39)*L40)*L41) -> 11587.469 | M37: =(((M38*M39)*M40)*M41) -> 11613.394 | N37: =(((N38*N39)*N40)*N41) -> 11639.377 | O37: =(((O38*O39)*O40)*O41) -> 11665.417 | ... AQ37: =(((AQ38*AQ39)*AQ40)*AQ41) -> 12418.693
G38: National Live Births Per Month | H38: =H8 -> 145833 | I38: =I8 -> 146049.97 | J38: =J8 -> 146267.25 | K38: =K8 -> 146484.86 | L38: =L8 -> 146702.8 | M38: =M8 -> 146921.06 | N38: =N8 -> 147139.64 | O38: =O8 -> 147358.55 | ... AQ38: =AQ8 -> 153622.03
G39: times Eastern Regional Opportunity Weight | H39: =eastern_regional_opportunity_weight*(1+eastern_regional_opportunity_weight_growth)^((COLUMN()-8)/12) -> 0.25 | I39: =eastern_regional_opportunity_weight*(1+eastern_regional_opportunity_weight_growth)^((COLUMN()-8)/12) -> 0.25 | J39: =eastern_regional_opportunity_weight*(1+eastern_regional_opportunity_weight_growth)^((COLUMN()-8)/12) -> 0.25 | K39: =eastern_regional_opportunity_weight*(1+eastern_regional_opportunity_weight_growth)^((COLUMN()-8)/12) -> 0.25 | L39: =eastern_regional_opportunity_weight*(1+eastern_regional_opportunity_weight_growth)^((COLUMN()-8)/12) -> 0.25 | M39: =eastern_regional_opportunity_weight*(1+eastern_regional_opportunity_weight_growth)^((COLUMN()-8)/12) -> 0.25 | N39: =eastern_regional_opportunity_weight*(1+eastern_regional_opportunity_weight_growth)^((COLUMN()-8)/12) -> 0.25 | O39: =eastern_regional_opportunity_weight*(1+eastern_regional_opportunity_weight_growth)^((COLUMN()-8)/12) -> 0.25 | ... AQ39: =eastern_regional_opportunity_weight*(1+eastern_regional_opportunity_weight_growth)^((COLUMN()-8)/12) -> 0.25
G40: times Eastern ANC Access Rate | H40: =eastern_anc_access_rate*(1+eastern_anc_access_rate_growth)^((COLUMN()-8)/12) -> 0.63 | I40: =eastern_anc_access_rate*(1+eastern_anc_access_rate_growth)^((COLUMN()-8)/12) -> 0.63015728 | J40: =eastern_anc_access_rate*(1+eastern_anc_access_rate_growth)^((COLUMN()-8)/12) -> 0.63031461 | K40: =eastern_anc_access_rate*(1+eastern_anc_access_rate_growth)^((COLUMN()-8)/12) -> 0.63047197 | L40: =eastern_anc_access_rate*(1+eastern_anc_access_rate_growth)^((COLUMN()-8)/12) -> 0.63062937 | M40: =eastern_anc_access_rate*(1+eastern_anc_access_rate_growth)^((COLUMN()-8)/12) -> 0.63078681 | N40: =eastern_anc_access_rate*(1+eastern_anc_access_rate_growth)^((COLUMN()-8)/12) -> 0.63094429 | O40: =eastern_anc_access_rate*(1+eastern_anc_access_rate_growth)^((COLUMN()-8)/12) -> 0.63110181 | ... AQ40: =eastern_anc_access_rate*(1+eastern_anc_access_rate_growth)^((COLUMN()-8)/12) -> 0.63552836
G41: times Eastern Third Trimester Window Rate | H41: =eastern_third_trimester_window_rate*(1+eastern_third_trimester_window_rate_growth)^((COLUMN()-8)/12) -> 0.5 | I41: =eastern_third_trimester_window_rate*(1+eastern_third_trimester_window_rate_growth)^((COLUMN()-8)/12) -> 0.50024932 | J41: =eastern_third_trimester_window_rate*(1+eastern_third_trimester_window_rate_growth)^((COLUMN()-8)/12) -> 0.50049875 | K41: =eastern_third_trimester_window_rate*(1+eastern_third_trimester_window_rate_growth)^((COLUMN()-8)/12) -> 0.50074832 | L41: =eastern_third_trimester_window_rate*(1+eastern_third_trimester_window_rate_growth)^((COLUMN()-8)/12) -> 0.50099801 | M41: =eastern_third_trimester_window_rate*(1+eastern_third_trimester_window_rate_growth)^((COLUMN()-8)/12) -> 0.50124782 | N41: =eastern_third_trimester_window_rate*(1+eastern_third_trimester_window_rate_growth)^((COLUMN()-8)/12) -> 0.50149776 | O41: =eastern_third_trimester_window_rate*(1+eastern_third_trimester_window_rate_growth)^((COLUMN()-8)/12) -> 0.50174782 | ... AQ41: =eastern_third_trimester_window_rate*(1+eastern_third_trimester_window_rate_growth)^((COLUMN()-8)/12) -> 0.5088004
F42: times Eastern Public Eligibility Rate | H42: =eastern_public_eligibility_rate*(1+eastern_public_eligibility_rate_growth)^((COLUMN()-8)/12) -> 0.19 | I42: =eastern_public_eligibility_rate*(1+eastern_public_eligibility_rate_growth)^((COLUMN()-8)/12) -> 0.19122247 | J42: =eastern_public_eligibility_rate*(1+eastern_public_eligibility_rate_growth)^((COLUMN()-8)/12) -> 0.1924528 | K42: =eastern_public_eligibility_rate*(1+eastern_public_eligibility_rate_growth)^((COLUMN()-8)/12) -> 0.19369104 | L42: =eastern_public_eligibility_rate*(1+eastern_public_eligibility_rate_growth)^((COLUMN()-8)/12) -> 0.19493726 | M42: =eastern_public_eligibility_rate*(1+eastern_public_eligibility_rate_growth)^((COLUMN()-8)/12) -> 0.19619149 | N42: =eastern_public_eligibility_rate*(1+eastern_public_eligibility_rate_growth)^((COLUMN()-8)/12) -> 0.19745379 | O42: =eastern_public_eligibility_rate*(1+eastern_public_eligibility_rate_growth)^((COLUMN()-8)/12) -> 0.19872422 | ... AQ42: =eastern_public_eligibility_rate*(1+eastern_public_eligibility_rate_growth)^((COLUMN()-8)/12) -> 0.23781517
F43: times Eastern Public Provider Recommendation Rate | H43: =eastern_public_provider_recommendation_rate*(1+eastern_public_provider_recommendation_rate_growth)^((COLUMN()-8)/12) -> 0.44 | I43: =eastern_public_provider_recommendation_rate*(1+eastern_public_provider_recommendation_rate_growth)^((COLUMN()-8)/12) -> 0.44144045 | J43: =eastern_public_provider_recommendation_rate*(1+eastern_public_provider_recommendation_rate_growth)^((COLUMN()-8)/12) -> 0.44288561 | K43: =eastern_public_provider_recommendation_rate*(1+eastern_public_provider_recommendation_rate_growth)^((COLUMN()-8)/12) -> 0.4443355 | L43: =eastern_public_provider_recommendation_rate*(1+eastern_public_provider_recommendation_rate_growth)^((COLUMN()-8)/12) -> 0.44579014 | M43: =eastern_public_provider_recommendation_rate*(1+eastern_public_provider_recommendation_rate_growth)^((COLUMN()-8)/12) -> 0.44724954 | N43: =eastern_public_provider_recommendation_rate*(1+eastern_public_provider_recommendation_rate_growth)^((COLUMN()-8)/12) -> 0.44871372 | O43: =eastern_public_provider_recommendation_rate*(1+eastern_public_provider_recommendation_rate_growth)^((COLUMN()-8)/12) -> 0.45018269 | ... AQ43: =eastern_public_provider_recommendation_rate*(1+eastern_public_provider_recommendation_rate_growth)^((COLUMN()-8)/12) -> 0.49332514
F44: times Eastern Public Acceptance Rate | H44: =eastern_public_acceptance_rate*(1+eastern_public_acceptance_rate_growth)^((COLUMN()-8)/12) -> 0.78 | I44: =eastern_public_acceptance_rate*(1+eastern_public_acceptance_rate_growth)^((COLUMN()-8)/12) -> 0.78128823 | J44: =eastern_public_acceptance_rate*(1+eastern_public_acceptance_rate_growth)^((COLUMN()-8)/12) -> 0.78257859 | K44: =eastern_public_acceptance_rate*(1+eastern_public_acceptance_rate_growth)^((COLUMN()-8)/12) -> 0.78387109 | L44: =eastern_public_acceptance_rate*(1+eastern_public_acceptance_rate_growth)^((COLUMN()-8)/12) -> 0.78516571 | M44: =eastern_public_acceptance_rate*(1+eastern_public_acceptance_rate_growth)^((COLUMN()-8)/12) -> 0.78646248 | N44: =eastern_public_acceptance_rate*(1+eastern_public_acceptance_rate_growth)^((COLUMN()-8)/12) -> 0.78776139 | O44: =eastern_public_acceptance_rate*(1+eastern_public_acceptance_rate_growth)^((COLUMN()-8)/12) -> 0.78906244 | ... AQ44: =eastern_public_acceptance_rate*(1+eastern_public_acceptance_rate_growth)^((COLUMN()-8)/12) -> 0.82637741
F45: times Eastern Public Stock Availability Rate | H45: =eastern_public_stock_availability_rate*(1+eastern_public_stock_availability_rate_growth)^((COLUMN()-8)/12) -> 0.82 | I45: =eastern_public_stock_availability_rate*(1+eastern_public_stock_availability_rate_growth)^((COLUMN()-8)/12) -> 0.82101802 | J45: =eastern_public_stock_availability_rate*(1+eastern_public_stock_availability_rate_growth)^((COLUMN()-8)/12) -> 0.8220373 | K45: =eastern_public_stock_availability_rate*(1+eastern_public_stock_availability_rate_growth)^((COLUMN()-8)/12) -> 0.82305785 | L45: =eastern_public_stock_availability_rate*(1+eastern_public_stock_availability_rate_growth)^((COLUMN()-8)/12) -> 0.82407967 | M45: =eastern_public_stock_availability_rate*(1+eastern_public_stock_availability_rate_growth)^((COLUMN()-8)/12) -> 0.82510275 | N45: =eastern_public_stock_availability_rate*(1+eastern_public_stock_availability_rate_growth)^((COLUMN()-8)/12) -> 0.82612711 | O45: =eastern_public_stock_availability_rate*(1+eastern_public_stock_availability_rate_growth)^((COLUMN()-8)/12) -> 0.82715274 | ... AQ45: =eastern_public_stock_availability_rate*(1+eastern_public_stock_availability_rate_growth)^((COLUMN()-8)/12) -> 0.85639307
F46: times Eastern Public Active Coverage State | H46: =0.08 -> 0.08 | I46: =H46+I47-I48 -> 0.090034528 | J46: =I46+J47-J48 -> 0.10010367 | K46: =J46+K47-K48 -> 0.11020751 | L46: =K46+L47-L48 -> 0.12034613 | M46: =L46+M47-M48 -> 0.13051962 | N46: =M46+N47-N48 -> 0.14072807 | O46: =N46+O47-O48 -> 0.15097156 | P46: =O46+P47-P48 -> 0.16125018 | ... AQ46: =AP46+AQ47-AQ48 -> 0.45237307
G47: Eastern Public Coverage Additions | H47: =eastern_public_coverage_additions*(1+eastern_public_coverage_additions_growth)^((COLUMN()-8)/12) -> 0.014 | I47: =eastern_public_coverage_additions*(1+eastern_public_coverage_additions_growth)^((COLUMN()-8)/12) -> 0.014034528 | J47: =eastern_public_coverage_additions*(1+eastern_public_coverage_additions_growth)^((COLUMN()-8)/12) -> 0.014069141 | K47: =eastern_public_coverage_additions*(1+eastern_public_coverage_additions_growth)^((COLUMN()-8)/12) -> 0.014103839 | L47: =eastern_public_coverage_additions*(1+eastern_public_coverage_additions_growth)^((COLUMN()-8)/12) -> 0.014138623 | M47: =eastern_public_coverage_additions*(1+eastern_public_coverage_additions_growth)^((COLUMN()-8)/12) -> 0.014173493 | N47: =eastern_public_coverage_additions*(1+eastern_public_coverage_additions_growth)^((COLUMN()-8)/12) -> 0.014208448 | O47: =eastern_public_coverage_additions*(1+eastern_public_coverage_additions_growth)^((COLUMN()-8)/12) -> 0.01424349 | ... AQ47: =eastern_public_coverage_additions*(1+eastern_public_coverage_additions_growth)^((COLUMN()-8)/12) -> 0.015260541
G48: plus Eastern Public Coverage Churn | H48: =eastern_public_coverage_churn*(1+eastern_public_coverage_churn_growth)^((COLUMN()-8)/12) -> 0.004 | I48: =eastern_public_coverage_churn*(1+eastern_public_coverage_churn_growth)^((COLUMN()-8)/12) -> 0.004 | J48: =eastern_public_coverage_churn*(1+eastern_public_coverage_churn_growth)^((COLUMN()-8)/12) -> 0.004 | K48: =eastern_public_coverage_churn*(1+eastern_public_coverage_churn_growth)^((COLUMN()-8)/12) -> 0.004 | L48: =eastern_public_coverage_churn*(1+eastern_public_coverage_churn_growth)^((COLUMN()-8)/12) -> 0.004 | M48: =eastern_public_coverage_churn*(1+eastern_public_coverage_churn_growth)^((COLUMN()-8)/12) -> 0.004 | N48: =eastern_public_coverage_churn*(1+eastern_public_coverage_churn_growth)^((COLUMN()-8)/12) -> 0.004 | O48: =eastern_public_coverage_churn*(1+eastern_public_coverage_churn_growth)^((COLUMN()-8)/12) -> 0.004 | ... AQ48: =eastern_public_coverage_churn*(1+eastern_public_coverage_churn_growth)^((COLUMN()-8)/12) -> 0.004
E49: times Eastern Public Net Realised Price Per Dose | H49: =eastern_public_net_price_per_dose*(1+eastern_public_net_price_per_dose_growth)^((COLUMN()-8)/12) -> 33500 | I49: =eastern_public_net_price_per_dose*(1+eastern_public_net_price_per_dose_growth)^((COLUMN()-8)/12) -> 33582.62 | J49: =eastern_public_net_price_per_dose*(1+eastern_public_net_price_per_dose_growth)^((COLUMN()-8)/12) -> 33665.444 | K49: =eastern_public_net_price_per_dose*(1+eastern_public_net_price_per_dose_growth)^((COLUMN()-8)/12) -> 33748.472 | L49: =eastern_public_net_price_per_dose*(1+eastern_public_net_price_per_dose_growth)^((COLUMN()-8)/12) -> 33831.705 | M49: =eastern_public_net_price_per_dose*(1+eastern_public_net_price_per_dose_growth)^((COLUMN()-8)/12) -> 33915.143 | N49: =eastern_public_net_price_per_dose*(1+eastern_public_net_price_per_dose_growth)^((COLUMN()-8)/12) -> 33998.787 | O49: =eastern_public_net_price_per_dose*(1+eastern_public_net_price_per_dose_growth)^((COLUMN()-8)/12) -> 34082.637 | ... AQ49: =eastern_public_net_price_per_dose*(1+eastern_public_net_price_per_dose_growth)^((COLUMN()-8)/12) -> 36516.295
D50: plus Northern Public Revenue | H50: =(H51*H64) -> 878203.33 | I50: =(I51*I64) -> 971986.76 | J50: =(J51*J64) -> 1069080.3 | K50: =(K51*K64) -> 1169576.9 | L50: =(L51*L64) -> 1273572 | M50: =(M51*M64) -> 1381163.4 | N50: =(N51*N64) -> 1492451.3 | O50: =(O51*O64) -> 1607538.6 | ... AQ50: =(AQ51*AQ64) -> 6883141.6
E51: Northern Public Administered Doses | H51: =(((((H52*H57)*H58)*H59)*H60)*H61) -> 27.021641 | I51: =(((((I52*I57)*I58)*I59)*I60)*I61) -> 29.833707 | J51: =(((((J52*J57)*J58)*J59)*J60)*J61) -> 32.733121 | K51: =(((((K52*K57)*K58)*K59)*K60)*K61) -> 35.722028 | L51: =(((((L52*L57)*L58)*L59)*L60)*L61) -> 38.802621 | M51: =(((((M52*M57)*M58)*M59)*M60)*M61) -> 41.97714 | N51: =(((((N52*N57)*N58)*N59)*N60)*N61) -> 45.247877 | O51: =(((((O52*O57)*O58)*O59)*O60)*O61) -> 48.617171 | ... AQ51: =(((((AQ52*AQ57)*AQ58)*AQ59)*AQ60)*AQ61) -> 194.29492
F52: Northern Reachable Pregnancies | H52: =(((H53*H54)*H55)*H56) -> 8373.7309 | I52: =(((I53*I54)*I55)*I56) -> 8392.4653 | J52: =(((J53*J54)*J55)*J56) -> 8411.2417 | K52: =(((K53*K54)*K55)*K56) -> 8430.0601 | L52: =(((L53*L54)*L55)*L56) -> 8448.9206 | M52: =(((M53*M54)*M55)*M56) -> 8467.8233 | N52: =(((N53*N54)*N55)*N56) -> 8486.7683 | O52: =(((O53*O54)*O55)*O56) -> 8505.7556 | ... AQ52: =(((AQ53*AQ54)*AQ55)*AQ56) -> 9055.0013
G53: National Live Births Per Month | H53: =H8 -> 145833 | I53: =I8 -> 146049.97 | J53: =J8 -> 146267.25 | K53: =K8 -> 146484.86 | L53: =L8 -> 146702.8 | M53: =M8 -> 146921.06 | N53: =N8 -> 147139.64 | O53: =O8 -> 147358.55 | ... AQ53: =AQ8 -> 153622.03
G54: times Northern Regional Opportunity Weight | H54: =northern_regional_opportunity_weight*(1+northern_regional_opportunity_weight_growth)^((COLUMN()-8)/12) -> 0.22 | I54: =northern_regional_opportunity_weight*(1+northern_regional_opportunity_weight_growth)^((COLUMN()-8)/12) -> 0.22 | J54: =northern_regional_opportunity_weight*(1+northern_regional_opportunity_weight_growth)^((COLUMN()-8)/12) -> 0.22 | K54: =northern_regional_opportunity_weight*(1+northern_regional_opportunity_weight_growth)^((COLUMN()-8)/12) -> 0.22 | L54: =northern_regional_opportunity_weight*(1+northern_regional_opportunity_weight_growth)^((COLUMN()-8)/12) -> 0.22 | M54: =northern_regional_opportunity_weight*(1+northern_regional_opportunity_weight_growth)^((COLUMN()-8)/12) -> 0.22 | N54: =northern_regional_opportunity_weight*(1+northern_regional_opportunity_weight_growth)^((COLUMN()-8)/12) -> 0.22 | O54: =northern_regional_opportunity_weight*(1+northern_regional_opportunity_weight_growth)^((COLUMN()-8)/12) -> 0.22 | ... AQ54: =northern_regional_opportunity_weight*(1+northern_regional_opportunity_weight_growth)^((COLUMN()-8)/12) -> 0.22
G55: times Northern ANC Access Rate | H55: =northern_anc_access_rate*(1+northern_anc_access_rate_growth)^((COLUMN()-8)/12) -> 0.58 | I55: =northern_anc_access_rate*(1+northern_anc_access_rate_growth)^((COLUMN()-8)/12) -> 0.5801448 | J55: =northern_anc_access_rate*(1+northern_anc_access_rate_growth)^((COLUMN()-8)/12) -> 0.58028964 | K55: =northern_anc_access_rate*(1+northern_anc_access_rate_growth)^((COLUMN()-8)/12) -> 0.58043451 | L55: =northern_anc_access_rate*(1+northern_anc_access_rate_growth)^((COLUMN()-8)/12) -> 0.58057942 | M55: =northern_anc_access_rate*(1+northern_anc_access_rate_growth)^((COLUMN()-8)/12) -> 0.58072437 | N55: =northern_anc_access_rate*(1+northern_anc_access_rate_growth)^((COLUMN()-8)/12) -> 0.58086935 | O55: =northern_anc_access_rate*(1+northern_anc_access_rate_growth)^((COLUMN()-8)/12) -> 0.58101437 | ... AQ55: =northern_anc_access_rate*(1+northern_anc_access_rate_growth)^((COLUMN()-8)/12) -> 0.5850896
G56: times Northern Third Trimester Window Rate | H56: =northern_third_trimester_window_rate*(1+northern_third_trimester_window_rate_growth)^((COLUMN()-8)/12) -> 0.45 | I56: =northern_third_trimester_window_rate*(1+northern_third_trimester_window_rate_growth)^((COLUMN()-8)/12) -> 0.45022438 | J56: =northern_third_trimester_window_rate*(1+northern_third_trimester_window_rate_growth)^((COLUMN()-8)/12) -> 0.45044888 | K56: =northern_third_trimester_window_rate*(1+northern_third_trimester_window_rate_growth)^((COLUMN()-8)/12) -> 0.45067349 | L56: =northern_third_trimester_window_rate*(1+northern_third_trimester_window_rate_growth)^((COLUMN()-8)/12) -> 0.45089821 | M56: =northern_third_trimester_window_rate*(1+northern_third_trimester_window_rate_growth)^((COLUMN()-8)/12) -> 0.45112304 | N56: =northern_third_trimester_window_rate*(1+northern_third_trimester_window_rate_growth)^((COLUMN()-8)/12) -> 0.45134798 | O56: =northern_third_trimester_window_rate*(1+northern_third_trimester_window_rate_growth)^((COLUMN()-8)/12) -> 0.45157304 | ... AQ56: =northern_third_trimester_window_rate*(1+northern_third_trimester_window_rate_growth)^((COLUMN()-8)/12) -> 0.45792036
F57: times Northern Public Eligibility Rate | H57: =northern_public_eligibility_rate*(1+northern_public_eligibility_rate_growth)^((COLUMN()-8)/12) -> 0.17 | I57: =northern_public_eligibility_rate*(1+northern_public_eligibility_rate_growth)^((COLUMN()-8)/12) -> 0.17109379 | J57: =northern_public_eligibility_rate*(1+northern_public_eligibility_rate_growth)^((COLUMN()-8)/12) -> 0.17219461 | K57: =northern_public_eligibility_rate*(1+northern_public_eligibility_rate_growth)^((COLUMN()-8)/12) -> 0.17330251 | L57: =northern_public_eligibility_rate*(1+northern_public_eligibility_rate_growth)^((COLUMN()-8)/12) -> 0.17441755 | M57: =northern_public_eligibility_rate*(1+northern_public_eligibility_rate_growth)^((COLUMN()-8)/12) -> 0.17553975 | N57: =northern_public_eligibility_rate*(1+northern_public_eligibility_rate_growth)^((COLUMN()-8)/12) -> 0.17666918 | O57: =northern_public_eligibility_rate*(1+northern_public_eligibility_rate_growth)^((COLUMN()-8)/12) -> 0.17780588 | ... AQ57: =northern_public_eligibility_rate*(1+northern_public_eligibility_rate_growth)^((COLUMN()-8)/12) -> 0.21278199
F58: times Northern Public Provider Recommendation Rate | H58: =northern_public_provider_recommendation_rate*(1+northern_public_provider_recommendation_rate_growth)^((COLUMN()-8)/12) -> 0.39 | I58: =northern_public_provider_recommendation_rate*(1+northern_public_provider_recommendation_rate_growth)^((COLUMN()-8)/12) -> 0.39127676 | J58: =northern_public_provider_recommendation_rate*(1+northern_public_provider_recommendation_rate_growth)^((COLUMN()-8)/12) -> 0.3925577 | K58: =northern_public_provider_recommendation_rate*(1+northern_public_provider_recommendation_rate_growth)^((COLUMN()-8)/12) -> 0.39384283 | L58: =northern_public_provider_recommendation_rate*(1+northern_public_provider_recommendation_rate_growth)^((COLUMN()-8)/12) -> 0.39513217 | M58: =northern_public_provider_recommendation_rate*(1+northern_public_provider_recommendation_rate_growth)^((COLUMN()-8)/12) -> 0.39642573 | N58: =northern_public_provider_recommendation_rate*(1+northern_public_provider_recommendation_rate_growth)^((COLUMN()-8)/12) -> 0.39772352 | O58: =northern_public_provider_recommendation_rate*(1+northern_public_provider_recommendation_rate_growth)^((COLUMN()-8)/12) -> 0.39902557 | ... AQ58: =northern_public_provider_recommendation_rate*(1+northern_public_provider_recommendation_rate_growth)^((COLUMN()-8)/12) -> 0.43726547
F59: times Northern Public Acceptance Rate | H59: =northern_public_acceptance_rate*(1+northern_public_acceptance_rate_growth)^((COLUMN()-8)/12) -> 0.78 | I59: =northern_public_acceptance_rate*(1+northern_public_acceptance_rate_growth)^((COLUMN()-8)/12) -> 0.78128823 | J59: =northern_public_acceptance_rate*(1+northern_public_acceptance_rate_growth)^((COLUMN()-8)/12) -> 0.78257859 | K59: =northern_public_acceptance_rate*(1+northern_public_acceptance_rate_growth)^((COLUMN()-8)/12) -> 0.78387109 | L59: =northern_public_acceptance_rate*(1+northern_public_acceptance_rate_growth)^((COLUMN()-8)/12) -> 0.78516571 | M59: =northern_public_acceptance_rate*(1+northern_public_acceptance_rate_growth)^((COLUMN()-8)/12) -> 0.78646248 | N59: =northern_public_acceptance_rate*(1+northern_public_acceptance_rate_growth)^((COLUMN()-8)/12) -> 0.78776139 | O59: =northern_public_acceptance_rate*(1+northern_public_acceptance_rate_growth)^((COLUMN()-8)/12) -> 0.78906244 | ... AQ59: =northern_public_acceptance_rate*(1+northern_public_acceptance_rate_growth)^((COLUMN()-8)/12) -> 0.82637741
F60: times Northern Public Stock Availability Rate | H60: =northern_public_stock_availability_rate*(1+northern_public_stock_availability_rate_growth)^((COLUMN()-8)/12) -> 0.78 | I60: =northern_public_stock_availability_rate*(1+northern_public_stock_availability_rate_growth)^((COLUMN()-8)/12) -> 0.78096836 | J60: =northern_public_stock_availability_rate*(1+northern_public_stock_availability_rate_growth)^((COLUMN()-8)/12) -> 0.78193792 | K60: =northern_public_stock_availability_rate*(1+northern_public_stock_availability_rate_growth)^((COLUMN()-8)/12) -> 0.78290869 | L60: =northern_public_stock_availability_rate*(1+northern_public_stock_availability_rate_growth)^((COLUMN()-8)/12) -> 0.78388066 | M60: =northern_public_stock_availability_rate*(1+northern_public_stock_availability_rate_growth)^((COLUMN()-8)/12) -> 0.78485384 | N60: =northern_public_stock_availability_rate*(1+northern_public_stock_availability_rate_growth)^((COLUMN()-8)/12) -> 0.78582823 | O60: =northern_public_stock_availability_rate*(1+northern_public_stock_availability_rate_growth)^((COLUMN()-8)/12) -> 0.78680382 | ... AQ60: =northern_public_stock_availability_rate*(1+northern_public_stock_availability_rate_growth)^((COLUMN()-8)/12) -> 0.81461779
F61: times Northern Public Active Coverage State | H61: =0.08 -> 0.08 | I61: =H61+I62-I63 -> 0.087027129 | J61: =I61+J62-J63 -> 0.094081454 | K61: =J61+K62-K63 -> 0.10116304 | L61: =K61+L62-L63 -> 0.10827196 | M61: =L61+M62-M63 -> 0.11540828 | N61: =M61+N62-N63 -> 0.12257206 | O61: =N61+O62-O63 -> 0.12976337 | P61: =O61+P62-P63 -> 0.13698228 | ... AQ61: =AP61+AQ62-AQ63 -> 0.34257884
G62: Northern Public Coverage Additions | H62: =northern_public_coverage_additions*(1+northern_public_coverage_additions_growth)^((COLUMN()-8)/12) -> 0.011 | I62: =northern_public_coverage_additions*(1+northern_public_coverage_additions_growth)^((COLUMN()-8)/12) -> 0.011027129 | J62: =northern_public_coverage_additions*(1+northern_public_coverage_additions_growth)^((COLUMN()-8)/12) -> 0.011054325 | K62: =northern_public_coverage_additions*(1+northern_public_coverage_additions_growth)^((COLUMN()-8)/12) -> 0.011081588 | L62: =northern_public_coverage_additions*(1+northern_public_coverage_additions_growth)^((COLUMN()-8)/12) -> 0.011108918 | M62: =northern_public_coverage_additions*(1+northern_public_coverage_additions_growth)^((COLUMN()-8)/12) -> 0.011136316 | N62: =northern_public_coverage_additions*(1+northern_public_coverage_additions_growth)^((COLUMN()-8)/12) -> 0.011163781 | O62: =northern_public_coverage_additions*(1+northern_public_coverage_additions_growth)^((COLUMN()-8)/12) -> 0.011191314 | ... AQ62: =northern_public_coverage_additions*(1+northern_public_coverage_additions_growth)^((COLUMN()-8)/12) -> 0.011990425
G63: plus Northern Public Coverage Churn | H63: =northern_public_coverage_churn*(1+northern_public_coverage_churn_growth)^((COLUMN()-8)/12) -> 0.004 | I63: =northern_public_coverage_churn*(1+northern_public_coverage_churn_growth)^((COLUMN()-8)/12) -> 0.004 | J63: =northern_public_coverage_churn*(1+northern_public_coverage_churn_growth)^((COLUMN()-8)/12) -> 0.004 | K63: =northern_public_coverage_churn*(1+northern_public_coverage_churn_growth)^((COLUMN()-8)/12) -> 0.004 | L63: =northern_public_coverage_churn*(1+northern_public_coverage_churn_growth)^((COLUMN()-8)/12) -> 0.004 | M63: =northern_public_coverage_churn*(1+northern_public_coverage_churn_growth)^((COLUMN()-8)/12) -> 0.004 | N63: =northern_public_coverage_churn*(1+northern_public_coverage_churn_growth)^((COLUMN()-8)/12) -> 0.004 | O63: =northern_public_coverage_churn*(1+northern_public_coverage_churn_growth)^((COLUMN()-8)/12) -> 0.004 | ... AQ63: =northern_public_coverage_churn*(1+northern_public_coverage_churn_growth)^((COLUMN()-8)/12) -> 0.004
E64: times Northern Public Net Realised Price Per Dose | H64: =northern_public_net_price_per_dose*(1+northern_public_net_price_per_dose_growth)^((COLUMN()-8)/12) -> 32500 | I64: =northern_public_net_price_per_dose*(1+northern_public_net_price_per_dose_growth)^((COLUMN()-8)/12) -> 32580.154 | J64: =northern_public_net_price_per_dose*(1+northern_public_net_price_per_dose_growth)^((COLUMN()-8)/12) -> 32660.505 | K64: =northern_public_net_price_per_dose*(1+northern_public_net_price_per_dose_growth)^((COLUMN()-8)/12) -> 32741.055 | L64: =northern_public_net_price_per_dose*(1+northern_public_net_price_per_dose_growth)^((COLUMN()-8)/12) -> 32821.803 | M64: =northern_public_net_price_per_dose*(1+northern_public_net_price_per_dose_growth)^((COLUMN()-8)/12) -> 32902.751 | N64: =northern_public_net_price_per_dose*(1+northern_public_net_price_per_dose_growth)^((COLUMN()-8)/12) -> 32983.898 | O64: =northern_public_net_price_per_dose*(1+northern_public_net_price_per_dose_growth)^((COLUMN()-8)/12) -> 33065.245 | ... AQ64: =northern_public_net_price_per_dose*(1+northern_public_net_price_per_dose_growth)^((COLUMN()-8)/12) -> 35426.257
C65: plus Private Revenue | H65: =(((H66+H77)+H88)+H99) -> 5176560.3 | I65: =(((I66+I77)+I88)+I99) -> 6678769.1 | J65: =(((J66+J77)+J88)+J99) -> 8233561.3 | K65: =(((K66+K77)+K88)+K99) -> 9842345.3 | L65: =(((L66+L77)+L88)+L99) -> 11506563 | M65: =(((M66+M77)+M88)+M99) -> 13227692 | N65: =(((N66+N77)+N88)+N99) -> 15007243 | O65: =(((O66+O77)+O88)+O99) -> 16846765 | ... AQ65: =(((AQ66+AQ77)+AQ88)+AQ99) -> 1.0029822e+08
D66: Central Private Revenue | H66: =(H67*H76) -> 3840393.7 | I66: =(I67*I76) -> 5097231 | J66: =(J67*J76) -> 6398062.3 | K66: =(K67*K76) -> 7744063.4 | L66: =(L67*L76) -> 9136438.5 | M66: =(M67*M76) -> 10576420 | N66: =(N67*N76) -> 12065270 | O66: =(O67*O76) -> 13604281 | ... AQ66: =(AQ67*AQ76) -> 83400332
E67: Central Private Administered Doses | H67: =(((((H68*H69)*H70)*H71)*H72)*H73) -> 32.54571 | I67: =(((((I68*I69)*I70)*I71)*I72)*I73) -> 43.073214 | J67: =(((((J68*J69)*J70)*J71)*J72)*J73) -> 53.910877 | K67: =(((((K68*K69)*K70)*K71)*K72)*K73) -> 65.065655 | L67: =(((((L68*L69)*L70)*L71)*L72)*L73) -> 76.544645 | M67: =(((((M68*M69)*M70)*M71)*M72)*M73) -> 88.355083 | N67: =(((((N68*N69)*N70)*N71)*N72)*N73) -> 100.50435 | O67: =(((((O68*O69)*O70)*O71)*O72)*O73) -> 112.99999 | ... AQ67: =(((((AQ68*AQ69)*AQ70)*AQ71)*AQ72)*AQ73) -> 639.30743
F68: Central Reachable Pregnancies | H68: =H7 -> 18227.958 | I68: =I7 -> 18268.74 | J68: =J7 -> 18309.612 | K68: =K7 -> 18350.576 | L68: =L7 -> 18391.632 | M68: =M7 -> 18432.779 | N68: =N7 -> 18474.018 | O68: =O7 -> 18515.35 | ... AQ68: =AQ7 -> 19710.949
F69: times Central Private Eligibility Rate | H69: =central_private_eligibility_rate*(1+central_private_eligibility_rate_growth)^((COLUMN()-8)/12) -> 0.07 | I69: =central_private_eligibility_rate*(1+central_private_eligibility_rate_growth)^((COLUMN()-8)/12) -> 0.070340729 | J69: =central_private_eligibility_rate*(1+central_private_eligibility_rate_growth)^((COLUMN()-8)/12) -> 0.070683116 | K69: =central_private_eligibility_rate*(1+central_private_eligibility_rate_growth)^((COLUMN()-8)/12) -> 0.071027169 | L69: =central_private_eligibility_rate*(1+central_private_eligibility_rate_growth)^((COLUMN()-8)/12) -> 0.071372898 | M69: =central_private_eligibility_rate*(1+central_private_eligibility_rate_growth)^((COLUMN()-8)/12) -> 0.071720309 | N69: =central_private_eligibility_rate*(1+central_private_eligibility_rate_growth)^((COLUMN()-8)/12) -> 0.072069411 | O69: =central_private_eligibility_rate*(1+central_private_eligibility_rate_growth)^((COLUMN()-8)/12) -> 0.072420212 | ... AQ69: =central_private_eligibility_rate*(1+central_private_eligibility_rate_growth)^((COLUMN()-8)/12) -> 0.082967273
F70: times Central Private Provider Recommendation Rate | H70: =central_private_provider_recommendation_rate*(1+central_private_provider_recommendation_rate_growth)^((COLUMN()-8)/12) -> 0.67 | I70: =central_private_provider_recommendation_rate*(1+central_private_provider_recommendation_rate_growth)^((COLUMN()-8)/12) -> 0.67219341 | J70: =central_private_provider_recommendation_rate*(1+central_private_provider_recommendation_rate_growth)^((COLUMN()-8)/12) -> 0.67439399 | K70: =central_private_provider_recommendation_rate*(1+central_private_provider_recommendation_rate_growth)^((COLUMN()-8)/12) -> 0.67660178 | L70: =central_private_provider_recommendation_rate*(1+central_private_provider_recommendation_rate_growth)^((COLUMN()-8)/12) -> 0.6788168 | M70: =central_private_provider_recommendation_rate*(1+central_private_provider_recommendation_rate_growth)^((COLUMN()-8)/12) -> 0.68103907 | N70: =central_private_provider_recommendation_rate*(1+central_private_provider_recommendation_rate_growth)^((COLUMN()-8)/12) -> 0.68326861 | O70: =central_private_provider_recommendation_rate*(1+central_private_provider_recommendation_rate_growth)^((COLUMN()-8)/12) -> 0.68550546 | ... AQ70: =central_private_provider_recommendation_rate*(1+central_private_provider_recommendation_rate_growth)^((COLUMN()-8)/12) -> 0.75119965
F71: times Central Private Acceptance Rate | H71: =central_private_acceptance_rate*(1+central_private_acceptance_rate_growth)^((COLUMN()-8)/12) -> 0.81 | I71: =central_private_acceptance_rate*(1+central_private_acceptance_rate_growth)^((COLUMN()-8)/12) -> 0.81133778 | J71: =central_private_acceptance_rate*(1+central_private_acceptance_rate_growth)^((COLUMN()-8)/12) -> 0.81267777 | K71: =central_private_acceptance_rate*(1+central_private_acceptance_rate_growth)^((COLUMN()-8)/12) -> 0.81401997 | L71: =central_private_acceptance_rate*(1+central_private_acceptance_rate_growth)^((COLUMN()-8)/12) -> 0.81536439 | M71: =central_private_acceptance_rate*(1+central_private_acceptance_rate_growth)^((COLUMN()-8)/12) -> 0.81671104 | N71: =central_private_acceptance_rate*(1+central_private_acceptance_rate_growth)^((COLUMN()-8)/12) -> 0.8180599 | O71: =central_private_acceptance_rate*(1+central_private_acceptance_rate_growth)^((COLUMN()-8)/12) -> 0.81941099 | ... AQ71: =central_private_acceptance_rate*(1+central_private_acceptance_rate_growth)^((COLUMN()-8)/12) -> 0.85816116
F72: times Central Private Stock Availability Rate | H72: =central_private_stock_availability_rate*(1+central_private_stock_availability_rate_growth)^((COLUMN()-8)/12) -> 0.94 | I72: =central_private_stock_availability_rate*(1+central_private_stock_availability_rate_growth)^((COLUMN()-8)/12) -> 0.941167 | J72: =central_private_stock_availability_rate*(1+central_private_stock_availability_rate_growth)^((COLUMN()-8)/12) -> 0.94233545 | K72: =central_private_stock_availability_rate*(1+central_private_stock_availability_rate_growth)^((COLUMN()-8)/12) -> 0.94350534 | L72: =central_private_stock_availability_rate*(1+central_private_stock_availability_rate_growth)^((COLUMN()-8)/12) -> 0.94467669 | M72: =central_private_stock_availability_rate*(1+central_private_stock_availability_rate_growth)^((COLUMN()-8)/12) -> 0.9458495 | N72: =central_private_stock_availability_rate*(1+central_private_stock_availability_rate_growth)^((COLUMN()-8)/12) -> 0.94702376 | O72: =central_private_stock_availability_rate*(1+central_private_stock_availability_rate_growth)^((COLUMN()-8)/12) -> 0.94819948 | ... AQ72: =central_private_stock_availability_rate*(1+central_private_stock_availability_rate_growth)^((COLUMN()-8)/12) -> 0.98171888
F73: times Central Private Active Coverage State | H73: =0.05 -> 0.05 | I73: =H73+I74-I75 -> 0.065302408 | J73: =I73+J74-J75 -> 0.080657354 | K73: =J73+K74-K75 -> 0.096064967 | L73: =K73+L74-L75 -> 0.11152538 | M73: =L73+M74-M75 -> 0.12703871 | N73: =M73+N74-N75 -> 0.14260511 | O73: =N73+O74-O75 -> 0.15822469 | P73: =O73+P74-P75 -> 0.17389759 | ... AQ73: =AP73+AQ74-AQ75 -> 0.61770913
G74: Central Private Coverage Additions | H74: =central_private_coverage_additions*(1+central_private_coverage_additions_growth)^((COLUMN()-8)/12) -> 0.02125 | I74: =central_private_coverage_additions*(1+central_private_coverage_additions_growth)^((COLUMN()-8)/12) -> 0.021302408 | J74: =central_private_coverage_additions*(1+central_private_coverage_additions_growth)^((COLUMN()-8)/12) -> 0.021354946 | K74: =central_private_coverage_additions*(1+central_private_coverage_additions_growth)^((COLUMN()-8)/12) -> 0.021407613 | L74: =central_private_coverage_additions*(1+central_private_coverage_additions_growth)^((COLUMN()-8)/12) -> 0.02146041 | M74: =central_private_coverage_additions*(1+central_private_coverage_additions_growth)^((COLUMN()-8)/12) -> 0.021513337 | N74: =central_private_coverage_additions*(1+central_private_coverage_additions_growth)^((COLUMN()-8)/12) -> 0.021566395 | O74: =central_private_coverage_additions*(1+central_private_coverage_additions_growth)^((COLUMN()-8)/12) -> 0.021619583 | ... AQ74: =central_private_coverage_additions*(1+central_private_coverage_additions_growth)^((COLUMN()-8)/12) -> 0.023163322
G75: plus Central Private Coverage Churn | H75: =central_private_coverage_churn*(1+central_private_coverage_churn_growth)^((COLUMN()-8)/12) -> 0.006 | I75: =central_private_coverage_churn*(1+central_private_coverage_churn_growth)^((COLUMN()-8)/12) -> 0.006 | J75: =central_private_coverage_churn*(1+central_private_coverage_churn_growth)^((COLUMN()-8)/12) -> 0.006 | K75: =central_private_coverage_churn*(1+central_private_coverage_churn_growth)^((COLUMN()-8)/12) -> 0.006 | L75: =central_private_coverage_churn*(1+central_private_coverage_churn_growth)^((COLUMN()-8)/12) -> 0.006 | M75: =central_private_coverage_churn*(1+central_private_coverage_churn_growth)^((COLUMN()-8)/12) -> 0.006 | N75: =central_private_coverage_churn*(1+central_private_coverage_churn_growth)^((COLUMN()-8)/12) -> 0.006 | O75: =central_private_coverage_churn*(1+central_private_coverage_churn_growth)^((COLUMN()-8)/12) -> 0.006 | ... AQ75: =central_private_coverage_churn*(1+central_private_coverage_churn_growth)^((COLUMN()-8)/12) -> 0.006
E76: times Central Private Net Realised Price Per Dose | H76: =central_private_net_price_per_dose*(1+central_private_net_price_per_dose_growth)^((COLUMN()-8)/12) -> 118000 | I76: =central_private_net_price_per_dose*(1+central_private_net_price_per_dose_growth)^((COLUMN()-8)/12) -> 118338.77 | J76: =central_private_net_price_per_dose*(1+central_private_net_price_per_dose_growth)^((COLUMN()-8)/12) -> 118678.5 | K76: =central_private_net_price_per_dose*(1+central_private_net_price_per_dose_growth)^((COLUMN()-8)/12) -> 119019.22 | L76: =central_private_net_price_per_dose*(1+central_private_net_price_per_dose_growth)^((COLUMN()-8)/12) -> 119360.91 | M76: =central_private_net_price_per_dose*(1+central_private_net_price_per_dose_growth)^((COLUMN()-8)/12) -> 119703.58 | N76: =central_private_net_price_per_dose*(1+central_private_net_price_per_dose_growth)^((COLUMN()-8)/12) -> 120047.24 | O76: =central_private_net_price_per_dose*(1+central_private_net_price_per_dose_growth)^((COLUMN()-8)/12) -> 120391.88 | ... AQ76: =central_private_net_price_per_dose*(1+central_private_net_price_per_dose_growth)^((COLUMN()-8)/12) -> 130454.19
D77: plus Western Private Revenue | H77: =(H78*H87) -> 964397.82 | I77: =(I78*I87) -> 1163098.6 | J77: =(J78*J87) -> 1368755 | K77: =(K78*K87) -> 1581554.8 | L77: =(L78*L87) -> 1801690 | M77: =(M78*M87) -> 2029357.6 | N77: =(N78*N87) -> 2264759.2 | O77: =(O78*O87) -> 2508101.3 | ... AQ77: =(AQ78*AQ87) -> 13560339
E78: Western Private Administered Doses | H78: =(((((H79*H80)*H81)*H82)*H83)*H84) -> 9.4548806 | I78: =(((((I79*I80)*I81)*I82)*I83)*I84) -> 11.370285 | J78: =(((((J79*J80)*J81)*J82)*J83)*J84) -> 13.342447 | K78: =(((((K79*K80)*K81)*K82)*K83)*K84) -> 15.372658 | L78: =(((((L79*L80)*L81)*L82)*L83)*L84) -> 17.462233 | M78: =(((((M79*M80)*M81)*M82)*M83)*M84) -> 19.612514 | N78: =(((((N79*N80)*N81)*N82)*N83)*N84) -> 21.824871 | O78: =(((((O79*O80)*O81)*O82)*O83)*O84) -> 24.100702 | ... AQ78: =(((((AQ79*AQ80)*AQ81)*AQ82)*AQ83)*AQ84) -> 120.25257
F79: Western Reachable Pregnancies | H79: =H22 -> 13474.969 | I79: =I22 -> 13505.117 | J79: =J22 -> 13535.331 | K79: =K22 -> 13565.614 | L79: =L22 -> 13595.964 | M79: =M22 -> 13626.382 | N79: =N22 -> 13656.868 | O79: =O22 -> 13687.423 | ... AQ79: =AQ22 -> 14571.266
F80: times Western Private Eligibility Rate | H80: =western_private_eligibility_rate*(1+western_private_eligibility_rate_growth)^((COLUMN()-8)/12) -> 0.035 | I80: =western_private_eligibility_rate*(1+western_private_eligibility_rate_growth)^((COLUMN()-8)/12) -> 0.035170364 | J80: =western_private_eligibility_rate*(1+western_private_eligibility_rate_growth)^((COLUMN()-8)/12) -> 0.035341558 | K80: =western_private_eligibility_rate*(1+western_private_eligibility_rate_growth)^((COLUMN()-8)/12) -> 0.035513585 | L80: =western_private_eligibility_rate*(1+western_private_eligibility_rate_growth)^((COLUMN()-8)/12) -> 0.035686449 | M80: =western_private_eligibility_rate*(1+western_private_eligibility_rate_growth)^((COLUMN()-8)/12) -> 0.035860154 | N80: =western_private_eligibility_rate*(1+western_private_eligibility_rate_growth)^((COLUMN()-8)/12) -> 0.036034705 | O80: =western_private_eligibility_rate*(1+western_private_eligibility_rate_growth)^((COLUMN()-8)/12) -> 0.036210106 | ... AQ80: =western_private_eligibility_rate*(1+western_private_eligibility_rate_growth)^((COLUMN()-8)/12) -> 0.041483636
F81: times Western Private Provider Recommendation Rate | H81: =western_private_provider_recommendation_rate*(1+western_private_provider_recommendation_rate_growth)^((COLUMN()-8)/12) -> 0.55 | I81: =western_private_provider_recommendation_rate*(1+western_private_provider_recommendation_rate_growth)^((COLUMN()-8)/12) -> 0.55180056 | J81: =western_private_provider_recommendation_rate*(1+western_private_provider_recommendation_rate_growth)^((COLUMN()-8)/12) -> 0.55360701 | K81: =western_private_provider_recommendation_rate*(1+western_private_provider_recommendation_rate_growth)^((COLUMN()-8)/12) -> 0.55541937 | L81: =western_private_provider_recommendation_rate*(1+western_private_provider_recommendation_rate_growth)^((COLUMN()-8)/12) -> 0.55723767 | M81: =western_private_provider_recommendation_rate*(1+western_private_provider_recommendation_rate_growth)^((COLUMN()-8)/12) -> 0.55906192 | N81: =western_private_provider_recommendation_rate*(1+western_private_provider_recommendation_rate_growth)^((COLUMN()-8)/12) -> 0.56089215 | O81: =western_private_provider_recommendation_rate*(1+western_private_provider_recommendation_rate_growth)^((COLUMN()-8)/12) -> 0.56272836 | ... AQ81: =western_private_provider_recommendation_rate*(1+western_private_provider_recommendation_rate_growth)^((COLUMN()-8)/12) -> 0.61665643
F82: times Western Private Acceptance Rate | H82: =western_private_acceptance_rate*(1+western_private_acceptance_rate_growth)^((COLUMN()-8)/12) -> 0.81 | I82: =western_private_acceptance_rate*(1+western_private_acceptance_rate_growth)^((COLUMN()-8)/12) -> 0.81133778 | J82: =western_private_acceptance_rate*(1+western_private_acceptance_rate_growth)^((COLUMN()-8)/12) -> 0.81267777 | K82: =western_private_acceptance_rate*(1+western_private_acceptance_rate_growth)^((COLUMN()-8)/12) -> 0.81401997 | L82: =western_private_acceptance_rate*(1+western_private_acceptance_rate_growth)^((COLUMN()-8)/12) -> 0.81536439 | M82: =western_private_acceptance_rate*(1+western_private_acceptance_rate_growth)^((COLUMN()-8)/12) -> 0.81671104 | N82: =western_private_acceptance_rate*(1+western_private_acceptance_rate_growth)^((COLUMN()-8)/12) -> 0.8180599 | O82: =western_private_acceptance_rate*(1+western_private_acceptance_rate_growth)^((COLUMN()-8)/12) -> 0.81941099 | ... AQ82: =western_private_acceptance_rate*(1+western_private_acceptance_rate_growth)^((COLUMN()-8)/12) -> 0.85816116
F83: times Western Private Stock Availability Rate | H83: =western_private_stock_availability_rate*(1+western_private_stock_availability_rate_growth)^((COLUMN()-8)/12) -> 0.9 | I83: =western_private_stock_availability_rate*(1+western_private_stock_availability_rate_growth)^((COLUMN()-8)/12) -> 0.90111734 | J83: =western_private_stock_availability_rate*(1+western_private_stock_availability_rate_growth)^((COLUMN()-8)/12) -> 0.90223607 | K83: =western_private_stock_availability_rate*(1+western_private_stock_availability_rate_growth)^((COLUMN()-8)/12) -> 0.90335618 | L83: =western_private_stock_availability_rate*(1+western_private_stock_availability_rate_growth)^((COLUMN()-8)/12) -> 0.90447769 | M83: =western_private_stock_availability_rate*(1+western_private_stock_availability_rate_growth)^((COLUMN()-8)/12) -> 0.90560058 | N83: =western_private_stock_availability_rate*(1+western_private_stock_availability_rate_growth)^((COLUMN()-8)/12) -> 0.90672488 | O83: =western_private_stock_availability_rate*(1+western_private_stock_availability_rate_growth)^((COLUMN()-8)/12) -> 0.90785056 | ... AQ83: =western_private_stock_availability_rate*(1+western_private_stock_availability_rate_growth)^((COLUMN()-8)/12) -> 0.93994361
F84: times Western Private Active Coverage State | H84: =0.05 -> 0.05 | I84: =H84+I85-I86 -> 0.059337734 | J84: =I84+J85-J86 -> 0.068713295 | K84: =J84+K85-K86 -> 0.078126776 | L84: =K84+L85-L86 -> 0.087578271 | M84: =L84+M85-M86 -> 0.097067874 | N84: =M84+N85-N86 -> 0.10659568 | O84: =N84+O85-O86 -> 0.11616178 | P84: =O84+P85-P86 -> 0.12576627 | ... AQ84: =AP84+AQ85-AQ86 -> 0.39995057
G85: Western Private Coverage Additions | H85: =western_private_coverage_additions*(1+western_private_coverage_additions_growth)^((COLUMN()-8)/12) -> 0.0153 | I85: =western_private_coverage_additions*(1+western_private_coverage_additions_growth)^((COLUMN()-8)/12) -> 0.015337734 | J85: =western_private_coverage_additions*(1+western_private_coverage_additions_growth)^((COLUMN()-8)/12) -> 0.015375561 | K85: =western_private_coverage_additions*(1+western_private_coverage_additions_growth)^((COLUMN()-8)/12) -> 0.015413481 | L85: =western_private_coverage_additions*(1+western_private_coverage_additions_growth)^((COLUMN()-8)/12) -> 0.015451495 | M85: =western_private_coverage_additions*(1+western_private_coverage_additions_growth)^((COLUMN()-8)/12) -> 0.015489603 | N85: =western_private_coverage_additions*(1+western_private_coverage_additions_growth)^((COLUMN()-8)/12) -> 0.015527804 | O85: =western_private_coverage_additions*(1+western_private_coverage_additions_growth)^((COLUMN()-8)/12) -> 0.0155661 | ... AQ85: =western_private_coverage_additions*(1+western_private_coverage_additions_growth)^((COLUMN()-8)/12) -> 0.016677592
G86: plus Western Private Coverage Churn | H86: =western_private_coverage_churn*(1+western_private_coverage_churn_growth)^((COLUMN()-8)/12) -> 0.006 | I86: =western_private_coverage_churn*(1+western_private_coverage_churn_growth)^((COLUMN()-8)/12) -> 0.006 | J86: =western_private_coverage_churn*(1+western_private_coverage_churn_growth)^((COLUMN()-8)/12) -> 0.006 | K86: =western_private_coverage_churn*(1+western_private_coverage_churn_growth)^((COLUMN()-8)/12) -> 0.006 | L86: =western_private_coverage_churn*(1+western_private_coverage_churn_growth)^((COLUMN()-8)/12) -> 0.006 | M86: =western_private_coverage_churn*(1+western_private_coverage_churn_growth)^((COLUMN()-8)/12) -> 0.006 | N86: =western_private_coverage_churn*(1+western_private_coverage_churn_growth)^((COLUMN()-8)/12) -> 0.006 | O86: =western_private_coverage_churn*(1+western_private_coverage_churn_growth)^((COLUMN()-8)/12) -> 0.006 | ... AQ86: =western_private_coverage_churn*(1+western_private_coverage_churn_growth)^((COLUMN()-8)/12) -> 0.006
E87: times Western Private Net Realised Price Per Dose | H87: =western_private_net_price_per_dose*(1+western_private_net_price_per_dose_growth)^((COLUMN()-8)/12) -> 102000 | I87: =western_private_net_price_per_dose*(1+western_private_net_price_per_dose_growth)^((COLUMN()-8)/12) -> 102292.83 | J87: =western_private_net_price_per_dose*(1+western_private_net_price_per_dose_growth)^((COLUMN()-8)/12) -> 102586.5 | K87: =western_private_net_price_per_dose*(1+western_private_net_price_per_dose_growth)^((COLUMN()-8)/12) -> 102881.02 | L87: =western_private_net_price_per_dose*(1+western_private_net_price_per_dose_growth)^((COLUMN()-8)/12) -> 103176.38 | M87: =western_private_net_price_per_dose*(1+western_private_net_price_per_dose_growth)^((COLUMN()-8)/12) -> 103472.59 | N87: =western_private_net_price_per_dose*(1+western_private_net_price_per_dose_growth)^((COLUMN()-8)/12) -> 103769.65 | O87: =western_private_net_price_per_dose*(1+western_private_net_price_per_dose_growth)^((COLUMN()-8)/12) -> 104067.56 | ... AQ87: =western_private_net_price_per_dose*(1+western_private_net_price_per_dose_growth)^((COLUMN()-8)/12) -> 112765.48
D88: plus Eastern Private Revenue | H88: =(H89*H98) -> 291455.9 | I88: =(I89*I98) -> 331315.68 | J88: =(J89*J98) -> 372570.85 | K88: =(K89*K98) -> 415259.57 | L88: =(L89*L98) -> 459420.91 | M88: =(M89*M98) -> 505094.89 | N88: =(N89*N98) -> 552322.54 | O88: =(O89*O98) -> 601145.85 | ... AQ88: =(AQ89*AQ98) -> 2823120.6
E89: Eastern Private Administered Doses | H89: =(((((H90*H91)*H92)*H93)*H94)*H95) -> 3.3119989 | I89: =(((((I90*I91)*I92)*I93)*I94)*I95) -> 3.754173 | J89: =(((((J90*J91)*J92)*J93)*J94)*J95) -> 4.2095546 | K89: =(((((K90*K91)*K92)*K93)*K94)*K95) -> 4.6784489 | L89: =(((((L90*L91)*L92)*L93)*L94)*L95) -> 5.1611676 | M89: =(((((M90*M91)*M92)*M93)*M94)*M95) -> 5.6580289 | N89: =(((((N90*N91)*N92)*N93)*N94)*N95) -> 6.1693572 | O89: =(((((O90*O91)*O92)*O93)*O94)*O95) -> 6.695484 | ... AQ89: =(((((AQ90*AQ91)*AQ92)*AQ93)*AQ94)*AQ95) -> 29.018218
F90: Eastern Reachable Pregnancies | H90: =H37 -> 11484.349 | I90: =I37 -> 11510.043 | J90: =J37 -> 11535.794 | K90: =K37 -> 11561.603 | L90: =L37 -> 11587.469 | M90: =M37 -> 11613.394 | N90: =N37 -> 11639.377 | O90: =O37 -> 11665.417 | ... AQ90: =AQ37 -> 12418.693
F91: times Eastern Private Eligibility Rate | H91: =eastern_private_eligibility_rate*(1+eastern_private_eligibility_rate_growth)^((COLUMN()-8)/12) -> 0.018 | I91: =eastern_private_eligibility_rate*(1+eastern_private_eligibility_rate_growth)^((COLUMN()-8)/12) -> 0.018087616 | J91: =eastern_private_eligibility_rate*(1+eastern_private_eligibility_rate_growth)^((COLUMN()-8)/12) -> 0.018175658 | K91: =eastern_private_eligibility_rate*(1+eastern_private_eligibility_rate_growth)^((COLUMN()-8)/12) -> 0.018264129 | L91: =eastern_private_eligibility_rate*(1+eastern_private_eligibility_rate_growth)^((COLUMN()-8)/12) -> 0.018353031 | M91: =eastern_private_eligibility_rate*(1+eastern_private_eligibility_rate_growth)^((COLUMN()-8)/12) -> 0.018442365 | N91: =eastern_private_eligibility_rate*(1+eastern_private_eligibility_rate_growth)^((COLUMN()-8)/12) -> 0.018532134 | O91: =eastern_private_eligibility_rate*(1+eastern_private_eligibility_rate_growth)^((COLUMN()-8)/12) -> 0.01862234 | ... AQ91: =eastern_private_eligibility_rate*(1+eastern_private_eligibility_rate_growth)^((COLUMN()-8)/12) -> 0.021334442
F92: times Eastern Private Provider Recommendation Rate | H92: =eastern_private_provider_recommendation_rate*(1+eastern_private_provider_recommendation_rate_growth)^((COLUMN()-8)/12) -> 0.46 | I92: =eastern_private_provider_recommendation_rate*(1+eastern_private_provider_recommendation_rate_growth)^((COLUMN()-8)/12) -> 0.46150592 | J92: =eastern_private_provider_recommendation_rate*(1+eastern_private_provider_recommendation_rate_growth)^((COLUMN()-8)/12) -> 0.46301677 | K92: =eastern_private_provider_recommendation_rate*(1+eastern_private_provider_recommendation_rate_growth)^((COLUMN()-8)/12) -> 0.46453257 | L92: =eastern_private_provider_recommendation_rate*(1+eastern_private_provider_recommendation_rate_growth)^((COLUMN()-8)/12) -> 0.46605333 | M92: =eastern_private_provider_recommendation_rate*(1+eastern_private_provider_recommendation_rate_growth)^((COLUMN()-8)/12) -> 0.46757906 | N92: =eastern_private_provider_recommendation_rate*(1+eastern_private_provider_recommendation_rate_growth)^((COLUMN()-8)/12) -> 0.4691098 | O92: =eastern_private_provider_recommendation_rate*(1+eastern_private_provider_recommendation_rate_growth)^((COLUMN()-8)/12) -> 0.47064554 | ... AQ92: =eastern_private_provider_recommendation_rate*(1+eastern_private_provider_recommendation_rate_growth)^((COLUMN()-8)/12) -> 0.51574901
F93: times Eastern Private Acceptance Rate | H93: =eastern_private_acceptance_rate*(1+eastern_private_acceptance_rate_growth)^((COLUMN()-8)/12) -> 0.81 | I93: =eastern_private_acceptance_rate*(1+eastern_private_acceptance_rate_growth)^((COLUMN()-8)/12) -> 0.81133778 | J93: =eastern_private_acceptance_rate*(1+eastern_private_acceptance_rate_growth)^((COLUMN()-8)/12) -> 0.81267777 | K93: =eastern_private_acceptance_rate*(1+eastern_private_acceptance_rate_growth)^((COLUMN()-8)/12) -> 0.81401997 | L93: =eastern_private_acceptance_rate*(1+eastern_private_acceptance_rate_growth)^((COLUMN()-8)/12) -> 0.81536439 | M93: =eastern_private_acceptance_rate*(1+eastern_private_acceptance_rate_growth)^((COLUMN()-8)/12) -> 0.81671104 | N93: =eastern_private_acceptance_rate*(1+eastern_private_acceptance_rate_growth)^((COLUMN()-8)/12) -> 0.8180599 | O93: =eastern_private_acceptance_rate*(1+eastern_private_acceptance_rate_growth)^((COLUMN()-8)/12) -> 0.81941099 | ... AQ93: =eastern_private_acceptance_rate*(1+eastern_private_acceptance_rate_growth)^((COLUMN()-8)/12) -> 0.85816116
F94: times Eastern Private Stock Availability Rate | H94: =eastern_private_stock_availability_rate*(1+eastern_private_stock_availability_rate_growth)^((COLUMN()-8)/12) -> 0.86 | I94: =eastern_private_stock_availability_rate*(1+eastern_private_stock_availability_rate_growth)^((COLUMN()-8)/12) -> 0.86106768 | J94: =eastern_private_stock_availability_rate*(1+eastern_private_stock_availability_rate_growth)^((COLUMN()-8)/12) -> 0.86213668 | K94: =eastern_private_stock_availability_rate*(1+eastern_private_stock_availability_rate_growth)^((COLUMN()-8)/12) -> 0.86320702 | L94: =eastern_private_stock_availability_rate*(1+eastern_private_stock_availability_rate_growth)^((COLUMN()-8)/12) -> 0.86427868 | M94: =eastern_private_stock_availability_rate*(1+eastern_private_stock_availability_rate_growth)^((COLUMN()-8)/12) -> 0.86535167 | N94: =eastern_private_stock_availability_rate*(1+eastern_private_stock_availability_rate_growth)^((COLUMN()-8)/12) -> 0.86642599 | O94: =eastern_private_stock_availability_rate*(1+eastern_private_stock_availability_rate_growth)^((COLUMN()-8)/12) -> 0.86750165 | ... AQ94: =eastern_private_stock_availability_rate*(1+eastern_private_stock_availability_rate_growth)^((COLUMN()-8)/12) -> 0.89816834
F95: times Eastern Private Active Coverage State | H95: =0.05 -> 0.05 | I95: =H95+I96-I97 -> 0.055929349 | J95: =I95+J96-J97 -> 0.061888118 | K95: =J95+K96-K97 -> 0.067876381 | L95: =K95+L96-L97 -> 0.073894211 | M95: =L95+M96-M97 -> 0.079941679 | N95: =M95+N96-N97 -> 0.08601886 | O95: =N95+O96-O97 -> 0.092125827 | P95: =O95+P96-P97 -> 0.098262653 | ... AQ95: =AP95+AQ96-AQ97 -> 0.27551711
G96: Eastern Private Coverage Additions | H96: =eastern_private_coverage_additions*(1+eastern_private_coverage_additions_growth)^((COLUMN()-8)/12) -> 0.0119 | I96: =eastern_private_coverage_additions*(1+eastern_private_coverage_additions_growth)^((COLUMN()-8)/12) -> 0.011929349 | J96: =eastern_private_coverage_additions*(1+eastern_private_coverage_additions_growth)^((COLUMN()-8)/12) -> 0.01195877 | K96: =eastern_private_coverage_additions*(1+eastern_private_coverage_additions_growth)^((COLUMN()-8)/12) -> 0.011988263 | L96: =eastern_private_coverage_additions*(1+eastern_private_coverage_additions_growth)^((COLUMN()-8)/12) -> 0.012017829 | M96: =eastern_private_coverage_additions*(1+eastern_private_coverage_additions_growth)^((COLUMN()-8)/12) -> 0.012047469 | N96: =eastern_private_coverage_additions*(1+eastern_private_coverage_additions_growth)^((COLUMN()-8)/12) -> 0.012077181 | O96: =eastern_private_coverage_additions*(1+eastern_private_coverage_additions_growth)^((COLUMN()-8)/12) -> 0.012106967 | ... AQ96: =eastern_private_coverage_additions*(1+eastern_private_coverage_additions_growth)^((COLUMN()-8)/12) -> 0.01297146
G97: plus Eastern Private Coverage Churn | H97: =eastern_private_coverage_churn*(1+eastern_private_coverage_churn_growth)^((COLUMN()-8)/12) -> 0.006 | I97: =eastern_private_coverage_churn*(1+eastern_private_coverage_churn_growth)^((COLUMN()-8)/12) -> 0.006 | J97: =eastern_private_coverage_churn*(1+eastern_private_coverage_churn_growth)^((COLUMN()-8)/12) -> 0.006 | K97: =eastern_private_coverage_churn*(1+eastern_private_coverage_churn_growth)^((COLUMN()-8)/12) -> 0.006 | L97: =eastern_private_coverage_churn*(1+eastern_private_coverage_churn_growth)^((COLUMN()-8)/12) -> 0.006 | M97: =eastern_private_coverage_churn*(1+eastern_private_coverage_churn_growth)^((COLUMN()-8)/12) -> 0.006 | N97: =eastern_private_coverage_churn*(1+eastern_private_coverage_churn_growth)^((COLUMN()-8)/12) -> 0.006 | O97: =eastern_private_coverage_churn*(1+eastern_private_coverage_churn_growth)^((COLUMN()-8)/12) -> 0.006 | ... AQ97: =eastern_private_coverage_churn*(1+eastern_private_coverage_churn_growth)^((COLUMN()-8)/12) -> 0.006
E98: times Eastern Private Net Realised Price Per Dose | H98: =eastern_private_net_price_per_dose*(1+eastern_private_net_price_per_dose_growth)^((COLUMN()-8)/12) -> 88000 | I98: =eastern_private_net_price_per_dose*(1+eastern_private_net_price_per_dose_growth)^((COLUMN()-8)/12) -> 88252.639 | J98: =eastern_private_net_price_per_dose*(1+eastern_private_net_price_per_dose_growth)^((COLUMN()-8)/12) -> 88506.003 | K98: =eastern_private_net_price_per_dose*(1+eastern_private_net_price_per_dose_growth)^((COLUMN()-8)/12) -> 88760.095 | L98: =eastern_private_net_price_per_dose*(1+eastern_private_net_price_per_dose_growth)^((COLUMN()-8)/12) -> 89014.916 | M98: =eastern_private_net_price_per_dose*(1+eastern_private_net_price_per_dose_growth)^((COLUMN()-8)/12) -> 89270.469 | N98: =eastern_private_net_price_per_dose*(1+eastern_private_net_price_per_dose_growth)^((COLUMN()-8)/12) -> 89526.756 | O98: =eastern_private_net_price_per_dose*(1+eastern_private_net_price_per_dose_growth)^((COLUMN()-8)/12) -> 89783.778 | ... AQ98: =eastern_private_net_price_per_dose*(1+eastern_private_net_price_per_dose_growth)^((COLUMN()-8)/12) -> 97287.869
D99: plus Northern Private Revenue | H99: =(H100*H109) -> 80312.855 | I99: =(I100*I109) -> 87123.744 | J99: =(J100*J109) -> 94173.096 | K99: =(K100*K109) -> 101467.58 | L99: =(L100*L109) -> 109014.04 | M99: =(M100*M109) -> 116819.47 | N99: =(N100*N109) -> 124891.07 | O99: =(O100*O109) -> 133236.19 | ... AQ99: =(AQ100*AQ109) -> 514425.41
E100: Northern Private Administered Doses | H100: =(((((H101*H102)*H103)*H104)*H105)*H106) -> 1.0567481 | I100: =(((((I101*I102)*I103)*I104)*I105)*I106) -> 1.1430834 | J100: =(((((J101*J102)*J103)*J104)*J105)*J106) -> 1.2320354 | K100: =(((((K101*K102)*K103)*K104)*K105)*K106) -> 1.3236667 | L100: =(((((L101*L102)*L103)*L104)*L105)*L106) -> 1.4180408 | M100: =(((((M101*M102)*M103)*M104)*M105)*M106) -> 1.5152228 | N100: =(((((N101*N102)*N103)*N104)*N105)*N106) -> 1.6152793 | O100: =(((((O101*O102)*O103)*O104)*O105)*O106) -> 1.7182779 | ... AQ100: =(((((AQ101*AQ102)*AQ103)*AQ104)*AQ105)*AQ106) -> 6.1225565
...

Sheet Graphs
A1: Uganda RSV Market Entry Dashboard [CODEX]
A2: Scenario workbook copy with high-signal monthly curves for demo use
A4: KPI | B4: Base | C4: Positive | D4: Comment
A5: Month 1 Net Profit | B5: ='Model - Base'!H2 -> -1.189574e+08 | C5: ='Model - Positive'!H2 -> -92794715 | D5: Initial monthly profitability
A6: Month 12 Net Profit | B6: ='Model - Base'!S2 -> -1.0114337e+08 | C6: ='Model - Positive'!S2 -> -28568599 | D6: End of Year 1 run-rate
A7: Month 24 Net Profit | B7: ='Model - Base'!AE2 -> -71131760 | C7: ='Model - Positive'!AE2 -> 81823815 | D7: End of Year 2 run-rate
A8: Month 36 Net Profit | B8: ='Model - Base'!AQ2 -> -26265851 | C8: ='Model - Positive'!AQ2 -> 2.5207607e+08 | D8: End of plan run-rate
A11: Month | B11: Base Revenue | C11: Base Total Costs | D11: Base Net Profit | E11: Base Cumulative Profit | F11: Positive Revenue | G11: Positive Total Costs | H11: Positive Net Profit | I11: Positive Cumulative Profit
A12: Month 1 | B12: ='Model - Base'!H3 -> 16088066 | C12: ='Model - Base'!H110 -> 1.3504547e+08 | D12: ='Model - Base'!H2 -> -1.189574e+08 | E12: =D12 -> -1.189574e+08 | F12: ='Model - Positive'!H3 -> 26728497 | G12: ='Model - Positive'!H110 -> 1.1952321e+08 | H12: ='Model - Positive'!H2 -> -92794715 | I12: =H12 -> -92794715
A13: Month 2 | B13: ='Model - Base'!I3 -> 20075532 | C13: ='Model - Base'!I110 -> 1.3772848e+08 | D13: ='Model - Base'!I2 -> -1.1765295e+08 | E13: =E12+D13 -> -2.3661035e+08 | F13: ='Model - Positive'!I3 -> 36784643 | G13: ='Model - Positive'!I110 -> 1.2489686e+08 | H13: ='Model - Positive'!I2 -> -88112219 | I13: =I12+H13 -> -1.8090693e+08
A14: Month 3 | B14: ='Model - Base'!J3 -> 24206013 | C14: ='Model - Base'!J110 -> 1.4049644e+08 | D14: ='Model - Base'!J2 -> -1.1629043e+08 | E14: =E13+D14 -> -3.5290078e+08 | F14: ='Model - Positive'!J3 -> 47272383 | G14: ='Model - Positive'!J110 -> 1.3049229e+08 | H14: ='Model - Positive'!J2 -> -83219907 | I14: =I13+H14 -> -2.6412684e+08
A15: Month 4 | B15: ='Model - Base'!K3 -> 28483455 | C15: ='Model - Base'!K110 -> 1.4335172e+08 | D15: ='Model - Base'!K2 -> -1.1486827e+08 | E15: =E14+D15 -> -4.6776905e+08 | F15: ='Model - Positive'!K3 -> 58205907 | G15: ='Model - Positive'!K110 -> 1.3631694e+08 | H15: ='Model - Positive'!K2 -> -78111037 | I15: =I14+H15 -> -3.4223788e+08
A16: Month 5 | B16: ='Model - Base'!L3 -> 32911903 | C16: ='Model - Base'!L110 -> 1.4629677e+08 | D16: ='Model - Base'!L2 -> -1.1338486e+08 | E16: =E15+D16 -> -5.8115391e+08 | F16: ='Model - Positive'!L3 -> 69599826 | G16: ='Model - Positive'!L110 -> 1.423785e+08 | H16: ='Model - Positive'!L2 -> -72778670 | I16: =I15+H16 -> -4.1501655e+08
A17: Month 6 | B17: ='Model - Base'!M3 -> 37495503 | C17: ='Model - Base'!M110 -> 1.4933408e+08 | D17: ='Model - Base'!M2 -> -1.1183857e+08 | E17: =E16+D17 -> -6.9299248e+08 | F17: ='Model - Positive'!M3 -> 81469177 | G17: ='Model - Positive'!M110 -> 1.4868485e+08 | H17: ='Model - Positive'!M2 -> -67215672 | I17: =I16+H17 -> -4.8223222e+08
A18: Month 7 | B18: ='Model - Base'!N3 -> 42238502 | C18: ='Model - Base'!N110 -> 1.5246622e+08 | D18: ='Model - Base'!N2 -> -1.1022772e+08 | E18: =E17+D18 -> -8.032202e+08 | F18: ='Model - Positive'!N3 -> 93829439 | G18: ='Model - Positive'!N110 -> 1.5524414e+08 | H18: ='Model - Positive'!N2 -> -61414705 | I18: =I17+H18 -> -5.4364693e+08
A19: Month 8 | B19: ='Model - Base'!O3 -> 47145251 | C19: ='Model - Base'!O110 -> 1.5569583e+08 | D19: ='Model - Base'!O2 -> -1.0855058e+08 | E19: =E18+D19 -> -9.1177078e+08 | F19: ='Model - Positive'!O3 -> 1.0669655e+08 | G19: ='Model - Positive'!O110 -> 1.6206477e+08 | H19: ='Model - Positive'!O2 -> -55368223 | I19: =I18+H19 -> -5.9901515e+08
A20: Month 9 | B20: ='Model - Base'!P3 -> 52220209 | C20: ='Model - Base'!P110 -> 1.5902561e+08 | D20: ='Model - Base'!P2 -> -1.068054e+08 | E20: =E19+D20 -> -1.0185762e+09 | F20: ='Model - Positive'!P3 -> 1.200869e+08 | G20: ='Model - Positive'!P110 -> 1.6915536e+08 | H20: ='Model - Positive'!P2 -> -49068465 | I20: =I19+H20 -> -6.4808361e+08
A21: Month 10 | B21: ='Model - Base'!Q3 -> 57467943 | C21: ='Model - Base'!Q110 -> 1.6245832e+08 | D21: ='Model - Base'!Q2 -> -1.0499037e+08 | E21: =E20+D21 -> -1.1235666e+09 | F21: ='Model - Positive'!Q3 -> 1.3401736e+08 | G21: ='Model - Positive'!Q110 -> 1.7652481e+08 | H21: ='Model - Positive'!Q2 -> -42507451 | I21: =I20+H21 -> -6.9059106e+08
A22: Month 11 | B22: ='Model - Base'!R3 -> 62893133 | C22: ='Model - Base'!R110 -> 1.6599679e+08 | D22: ='Model - Base'!R2 -> -1.0310366e+08 | E22: =E21+D22 -> -1.2266702e+09 | F22: ='Model - Positive'!R3 -> 1.4850532e+08 | G22: ='Model - Positive'!R110 -> 1.8418229e+08 | H22: ='Model - Positive'!R2 -> -35676974 | I22: =I21+H22 -> -7.2626804e+08
A23: Month 12 | B23: ='Model - Base'!S3 -> 68500574 | C23: ='Model - Base'!S110 -> 1.6964395e+08 | D23: ='Model - Base'!S2 -> -1.0114337e+08 | E23: =E22+D23 -> -1.3278136e+09 | F23: ='Model - Positive'!S3 -> 1.6356864e+08 | G23: ='Model - Positive'!S110 -> 1.9213724e+08 | H23: ='Model - Positive'!S2 -> -28568599 | I23: =I22+H23 -> -7.5483664e+08
A24: Month 13 | B24: ='Model - Base'!T3 -> 74295178 | C24: ='Model - Base'!T110 -> 1.7340276e+08 | D24: ='Model - Base'!T2 -> -99107585 | E24: =E23+D24 -> -1.4269212e+09 | F24: ='Model - Positive'!T3 -> 1.7922571e+08 | G24: ='Model - Positive'!T110 -> 2.0039936e+08 | H24: ='Model - Positive'!T2 -> -21173648 | I24: =I23+H24 -> -7.7601028e+08
A25: Month 14 | B25: ='Model - Base'!U3 -> 80281974 | C25: ='Model - Base'!U110 -> 1.7727629e+08 | D25: ='Model - Base'!U2 -> -96994317 | E25: =E24+D25 -> -1.5239155e+09 | F25: ='Model - Positive'!U3 -> 1.9549546e+08 | G25: ='Model - Positive'!U110 -> 2.0897867e+08 | H25: ='Model - Positive'!U2 -> -13483203 | I25: =I24+H25 -> -7.8949349e+08
A26: Month 15 | B26: ='Model - Base'!V3 -> 86466119 | C26: ='Model - Base'!V110 -> 1.8126767e+08 | D26: ='Model - Base'!V2 -> -94801551 | E26: =E25+D26 -> -1.618717e+09 | F26: ='Model - Positive'!V3 -> 2.1239737e+08 | G26: ='Model - Positive'!V110 -> 2.1788547e+08 | H26: ='Model - Positive'!V2 -> -5488093.4 | I26: =I25+H26 -> -7.9498158e+08
A27: Month 16 | B27: ='Model - Base'!W3 -> 92852891 | C27: ='Model - Base'!W110 -> 1.8538011e+08 | D27: ='Model - Base'!W2 -> -92527219 | E27: =E26+D27 -> -1.7112443e+09 | F27: ='Model - Positive'!W3 -> 2.2995148e+08 | G27: ='Model - Positive'!W110 -> 2.2713037e+08 | H27: ='Model - Positive'!W2 -> 2821108.6 | I27: =I26+H27 -> -7.9216047e+08
A28: Month 17 | B28: ='Model - Base'!X3 -> 99447698 | C28: ='Model - Base'!X110 -> 1.896169e+08 | D28: ='Model - Base'!X2 -> -90169205 | E28: =E27+D28 -> -1.8014135e+09 | F28: ='Model - Positive'!X3 -> 2.4817839e+08 | G28: ='Model - Positive'!X110 -> 2.3672429e+08 | H28: ='Model - Positive'!X2 -> 11454094 | I28: =I27+H28 -> -7.8070638e+08
A29: Month 18 | B29: ='Model - Base'!Y3 -> 1.0625608e+08 | C29: ='Model - Base'!Y110 -> 1.9398142e+08 | D29: ='Model - Base'!Y2 -> -87725345 | E29: =E28+D29 -> -1.8891388e+09 | F29: ='Model - Positive'!Y3 -> 2.6709932e+08 | G29: ='Model - Positive'!Y110 -> 2.4667849e+08 | H29: ='Model - Positive'!Y2 -> 20420827 | I29: =I28+H29 -> -7.6028555e+08
A30: Month 19 | B30: ='Model - Base'!Z3 -> 1.1328371e+08 | C30: ='Model - Base'!Z110 -> 1.9847713e+08 | D30: ='Model - Base'!Z2 -> -85193424 | E30: =E29+D30 -> -1.9743322e+09 | F30: ='Model - Positive'!Z3 -> 2.8673609e+08 | G30: ='Model - Positive'!Z110 -> 2.5700455e+08 | H30: ='Model - Positive'!Z2 -> 29731547 | I30: =I29+H30 -> -7.30554e+08
A31: Month 20 | B31: ='Model - Base'!AA3 -> 1.205364e+08 | C31: ='Model - Base'!AA110 -> 2.0310757e+08 | D31: ='Model - Base'!AA2 -> -82571177 | E31: =E30+D31 -> -2.0569034e+09 | F31: ='Model - Positive'!AA3 -> 3.0711116e+08 | G31: ='Model - Positive'!AA110 -> 2.6771438e+08 | H31: ='Model - Positive'!AA2 -> 39396781 | I31: =I30+H31 -> -6.9115722e+08
A32: Month 21 | B32: ='Model - Base'!AB3 -> 1.280201e+08 | C32: ='Model - Base'!AB110 -> 2.0787638e+08 | D32: ='Model - Base'!AB2 -> -79856285 | E32: =E31+D32 -> -2.1367597e+09 | F32: ='Model - Positive'!AB3 -> 3.282476e+08 | G32: ='Model - Positive'!AB110 -> 2.7882025e+08 | H32: ='Model - Positive'!AB2 -> 49427349 | I32: =I31+H32 -> -6.4172987e+08
A33: Month 22 | B33: ='Model - Base'!AC3 -> 1.357409e+08 | C33: ='Model - Base'!AC110 -> 2.1278728e+08 | D33: ='Model - Base'!AC2 -> -77046378 | E33: =E32+D33 -> -2.2138061e+09 | F33: ='Model - Positive'!AC3 -> 3.5016918e+08 | G33: ='Model - Positive'!AC110 -> 2.9033481e+08 | H33: ='Model - Positive'!AC2 -> 59834371 | I33: =I32+H33 -> -5.818955e+08
A34: Month 23 | B34: ='Model - Base'!AD3 -> 1.4370506e+08 | C34: ='Model - Base'!AD110 -> 2.1784409e+08 | D34: ='Model - Base'!AD2 -> -74139030 | E34: =E33+D34 -> -2.2879451e+09 | F34: ='Model - Positive'!AD3 -> 3.7290034e+08 | G34: ='Model - Positive'!AD110 -> 3.0227106e+08 | H34: ='Model - Positive'!AD2 -> 70629278 | I34: =I33+H34 -> -5.1126623e+08
A35: Month 24 | B35: ='Model - Base'!AE3 -> 1.5191896e+08 | C35: ='Model - Base'!AE110 -> 2.2305072e+08 | D35: ='Model - Base'!AE2 -> -71131760 | E35: =E34+D35 -> -2.3590769e+09 | F35: ='Model - Positive'!AE3 -> 3.964662e+08 | G35: ='Model - Positive'!AE110 -> 3.1464239e+08 | H35: ='Model - Positive'!AE2 -> 81823815 | I35: =I34+H35 -> -4.2944241e+08
A36: Month 25 | B36: ='Model - Base'!AF3 -> 1.6038914e+08 | C36: ='Model - Base'!AF110 -> 2.2841117e+08 | D36: ='Model - Base'!AF2 -> -68022029 | E36: =E35+D36 -> -2.4270989e+09 | F36: ='Model - Positive'!AF3 -> 4.2089262e+08 | G36: ='Model - Positive'!AF110 -> 3.2746257e+08 | H36: ='Model - Positive'!AF2 -> 93430055 | I36: =I35+H36 -> -3.3601236e+08
A37: Month 26 | B37: ='Model - Base'!AG3 -> 1.6912232e+08 | C37: ='Model - Base'!AG110 -> 2.3392956e+08 | D37: ='Model - Base'!AG2 -> -64807241 | E37: =E36+D37 -> -2.4919061e+09 | F37: ='Model - Positive'!AG3 -> 4.4620619e+08 | G37: ='Model - Positive'!AG110 -> 3.4074579e+08 | H37: ='Model - Positive'!AG2 -> 1.054604e+08 | I37: =I36+H37 -> -2.3055195e+08
A38: Month 27 | B38: ='Model - Base'!AH3 -> 1.7812536e+08 | C38: ='Model - Base'!AH110 -> 2.396101e+08 | D38: ='Model - Base'!AH2 -> -61484740 | E38: =E37+D38 -> -2.5533909e+09 | F38: ='Model - Positive'!AH3 -> 4.7243425e+08 | G38: ='Model - Positive'!AH110 -> 3.5450664e+08 | H38: ='Model - Positive'!AH2 -> 1.1792761e+08 | I38: =I37+H38 -> -1.1262434e+08
A39: Month 28 | B39: ='Model - Base'!AI3 -> 1.8740529e+08 | C39: ='Model - Base'!AI110 -> 2.4545709e+08 | D39: ='Model - Base'!AI2 -> -58051809 | E39: =E38+D39 -> -2.6114427e+09 | F39: ='Model - Positive'!AI3 -> 4.9960492e+08 | G39: ='Model - Positive'!AI110 -> 3.6876015e+08 | H39: ='Model - Positive'!AI2 -> 1.3084477e+08 | I39: =I38+H39 -> 18220426
