Workbook

Sheet Monthly Headcount
B1: Group Headcount Report 2025
C2: Group | E2: Uganda | G2: APDL | I2: Tanzania | K2: Rwanda | M2: Burundi | O2: Kenya
C3: Number | D3: % | E3: Number | F3: % | G3: Number | H3: % | I3: Number | J3: % | K3: Number | L3: % | M3: Number | N3: % | O3: Number | P3: %
B4: Headcount December FY24 | C4: =SUM(E4,G4,I4,K4,M4,O4) -> 1173 | E4: 601 | G4: 219 | I4: 223 | K4: 36 | M4: 59 | O4: 35
A5: Monthly Headcount Growth (Direct staff) | C5: =SUM(E5,G5,I5,K5,M5,O5) -> 23 | D5: =C5/C4 -> 0.019607843 | E5: =E8-E4 -> 11 | F5: =E5/E4 -> 0.018302829 | G5: =G8-G4 -> 7 | H5: =G5/G4 -> 0.03196347 | I5: =I8-I4 -> 0 | J5: =I5/I4 -> 0 | K5: =K8-K4 -> 4 | L5: =K5/K4 -> 0.11111111 | M5: =M8-M4 -> 2 | N5: =M5/M4 -> 0.033898305 | O5: =O8-O4 -> -1 | P5: =O5/O4 -> -0.028571429
A7: 45658 | B7: Overall Headcount | C7: =SUM(E7,G7,I7,K7,M7,O7) -> 2151 | D7: =SUM(F7,H7,J7,L7,N7,P7) -> 1 | E7: =SUM(E8,E30,E33) -> 1004 | F7: =E7/C$7 -> 0.46675965 | G7: =SUM(G8,G30,G33) -> 716 | H7: =G7/C$7 -> 0.33286843 | I7: =SUM(I8,I30,I33) -> 243 | J7: =I7/C$7 -> 0.11297071 | K7: =SUM(K8,K30,K33) -> 77 | L7: =K7/C$7 -> 0.035797304 | M7: =SUM(M8,M30,M33) -> 67 | N7: =M7/C$7 -> 0.031148303 | O7: =SUM(O8,O30,O33) -> 44 | P7: =O7/C$7 -> 0.020455602
B8: Direct Staff | C8: =SUM(E8,G8,I8,K8,M8,O8) -> 1196 | D8: =C8/C7 -> 0.55602046 | E8: =E9+E10 -> 612 | F8: =E8/C8 -> 0.51170569 | G8: =G9+G10 -> 226 | H8: =G8/C8 -> 0.18896321 | I8: =I9+I10 -> 223 | J8: =I8/C8 -> 0.18645485 | K8: =K9+K10 -> 40 | L8: =K8/C8 -> 0.033444816 | M8: =M9+M10 -> 61 | N8: =M8/C8 -> 0.051003344 | O8: =O9+O10 -> 34 | P8: =O8/C8 -> 0.028428094
B9: Female | C9: =SUM(E9,G9,I9,K9,M9,O9) -> 307 | D9: =C9/C8 -> 0.25668896 | E9: 146 | F9: =E9/E8 -> 0.23856209 | G9: 45 | H9: =G9/G8 -> 0.19911504 | I9: 66 | J9: =I9/I8 -> 0.29596413 | K9: 15 | L9: =K9/K8 -> 0.375 | M9: 18 | N9: =M9/M8 -> 0.29508197 | O9: 17 | P9: =O9/O8 -> 0.5
B10: Male | C10: =SUM(E10,G10,I10,K10,M10,O10) -> 889 | D10: =C10/C8 -> 0.74331104 | E10: 466 | F10: =E11/E8 -> 0.86437908 | G10: 181 | H10: =G10/G8 -> 0.80088496 | I10: 157 | J10: =I10/I8 -> 0.70403587 | K10: 25 | L10: =K10/K8 -> 0.625 | M10: 43 | N10: =M10/M8 -> 0.70491803 | O10: 17 | P10: =O10/O8 -> 0.5
B11: Nationals | C11: =SUM(E11,G11,I11,K11,M11,O11) -> 1077 | D11: =C11/C8 -> 0.90050167 | E11: 529 | F11: =E11/E8 -> 0.86437908 | G11: 214 | H11: =G11/G8 -> 0.94690265 | I11: 209 | J11: =I11/I8 -> 0.93721973 | K11: 36 | L11: =K11/K8 -> 0.9 | M11: 56 | N11: =M11/M8 -> 0.91803279 | O11: 33 | P11: =O11/O8 -> 0.97058824
B12: Expatriates | C12: =SUM(E12,G12,I12,K12,M12,O12) -> 119 | D12: =C12/C8 -> 0.099498328 | E12: 83 | F12: =E12/E8 -> 0.13562092 | G12: 12 | H12: =G12/G8 -> 0.053097345 | I12: 14 | J12: =I12/I8 -> 0.062780269 | K12: 4 | L12: =K12/K8 -> 0.1 | M12: 5 | N12: =M12/M8 -> 0.081967213 | O12: 1 | P12: =O12/O8 -> 0.029411765
B13: Management | C13: =SUM(E13,G13,I13,K13,M13,O13) -> 267 | D13: =C13/C8 -> 0.22324415 | E13: 127 | F13: =E13/E8 -> 0.20751634 | G13: 65 | H13: =G13/G8 -> 0.28761062 | I13: 40 | J13: =I13/I8 -> 0.1793722 | K13: 11 | L13: =K13/K8 -> 0.275 | M13: 17 | N13: =M13/M8 -> 0.27868852 | O13: 7 | P13: =O13/O8 -> 0.20588235
B14: Female in Management | C14: =SUM(E14,G14,I14,K14,M14,O14) -> 45 | D14: =C14/C13 -> 0.16853933 | E14: 18 | F14: =E14/E13 -> 0.14173228 | G14: 10 | H14: =G14/G13 -> 0.15384615 | I14: 8 | J14: =I14/I13 -> 0.2 | K14: 3 | L14: =K14/K13 -> 0.27272727 | M14: 4 | N14: =M14/M13 -> 0.23529412 | O14: 2 | P14: =O14/O13 -> 0.28571429
B15: Below 40 years of age | C15: =SUM(E15,G15,I15,K15,M15,O15) -> 948 | D15: =C15/C8 -> 0.79264214 | E15: 469 | F15: =E15/E8 -> 0.76633987 | G15: 187 | H15: =G15/G8 -> 0.82743363 | I15: 182 | J15: =I15/I8 -> 0.8161435 | K15: 34 | L15: =K15/K8 -> 0.85 | M15: 50 | N15: =M15/M8 -> 0.81967213 | O15: 26 | P15: =O15/O8 -> 0.76470588
B16: Atleast 40 years of age | C16: =SUM(E16,G16,I16,K16,M16,O16) -> 248 | D16: =C16/C8 -> 0.20735786 | E16: 143 | F16: =E16/E8 -> 0.23366013 | G16: 39 | H16: =G16/G8 -> 0.17256637 | I16: 41 | J16: =I16/I8 -> 0.1838565 | K16: 6 | L16: =K16/K8 -> 0.15 | M16: 11 | N16: =M16/M8 -> 0.18032787 | O16: 8 | P16: =O16/O8 -> 0.23529412
B17: Less than 5 years with Abacus | C17: =SUM(E17,G17,I17,K17,M17,O17) -> 678 | D17: =C17/C8 -> 0.56688963 | E17: 361 | F17: =E17/E8 -> 0.58986928 | G17: 91 | H17: =G17/G8 -> 0.40265487 | I17: 140 | J17: =I17/I8 -> 0.62780269 | K17: 30 | L17: =K17/K8 -> 0.75 | M17: 31 | N17: =M17/M8 -> 0.50819672 | O17: 25 | P17: =O17/O8 -> 0.73529412
B18: Atleast 5 years with Abacus | C18: =SUM(E18,G18,I18,K18,M18,O18) -> 518 | D18: =C18/C8 -> 0.43311037 | E18: 251 | F18: =E18/E8 -> 0.41013072 | G18: 135 | H18: =G18/G8 -> 0.59734513 | I18: 83 | J18: =I18/I8 -> 0.37219731 | K18: 10 | L18: =K18/K8 -> 0.25 | M18: =M8-M17 -> 30 | N18: =M18/M8 -> 0.49180328 | O18: 9 | P18: =O18/O8 -> 0.26470588
B19: Total New hires | C19: =SUM(E19,G19,I19,K19,M19,O19) -> 27 | D19: =SUM(D20:D22) -> 1 | E19: =SUM(E20:E22) -> 4 | F19: =SUM(F20:F22) -> 1 | G19: =SUM(G20:G22) -> 3 | H19: =SUM(H20:H22) -> 1 | I19: =SUM(I20:I22) -> 14 | J19: =SUM(J20:J22) -> 1 | K19: =SUM(K20:K22) -> 1 | ... P19: =SUM(P20:P22) -> 1
B20: New hires at EXCO | C20: =SUM(E20,G20,I20,K20,M20,O20) -> 0 | D20: =C20/C19 -> 0 | E20: 0 | F20: =E20/E19 -> 0 | G20: 0 | H20: 0 | I20: 0 | J20: 0 | K20: 0 | L20: 0 | M20: 0 | N20: 0 | O20: 0 | P20: 0
B21: New hires at EXCO - 1&2 | C21: =SUM(E21,G21,I21,K21,M21,O21) -> 1 | D21: =C21/C19 -> 0.037037037 | E21: 0 | F21: =E21/E19 -> 0 | G21: 0 | H21: =G21/G19 -> 0 | I21: 0 | J21: =I21/I19 -> 0 | K21: 1 | L21: - | M21: 0 | N21: =M21/M19 -> 0 | O21: 0 | P21: =O21/O19 -> 0
B22: New hires at Other Levels | C22: =SUM(E22,G22,I22,K22,M22,O22) -> 26 | D22: =C22/C19 -> 0.96296296 | E22: 4 | F22: =E22/E19 -> 1 | G22: 3 | H22: =G22/G19 -> 1 | I22: 14 | J22: =I22/I19 -> 1 | K22: 0 | L22: =K22/K19 -> 0 | M22: 1 | N22: =M22/M19 -> 1 | O22: 4 | P22: =O22/O19 -> 1
B23: Total Exits | C23: =SUM(E23,G23,I23,K23,M23,O23) -> 14 | D23: =SUM(D24:D26) -> 0.011705686 | E23: =SUM(E24:E26) -> 6 | F23: =SUM(F24:F26) -> 0.0098039216 | G23: =SUM(G24:G26) -> 1 | H23: =SUM(H24:H26) -> 0.0044247788 | I23: =SUM(I24:I26) -> 4 | J23: =SUM(J24:J26) -> 0.01793722 | K23: =SUM(K24:K26) -> 1 | ... P23: =SUM(P24:P26) -> 0.029411765
B24: Exits at EXCO | C24: =SUM(E24,G24,I24,K24,M24,O24) -> 0 | D24: =C24/$C$8 -> 0 | E24: 0 | F24: =E24/$E$8 -> 0 | G24: 0 | H24: =G24/$G$8 -> 0 | I24: 0 | J24: =I24/$I$8 -> 0 | K24: 0 | L24: =K24/$K$8 -> 0 | M24: 0 | N24: =M24/$M$8 -> 0 | O24: 0 | P24: =O24/$O$8 -> 0
B25: Exits at EXCO - 1&2 | C25: =SUM(E25,G25,I25,K25,M25,O25) -> 1 | D25: =C25/$C$8 -> 0.0008361204 | E25: 1 | F25: =E25/$E$8 -> 0.0016339869 | G25: 0 | H25: =G25/$G$8 -> 0 | I25: 0 | J25: =I25/$I$8 -> 0 | K25: 0 | L25: =K25/$K$8 -> 0 | M25: 0 | N25: =M25/$M$8 -> 0 | O25: 0 | P25: =O25/$O$8 -> 0
B26: Exits at Other Levels | C26: =SUM(E26,G26,I26,K26,M26,O26) -> 13 | D26: =C26/$C$8 -> 0.010869565 | E26: 5 | F26: =E26/$E$8 -> 0.0081699346 | G26: 1 | H26: =G26/$G$8 -> 0.0044247788 | I26: 4 | J26: =I26/$I$8 -> 0.01793722 | K26: 1 | L26: =K26/$K$8 -> 0.025 | M26: 1 | N26: =M26/$M$8 -> 0.016393443 | O26: 1 | P26: =O26/$O$8 -> 0.029411765
B27: Total Internal Movements | C27: =SUM(E27,G27,I27,K27,M27,O27) -> 29 | E27: =SUM(E28:E29) -> 16 | F27: =SUM(F28:F29) -> 0 | G27: =SUM(G28:G29) -> 1 | H27: =SUM(H28:H29) -> 0 | I27: =SUM(I28:I29) -> 7 | J27: =SUM(J28:J29) -> 0 | K27: =SUM(K28:K29) -> 0 | L27: =SUM(L28:L29) -> 0 | ... P27: =SUM(P28:P29) -> 0
B28: Promotions | C28: =SUM(E28,G28,I28,K28,M28,O28) -> 28 | E28: 15 | G28: 1 | I28: 7 | K28: 0 | M28: 3 | O28: 2
B29: Transfers | C29: =SUM(E29,G29,I29,K29,M29,O29) -> 1 | E29: 1 | G29: 0 | I29: 0 | K29: 0 | M29: 0 | O29: 0
B30: Principals | C30: =SUM(E30,G30,I30,K30,M30,O30) -> 413 | D30: =C30/C7 -> 0.19200372 | E30: =E31+E32 -> 340 | F30: =E30/C30 -> 0.82324455 | G30: =G31+G32 -> 0 | H30: =G30/C30 -> 0 | I30: =I31+I32 -> 20 | J30: =I30/C30 -> 0.04842615 | K30: =K31+K32 -> 37 | L30: =K30/E30 -> 0.10882353 | M30: =M31+M32 -> 6 | N30: =M30/C30 -> 0.014527845 | O30: =O31+O32 -> 10 | P30: =O30/C30 -> 0.024213075
B31: Female | C31: =SUM(E31,G31,I31,K31,M31,O31) -> 122 | D31: =C31/C30 -> 0.29539952 | E31: 97 | F31: =E31/E30 -> 0.28529412 | G31: 0 | H31: 0 | I31: 6 | J31: =I31/I30 -> 0.3 | K31: 15 | L31: =K31/K30 -> 0.40540541 | M31: 1 | N31: =M31/M30 -> 0.16666667 | O31: 3 | P31: 0
B32: Male | C32: =SUM(E32,G32,I32,K32,M32,O32) -> 291 | D32: =C32/C30 -> 0.70460048 | E32: 243 | F32: =E32/E30 -> 0.71470588 | G32: 0 | H32: 0 | I32: 14 | J32: =I32/I30 -> 0.7 | K32: 22 | L32: =K32/K30 -> 0.59459459 | M32: 5 | N32: =M32/M30 -> 0.83333333 | O32: 7 | P32: 0
B33: Casuals/Contractors | C33: =SUM(E33,G33,I33,K33,M33,O33) -> 542 | D33: =C33/C7 -> 0.25197583 | E33: =E34+E35 -> 52 | F33: =E33/C33 -> 0.095940959 | G33: =G34+G35 -> 490 | H33: =G33/C33 -> 0.90405904 | I33: =I34+I35 -> 0 | J33: 0 | K33: =K34+K35 -> 0 | L33: =K33/C33 -> 0 | M33: =M34+M35 -> 0 | N33: 0 | O33: =O34+O35 -> 0 | P33: 0
B34: Female | C34: =SUM(E34,G34,I34,K34,M34,O34) -> 258 | D34: =C34/C33 -> 0.47601476 | E34: 6 | F34: =E34/E33 -> 0.11538462 | G34: 252 | H34: =G34/G33 -> 0.51428571 | I34: 0 | J34: 0 | K34: 0 | L34: 0 | M34: 0 | N34: 0 | O34: 0 | P34: 0
B35: Male | C35: =SUM(E35,G35,I35,K35,M35,O35) -> 284 | D35: =C35/C33 -> 0.52398524 | E35: 46 | F35: =E35/E33 -> 0.88461538 | G35: 238 | H35: =G35/G33 -> 0.48571429 | I35: 0 | J35: 0 | K35: 0 | L35: 0 | M35: 0 | N35: 0 | O35: 0 | P35: 0
A37: Monthly Headcount Growth (Direct staff) | C37: =C39-C8 -> 12 | D37: =C37/C8 -> 0.010033445 | E37: =E39-E8 -> 9 | F37: =E37/E8 -> 0.014705882 | G37: =G39-G8 -> 1 | H37: =G37/G8 -> 0.0044247788 | I37: =I39-I8 -> 3 | J37: =I37/I8 -> 0.013452915 | K37: =K39-K8 -> 0 | L37: =K37/K8 -> 0 | M37: =M39-M8 -> -1 | N37: =M37/M8 -> -0.016393443 | O37: =O39-O8 -> 0 | P37: =O37/O8 -> 0
A38: 45689 | B38: Overall Headcount | C38: =SUM(E38,G38,I38,K38,M38,O38) -> 2133 | D38: =SUM(F38,H38,J38,L38,N38,P38) -> 0.9998313 | E38: =SUM(E39,E61,E64) -> 997 | F38: =E38/C38 -> 0.46741678 | G38: =SUM(G39,G61,G64) -> 703 | H38: =G38/C38 -> 0.32958275 | I38: =SUM(I39,I61,I64) -> 248 | J38: =I38/C38 -> 0.11626817 | K38: =SUM(K39,K61,K64) -> 76 | L38: =K38/C38 -> 0.035630567 | M38: =SUM(M39,M61,M64) -> 66 | N38: =M38/C38 -> 0.030942335 | O38: =SUM(O39,O61,O64) -> 43 | P38: =O38/C$7 -> 0.019990702
B39: Direct Staff | C39: =SUM(E39,G39,I39,K39,M39,O39) -> 1208 | D39: =C39/C38 -> 0.56633849 | E39: =E40+E41 -> 621 | F39: =E39/E38 -> 0.62286861 | G39: =G40+G41 -> 227 | H39: =G39/C39 -> 0.18791391 | I39: =I40+I41 -> 226 | J39: =I39/C39 -> 0.18708609 | K39: =K40+K41 -> 40 | L39: =K39/C39 -> 0.033112583 | M39: =M40+M41 -> 60 | N39: =M39/C39 -> 0.049668874 | O39: =O40+O41 -> 34 | P39: =O39/C39 -> 0.028145695
B40: Female | C40: =SUM(E40,G40,I40,K40,M40,O40) -> 310 | D40: =C40/C39 -> 0.25662252 | E40: 147 | F40: =E40/$E$39 -> 0.23671498 | G40: 45 | H40: =G40/G39 -> 0.19823789 | I40: 68 | J40: =I40/I39 -> 0.30088496 | K40: 14 | L40: =K40/K39 -> 0.35 | M40: 18 | N40: =M40/M39 -> 0.3 | O40: 18 | P40: =O40/O39 -> 0.52941176
B41: Male | C41: =SUM(E41,G41,I41,K41,M41,O41) -> 898 | D41: =C41/C39 -> 0.74337748 | E41: 474 | F41: =E41/$E$39 -> 0.76328502 | G41: 182 | H41: =G41/G39 -> 0.80176211 | I41: 158 | J41: =I41/I39 -> 0.69911504 | K41: 26 | L41: =K41/K39 -> 0.65 | M41: 42 | N41: =M41/M39 -> 0.7 | O41: 16 | P41: =O41/O39 -> 0.47058824
B42: Nationals | C42: =SUM(E42,G42,I42,K42,M42,O42) -> 1085 | D42: =C42/C39 -> 0.89817881 | E42: 536 | F42: =E42/$E$39 -> 0.86312399 | G42: 215 | H42: =G42/G39 -> 0.94713656 | I42: 211 | J42: =I42/I39 -> 0.93362832 | K42: 35 | L42: =K42/K39 -> 0.875 | M42: 55 | N42: =M42/M39 -> 0.91666667 | O42: 33 | P42: =O42/O39 -> 0.97058824
B43: Expatriates | C43: =SUM(E43,G43,I43,K43,M43,O43) -> 123 | D43: =C43/C39 -> 0.10182119 | E43: 85 | F43: =E43/$E$39 -> 0.13687601 | G43: 12 | H43: =G43/G39 -> 0.052863436 | I43: 15 | J43: =I43/I39 -> 0.066371681 | K43: 5 | L43: =K43/K39 -> 0.125 | M43: 5 | N43: =M43/M39 -> 0.083333333 | O43: 1 | P43: =O43/O39 -> 0.029411765
B44: Management | C44: =SUM(E44,G44,I44,K44,M44,O44) -> 266 | D44: =C44/C39 -> 0.22019868 | E44: 126 | F44: =E44/$E$39 -> 0.20289855 | G44: 64 | H44: =G44/G39 -> 0.28193833 | I44: 41 | J44: =I44/I39 -> 0.18141593 | K44: 12 | L44: =K44/K39 -> 0.3 | M44: 16 | N44: =M44/M39 -> 0.26666667 | O44: 7 | P44: =O44/O39 -> 0.20588235
B45: Female in Management | C45: =SUM(E45,G45,I45,K45,M45,O45) -> 44 | D45: =C45/C44 -> 0.16541353 | E45: 18 | F45: =E45/E44 -> 0.14285714 | G45: 9 | H45: =G45/G44 -> 0.140625 | I45: 8 | J45: =I45/I44 -> 0.19512195 | K45: 3 | L45: =K45/K44 -> 0.25 | M45: 4 | N45: =M45/M44 -> 0.25 | O45: 2 | P45: =O45/O44 -> 0.28571429
B46: Below 40 years of age | C46: =SUM(E46,G46,I46,K46,M46,O46) -> 959 | D46: =C46/C39 -> 0.79387417 | E46: 478 | F46: =E46/E39 -> 0.76972625 | G46: 186 | H46: =G46/G39 -> 0.81938326 | I46: 186 | J46: =I46/I39 -> 0.82300885 | K46: 34 | L46: =K46/K39 -> 0.85 | M46: 49 | N46: =M46/M39 -> 0.81666667 | O46: 26 | P46: =O46/O39 -> 0.76470588
B47: Atleast 40 years of age | C47: =SUM(E47,G47,I47,K47,M47,O47) -> 249 | D47: =C47/C39 -> 0.20612583 | E47: 143 | F47: =E47/E39 -> 0.23027375 | G47: 41 | H47: =G47/G39 -> 0.18061674 | I47: 40 | J47: =I47/I39 -> 0.17699115 | K47: 6 | L47: =K47/K39 -> 0.15 | M47: 11 | N47: =M47/M39 -> 0.18333333 | O47: 8 | P47: =O47/O39 -> 0.23529412
B48: Less than 5 years with Abacus | C48: =SUM(E48,G48,I48,K48,M48,O48) -> 691 | D48: =C48/C39 -> 0.57201987 | E48: 369 | F48: =E48/E39 -> 0.5942029 | G48: 93 | H48: =G48/G39 -> 0.40969163 | I48: 143 | J48: =I48/I39 -> 0.63274336 | K48: 30 | L48: =K48/K39 -> 0.75 | M48: 31 | N48: =M48/M39 -> 0.51666667 | O48: 25 | P48: =O48/O39 -> 0.73529412
B49: Atleast 5 years with Abacus | C49: =SUM(E49,G49,I49,K49,M49,O49) -> 517 | D49: =C49/C39 -> 0.42798013 | E49: 252 | F49: =E49/E39 -> 0.4057971 | G49: 134 | H49: =G49/G39 -> 0.59030837 | I49: 83 | J49: =I49/I39 -> 0.36725664 | K49: 10 | L49: =K49/K39 -> 0.25 | M49: =M39-M48 -> 29 | N49: =M49/M39 -> 0.48333333 | O49: 9 | P49: =O49/O39 -> 0.26470588
B50: Total New hires | C50: =SUM(E50,G50,I50,K50,M50,O50) -> 22 | D50: =SUM(D51:D53) -> 1 | E50: =SUM(E51:E53) -> 12 | F50: =SUM(F51:F53) -> 1 | G50: =SUM(G51:G53) -> 2 | H50: =SUM(H51:H53) -> 1 | I50: =SUM(I51:I53) -> 6 | J50: =SUM(J51:J53) -> 1 | K50: =SUM(K51:K53) -> 1 | ... P50: =SUM(P51:P53) -> 1
B51: New hires at EXCO | C51: =SUM(E51,G51,I51,K51,M51,O51) -> 1 | D51: =C51/C50 -> 0.045454545 | E51: 1 | F51: =E51/E50 -> 0.083333333 | G51: 0 | H51: 0 | I51: 0 | J51: 0 | K51: 0 | L51: 0 | M51: 0 | N51: =M51/$M$70 -> 0 | O51: 0 | P51: 0
B52: New hires at EXCO - 1&2 | C52: =SUM(E52,G52,I52,K52,M52,O52) -> 2 | D52: =C52/C50 -> 0.090909091 | E52: 0 | F52: =E52/E50 -> 0 | G52: 0 | H52: =G52/G50 -> 0 | I52: 1 | J52: =I52/I50 -> 0.16666667 | K52: 1 | L52: - | M52: 0 | N52: =M52/$M$70 -> 0 | O52: 0 | P52: =O52/O50 -> 0
B53: New hires at Other Levels | C53: =SUM(E53,G53,I53,K53,M53,O53) -> 19 | D53: =C53/C50 -> 0.86363636 | E53: 11 | F53: =E53/E50 -> 0.91666667 | G53: 2 | H53: =G53/G50 -> 1 | I53: 5 | J53: =I53/I50 -> 0.83333333 | K53: 0 | L53: =K53/K50 -> 0 | M53: 0 | N53: =M53/$M$70 -> 0 | O53: 1 | P53: =O53/O50 -> 1
B54: Total Exits | C54: =SUM(E54,G54,I54,K54,M54,O54) -> 19 | D54: =SUM(D55:D57) -> 0.015728477 | E54: =SUM(E55:E57) -> 3 | F54: =SUM(F55:F57) -> 0.0048309179 | G54: =SUM(G55:G57) -> 4 | H54: =SUM(H55:H57) -> 0.017621145 | I54: =SUM(I55:I57) -> 5 | J54: =SUM(J55:J57) -> 0.022123894 | K54: =SUM(K55:K57) -> 3 | ... P54: =SUM(P55:P57) -> 0.058823529
B55: Exits at EXCO | C55: =SUM(E55,G55,I55,K55,M55,O55) -> 0 | D55: =C55/$C$39 -> 0 | E55: 0 | F55: =E55/$E$39 -> 0 | G55: 0 | H55: =G55/$G$39 -> 0 | I55: 0 | J55: =I55/$I$39 -> 0 | K55: 0 | L55: =K55/$K$39 -> 0 | M55: 0 | N55: 0 | O55: 0 | P55: =O55/$O$39 -> 0
B56: Exits at EXCO - 1&2 | C56: =SUM(E56,G56,I56,K56,M56,O56) -> 1 | D56: =C56/$C$39 -> 0.00082781457 | E56: 0 | F56: =E56/$E$39 -> 0 | G56: 0 | H56: =G56/$G$39 -> 0 | I56: 0 | J56: =I56/$I$39 -> 0 | K56: 1 | L56: =K56/$K$39 -> 0.025 | M56: 0 | N56: 0 | O56: 0 | P56: =O56/$O$39 -> 0
B57: Exits at Other Levels | C57: =SUM(E57,G57,I57,K57,M57,O57) -> 18 | D57: =C57/$C$39 -> 0.014900662 | E57: 3 | F57: =E57/$E$39 -> 0.0048309179 | G57: 4 | H57: =G57/$G$39 -> 0.017621145 | I57: 5 | J57: =I57/$I$39 -> 0.022123894 | K57: 2 | L57: =K57/$K$39 -> 0.05 | M57: 2 | N57: 0 | O57: 2 | P57: =O57/$O$39 -> 0.058823529
B58: Total Internal Movements | C58: =SUM(E58,G58,I58,K58,M58,O58) -> 1 | E58: =SUM(E59:E60) -> 0 | F58: =SUM(F59:F60) -> 0 | G58: =SUM(G59:G60) -> 1 | H58: =SUM(H59:H60) -> 0 | I58: =SUM(I59:I60) -> 0 | J58: =SUM(J59:J60) -> 0 | K58: =SUM(K59:K60) -> 0 | L58: =SUM(L59:L60) -> 0 | ... O58: =SUM(O59:O60) -> 0 | P58: 0
B59: Promotions | C59: =SUM(E59,G59,I59,K59,M59,O59) -> 1 | E59: 0 | G59: 1 | I59: 0 | K59: 0 | M59: 0 | O59: 0
B60: Transfers | C60: =SUM(E60,G60,I60,K60,M60,O60) -> 0 | E60: 0 | G60: 0 | I60: 0 | K60: 0 | M60: 0 | O60: 0
B61: Principals | C61: =SUM(E61,G61,I61,K61,M61,O61) -> 411 | D61: =C61/C38 -> 0.19268636 | E61: =E62+E63 -> 338 | F61: =E61/C61 -> 0.82238443 | G61: =G62+G63 -> 0 | H61: =G61/C61 -> 0 | I61: =I62+I63 -> 22 | J61: =I61/C61 -> 0.053527981 | K61: =K62+K63 -> 36 | L61: =K61/E61 -> 0.10650888 | M61: =M62+M63 -> 6 | N61: =M61/C61 -> 0.01459854 | O61: =O62+O63 -> 9 | P61: =O61/C61 -> 0.02189781
B62: Female | C62: =SUM(E62,G62,I62,K62,M62,O62) -> 120 | D62: =C62/C61 -> 0.2919708 | E62: 96 | F62: =E62/E61 -> 0.28402367 | G62: 0 | H62: 0 | I62: 6 | J62: =I62/I61 -> 0.27272727 | K62: 14 | L62: =K62/K61 -> 0.38888889 | M62: 1 | N62: =M62/M61 -> 0.16666667 | O62: 3 | P62: 0
B63: Male | C63: =SUM(E63,G63,I63,K63,M63,O63) -> 291 | D63: =C63/C61 -> 0.7080292 | E63: 242 | F63: =E63/E61 -> 0.71597633 | G63: 0 | H63: 0 | I63: 16 | J63: =I63/I61 -> 0.72727273 | K63: 22 | L63: =K63/K61 -> 0.61111111 | M63: 5 | N63: 0 | O63: 6 | P63: 0
B64: Casuals/Contractors | C64: =SUM(E64,G64,I64,K64,M64,O64) -> 514 | D64: =C64/C38 -> 0.24097515 | E64: =E65+E66 -> 38 | F64: =E64/C64 -> 0.073929961 | G64: =G65+G66 -> 476 | H64: =G64/C64 -> 0.92607004 | I64: =I65+I66 -> 0 | J64: 0 | K64: =K65+K66 -> 0 | L64: =K64/C64 -> 0 | M64: =M65+M66 -> 0 | O64: =O65+O66 -> 0 | P64: 0
B65: Female | C65: =SUM(E65,G65,I65,K65,M65,O65) -> 208 | D65: =C65/C64 -> 0.40466926 | E65: 6 | F65: =E65/E64 -> 0.15789474 | G65: 202 | H65: =G65/G64 -> 0.42436975 | I65: 0 | J65: 0 | K65: 0 | L65: 0 | M65: 0 | N65: 0 | O65: 0 | P65: 0
B66: Male | C66: =SUM(E66,G66,I66,K66,M66,O66) -> 306 | D66: =C66/C64 -> 0.59533074 | E66: 32 | F66: =E66/E64 -> 0.84210526 | G66: 274 | H66: =G66/G64 -> 0.57563025 | I66: 0 | J66: 0 | K66: 0 | L66: 0 | M66: 0 | N66: 0 | O66: 0 | P66: 0
A68: Monthly Headcount Growth (Direct staff) | C68: =C70-C39 -> -6 | D68: =C68/C39 -> -0.0049668874 | E68: =E70-E39 -> -4 | F68: =E68/E39 -> -0.0064412238 | G68: =G70-G39 -> -1 | H68: =G68/G39 -> -0.0044052863 | I68: =I70-I39 -> 4 | J68: =I68/I39 -> 0.017699115 | K68: =K70-K39 -> -2 | L68: =K68/K39 -> -0.05 | M68: =M70-M39 -> -2 | N68: =M68/M39 -> -0.033333333 | O68: =O70-O39 -> -1 | P68: =O68/O39 -> -0.029411765
A69: 45717 | B69: Overall Headcount | C69: =SUM(E69,G69,I69,K69,M69,O69) -> 2165 | D69: =SUM(F69,H69,J69,L69,N69,P69) -> 1 | E69: =SUM(E70,E92,E95) -> 989 | F69: =E69/C69 -> 0.45681293 | G69: =SUM(G70,G92,G95) -> 742 | H69: =G69/C69 -> 0.34272517 | I69: =SUM(I70,I92,I95) -> 253 | J69: =I69/C69 -> 0.11685912 | K69: =SUM(K70,K92,K95) -> 75 | L69: =K69/C69 -> 0.034642032 | M69: =SUM(M70,M92,M95) -> 64 | N69: =M69/C69 -> 0.029561201 | O69: =SUM(O70,O92,O95) -> 42 | P69: =O69/C69 -> 0.019399538
B70: Direct Staff | C70: =SUM(E70,G70,I70,K70,M70,O70) -> 1202 | D70: =C70/C69 -> 0.5551963 | E70: =E71+E72 -> 617 | F70: =E70/C70 -> 0.51331115 | G70: =G71+G72 -> 226 | H70: =G70/C70 -> 0.18801997 | I70: =I71+I72 -> 230 | J70: =I70/C70 -> 0.19134775 | K70: =K71+K72 -> 38 | L70: =K70/C70 -> 0.031613977 | M70: =M71+M72 -> 58 | N70: =M70/C70 -> 0.048252912 | O70: =O71+O72 -> 33 | P70: =O70/C70 -> 0.027454243
B71: Female | C71: =SUM(E71,G71,I71,K71,M71,O71) -> 305 | D71: =C71/C70 -> 0.25374376 | E71: 145 | F71: =E71/$E$70 -> 0.2350081 | G71: 45 | H71: =G71/G70 -> 0.19911504 | I71: 68 | J71: =I71/I70 -> 0.29565217 | K71: 13 | L71: =K71/K70 -> 0.34210526 | M71: 17 | N71: =M71/M70 -> 0.29310345 | O71: 17 | P71: =O71/O70 -> 0.51515152
B72: Male | C72: =SUM(E72,G72,I72,K72,M72,O72) -> 897 | D72: =C72/C70 -> 0.74625624 | E72: 472 | F72: =E72/$E$70 -> 0.7649919 | G72: 181 | H72: =G72/G70 -> 0.80088496 | I72: 162 | J72: =I72/I70 -> 0.70434783 | K72: 25 | L72: =K72/K70 -> 0.65789474 | M72: 41 | N72: =M72/M70 -> 0.70689655 | O72: 16 | P72: =O72/O70 -> 0.48484848
B73: Nationals | C73: =SUM(E73,G73,I73,K73,M73,O73) -> 1079 | D73: =C73/C70 -> 0.89767055 | E73: 532 | F73: =E73/$E$70 -> 0.86223663 | G73: 214 | H73: =G73/G70 -> 0.94690265 | I73: 214 | J73: =I73/I70 -> 0.93043478 | K73: 34 | L73: =K73/K70 -> 0.89473684 | M73: 53 | N73: =M73/M70 -> 0.9137931 | O73: 32 | P73: =O73/O70 -> 0.96969697
B74: Expatriates | C74: =SUM(E74,G74,I74,K74,M74,O74) -> 123 | D74: =C74/C70 -> 0.10232945 | E74: 85 | F74: =E74/$E$70 -> 0.13776337 | G74: 12 | H74: =G74/G70 -> 0.053097345 | I74: 16 | J74: =I74/I70 -> 0.069565217 | K74: 4 | L74: =K74/K70 -> 0.10526316 | M74: 5 | N74: =M74/M70 -> 0.086206897 | O74: 1 | P74: =O74/O70 -> 0.03030303
B75: Management | C75: =SUM(E75,G75,I75,K75,M75,O75) -> 266 | D75: =C75/C70 -> 0.22129784 | E75: 127 | F75: =E75/$E$70 -> 0.20583468 | G75: 63 | H75: =G75/G70 -> 0.27876106 | I75: 42 | J75: =I75/I70 -> 0.1826087 | K75: 11 | L75: =K75/K70 -> 0.28947368 | M75: 16 | N75: =M75/M70 -> 0.27586207 | O75: 7 | P75: =O75/O70 -> 0.21212121
B76: Female in Management | C76: =SUM(E76,G76,I76,K76,M76,O76) -> 45 | D76: =C76/C75 -> 0.16917293 | E76: 20 | F76: =E76/E75 -> 0.15748031 | G76: 9 | H76: =G76/G75 -> 0.14285714 | I76: 8 | J76: =I76/I75 -> 0.19047619 | K76: 2 | L76: =K76/K75 -> 0.18181818 | M76: 4 | N76: =M76/M75 -> 0.25 | O76: 2 | P76: =O76/O75 -> 0.28571429
B77: Below 40 years of age | C77: =SUM(E77,G77,I77,K77,M77,O77) -> 945 | D77: =C77/C70 -> 0.78618968 | E77: 474 | F77: =E77/$E$70 -> 0.76823339 | G77: 180 | H77: =G77/G70 -> 0.79646018 | I77: 185 | J77: =I77/I70 -> 0.80434783 | K77: 33 | L77: =K77/K70 -> 0.86842105 | M77: 47 | N77: =M77/M70 -> 0.81034483 | O77: 26 | P77: =O77/O70 -> 0.78787879
B78: Atleast 40 years of age | C78: =SUM(E78,G78,I78,K78,M78,O78) -> 257 | D78: =C78/C70 -> 0.21381032 | E78: 143 | F78: =E78/$E$70 -> 0.23176661 | G78: 46 | H78: =G78/G70 -> 0.20353982 | I78: 45 | J78: =I78/I70 -> 0.19565217 | K78: 5 | L78: =K78/K70 -> 0.13157895 | M78: 11 | N78: =M78/M70 -> 0.18965517 | O78: 7 | P78: =O78/O70 -> 0.21212121
B79: Less than 5 years with Abacus | C79: =SUM(E79,G79,I79,K79,M79,O79) -> 688 | D79: =C79/C70 -> 0.57237937 | E79: 367 | F79: =E79/$E$70 -> 0.59481361 | G79: 92 | H79: =G79/G70 -> 0.40707965 | I79: 146 | J79: =I79/I70 -> 0.63478261 | K79: 28 | L79: =K79/K70 -> 0.73684211 | M79: 29 | N79: =M79/M70 -> 0.5 | O79: 26 | P79: =O79/O70 -> 0.78787879
B80: Atleast 5 years with Abacus | C80: =SUM(E80,G80,I80,K80,M80,O80) -> 514 | D80: =C80/C70 -> 0.42762063 | E80: 250 | F80: =E80/$E$70 -> 0.40518639 | G80: 134 | H80: =G80/G70 -> 0.59292035 | I80: 84 | J80: =I80/I70 -> 0.36521739 | K80: 10 | L80: =K80/K70 -> 0.26315789 | M80: 29 | N80: =M80/M70 -> 0.5 | O80: 7 | P80: =O80/O70 -> 0.21212121
B81: Total New hires | C81: =SUM(E81,G81,I81,K81,M81,O81) -> 16 | D81: =SUM(D82:D84) -> 1 | E81: =SUM(E82:E84) -> 4 | F81: =SUM(F82:F84) -> 1 | G81: =SUM(G82:G84) -> 2 | H81: =SUM(H82:H84) -> 1 | I81: =SUM(I82:I84) -> 9 | J81: =SUM(J82:J84) -> 1 | K81: =SUM(K82:K84) -> 0 | ... P81: =SUM(P82:P84) -> 1
B82: New hires at EXCO | C82: =SUM(E82,G82,I82,K82,M82,O82) -> 0 | D82: =C82/C81 -> 0 | E82: 0 | F82: =E82/E81 -> 0 | G82: =SUM(I82,K82,M82,O82,Q82,S82,U82,W82,Y82,AA82) -> 0 | H82: 0 | I82: =SUM(K82,M82,O82,Q82,S82,U82,W82,Y82) -> 0 | J82: 0 | K82: 0 | L82: 0 | M82: 0 | N82: 0 | O82: 0 | P82: 0
B83: New hires at EXCO - 1&2 | C83: =SUM(E83,G83,I83,K83,M83,O83) -> 0 | D83: =C83/C81 -> 0 | E83: 0 | F83: =E83/E81 -> 0 | G83: 0 | H83: =G83/G81 -> 0 | I83: 0 | J83: =I83/I81 -> 0 | K83: 0 | L83: - | M83: 0 | N83: 0 | O83: 0 | P83: =O83/O81 -> 0
B84: New hires at Other Levels | C84: =SUM(E84,G84,I84,K84,M84,O84) -> 16 | D84: =C84/C81 -> 1 | E84: 4 | F84: =E84/E81 -> 1 | G84: 2 | H84: =G84/G81 -> 1 | I84: 9 | J84: =I84/I81 -> 1 | K84: 0 | L84: 0 | M84: 0 | N84: 0 | O84: 1 | P84: =O84/O81 -> 1
B85: Total Exits | C85: =SUM(E85,G85,I85,K85,M85,O85) -> 47 | D85: =SUM(D86:D88) -> 0.039101498 | E85: =SUM(E86:E88) -> 27 | F85: =SUM(F86:F88) -> 0.04376013 | G85: =SUM(G86:G88) -> 7 | H85: =SUM(H86:H88) -> 0.030973451 | I85: =SUM(I86:I88) -> 10 | J85: =SUM(J86:J88) -> 0.043478261 | K85: =SUM(K86:K88) -> 3 | ... P85: =SUM(P86:P88) -> 0
B86: Exits at EXCO | C86: =SUM(E86,G86,I86,K86,M86,O86) -> 0 | D86: =C86/$C$70 -> 0 | E86: 0 | F86: =E86/$E$70 -> 0 | G86: 0 | H86: =G86/$G$70 -> 0 | I86: =SUM(K86,M86,O86,Q86,S86,U86,W86,Y86) -> 0 | J86: =I86/$I$70 -> 0 | K86: 0 | L86: =K86/$K$70 -> 0 | M86: 0 | N86: =M86/$M$70 -> 0 | O86: 0 | P86: =O86/$O$70 -> 0
B87: Exits at EXCO - 1&2 | C87: =SUM(E87,G87,I87,K87,M87,O87) -> 8 | D87: =C87/$C$70 -> 0.006655574 | E87: 4 | F87: =E87/$E$70 -> 0.0064829822 | G87: 2 | H87: =G87/$G$70 -> 0.0088495575 | I87: 1 | J87: =I87/$I$70 -> 0.0043478261 | K87: 1 | L87: =K87/$K$70 -> 0.026315789 | M87: 0 | N87: =M87/$M$70 -> 0 | O87: 0 | P87: =O87/$O$70 -> 0
B88: Exits at Other Levels | C88: =SUM(E88,G88,I88,K88,M88,O88) -> 39 | D88: =C88/$C$70 -> 0.032445923 | E88: 23 | F88: =E88/$E$70 -> 0.037277147 | G88: 5 | H88: =G88/$G$70 -> 0.022123894 | I88: 9 | J88: =I88/$I$70 -> 0.039130435 | K88: 2 | L88: =K88/$K$70 -> 0.052631579 | M88: 0 | N88: =M88/$M$70 -> 0 | O88: 0 | P88: =O88/$O$70 -> 0
B89: Total Internal Movements | C89: =SUM(E89,G89,I89,K89,M89,O89) -> 1 | E89: =SUM(E90:E91) -> 0 | F89: =SUM(F90:F91) -> 0 | G89: =SUM(G90:G91) -> 0 | H89: =SUM(H90:H91) -> 0 | I89: =SUM(I90:I91) -> 1 | J89: =SUM(J90:J91) -> 0 | K89: =SUM(K90:K91) -> 0 | L89: =SUM(L90:L91) -> 0 | ... O89: =SUM(O90:O91) -> 0 | P89: 0
B90: Promotions | C90: =SUM(E90,G90,I90,K90,M90,O90) -> 0 | E90: 0 | G90: 0 | I90: 0 | K90: 0 | M90: 0 | O90: 0
B91: Transfers | C91: =SUM(E91,G91,I91,K91,M91,O91) -> 1 | E91: 0 | G91: 0 | I91: 1 | K91: 0 | M91: 0 | O91: 0
B92: Principals | C92: =SUM(E92,G92,I92,K92,M92,O92) -> 409 | D92: =C92/C69 -> 0.18891455 | E92: =E93+E94 -> 334 | F92: =E92/C92 -> 0.81662592 | G92: =G93+G94 -> 0 | H92: =G92/C92 -> 0 | I92: =I93+I94 -> 23 | J92: =I92/C92 -> 0.056234719 | K92: =K93+K94 -> 37 | L92: =K92/E92 -> 0.11077844 | M92: =M93+M94 -> 6 | N92: =M92/C92 -> 0.014669927 | O92: =O93+O94 -> 9 | P92: =O92/C92 -> 0.02200489
B93: Female | C93: =SUM(E93,G93,I93,K93,M93,O93) -> 119 | D93: =C93/C92 -> 0.29095355 | E93: 93 | F93: =E93/E92 -> 0.27844311 | G93: 0 | H93: 0 | I93: 6 | J93: =I93/I92 -> 0.26086957 | K93: 15 | L93: 0 | M93: 1 | N93: =M93/M92 -> 0.16666667 | O93: 4 | P93: 0
B94: Male | C94: =SUM(E94,G94,I94,K94,M94,O94) -> 290 | D94: =C94/C92 -> 0.70904645 | E94: 241 | F94: =E94/E92 -> 0.72155689 | G94: 0 | H94: 0 | I94: 17 | J94: =I94/I92 -> 0.73913043 | K94: 22 | L94: 0 | M94: 5 | N94: =M94/M92 -> 0.83333333 | O94: 5 | P94: 0
B95: Casuals/Contractors | C95: =SUM(E95,G95,I95,K95,M95,O95) -> 554 | D95: =C95/C69 -> 0.25588915 | E95: =E96+E97 -> 38 | F95: =E95/C95 -> 0.068592058 | G95: =G96+G97 -> 516 | H95: =G95/C95 -> 0.93140794 | I95: =I96+I97 -> 0 | J95: 0 | K95: =K96+K97 -> 0 | L95: =K95/C95 -> 0 | M95: =M96+M97 -> 0 | N95: 0 | O95: =O96+O97 -> 0 | P95: 0
B96: Female | C96: =SUM(E96,G96,I96,K96,M96,O96) -> 222 | D96: =C96/C95 -> 0.40072202 | E96: 6 | F96: =E96/E95 -> 0.15789474 | G96: 216 | H96: =G96/G95 -> 0.41860465 | I96: 0 | J96: 0 | K96: 0 | L96: 0 | M96: 0 | N96: 0 | O96: 0 | P96: 0
B97: Male | C97: =SUM(E97,G97,I97,K97,M97,O97) -> 332 | D97: =C97/C95 -> 0.59927798 | E97: 32 | F97: =E97/E95 -> 0.84210526 | G97: 300 | H97: =G97/G95 -> 0.58139535 | I97: 0 | J97: 0 | K97: 0 | L97: 0 | M97: 0 | N97: 0 | O97: 0 | P97: 0
A99: Monthly Headcount Growth (Direct staff) | C99: =C101-C70 -> -38 | D99: =C99/C70 -> -0.031613977 | E99: =E101-E70 -> -15 | F99: =E99/E70 -> -0.024311183 | G99: =G101-G70 -> -9 | H99: =G99/G70 -> -0.039823009 | I99: =I101-I70 -> -11 | J99: =I99/I70 -> -0.047826087 | K99: =K101-K70 -> -4 | L99: =K99/K70 -> -0.10526316 | M99: =M101-M70 -> 0 | N99: =M99/M70 -> 0 | O99: =O101-O70 -> 1 | P99: =O99/O70 -> 0.03030303
A100: 45748 | B100: Overall Headcount | C100: =SUM(E100,G100,I100,K100,M100,O100) -> 2088 | D100: =SUM(F100,H100,J100,L100,N100,P100) -> 1 | E100: =SUM(E101,E123,E126) -> 963 | F100: =E100/C100 -> 0.4612069 | G100: =SUM(G101,G123,G126) -> 697 | H100: =G100/C100 -> 0.33381226 | I100: =SUM(I101,I123,I126) -> 251 | J100: =I100/C100 -> 0.12021073 | K100: =SUM(K101,K123,K126) -> 72 | L100: =K100/C100 -> 0.034482759 | M100: =SUM(M101,M123,M126) -> 63 | N100: =M100/C100 -> 0.030172414 | O100: =SUM(O101,O123,O126) -> 42 | P100: =O100/C100 -> 0.020114943
B101: Direct Staff | C101: =SUM(E101,G101,I101,K101,M101,O101) -> 1164 | D101: =C101/C100 -> 0.55747126 | E101: =E102+E103 -> 602 | F101: =E101/C101 -> 0.51718213 | G101: =G102+G103 -> 217 | H101: =G101/C101 -> 0.18642612 | I101: =I102+I103 -> 219 | J101: =I101/C101 -> 0.18814433 | K101: =K102+K103 -> 34 | L101: =K101/C101 -> 0.029209622 | M101: =M102+M103 -> 58 | N101: =M101/C101 -> 0.049828179 | O101: =O102+O103 -> 34 | P101: =O101/C101 -> 0.029209622
B102: Female | C102: =SUM(E102,G102,I102,K102,M102,O102) -> 290 | D102: =C102/C101 -> 0.24914089 | E102: 134 | F102: =E102/E101 -> 0.22259136 | G102: 43 | H102: =G102/G101 -> 0.19815668 | I102: 66 | J102: =I102/I101 -> 0.30136986 | K102: 13 | L102: =K102/K101 -> 0.38235294 | M102: 16 | N102: =M102/M101 -> 0.27586207 | O102: 18 | P102: =O102/O101 -> 0.52941176
B103: Male | C103: =SUM(E103,G103,I103,K103,M103,O103) -> 874 | D103: =C103/C101 -> 0.75085911 | E103: 468 | F103: =E103/E101 -> 0.77740864 | G103: 174 | H103: =G103/G101 -> 0.80184332 | I103: 153 | J103: =I103/I101 -> 0.69863014 | K103: 21 | L103: =K103/K101 -> 0.61764706 | M103: 42 | N103: =M103/M101 -> 0.72413793 | O103: 16 | P103: =O103/O101 -> 0.47058824
B104: Nationals | C104: =SUM(E104,G104,I104,K104,M104,O104) -> 1048 | D104: =C104/C101 -> 0.90034364 | E104: 519 | F104: =E104/E101 -> 0.86212625 | G104: 207 | H104: =G104/G101 -> 0.95391705 | I104: 204 | J104: =I104/I101 -> 0.93150685 | K104: 31 | L104: =K104/K101 -> 0.91176471 | M104: 54 | N104: =M104/M101 -> 0.93103448 | O104: 33 | P104: =O104/O101 -> 0.97058824
...

Sheet YTD Headcount
B1: Group YTD Headcount Report FY25
C2: Group | E2: Uganda | G2: APDL | I2: Tanzania | K2: Rwanda | M2: Burundi | O2: Kenya
C3: Number | D3: % | E3: Number | F3: % | G3: Number | H3: % | I3: Number | J3: % | K3: Number | L3: % | M3: Number | N3: % | O3: Number | P3: %
A5: Q1 | B5: Overall Headcount | C5: =SUM(E5,G5,I5,K5,M5,O5) -> 2149.6667 | D5: =SUM(F5,H5,J5,L5,N5,P5) -> 1 | E5: =SUM(E6,E28,E31) -> 996.66667 | F5: =E5/C$5 -> 0.46363777 | G5: =SUM(G6,G28,G31) -> 720.33333 | H5: =G5/C$5 -> 0.33509071 | I5: =SUM(I6,I28,I31) -> 248 | J5: =I5/C$5 -> 0.11536672 | K5: =SUM(K6,K28,K31) -> 76 | L5: =K5/C$5 -> 0.035354318 | M5: =SUM(M6,M28,M31) -> 65.666667 | N5: =M5/C$5 -> 0.030547372 | O5: =SUM(O6,O28,O31) -> 43 | P5: =O5/C$5 -> 0.020003101
B6: Direct Staff | C6: =SUM(E6,G6,I6,K6,M6,O6) -> 1202 | D6: =C6/C5 -> 0.55915646 | E6: =E7+E8 -> 616.66667 | F6: =E6/C6 -> 0.51303383 | G6: =G7+G8 -> 226.33333 | H6: =G6/C6 -> 0.18829728 | I6: =I7+I8 -> 226.33333 | J6: =I6/C6 -> 0.18829728 | K6: =K7+K8 -> 39.333333 | L6: =K6/C6 -> 0.032723239 | M6: =M7+M8 -> 59.666667 | N6: =M6/C6 -> 0.04963949 | O6: =O7+O8 -> 33.666667 | P6: =O6/C6 -> 0.028008874
B7: Female | C7: =SUM(E7,G7,I7,K7,M7,O7) -> 307.33333 | D7: =C7/C6 -> 0.25568497 | E7: =AVERAGE('Monthly Headcount'!E9,'Monthly Headcount'!E40,'Monthly Headcount'!E71) -> 146 | F7: =E7/E6 -> 0.23675676 | G7: =AVERAGE('Monthly Headcount'!G9,'Monthly Headcount'!G40,'Monthly Headcount'!G71) -> 45 | H7: =G7/G6 -> 0.1988218 | I7: =AVERAGE('Monthly Headcount'!I9,'Monthly Headcount'!I40,'Monthly Headcount'!I71) -> 67.333333 | J7: =I7/I6 -> 0.29749632 | K7: =AVERAGE('Monthly Headcount'!K9,'Monthly Headcount'!K40,'Monthly Headcount'!K71) -> 14 | L7: =K7/K6 -> 0.3559322 | M7: =AVERAGE('Monthly Headcount'!M9,'Monthly Headcount'!M40,'Monthly Headcount'!M71) -> 17.666667 | N7: =M7/M6 -> 0.29608939 | O7: =AVERAGE('Monthly Headcount'!O9,'Monthly Headcount'!O40,'Monthly Headcount'!O71) -> 17.333333 | P7: =O7/O6 -> 0.51485149
B8: Male | C8: =SUM(E8,G8,I8,K8,M8,O8) -> 894.66667 | D8: =C8/C6 -> 0.74431503 | E8: =AVERAGE('Monthly Headcount'!E10,'Monthly Headcount'!E41,'Monthly Headcount'!E72) -> 470.66667 | F8: =E9/E6 -> 0.86324324 | G8: =AVERAGE('Monthly Headcount'!G10,'Monthly Headcount'!G41,'Monthly Headcount'!G72) -> 181.33333 | H8: =G8/G6 -> 0.8011782 | I8: =AVERAGE('Monthly Headcount'!I10,'Monthly Headcount'!I41,'Monthly Headcount'!I72) -> 159 | J8: =I8/I6 -> 0.70250368 | K8: =AVERAGE('Monthly Headcount'!K10,'Monthly Headcount'!K41,'Monthly Headcount'!K72) -> 25.333333 | L8: =K8/K6 -> 0.6440678 | M8: =AVERAGE('Monthly Headcount'!M10,'Monthly Headcount'!M41,'Monthly Headcount'!M72) -> 42 | N8: =M8/M6 -> 0.70391061 | O8: =AVERAGE('Monthly Headcount'!O10,'Monthly Headcount'!O41,'Monthly Headcount'!O72) -> 16.333333 | P8: =O8/O6 -> 0.48514851
B9: Nationals | C9: =SUM(E9,G9,I9,K9,M9,O9) -> 1080.3333 | D9: =C9/C6 -> 0.89877981 | E9: =AVERAGE('Monthly Headcount'!E11,'Monthly Headcount'!E42,'Monthly Headcount'!E73) -> 532.33333 | F9: =E9/E6 -> 0.86324324 | G9: =AVERAGE('Monthly Headcount'!G11,'Monthly Headcount'!G42,'Monthly Headcount'!G73) -> 214.33333 | H9: =G9/G6 -> 0.94698085 | I9: =AVERAGE('Monthly Headcount'!I11,'Monthly Headcount'!I42,'Monthly Headcount'!I73) -> 211.33333 | J9: =I9/I6 -> 0.93372607 | K9: =AVERAGE('Monthly Headcount'!K11,'Monthly Headcount'!K42,'Monthly Headcount'!K73) -> 35 | L9: =K9/K6 -> 0.88983051 | M9: =AVERAGE('Monthly Headcount'!M11,'Monthly Headcount'!M42,'Monthly Headcount'!M73) -> 54.666667 | N9: =M9/M6 -> 0.91620112 | O9: =AVERAGE('Monthly Headcount'!O11,'Monthly Headcount'!O42,'Monthly Headcount'!O73) -> 32.666667 | P9: =O9/O6 -> 0.97029703
B10: Expatriates | C10: =SUM(E10,G10,I10,K10,M10,O10) -> 121.66667 | D10: =C10/C6 -> 0.10122019 | E10: =AVERAGE('Monthly Headcount'!E12,'Monthly Headcount'!E43,'Monthly Headcount'!E74) -> 84.333333 | F10: =E10/E6 -> 0.13675676 | G10: =AVERAGE('Monthly Headcount'!G12,'Monthly Headcount'!G43,'Monthly Headcount'!G74) -> 12 | H10: =G10/G6 -> 0.053019146 | I10: =AVERAGE('Monthly Headcount'!I12,'Monthly Headcount'!I43,'Monthly Headcount'!I74) -> 15 | J10: =I10/I6 -> 0.066273932 | K10: =AVERAGE('Monthly Headcount'!K12,'Monthly Headcount'!K43,'Monthly Headcount'!K74) -> 4.3333333 | L10: =K10/K6 -> 0.11016949 | M10: =AVERAGE('Monthly Headcount'!M12,'Monthly Headcount'!M43,'Monthly Headcount'!M74) -> 5 | N10: =M10/M6 -> 0.083798883 | O10: =AVERAGE('Monthly Headcount'!O12,'Monthly Headcount'!O43,'Monthly Headcount'!O74) -> 1 | P10: =O10/O6 -> 0.02970297
B11: Management | C11: =SUM(E11,G11,I11,K11,M11,O11) -> 266.33333 | D11: =C11/C6 -> 0.22157515 | E11: =AVERAGE('Monthly Headcount'!E13,'Monthly Headcount'!E44,'Monthly Headcount'!E75) -> 126.66667 | F11: =E11/E6 -> 0.20540541 | G11: =AVERAGE('Monthly Headcount'!G13,'Monthly Headcount'!G44,'Monthly Headcount'!G75) -> 64 | H11: =G11/G6 -> 0.28276878 | I11: =AVERAGE('Monthly Headcount'!I13,'Monthly Headcount'!I44,'Monthly Headcount'!I75) -> 41 | J11: =I11/I6 -> 0.18114875 | K11: =AVERAGE('Monthly Headcount'!K13,'Monthly Headcount'!K44,'Monthly Headcount'!K75) -> 11.333333 | L11: =K11/K6 -> 0.28813559 | M11: =AVERAGE('Monthly Headcount'!M13,'Monthly Headcount'!M44,'Monthly Headcount'!M75) -> 16.333333 | N11: =M11/M6 -> 0.27374302 | O11: =AVERAGE('Monthly Headcount'!O13,'Monthly Headcount'!O44,'Monthly Headcount'!O75) -> 7 | P11: =O11/O6 -> 0.20792079
B12: Female in Management | C12: =SUM(E12,G12,I12,K12,M12,O12) -> 44.666667 | D12: =C12/C11 -> 0.16770964 | E12: =AVERAGE('Monthly Headcount'!E14,'Monthly Headcount'!E45,'Monthly Headcount'!E76) -> 18.666667 | F12: =E12/E11 -> 0.14736842 | G12: =AVERAGE('Monthly Headcount'!G14,'Monthly Headcount'!G45,'Monthly Headcount'!G76) -> 9.3333333 | H12: =G12/G11 -> 0.14583333 | I12: =AVERAGE('Monthly Headcount'!I14,'Monthly Headcount'!I45,'Monthly Headcount'!I76) -> 8 | J12: =I12/I11 -> 0.19512195 | K12: =AVERAGE('Monthly Headcount'!K14,'Monthly Headcount'!K45,'Monthly Headcount'!K76) -> 2.6666667 | L12: =K12/K11 -> 0.23529412 | M12: =AVERAGE('Monthly Headcount'!M14,'Monthly Headcount'!M45,'Monthly Headcount'!M76) -> 4 | N12: =M12/M11 -> 0.24489796 | O12: =AVERAGE('Monthly Headcount'!O14,'Monthly Headcount'!O45,'Monthly Headcount'!O76) -> 2 | P12: =O12/O11 -> 0.28571429
B13: Below 40 years of age | C13: =SUM(E13,G13,I13,K13,M13,O13) -> 950.66667 | D13: =C13/C6 -> 0.79090405 | E13: =AVERAGE('Monthly Headcount'!E15,'Monthly Headcount'!E46,'Monthly Headcount'!E77) -> 473.66667 | F13: =E13/E6 -> 0.76810811 | G13: =AVERAGE('Monthly Headcount'!G15,'Monthly Headcount'!G46,'Monthly Headcount'!G77) -> 184.33333 | H13: =G13/G6 -> 0.81443299 | I13: =AVERAGE('Monthly Headcount'!I15,'Monthly Headcount'!I46,'Monthly Headcount'!I77) -> 184.33333 | J13: =I13/I6 -> 0.81443299 | K13: =AVERAGE('Monthly Headcount'!K15,'Monthly Headcount'!K46,'Monthly Headcount'!K77) -> 33.666667 | L13: =K13/K6 -> 0.8559322 | M13: =AVERAGE('Monthly Headcount'!M15,'Monthly Headcount'!M46,'Monthly Headcount'!M77) -> 48.666667 | N13: =M13/M6 -> 0.81564246 | O13: =AVERAGE('Monthly Headcount'!O15,'Monthly Headcount'!O46,'Monthly Headcount'!O77) -> 26 | P13: =O13/O6 -> 0.77227723
B14: Atleast 40 years of age | C14: =SUM(E14,G14,I14,K14,M14,O14) -> 251.33333 | D14: =C14/C6 -> 0.20909595 | E14: =AVERAGE('Monthly Headcount'!E16,'Monthly Headcount'!E47,'Monthly Headcount'!E78) -> 143 | F14: =E14/E6 -> 0.23189189 | G14: =AVERAGE('Monthly Headcount'!G16,'Monthly Headcount'!G47,'Monthly Headcount'!G78) -> 42 | H14: =G14/G6 -> 0.18556701 | I14: =AVERAGE('Monthly Headcount'!I16,'Monthly Headcount'!I47,'Monthly Headcount'!I78) -> 42 | J14: =I14/I6 -> 0.18556701 | K14: =AVERAGE('Monthly Headcount'!K16,'Monthly Headcount'!K47,'Monthly Headcount'!K78) -> 5.6666667 | L14: =K14/K6 -> 0.1440678 | M14: =AVERAGE('Monthly Headcount'!M16,'Monthly Headcount'!M47,'Monthly Headcount'!M78) -> 11 | N14: =M14/M6 -> 0.18435754 | O14: =AVERAGE('Monthly Headcount'!O16,'Monthly Headcount'!O47,'Monthly Headcount'!O78) -> 7.6666667 | P14: =O14/O6 -> 0.22772277
B15: Less than 5 years with Abacus | C15: =SUM(E15,G15,I15,K15,M15,O15) -> 685.66667 | D15: =C15/C6 -> 0.57043816 | E15: =AVERAGE('Monthly Headcount'!E17,'Monthly Headcount'!E48,'Monthly Headcount'!E79) -> 365.66667 | F15: =E15/E6 -> 0.59297297 | G15: =AVERAGE('Monthly Headcount'!G17,'Monthly Headcount'!G48,'Monthly Headcount'!G79) -> 92 | H15: =G15/G6 -> 0.40648012 | I15: =AVERAGE('Monthly Headcount'!I17,'Monthly Headcount'!I48,'Monthly Headcount'!I79) -> 143 | J15: =I15/I6 -> 0.63181149 | K15: =AVERAGE('Monthly Headcount'!K17,'Monthly Headcount'!K48,'Monthly Headcount'!K79) -> 29.333333 | L15: =K15/K6 -> 0.74576271 | M15: =AVERAGE('Monthly Headcount'!M17,'Monthly Headcount'!M48,'Monthly Headcount'!M79) -> 30.333333 | N15: =M15/M6 -> 0.50837989 | O15: =AVERAGE('Monthly Headcount'!O17,'Monthly Headcount'!O48,'Monthly Headcount'!O79) -> 25.333333 | P15: =O15/O6 -> 0.75247525
B16: Atleast 5 years with Abacus | C16: =SUM(E16,G16,I16,K16,M16,O16) -> 516.33333 | D16: =C16/C6 -> 0.42956184 | E16: =AVERAGE('Monthly Headcount'!E18,'Monthly Headcount'!E49,'Monthly Headcount'!E80) -> 251 | F16: =E16/E6 -> 0.40702703 | G16: =AVERAGE('Monthly Headcount'!G18,'Monthly Headcount'!G49,'Monthly Headcount'!G80) -> 134.33333 | H16: =G16/G6 -> 0.59351988 | I16: =AVERAGE('Monthly Headcount'!I18,'Monthly Headcount'!I49,'Monthly Headcount'!I80) -> 83.333333 | J16: =I16/I6 -> 0.36818851 | K16: =AVERAGE('Monthly Headcount'!K18,'Monthly Headcount'!K49,'Monthly Headcount'!K80) -> 10 | L16: =K16/K6 -> 0.25423729 | M16: =AVERAGE('Monthly Headcount'!M18,'Monthly Headcount'!M49,'Monthly Headcount'!M80) -> 29.333333 | N16: =M16/M6 -> 0.49162011 | O16: =AVERAGE('Monthly Headcount'!O18,'Monthly Headcount'!O49,'Monthly Headcount'!O80) -> 8.3333333 | P16: =O16/O6 -> 0.24752475
B17: Total New hires | C17: =SUM(E17,G17,I17,K17,M17,O17) -> 21.666667 | D17: =SUM(D18:D20) -> 0.018025513 | E17: =SUM(E18:E20) -> 6.6666667 | F17: =SUM(F18:F20) -> 1 | G17: =SUM(G18:G20) -> 2.3333333 | H17: =SUM(H18:H20) -> 1 | I17: =SUM(I18:I20) -> 9.6666667 | J17: =SUM(J18:J20) -> 1 | K17: =SUM(K18:K20) -> 0.66666667 | ... P17: =SUM(P18:P20) -> 1
B18: New hires at EXCO | C18: =SUM(E18,G18,I18,K18,M18,O18) -> 0.33333333 | D18: =C18/$C$6 -> 0.00027731559 | E18: =AVERAGE('Monthly Headcount'!E20,'Monthly Headcount'!E51,'Monthly Headcount'!E82) -> 0.33333333 | F18: =E18/E17 -> 0.05 | G18: =AVERAGE('Monthly Headcount'!G20,'Monthly Headcount'!G51,'Monthly Headcount'!G82) -> 0 | H18: 0 | I18: =AVERAGE('Monthly Headcount'!I20,'Monthly Headcount'!I51,'Monthly Headcount'!I82) -> 0 | J18: 0 | K18: =AVERAGE('Monthly Headcount'!K20,'Monthly Headcount'!K51,'Monthly Headcount'!K82) -> 0 | L18: 0 | M18: =AVERAGE('Monthly Headcount'!M20,'Monthly Headcount'!M51,'Monthly Headcount'!M82) -> 0 | N18: 0 | O18: =AVERAGE('Monthly Headcount'!O20,'Monthly Headcount'!O51,'Monthly Headcount'!O82) -> 0 | P18: 0
B19: New hires at EXCO - 1&2 | C19: =SUM(E19,G19,I19,K19,M19,O19) -> 1 | D19: =C19/$C$6 -> 0.00083194676 | E19: =AVERAGE('Monthly Headcount'!E21,'Monthly Headcount'!E52,'Monthly Headcount'!E83) -> 0 | F19: =E19/E17 -> 0 | G19: =AVERAGE('Monthly Headcount'!G21,'Monthly Headcount'!G52,'Monthly Headcount'!G83) -> 0 | H19: =G19/G17 -> 0 | I19: =AVERAGE('Monthly Headcount'!I21,'Monthly Headcount'!I52,'Monthly Headcount'!I83) -> 0.33333333 | J19: =I19/I17 -> 0.034482759 | K19: =AVERAGE('Monthly Headcount'!K21,'Monthly Headcount'!K52,'Monthly Headcount'!K83) -> 0.66666667 | L19: - | M19: =AVERAGE('Monthly Headcount'!M21,'Monthly Headcount'!M52,'Monthly Headcount'!M83) -> 0 | N19: =M19/M17 -> 0 | O19: =AVERAGE('Monthly Headcount'!O21,'Monthly Headcount'!O52,'Monthly Headcount'!O83) -> 0 | P19: =O19/O17 -> 0
B20: New hires at Other Levels | C20: =SUM(E20,G20,I20,K20,M20,O20) -> 20.333333 | D20: =C20/$C$6 -> 0.016916251 | E20: =AVERAGE('Monthly Headcount'!E22,'Monthly Headcount'!E53,'Monthly Headcount'!E84) -> 6.3333333 | F20: =E20/E17 -> 0.95 | G20: =AVERAGE('Monthly Headcount'!G22,'Monthly Headcount'!G53,'Monthly Headcount'!G84) -> 2.3333333 | H20: =G20/G17 -> 1 | I20: =AVERAGE('Monthly Headcount'!I22,'Monthly Headcount'!I53,'Monthly Headcount'!I84) -> 9.3333333 | J20: =I20/I17 -> 0.96551724 | K20: 0 | L20: =K20/K17 -> 0 | M20: =AVERAGE('Monthly Headcount'!M22,'Monthly Headcount'!M53,'Monthly Headcount'!M84) -> 0.33333333 | N20: =M20/M17 -> 1 | O20: =AVERAGE('Monthly Headcount'!O22,'Monthly Headcount'!O53,'Monthly Headcount'!O84) -> 2 | P20: =O20/O17 -> 1
B21: Total Exits | C21: =SUM(E21,G21,I21,K21,M21,O21) -> 26.666667 | D21: =SUM(D22:D24) -> 0.022185247 | E21: =SUM(E22:E24) -> 12 | F21: =SUM(F22:F24) -> 0.019459459 | G21: =SUM(G22:G24) -> 4 | H21: =SUM(H22:H24) -> 0.017673049 | I21: =SUM(I22:I24) -> 6.3333333 | J21: =SUM(J22:J24) -> 0.027982327 | K21: =SUM(K22:K24) -> 2.3333333 | ... P21: =SUM(P22:P24) -> 0.02970297
B22: Exits at EXCO | C22: =SUM(E22,G22,I22,K22,M22,O22) -> 0 | D22: =C22/$C$6 -> 0 | E22: =AVERAGE('Monthly Headcount'!E24,'Monthly Headcount'!E55,'Monthly Headcount'!E86) -> 0 | F22: =E22/$E$6 -> 0 | G22: =SUM('Monthly Headcount'!G24,'Monthly Headcount'!G55,'Monthly Headcount'!G86) -> 0 | H22: =G22/$G$6 -> 0 | I22: =AVERAGE('Monthly Headcount'!I24,'Monthly Headcount'!I55,'Monthly Headcount'!I86) -> 0 | J22: =I22/$I$6 -> 0 | K22: =AVERAGE('Monthly Headcount'!K24,'Monthly Headcount'!K55,'Monthly Headcount'!K86) -> 0 | L22: =K22/$K$6 -> 0 | M22: =AVERAGE('Monthly Headcount'!M24,'Monthly Headcount'!M55,'Monthly Headcount'!M86) -> 0 | N22: =M22/$M$6 -> 0 | O22: =AVERAGE('Monthly Headcount'!O24,'Monthly Headcount'!O55,'Monthly Headcount'!O86) -> 0 | P22: =O22/$O$6 -> 0
B23: Exits at EXCO - 1&2 | C23: =SUM(E23,G23,I23,K23,M23,O23) -> 3.3333333 | D23: =C23/$C$6 -> 0.0027731559 | E23: =AVERAGE('Monthly Headcount'!E25,'Monthly Headcount'!E56,'Monthly Headcount'!E87) -> 1.6666667 | F23: =E23/$E$6 -> 0.0027027027 | G23: =AVERAGE('Monthly Headcount'!G25,'Monthly Headcount'!G56,'Monthly Headcount'!G87) -> 0.66666667 | H23: =G23/$G$6 -> 0.0029455081 | I23: =AVERAGE('Monthly Headcount'!I25,'Monthly Headcount'!I56,'Monthly Headcount'!I87) -> 0.33333333 | J23: =I23/$I$6 -> 0.0014727541 | K23: =AVERAGE('Monthly Headcount'!K25,'Monthly Headcount'!K56,'Monthly Headcount'!K87) -> 0.66666667 | L23: =K23/$K$6 -> 0.016949153 | M23: =AVERAGE('Monthly Headcount'!M25,'Monthly Headcount'!M56,'Monthly Headcount'!M87) -> 0 | N23: =M23/$M$6 -> 0 | O23: =AVERAGE('Monthly Headcount'!O25,'Monthly Headcount'!O56,'Monthly Headcount'!O87) -> 0 | P23: =O23/$O$6 -> 0
B24: Exits at Other Levels | C24: =SUM(E24,G24,I24,K24,M24,O24) -> 23.333333 | D24: =C24/$C$6 -> 0.019412091 | E24: =AVERAGE('Monthly Headcount'!E26,'Monthly Headcount'!E57,'Monthly Headcount'!E88) -> 10.333333 | F24: =E24/$E$6 -> 0.016756757 | G24: =AVERAGE('Monthly Headcount'!G26,'Monthly Headcount'!G57,'Monthly Headcount'!G88) -> 3.3333333 | H24: =G24/$G$6 -> 0.014727541 | I24: =AVERAGE('Monthly Headcount'!I26,'Monthly Headcount'!I57,'Monthly Headcount'!I88) -> 6 | J24: =I24/$I$6 -> 0.026509573 | K24: =AVERAGE('Monthly Headcount'!K26,'Monthly Headcount'!K57,'Monthly Headcount'!K88) -> 1.6666667 | L24: =K24/$K$6 -> 0.042372881 | M24: =AVERAGE('Monthly Headcount'!M26,'Monthly Headcount'!M57,'Monthly Headcount'!M88) -> 1 | N24: =M24/$M$6 -> 0.016759777 | O24: =AVERAGE('Monthly Headcount'!O26,'Monthly Headcount'!O57,'Monthly Headcount'!O88) -> 1 | P24: =O24/$O$6 -> 0.02970297
B25: Total Internal Movements | C25: =SUM(E25,G25,I25,K25,M25,O25) -> 10.333333 | E25: =SUM(E26:E27) -> 5.3333333 | F25: =SUM(F26:F27) -> 0 | G25: =SUM(G26:G27) -> 0.66666667 | H25: =SUM(H26:H27) -> 0 | I25: =SUM(I26:I27) -> 2.6666667 | J25: =SUM(J26:J27) -> 0 | K25: =SUM(K26:K27) -> 0 | L25: =SUM(L26:L27) -> 0 | ... N25: =SUM(N26:N27) -> 0 | O25: =AVERAGE('Monthly Headcount'!O27,'Monthly Headcount'!O58,'Monthly Headcount'!O89) -> 0.66666667 | P25: =SUM(P26:P27) -> 0
B26: Promotions | C26: =SUM(E26,G26,I26,K26,M26,O26) -> 9.6666667 | E26: =AVERAGE('Monthly Headcount'!E28,'Monthly Headcount'!E59,'Monthly Headcount'!E90) -> 5 | G26: =AVERAGE('Monthly Headcount'!G28,'Monthly Headcount'!G59,'Monthly Headcount'!G90) -> 0.66666667 | I26: =AVERAGE('Monthly Headcount'!I28,'Monthly Headcount'!I59,'Monthly Headcount'!I90) -> 2.3333333 | K26: =AVERAGE('Monthly Headcount'!K28,'Monthly Headcount'!K59,'Monthly Headcount'!K90) -> 0 | M26: =AVERAGE('Monthly Headcount'!M28,'Monthly Headcount'!M59,'Monthly Headcount'!M90) -> 1 | O26: =AVERAGE('Monthly Headcount'!O28,'Monthly Headcount'!O59,'Monthly Headcount'!O90) -> 0.66666667
B27: Transfers | C27: =SUM(E27,G27,I27,K27,M27,O27) -> 0.66666667 | E27: =AVERAGE('Monthly Headcount'!E29,'Monthly Headcount'!E60,'Monthly Headcount'!E91) -> 0.33333333 | G27: =AVERAGE('Monthly Headcount'!G29,'Monthly Headcount'!G60,'Monthly Headcount'!G91) -> 0 | I27: =AVERAGE('Monthly Headcount'!I29,'Monthly Headcount'!I60,'Monthly Headcount'!I91) -> 0.33333333 | K27: =AVERAGE('Monthly Headcount'!K29,'Monthly Headcount'!K60,'Monthly Headcount'!K91) -> 0 | M27: =AVERAGE('Monthly Headcount'!M29,'Monthly Headcount'!M60,'Monthly Headcount'!M91) -> 0 | O27: =AVERAGE('Monthly Headcount'!O29,'Monthly Headcount'!O60,'Monthly Headcount'!O91) -> 0
B28: Principals | C28: =SUM(E28,G28,I28,K28,M28,O28) -> 411 | D28: =C28/C5 -> 0.19119243 | E28: =E29+E30 -> 337.33333 | F28: =E28/C28 -> 0.82076237 | G28: =G29+G30 -> 0 | H28: =G28/C28 -> 0 | I28: =I29+I30 -> 21.666667 | J28: =I28/C28 -> 0.052716951 | K28: =K29+K30 -> 36.666667 | L28: =K28/E28 -> 0.10869565 | M28: =M29+M30 -> 6 | N28: =M28/C28 -> 0.01459854 | O28: =O29+O30 -> 9.3333333 | P28: =O28/C28 -> 0.02270884
B29: Female | C29: =SUM(E29,G29,I29,K29,M29,O29) -> 120.33333 | D29: =C29/C28 -> 0.29278183 | E29: =AVERAGE('Monthly Headcount'!E31,'Monthly Headcount'!E62,'Monthly Headcount'!E93) -> 95.333333 | F29: =E29/E28 -> 0.2826087 | G29: =AVERAGE('Monthly Headcount'!G31,'Monthly Headcount'!G62,'Monthly Headcount'!G93) -> 0 | H29: 0 | I29: =AVERAGE('Monthly Headcount'!I31,'Monthly Headcount'!I62,'Monthly Headcount'!I93) -> 6 | J29: =I29/I28 -> 0.27692308 | K29: =AVERAGE('Monthly Headcount'!K31,'Monthly Headcount'!K62,'Monthly Headcount'!K93) -> 14.666667 | L29: =K29/K28 -> 0.4 | M29: =AVERAGE('Monthly Headcount'!M31,'Monthly Headcount'!M62,'Monthly Headcount'!M93) -> 1 | N29: =M29/M28 -> 0.16666667 | O29: =AVERAGE('Monthly Headcount'!O31,'Monthly Headcount'!O62,'Monthly Headcount'!O93) -> 3.3333333 | P29: 0
B30: Male | C30: =SUM(E30,G30,I30,K30,M30,O30) -> 290.66667 | D30: =C30/C28 -> 0.70721817 | E30: =AVERAGE('Monthly Headcount'!E32,'Monthly Headcount'!E63,'Monthly Headcount'!E94) -> 242 | F30: =E30/E28 -> 0.7173913 | G30: =AVERAGE('Monthly Headcount'!G32,'Monthly Headcount'!G63,'Monthly Headcount'!G94) -> 0 | H30: 0 | I30: =AVERAGE('Monthly Headcount'!I32,'Monthly Headcount'!I63,'Monthly Headcount'!I94) -> 15.666667 | J30: =I30/I28 -> 0.72307692 | K30: =AVERAGE('Monthly Headcount'!K32,'Monthly Headcount'!K63,'Monthly Headcount'!K94) -> 22 | L30: =K30/K28 -> 0.6 | M30: =AVERAGE('Monthly Headcount'!M32,'Monthly Headcount'!M63,'Monthly Headcount'!M94) -> 5 | N30: =M30/M28 -> 0.83333333 | O30: =AVERAGE('Monthly Headcount'!O32,'Monthly Headcount'!O63,'Monthly Headcount'!O94) -> 6 | P30: 0
B31: Casuals/Contractors | C31: =SUM(E31,G31,I31,K31,M31,O31) -> 536.66667 | D31: =C31/C5 -> 0.24965111 | E31: =E32+E33 -> 42.666667 | F31: =E31/C31 -> 0.079503106 | G31: =G32+G33 -> 494 | H31: =G31/C31 -> 0.92049689 | I31: =I32+I33 -> 0 | J31: 0 | K31: =K32+K33 -> 0 | L31: =K31/C31 -> 0 | M31: =M32+M33 -> 0 | N31: 0 | O31: =AVERAGE('Monthly Headcount'!O33,'Monthly Headcount'!O64,'Monthly Headcount'!O95) -> 0 | P31: 0
B32: Female | C32: =SUM(E32,G32,I32,K32,M32,O32) -> 229.33333 | D32: =C32/C31 -> 0.42732919 | E32: =AVERAGE('Monthly Headcount'!E34,'Monthly Headcount'!E65,'Monthly Headcount'!E96) -> 6 | F32: =E32/E31 -> 0.140625 | G32: =AVERAGE('Monthly Headcount'!G34,'Monthly Headcount'!G65,'Monthly Headcount'!G96) -> 223.33333 | H32: =G32/G31 -> 0.45209177 | I32: =AVERAGE('Monthly Headcount'!I34,'Monthly Headcount'!I65,'Monthly Headcount'!I96) -> 0 | J32: 0 | K32: =AVERAGE('Monthly Headcount'!K34,'Monthly Headcount'!K65,'Monthly Headcount'!K96) -> 0 | L32: 0 | M32: =AVERAGE('Monthly Headcount'!M34,'Monthly Headcount'!M65,'Monthly Headcount'!M96) -> 0 | N32: 0 | O32: =AVERAGE('Monthly Headcount'!O34,'Monthly Headcount'!O65,'Monthly Headcount'!O96) -> 0 | P32: 0
B33: Male | C33: =SUM(E33,G33,I33,K33,M33,O33) -> 307.33333 | D33: =C33/C31 -> 0.57267081 | E33: =AVERAGE('Monthly Headcount'!E35,'Monthly Headcount'!E66,'Monthly Headcount'!E97) -> 36.666667 | F33: =E33/E31 -> 0.859375 | G33: =AVERAGE('Monthly Headcount'!G35,'Monthly Headcount'!G66,'Monthly Headcount'!G97) -> 270.66667 | H33: =G33/G31 -> 0.54790823 | I33: =AVERAGE('Monthly Headcount'!I35,'Monthly Headcount'!I66,'Monthly Headcount'!I97) -> 0 | J33: 0 | K33: =AVERAGE('Monthly Headcount'!K35,'Monthly Headcount'!K66,'Monthly Headcount'!K97) -> 0 | L33: 0 | M33: =AVERAGE('Monthly Headcount'!M35,'Monthly Headcount'!M66,'Monthly Headcount'!M97) -> 0 | N33: 0 | O33: =AVERAGE('Monthly Headcount'!O35,'Monthly Headcount'!O66,'Monthly Headcount'!O97) -> 0 | P33: 0
A34: Q2 | B34: Overall Headcount | C34: =SUM(E34,G34,I34,K34,M34,O34) -> 2140 | D34: =SUM(F34,H34,J34,L34,N34,P34) -> 1 | E34: =SUM(E35,E57,E60) -> 949.66667 | F34: =E34/C34 -> 0.44376947 | G34: =SUM(G35,G57,G60) -> 760.33333 | H34: =G34/C34 -> 0.35529595 | I34: =SUM(I35,I57,I60) -> 254.66667 | J34: =I34/C34 -> 0.11900312 | K34: =SUM(K35,K57,K60) -> 71 | L34: =K34/C34 -> 0.03317757 | M34: =SUM(M35,M57,M60) -> 62.666667 | N34: =M34/C34 -> 0.029283489 | O34: =SUM(O35,O57,O60) -> 41.666667 | P34: =O34/C34 -> 0.019470405
B35: Direct Staff | C35: =SUM(E35,G35,I35,K35,M35,O35) -> 1173.3333 | D35: =C35/C34 -> 0.5482866 | E35: =E36+E37 -> 599.66667 | F35: =E35/C35 -> 0.51107955 | G35: =G36+G37 -> 223.66667 | H35: =G35/C35 -> 0.190625 | I35: =I36+I37 -> 222.33333 | J35: =I35/C35 -> 0.18948864 | K35: =K36+K37 -> 36.666667 | L35: =K35/C35 -> 0.03125 | M35: =M36+M37 -> 58 | N35: =M35/C35 -> 0.049431818 | O35: =O36+O37 -> 33 | P35: =O35/C35 -> 0.028125
B36: Female | C36: =SUM(E36,G36,I36,K36,M36,O36) -> 292.66667 | D36: =C36/C35 -> 0.24943182 | E36: =AVERAGE('Monthly Headcount'!E102,'Monthly Headcount'!E133,'Monthly Headcount'!E164) -> 134.33333 | F36: =E36/E35 -> 0.22401334 | G36: =AVERAGE('Monthly Headcount'!G102,'Monthly Headcount'!G133,'Monthly Headcount'!G164) -> 45.666667 | H36: =G36/G35 -> 0.20417288 | I36: =AVERAGE('Monthly Headcount'!I102,'Monthly Headcount'!I133,'Monthly Headcount'!I164) -> 64.666667 | J36: =I36/I35 -> 0.29085457 | K36: =AVERAGE('Monthly Headcount'!K102,'Monthly Headcount'!K133,'Monthly Headcount'!K164) -> 14.333333 | L36: =K36/K35 -> 0.39090909 | M36: =AVERAGE('Monthly Headcount'!M102,'Monthly Headcount'!M133,'Monthly Headcount'!M164) -> 16 | N36: =M36/M35 -> 0.27586207 | O36: =AVERAGE('Monthly Headcount'!O102,'Monthly Headcount'!O133,'Monthly Headcount'!O164) -> 17.666667 | P36: =O36/O35 -> 0.53535354
B37: Male | C37: =SUM(E37,G37,I37,K37,M37,O37) -> 880.66667 | D37: =C37/C35 -> 0.75056818 | E37: =AVERAGE('Monthly Headcount'!E103,'Monthly Headcount'!E134,'Monthly Headcount'!E165) -> 465.33333 | F37: =E37/E35 -> 0.77598666 | G37: =AVERAGE('Monthly Headcount'!G103,'Monthly Headcount'!G134,'Monthly Headcount'!G165) -> 178 | H37: =G37/G35 -> 0.79582712 | I37: =AVERAGE('Monthly Headcount'!I103,'Monthly Headcount'!I134,'Monthly Headcount'!I165) -> 157.66667 | J37: =I37/I35 -> 0.70914543 | K37: =AVERAGE('Monthly Headcount'!K103,'Monthly Headcount'!K134,'Monthly Headcount'!K165) -> 22.333333 | L37: =K37/K35 -> 0.60909091 | M37: =AVERAGE('Monthly Headcount'!M103,'Monthly Headcount'!M134,'Monthly Headcount'!M165) -> 42 | N37: =M37/M35 -> 0.72413793 | O37: =AVERAGE('Monthly Headcount'!O103,'Monthly Headcount'!O134,'Monthly Headcount'!O165) -> 15.333333 | P37: =O37/O35 -> 0.46464646
B38: Nationals | C38: =SUM(E38,G38,I38,K38,M38,O38) -> 1055.3333 | D38: =C38/C35 -> 0.89943182 | E38: =AVERAGE('Monthly Headcount'!E104,'Monthly Headcount'!E135,'Monthly Headcount'!E166) -> 517.33333 | F38: =E38/E35 -> 0.8627015 | G38: =AVERAGE('Monthly Headcount'!G104,'Monthly Headcount'!G135,'Monthly Headcount'!G166) -> 213 | H38: =G38/G35 -> 0.95230999 | I38: =AVERAGE('Monthly Headcount'!I104,'Monthly Headcount'!I135,'Monthly Headcount'!I166) -> 207.33333 | J38: =I38/I35 -> 0.93253373 | K38: =AVERAGE('Monthly Headcount'!K104,'Monthly Headcount'!K135,'Monthly Headcount'!K166) -> 33 | L38: =K38/K35 -> 0.9 | M38: =AVERAGE('Monthly Headcount'!M104,'Monthly Headcount'!M135,'Monthly Headcount'!M166) -> 52.666667 | N38: =M38/M35 -> 0.90804598 | O38: =AVERAGE('Monthly Headcount'!O104,'Monthly Headcount'!O135,'Monthly Headcount'!O166) -> 32 | P38: =O38/O35 -> 0.96969697
B39: Expatriates | C39: =SUM(E39,G39,I39,K39,M39,O39) -> 118.66667 | D39: =C39/C35 -> 0.10113636 | E39: =AVERAGE('Monthly Headcount'!E105,'Monthly Headcount'!E136,'Monthly Headcount'!E167) -> 82.333333 | F39: =E39/E35 -> 0.1372985 | G39: =AVERAGE('Monthly Headcount'!G105,'Monthly Headcount'!G136,'Monthly Headcount'!G167) -> 10.666667 | H39: =G39/G35 -> 0.047690015 | I39: =AVERAGE('Monthly Headcount'!I105,'Monthly Headcount'!I136,'Monthly Headcount'!I167) -> 15 | J39: =I39/I35 -> 0.067466267 | K39: =AVERAGE('Monthly Headcount'!K105,'Monthly Headcount'!K136,'Monthly Headcount'!K167) -> 3.6666667 | L39: =K39/K35 -> 0.1 | M39: =AVERAGE('Monthly Headcount'!M105,'Monthly Headcount'!M136,'Monthly Headcount'!M167) -> 6 | N39: =M39/M35 -> 0.10344828 | O39: =AVERAGE('Monthly Headcount'!O105,'Monthly Headcount'!O136,'Monthly Headcount'!O167) -> 1 | P39: =O39/O35 -> 0.03030303
B40: Management | C40: =SUM(E40,G40,I40,K40,M40,O40) -> 255.33333 | D40: =C40/C35 -> 0.21761364 | E40: =AVERAGE('Monthly Headcount'!E106,'Monthly Headcount'!E137,'Monthly Headcount'!E168) -> 122.33333 | F40: =E40/E35 -> 0.20400222 | G40: =AVERAGE('Monthly Headcount'!G106,'Monthly Headcount'!G137,'Monthly Headcount'!G168) -> 57.333333 | H40: =G40/G35 -> 0.25633383 | I40: =AVERAGE('Monthly Headcount'!I106,'Monthly Headcount'!I137,'Monthly Headcount'!I168) -> 41.666667 | J40: =I40/I35 -> 0.1874063 | K40: =AVERAGE('Monthly Headcount'!K106,'Monthly Headcount'!K137,'Monthly Headcount'!K168) -> 11 | L40: =K40/K35 -> 0.3 | M40: =AVERAGE('Monthly Headcount'!M106,'Monthly Headcount'!M137,'Monthly Headcount'!M168) -> 16 | N40: =M40/M35 -> 0.27586207 | O40: =AVERAGE('Monthly Headcount'!O106,'Monthly Headcount'!O137,'Monthly Headcount'!O168) -> 7 | P40: =O40/O35 -> 0.21212121
B41: Female in Management | C41: =SUM(E41,G41,I41,K41,M41,O41) -> 46 | D41: =C41/C40 -> 0.18015666 | E41: =AVERAGE('Monthly Headcount'!E107,'Monthly Headcount'!E138,'Monthly Headcount'!E169) -> 21 | F41: =E41/E40 -> 0.17166213 | G41: =AVERAGE('Monthly Headcount'!G107,'Monthly Headcount'!G138,'Monthly Headcount'!G169) -> 8.6666667 | H41: =G41/G40 -> 0.15116279 | I41: =AVERAGE('Monthly Headcount'!I107,'Monthly Headcount'!I138,'Monthly Headcount'!I169) -> 7.3333333 | J41: =I41/I40 -> 0.176 | K41: =AVERAGE('Monthly Headcount'!K107,'Monthly Headcount'!K138,'Monthly Headcount'!K169) -> 3 | L41: =K41/K40 -> 0.27272727 | M41: =AVERAGE('Monthly Headcount'!M107,'Monthly Headcount'!M138,'Monthly Headcount'!M169) -> 4 | N41: =M41/M40 -> 0.25 | O41: =AVERAGE('Monthly Headcount'!O107,'Monthly Headcount'!O138,'Monthly Headcount'!O169) -> 2 | P41: =O41/O40 -> 0.28571429
B42: Below 40 years of age | C42: =SUM(E42,G42,I42,K42,M42,O42) -> 927.33333 | D42: =C42/C35 -> 0.79034091 | E42: =AVERAGE('Monthly Headcount'!E108,'Monthly Headcount'!E139,'Monthly Headcount'!E170) -> 462 | F42: =E42/E35 -> 0.77042802 | G42: =AVERAGE('Monthly Headcount'!G108,'Monthly Headcount'!G139,'Monthly Headcount'!G170) -> 178.33333 | H42: =G42/G35 -> 0.79731744 | I42: =AVERAGE('Monthly Headcount'!I108,'Monthly Headcount'!I139,'Monthly Headcount'!I170) -> 182.33333 | J42: =I42/I35 -> 0.82008996 | K42: =AVERAGE('Monthly Headcount'!K108,'Monthly Headcount'!K139,'Monthly Headcount'!K170) -> 31.666667 | L42: =K42/K35 -> 0.86363636 | M42: =AVERAGE('Monthly Headcount'!M108,'Monthly Headcount'!M139,'Monthly Headcount'!M170) -> 47 | N42: =M42/M35 -> 0.81034483 | O42: =AVERAGE('Monthly Headcount'!O108,'Monthly Headcount'!O139,'Monthly Headcount'!O170) -> 26 | P42: =O42/O35 -> 0.78787879
B43: Atleast 40 years of age | C43: =SUM(E43,G43,I43,K43,M43,O43) -> 246 | D43: =C43/C35 -> 0.20965909 | E43: =AVERAGE('Monthly Headcount'!E109,'Monthly Headcount'!E140,'Monthly Headcount'!E171) -> 137.66667 | F43: =E43/E35 -> 0.22957198 | G43: =AVERAGE('Monthly Headcount'!G109,'Monthly Headcount'!G140,'Monthly Headcount'!G171) -> 45.333333 | H43: =G43/G35 -> 0.20268256 | I43: =AVERAGE('Monthly Headcount'!I109,'Monthly Headcount'!I140,'Monthly Headcount'!I171) -> 40 | J43: =I43/I35 -> 0.17991004 | K43: =AVERAGE('Monthly Headcount'!K109,'Monthly Headcount'!K140,'Monthly Headcount'!K171) -> 5 | L43: =K43/K35 -> 0.13636364 | M43: =AVERAGE('Monthly Headcount'!M109,'Monthly Headcount'!M140,'Monthly Headcount'!M171) -> 11 | N43: =M43/M35 -> 0.18965517 | O43: =AVERAGE('Monthly Headcount'!O109,'Monthly Headcount'!O140,'Monthly Headcount'!O171) -> 7 | P43: =O43/O35 -> 0.21212121
B44: Less than 5 years with Abacus | C44: =SUM(E44,G44,I44,K44,M44,O44) -> 693 | D44: =C44/C35 -> 0.590625 | E44: =AVERAGE('Monthly Headcount'!E110,'Monthly Headcount'!E141,'Monthly Headcount'!E172) -> 367.33333 | F44: =E44/E35 -> 0.61256253 | G44: =AVERAGE('Monthly Headcount'!G110,'Monthly Headcount'!G141,'Monthly Headcount'!G172) -> 98.666667 | H44: =G44/G35 -> 0.44113264 | I44: =AVERAGE('Monthly Headcount'!I110,'Monthly Headcount'!I141,'Monthly Headcount'!I172) -> 145 | J44: =I44/I35 -> 0.65217391 | K44: =AVERAGE('Monthly Headcount'!K110,'Monthly Headcount'!K141,'Monthly Headcount'!K172) -> 28 | L44: =K44/K35 -> 0.76363636 | M44: =AVERAGE('Monthly Headcount'!M110,'Monthly Headcount'!M141,'Monthly Headcount'!M172) -> 29 | N44: =M44/M35 -> 0.5 | O44: =AVERAGE('Monthly Headcount'!O110,'Monthly Headcount'!O141,'Monthly Headcount'!O172) -> 25 | P44: =O44/O35 -> 0.75757576
B45: Atleast 5 years with Abacus | C45: =SUM(E45,G45,I45,K45,M45,O45) -> 480.33333 | D45: =C45/C35 -> 0.409375 | E45: =AVERAGE('Monthly Headcount'!E111,'Monthly Headcount'!E142,'Monthly Headcount'!E173) -> 232.33333 | F45: =E45/E35 -> 0.38743747 | G45: =AVERAGE('Monthly Headcount'!G111,'Monthly Headcount'!G142,'Monthly Headcount'!G173) -> 125 | H45: =G45/G35 -> 0.55886736 | I45: =AVERAGE('Monthly Headcount'!I111,'Monthly Headcount'!I142,'Monthly Headcount'!I173) -> 77.333333 | J45: =I45/I35 -> 0.34782609 | K45: =AVERAGE('Monthly Headcount'!K111,'Monthly Headcount'!K142,'Monthly Headcount'!K173) -> 8.6666667 | L45: =K45/K35 -> 0.23636364 | M45: =AVERAGE('Monthly Headcount'!M111,'Monthly Headcount'!M142,'Monthly Headcount'!M173) -> 29 | N45: =M45/M35 -> 0.5 | O45: =AVERAGE('Monthly Headcount'!O111,'Monthly Headcount'!O142,'Monthly Headcount'!O173) -> 8 | P45: =O45/O35 -> 0.24242424
B46: Total New hires | C46: =SUM(E46,G46,I46,K46,M46,O46) -> 41.833333 | D46: =SUM(D47:D49) -> 0.034803106 | E46: =SUM(E47:E49) -> 18.666667 | F46: =SUM(F47:F49) -> 1 | G46: =SUM(G47:G49) -> 11 | H46: =SUM(H47:H49) -> 1 | I46: =SUM(I47:I49) -> 8 | J46: =SUM(J47:J49) -> 1 | K46: =SUM(K47:K49) -> 2.6666667 | ... P46: =SUM(P47:P49) -> 1
B47: New hires at EXCO | C47: =SUM(E47,G47,I47,K47,M47,O47) -> 0 | D47: =C47/$C$6 -> 0 | E47: =AVERAGE('Monthly Headcount'!E113,'Monthly Headcount'!E144,'Monthly Headcount'!E175) -> 0 | F47: =E47/E46 -> 0 | G47: =AVERAGE('Monthly Headcount'!G113,'Monthly Headcount'!G144,'Monthly Headcount'!G175) -> 0 | H47: 0 | I47: =AVERAGE('Monthly Headcount'!I113,'Monthly Headcount'!I144,'Monthly Headcount'!I175) -> 0 | J47: 0 | K47: =AVERAGE('Monthly Headcount'!K113,'Monthly Headcount'!K144,'Monthly Headcount'!K175) -> 0 | L47: 0 | M47: =AVERAGE('Monthly Headcount'!M113,'Monthly Headcount'!M144,'Monthly Headcount'!M175) -> 0 | N47: 0 | O47: =AVERAGE('Monthly Headcount'!O113,'Monthly Headcount'!O144,'Monthly Headcount'!O175) -> 0 | P47: 0
B48: New hires at EXCO - 1&2 | C48: =SUM(E48,G48,I48,K48,M48,O48) -> 9 | D48: =C48/$C$6 -> 0.0074875208 | E48: =AVERAGE('Monthly Headcount'!E50,'Monthly Headcount'!E81,'Monthly Headcount'!E112) -> 9 | F48: =E48/E46 -> 0.48214286 | G48: =AVERAGE('Monthly Headcount'!G114,'Monthly Headcount'!G145,'Monthly Headcount'!G176) -> 0 | H48: =G48/G46 -> 0 | I48: =AVERAGE('Monthly Headcount'!I114,'Monthly Headcount'!I145,'Monthly Headcount'!I176) -> 0 | J48: =I48/I46 -> 0 | K48: =AVERAGE('Monthly Headcount'!K114,'Monthly Headcount'!K145,'Monthly Headcount'!K176) -> 0 | L48: - | M48: =AVERAGE('Monthly Headcount'!M114,'Monthly Headcount'!M145,'Monthly Headcount'!M176) -> 0 | N48: =M48/M46 -> 0 | O48: =AVERAGE('Monthly Headcount'!O114,'Monthly Headcount'!O145,'Monthly Headcount'!O176) -> 0 | P48: =O48/O46 -> 0
B49: New hires at Other Levels | C49: =SUM(E49,G49,I49,K49,M49,O49) -> 32.833333 | D49: =C49/$C$6 -> 0.027315585 | E49: =AVERAGE('Monthly Headcount'!E115,'Monthly Headcount'!E146,'Monthly Headcount'!E177) -> 9.6666667 | F49: =E49/E46 -> 0.51785714 | G49: =AVERAGE('Monthly Headcount'!G115,'Monthly Headcount'!G146,'Monthly Headcount'!G177) -> 11 | H49: =G49/G46 -> 1 | I49: =AVERAGE('Monthly Headcount'!I115,'Monthly Headcount'!I146,'Monthly Headcount'!I177) -> 8 | J49: =I49/I46 -> 1 | K49: =AVERAGE('Monthly Headcount'!K115,'Monthly Headcount'!K146,'Monthly Headcount'!K177) -> 2.6666667 | L49: =K49/K46 -> 1 | M49: =AVERAGE('Monthly Headcount'!M115,'Monthly Headcount'!M146,'Monthly Headcount'!M177) -> 0.5 | N49: =M49/M46 -> 1 | O49: =AVERAGE('Monthly Headcount'!O115,'Monthly Headcount'!O146,'Monthly Headcount'!O177) -> 1 | P49: =O49/O46 -> 1
B50: Total Exits | C50: =SUM(E50,G50,I50,K50,M50,O50) -> 24.333333 | D50: =SUM(D51:D53) -> 0.020244038 | E50: =SUM(E51:E53) -> 9.3333333 | F50: =SUM(F51:F53) -> 0.015135135 | G50: =SUM(G51:G53) -> 4.3333333 | H50: =SUM(H51:H53) -> 0.019145803 | I50: =SUM(I51:I53) -> 5.6666667 | J50: =SUM(J51:J53) -> 0.025036819 | K50: =SUM(K51:K53) -> 1.5 | ... P50: =SUM(P51:P53) -> 0.089108911
B51: Exits at EXCO | C51: =SUM(E51,G51,I51,K51,M51,O51) -> 0.33333333 | D51: =C51/$C$6 -> 0.00027731559 | E51: =AVERAGE('Monthly Headcount'!E117,'Monthly Headcount'!E148,'Monthly Headcount'!E179) -> 0.33333333 | F51: =E51/$E$6 -> 0.00054054054 | G51: =AVERAGE('Monthly Headcount'!G117,'Monthly Headcount'!G148,'Monthly Headcount'!G179) -> 0 | H51: =G51/$G$6 -> 0 | I51: =AVERAGE('Monthly Headcount'!I117,'Monthly Headcount'!I148,'Monthly Headcount'!I179) -> 0 | J51: =I51/$I$6 -> 0 | K51: =AVERAGE('Monthly Headcount'!K117,'Monthly Headcount'!K148,'Monthly Headcount'!K179) -> 0 | L51: =K51/$K$6 -> 0 | M51: =AVERAGE('Monthly Headcount'!M117,'Monthly Headcount'!M148,'Monthly Headcount'!M179) -> 0 | N51: =M51/$M$6 -> 0 | O51: =AVERAGE('Monthly Headcount'!O117,'Monthly Headcount'!O148,'Monthly Headcount'!O179) -> 0 | P51: =O51/$O$6 -> 0
B52: Exits at EXCO - 1&2 | C52: =SUM(E52,G52,I52,K52,M52,O52) -> 0.66666667 | D52: =C52/$C$6 -> 0.00055463117 | E52: =AVERAGE('Monthly Headcount'!E118,'Monthly Headcount'!E149,'Monthly Headcount'!E180) -> 0.66666667 | F52: =E52/$E$6 -> 0.0010810811 | G52: =AVERAGE('Monthly Headcount'!G118,'Monthly Headcount'!G149,'Monthly Headcount'!G180) -> 0 | H52: =G52/$G$6 -> 0 | I52: =AVERAGE('Monthly Headcount'!I118,'Monthly Headcount'!I149,'Monthly Headcount'!I180) -> 0 | J52: =I52/$I$6 -> 0 | K52: =AVERAGE('Monthly Headcount'!K118,'Monthly Headcount'!K149,'Monthly Headcount'!K180) -> 0 | L52: =K52/$K$6 -> 0 | M52: =AVERAGE('Monthly Headcount'!M118,'Monthly Headcount'!M149,'Monthly Headcount'!M180) -> 0 | N52: =M52/$M$6 -> 0 | O52: =AVERAGE('Monthly Headcount'!O118,'Monthly Headcount'!O149,'Monthly Headcount'!O180) -> 0 | P52: =O52/$O$6 -> 0
B53: Exits at Other Levels | C53: =SUM(E53,G53,I53,K53,M53,O53) -> 23.333333 | D53: =C53/$C$6 -> 0.019412091 | E53: =AVERAGE('Monthly Headcount'!E119,'Monthly Headcount'!E150,'Monthly Headcount'!E181) -> 8.3333333 | F53: =E53/$E$6 -> 0.013513514 | G53: =AVERAGE('Monthly Headcount'!G119,'Monthly Headcount'!G150,'Monthly Headcount'!G181) -> 4.3333333 | H53: =G53/$G$6 -> 0.019145803 | I53: =AVERAGE('Monthly Headcount'!I119,'Monthly Headcount'!I150,'Monthly Headcount'!I181) -> 5.6666667 | J53: =I53/$I$6 -> 0.025036819 | K53: =AVERAGE('Monthly Headcount'!K119,'Monthly Headcount'!K150,'Monthly Headcount'!K181) -> 1.5 | L53: =K53/$K$6 -> 0.038135593 | M53: =AVERAGE('Monthly Headcount'!M119,'Monthly Headcount'!M150,'Monthly Headcount'!M181) -> 0.5 | N53: =M53/$M$6 -> 0.0083798883 | O53: =AVERAGE('Monthly Headcount'!O119,'Monthly Headcount'!O150,'Monthly Headcount'!O181) -> 3 | P53: =O53/$O$6 -> 0.089108911
B54: Total Internal Movements | C54: =SUM(E54,G54,I54,K54,M54,O54) -> 14.666667 | E54: =SUM(E55:E56) -> 6 | F54: =SUM(F55:F56) -> 0 | G54: =SUM(G55:G56) -> 1.3333333 | H54: =SUM(H55:H56) -> 0 | I54: =SUM(I55:I56) -> 7.3333333 | J54: =SUM(J55:J56) -> 0 | K54: =SUM(K55:K56) -> 0 | L54: =SUM(L55:L56) -> 0 | ... P54: =SUM(P55:P56) -> 0
B55: Promotions | C55: =SUM(E55,G55,I55,K55,M55,O55) -> 8.3333333 | E55: =AVERAGE('Monthly Headcount'!E121,'Monthly Headcount'!E152,'Monthly Headcount'!E183) -> 1 | G55: =AVERAGE('Monthly Headcount'!G121,'Monthly Headcount'!G152,'Monthly Headcount'!G183) -> 1 | I55: =AVERAGE('Monthly Headcount'!I57,'Monthly Headcount'!I88,'Monthly Headcount'!I119) -> 6.3333333 | K55: =AVERAGE('Monthly Headcount'!K121,'Monthly Headcount'!K152,'Monthly Headcount'!K183) -> 0 | M55: =AVERAGE('Monthly Headcount'!M121,'Monthly Headcount'!M152,'Monthly Headcount'!M183) -> 0 | O55: =AVERAGE('Monthly Headcount'!O121,'Monthly Headcount'!O152,'Monthly Headcount'!O183) -> 0
B56: Transfers | C56: =SUM(E56,G56,I56,K56,M56,O56) -> 6.3333333 | E56: =AVERAGE('Monthly Headcount'!E122,'Monthly Headcount'!E153,'Monthly Headcount'!E184) -> 5 | G56: =AVERAGE('Monthly Headcount'!G58,'Monthly Headcount'!G89,'Monthly Headcount'!G120) -> 0.33333333 | I56: =AVERAGE('Monthly Headcount'!I122,'Monthly Headcount'!I153,'Monthly Headcount'!I184) -> 1 | K56: =AVERAGE('Monthly Headcount'!K122,'Monthly Headcount'!K153,'Monthly Headcount'!K184) -> 0 | M56: =AVERAGE('Monthly Headcount'!M122,'Monthly Headcount'!M153,'Monthly Headcount'!M184) -> 0 | O56: =AVERAGE('Monthly Headcount'!O122,'Monthly Headcount'!O153,'Monthly Headcount'!O184) -> 0
B57: Principals | C57: =SUM(E57,G57,I57,K57,M57,O57) -> 388 | D57: =C57/$C$6 -> 0.32279534 | E57: =E58+E59 -> 308 | F57: =E57/C57 -> 0.79381443 | G57: =G58+G59 -> 0 | H57: =G57/C57 -> 0 | I57: =I58+I59 -> 32.333333 | J57: =I57/C57 -> 0.083333333 | K57: =K58+K59 -> 34.333333 | L57: =K57/E57 -> 0.11147186 | M57: =M58+M59 -> 4.6666667 | N57: =M57/C57 -> 0.012027491 | O57: =O58+O59 -> 8.6666667 | P57: =O57/C57 -> 0.02233677
B58: Female | C58: =SUM(E58,G58,I58,K58,M58,O58) -> 98.666667 | D58: =C58/C57 -> 0.25429553 | E58: =AVERAGE('Monthly Headcount'!E124,'Monthly Headcount'!E155,'Monthly Headcount'!E186) -> 69.333333 | F58: =E58/E57 -> 0.22510823 | G58: =AVERAGE('Monthly Headcount'!G124,'Monthly Headcount'!G155,'Monthly Headcount'!G186) -> 0 | H58: 0 | I58: =AVERAGE('Monthly Headcount'!I124,'Monthly Headcount'!I155,'Monthly Headcount'!I186) -> 10.333333 | J58: =I58/I57 -> 0.31958763 | K58: =AVERAGE('Monthly Headcount'!K124,'Monthly Headcount'!K155,'Monthly Headcount'!K186) -> 14 | L58: =K58/K57 -> 0.40776699 | M58: =AVERAGE('Monthly Headcount'!M124,'Monthly Headcount'!M155,'Monthly Headcount'!M186) -> 1 | N58: =M58/M57 -> 0.21428571 | O58: =AVERAGE('Monthly Headcount'!O124,'Monthly Headcount'!O155,'Monthly Headcount'!O186) -> 4 | P58: 0
B59: Male | C59: =SUM(E59,G59,I59,K59,M59,O59) -> 289.33333 | D59: =C59/C57 -> 0.74570447 | E59: =AVERAGE('Monthly Headcount'!E125,'Monthly Headcount'!E156,'Monthly Headcount'!E187) -> 238.66667 | F59: =E59/E57 -> 0.77489177 | G59: =AVERAGE('Monthly Headcount'!G125,'Monthly Headcount'!G156,'Monthly Headcount'!G187) -> 0 | H59: 0 | I59: =AVERAGE('Monthly Headcount'!I125,'Monthly Headcount'!I156,'Monthly Headcount'!I187) -> 22 | J59: =I59/I57 -> 0.68041237 | K59: =AVERAGE('Monthly Headcount'!K125,'Monthly Headcount'!K156,'Monthly Headcount'!K187) -> 20.333333 | L59: =K59/K57 -> 0.59223301 | M59: =AVERAGE('Monthly Headcount'!M125,'Monthly Headcount'!M156,'Monthly Headcount'!M187) -> 3.6666667 | N59: =M59/M57 -> 0.78571429 | O59: =AVERAGE('Monthly Headcount'!O125,'Monthly Headcount'!O156,'Monthly Headcount'!O187) -> 4.6666667 | P59: 0
B60: Casuals/Contractors | C60: =SUM(E60,G60,I60,K60,M60,O60) -> 578.66667 | D60: =C60/C34 -> 0.27040498 | E60: =E61+E62 -> 42 | F60: =E60/C60 -> 0.072580645 | G60: =G61+G62 -> 536.66667 | H60: =G60/C60 -> 0.92741935 | I60: =I61+I62 -> 0 | J60: 0 | K60: =K61+K62 -> 0 | L60: =K60/C60 -> 0 | M60: =M61+M62 -> 0 | N60: 0 | O60: =O61+O62 -> 0 | P60: 0
B61: Female | C61: =SUM(E61,G61,I61,K61,M61,O61) -> 242.66667 | D61: =C61/C60 -> 0.41935484 | E61: =AVERAGE('Monthly Headcount'!E127,'Monthly Headcount'!E158,'Monthly Headcount'!E189) -> 6 | F61: =E61/E60 -> 0.14285714 | G61: =AVERAGE('Monthly Headcount'!G127,'Monthly Headcount'!G158,'Monthly Headcount'!G189) -> 236.66667 | H61: =G61/G60 -> 0.44099379 | I61: =AVERAGE('Monthly Headcount'!I127,'Monthly Headcount'!I158,'Monthly Headcount'!I189) -> 0 | J61: 0 | K61: =AVERAGE('Monthly Headcount'!K127,'Monthly Headcount'!K158,'Monthly Headcount'!K189) -> 0 | L61: 0 | M61: =AVERAGE('Monthly Headcount'!M127,'Monthly Headcount'!M158,'Monthly Headcount'!M189) -> 0 | N61: 0 | O61: =AVERAGE('Monthly Headcount'!O127,'Monthly Headcount'!O158,'Monthly Headcount'!O189) -> 0 | P61: 0
B62: Male | C62: =SUM(E62,G62,I62,K62,M62,O62) -> 336 | D62: =C62/C60 -> 0.58064516 | E62: =AVERAGE('Monthly Headcount'!E128,'Monthly Headcount'!E159,'Monthly Headcount'!E190) -> 36 | F62: =E62/E60 -> 0.85714286 | G62: =AVERAGE('Monthly Headcount'!G128,'Monthly Headcount'!G159,'Monthly Headcount'!G190) -> 300 | H62: =G62/G60 -> 0.55900621 | I62: =AVERAGE('Monthly Headcount'!I128,'Monthly Headcount'!I159,'Monthly Headcount'!I190) -> 0 | J62: 0 | K62: =AVERAGE('Monthly Headcount'!K128,'Monthly Headcount'!K159,'Monthly Headcount'!K190) -> 0 | L62: 0 | M62: =AVERAGE('Monthly Headcount'!M128,'Monthly Headcount'!M159,'Monthly Headcount'!M190) -> 0 | N62: 0 | O62: =AVERAGE('Monthly Headcount'!O128,'Monthly Headcount'!O159,'Monthly Headcount'!O190) -> 0 | P62: 0
A64: Q3 | B64: Overall Headcount | C64: =SUM(E64,G64,I64,K64,M64,O64) -> 2336.3333 | D64: =SUM(F64,H64,J64,L64,N64,P64) -> 1 | E64: =SUM(E65,E87,E90) -> 982.66667 | F64: =E64/C64 -> 0.42060208 | G64: =SUM(G65,G87,G90) -> 917.66667 | H64: =G64/C64 -> 0.39278071 | I64: =SUM(I65,I87,I90) -> 257.66667 | J64: =I64/C64 -> 0.11028677 | K64: =SUM(K65,K87,K90) -> 73.666667 | L64: =K64/C64 -> 0.031530889 | M64: =SUM(M65,M87,M90) -> 62.666667 | N64: =M64/C64 -> 0.026822657 | O64: =SUM(O65,O87,O90) -> 42 | P64: =O64/C64 -> 0.017976887
B65: Direct Staff | C65: =SUM(E65,G65,I65,K65,M65,O65) -> 1219 | D65: =C65/C64 -> 0.52175774 | E65: =E66+E67 -> 602.33333 | F65: =E65/C65 -> 0.49412086 | G65: =G66+G67 -> 262.66667 | H65: =G65/C65 -> 0.21547717 | I65: =I66+I67 -> 224.33333 | J65: =I65/C65 -> 0.18403063 | K65: =K66+K67 -> 39 | L65: =K65/C65 -> 0.031993437 | M65: =M66+M67 -> 58.666667 | N65: =M65/C65 -> 0.04812688 | O65: =O66+O67 -> 32 | P65: =O65/C65 -> 0.026251025
B66: Female | C66: =SUM(E66,G66,I66,K66,M66,O66) -> 288.66667 | D66: =C66/C65 -> 0.23680613 | E66: =AVERAGE('Monthly Headcount'!E195,'Monthly Headcount'!E226,'Monthly Headcount'!E257) -> 126.66667 | F66: =E66/E65 -> 0.2102933 | G66: =AVERAGE('Monthly Headcount'!G195,'Monthly Headcount'!G226,'Monthly Headcount'!G257) -> 49 | H66: =G66/G65 -> 0.18654822 | I66: =AVERAGE('Monthly Headcount'!I195,'Monthly Headcount'!I226,'Monthly Headcount'!I257) -> 62.333333 | J66: =I66/I65 -> 0.27786033 | K66: =AVERAGE('Monthly Headcount'!K195,'Monthly Headcount'!K226,'Monthly Headcount'!K257) -> 17 | L66: =K66/K65 -> 0.43589744 | M66: =AVERAGE('Monthly Headcount'!M195,'Monthly Headcount'!M226,'Monthly Headcount'!M257) -> 16.666667 | N66: =M66/M65 -> 0.28409091 | O66: =AVERAGE('Monthly Headcount'!O195,'Monthly Headcount'!O226,'Monthly Headcount'!O257) -> 17 | P66: =O66/O65 -> 0.53125
B67: Male | C67: =SUM(E67,G67,I67,K67,M67,O67) -> 930.33333 | D67: =C67/C65 -> 0.76319387 | E67: =AVERAGE('Monthly Headcount'!E196,'Monthly Headcount'!E227,'Monthly Headcount'!E258) -> 475.66667 | F67: =E67/E65 -> 0.7897067 | G67: =AVERAGE('Monthly Headcount'!G196,'Monthly Headcount'!G227,'Monthly Headcount'!G258) -> 213.66667 | H67: =G67/G65 -> 0.81345178 | I67: =AVERAGE('Monthly Headcount'!I196,'Monthly Headcount'!I227,'Monthly Headcount'!I258) -> 162 | J67: =I67/I65 -> 0.72213967 | K67: =AVERAGE('Monthly Headcount'!K196,'Monthly Headcount'!K227,'Monthly Headcount'!K258) -> 22 | L67: =K67/K65 -> 0.56410256 | M67: =AVERAGE('Monthly Headcount'!M196,'Monthly Headcount'!M227,'Monthly Headcount'!M258) -> 42 | N67: =M67/M65 -> 0.71590909 | O67: =AVERAGE('Monthly Headcount'!O196,'Monthly Headcount'!O227,'Monthly Headcount'!O258) -> 15 | P67: =O67/O65 -> 0.46875
B68: Nationals | C68: =SUM(E68,G68,I68,K68,M68,O68) -> 1102.6667 | D68: =C68/C65 -> 0.90456658 | E68: =AVERAGE('Monthly Headcount'!E197,'Monthly Headcount'!E228,'Monthly Headcount'!E259) -> 522.66667 | F68: =E68/E65 -> 0.86773658 | G68: =AVERAGE('Monthly Headcount'!G197,'Monthly Headcount'!G228,'Monthly Headcount'!G259) -> 251.66667 | H68: =G68/G65 -> 0.95812183 | I68: =AVERAGE('Monthly Headcount'!I197,'Monthly Headcount'!I228,'Monthly Headcount'!I259) -> 209.33333 | J68: =I68/I65 -> 0.93313522 | K68: =AVERAGE('Monthly Headcount'!K197,'Monthly Headcount'!K228,'Monthly Headcount'!K259) -> 35 | L68: =K68/K65 -> 0.8974359 | M68: =AVERAGE('Monthly Headcount'!M197,'Monthly Headcount'!M228,'Monthly Headcount'!M259) -> 53 | N68: =M68/M65 -> 0.90340909 | O68: =AVERAGE('Monthly Headcount'!O197,'Monthly Headcount'!O228,'Monthly Headcount'!O259) -> 31 | P68: =O68/O65 -> 0.96875
B69: Expatriates | C69: =SUM(E69,G69,I69,K69,M69,O69) -> 116.66667 | D69: =C69/C65 -> 0.095706864 | E69: =AVERAGE('Monthly Headcount'!E198,'Monthly Headcount'!E229,'Monthly Headcount'!E260) -> 79.666667 | F69: =E69/E65 -> 0.13226342 | G69: =AVERAGE('Monthly Headcount'!G198,'Monthly Headcount'!G229,'Monthly Headcount'!G260) -> 11 | H69: =G69/G65 -> 0.041878173 | I69: =AVERAGE('Monthly Headcount'!I198,'Monthly Headcount'!I229,'Monthly Headcount'!I260) -> 15 | J69: =I69/I65 -> 0.066864785 | K69: =AVERAGE('Monthly Headcount'!K198,'Monthly Headcount'!K229,'Monthly Headcount'!K260) -> 4 | L69: =K69/K65 -> 0.1025641 | M69: =AVERAGE('Monthly Headcount'!M198,'Monthly Headcount'!M229,'Monthly Headcount'!M260) -> 6 | N69: =M69/M65 -> 0.10227273 | O69: =AVERAGE('Monthly Headcount'!O198,'Monthly Headcount'!O229,'Monthly Headcount'!O260) -> 1 | P69: =O69/O65 -> 0.03125
B70: Management | C70: =SUM(E70,G70,I70,K70,M70,O70) -> 251.66667 | D70: =C70/C65 -> 0.20645338 | E70: =AVERAGE('Monthly Headcount'!E199,'Monthly Headcount'!E230,'Monthly Headcount'!E261) -> 122.33333 | F70: =E70/E65 -> 0.20309906 | G70: =AVERAGE('Monthly Headcount'!G199,'Monthly Headcount'!G230,'Monthly Headcount'!G261) -> 55 | H70: =G70/G65 -> 0.20939086 | I70: =AVERAGE('Monthly Headcount'!I199,'Monthly Headcount'!I230,'Monthly Headcount'!I261) -> 42.666667 | J70: =I70/I65 -> 0.19019316 | K70: =AVERAGE('Monthly Headcount'!K199,'Monthly Headcount'!K230,'Monthly Headcount'!K261) -> 9 | L70: =K70/K65 -> 0.23076923 | M70: =AVERAGE('Monthly Headcount'!M199,'Monthly Headcount'!M230,'Monthly Headcount'!M261) -> 16 | N70: =M70/M65 -> 0.27272727 | O70: =AVERAGE('Monthly Headcount'!O199,'Monthly Headcount'!O230,'Monthly Headcount'!O261) -> 6.6666667 | P70: =O70/O65 -> 0.20833333
B71: Female in Management | C71: =SUM(E71,G71,I71,K71,M71,O71) -> 39.333333 | D71: =C71/C70 -> 0.15629139 | E71: =AVERAGE('Monthly Headcount'!E200,'Monthly Headcount'!E231,'Monthly Headcount'!E262) -> 16.333333 | F71: =E71/E70 -> 0.13351499 | G71: =AVERAGE('Monthly Headcount'!G200,'Monthly Headcount'!G231,'Monthly Headcount'!G262) -> 8 | H71: =G71/G70 -> 0.14545455 | I71: =AVERAGE('Monthly Headcount'!I200,'Monthly Headcount'!I231,'Monthly Headcount'!I262) -> 6 | J71: =I71/I70 -> 0.140625 | K71: =AVERAGE('Monthly Headcount'!K200,'Monthly Headcount'!K231,'Monthly Headcount'!K262) -> 3 | L71: =K71/K70 -> 0.33333333 | M71: =AVERAGE('Monthly Headcount'!M200,'Monthly Headcount'!M231,'Monthly Headcount'!M262) -> 4 | N71: =M71/M70 -> 0.25 | O71: =AVERAGE('Monthly Headcount'!O200,'Monthly Headcount'!O231,'Monthly Headcount'!O262) -> 2 | P71: =O71/O70 -> 0.3
B72: Below 40 years of age | C72: =SUM(E72,G72,I72,K72,M72,O72) -> 985 | D72: =C72/C65 -> 0.80803938 | E72: =AVERAGE('Monthly Headcount'!E201,'Monthly Headcount'!E232,'Monthly Headcount'!E263) -> 464.66667 | F72: =E72/E65 -> 0.77144438 | G72: =AVERAGE('Monthly Headcount'!G201,'Monthly Headcount'!G232,'Monthly Headcount'!G263) -> 231.33333 | H72: =G72/G65 -> 0.88071066 | I72: =AVERAGE('Monthly Headcount'!I201,'Monthly Headcount'!I232,'Monthly Headcount'!I263) -> 184.33333 | J72: =I72/I65 -> 0.82169391 | K72: =AVERAGE('Monthly Headcount'!K201,'Monthly Headcount'!K232,'Monthly Headcount'!K263) -> 32 | L72: =K72/K65 -> 0.82051282 | M72: =AVERAGE('Monthly Headcount'!M201,'Monthly Headcount'!M232,'Monthly Headcount'!M263) -> 47.666667 | N72: =M72/M65 -> 0.8125 | O72: =AVERAGE('Monthly Headcount'!O201,'Monthly Headcount'!O232,'Monthly Headcount'!O263) -> 25 | P72: =O72/O65 -> 0.78125
B73: Atleast 40 years of age | C73: =SUM(E73,G73,I73,K73,M73,O73) -> 248.66667 | D73: =C73/C65 -> 0.20399234 | E73: =AVERAGE('Monthly Headcount'!E202,'Monthly Headcount'!E233,'Monthly Headcount'!E264) -> 137.66667 | F73: =E73/E65 -> 0.22855562 | G73: =AVERAGE('Monthly Headcount'!G202,'Monthly Headcount'!G233,'Monthly Headcount'!G264) -> 46 | H73: =G73/G65 -> 0.1751269 | I73: =AVERAGE('Monthly Headcount'!I202,'Monthly Headcount'!I233,'Monthly Headcount'!I264) -> 40 | J73: =I73/I65 -> 0.17830609 | K73: =AVERAGE('Monthly Headcount'!K202,'Monthly Headcount'!K233,'Monthly Headcount'!K264) -> 7 | L73: =K73/K65 -> 0.17948718 | M73: =AVERAGE('Monthly Headcount'!M202,'Monthly Headcount'!M233,'Monthly Headcount'!M264) -> 11 | N73: =M73/M65 -> 0.1875 | O73: =AVERAGE('Monthly Headcount'!O202,'Monthly Headcount'!O233,'Monthly Headcount'!O264) -> 7 | P73: =O73/O65 -> 0.21875
B74: Less than 5 years with Abacus | C74: =SUM(E74,G74,I74,K74,M74,O74) -> 748.66667 | D74: =C74/C65 -> 0.61416462 | E74: =AVERAGE('Monthly Headcount'!E203,'Monthly Headcount'!E234,'Monthly Headcount'!E265) -> 370.33333 | F74: =E74/E65 -> 0.61483121 | G74: =AVERAGE('Monthly Headcount'!G203,'Monthly Headcount'!G234,'Monthly Headcount'!G265) -> 144.33333 | H74: =G74/G65 -> 0.54949239 | I74: =AVERAGE('Monthly Headcount'!I203,'Monthly Headcount'!I234,'Monthly Headcount'!I265) -> 153.33333 | J74: =I74/I65 -> 0.68350669 | K74: =AVERAGE('Monthly Headcount'!K203,'Monthly Headcount'!K234,'Monthly Headcount'!K265) -> 29 | L74: =K74/K65 -> 0.74358974 | M74: =AVERAGE('Monthly Headcount'!M203,'Monthly Headcount'!M234,'Monthly Headcount'!M265) -> 27.666667 | N74: =M74/M65 -> 0.47159091 | O74: =AVERAGE('Monthly Headcount'!O203,'Monthly Headcount'!O234,'Monthly Headcount'!O265) -> 24 | P74: =O74/O65 -> 0.75
B75: Atleast 5 years with Abacus | C75: =SUM(E75,G75,I75,K75,M75,O75) -> 470.33333 | D75: =C75/C65 -> 0.38583538 | E75: =AVERAGE('Monthly Headcount'!E204,'Monthly Headcount'!E235,'Monthly Headcount'!E266) -> 232 | F75: =E75/E65 -> 0.38516879 | G75: =AVERAGE('Monthly Headcount'!G204,'Monthly Headcount'!G235,'Monthly Headcount'!G266) -> 118.33333 | H75: =G75/G65 -> 0.45050761 | I75: =AVERAGE('Monthly Headcount'!I204,'Monthly Headcount'!I235,'Monthly Headcount'!I266) -> 71 | J75: =I75/I65 -> 0.31649331 | K75: =AVERAGE('Monthly Headcount'!K204,'Monthly Headcount'!K235,'Monthly Headcount'!K266) -> 10 | L75: =K75/K65 -> 0.25641026 | M75: =AVERAGE('Monthly Headcount'!M204,'Monthly Headcount'!M235,'Monthly Headcount'!M266) -> 31 | N75: =M75/M65 -> 0.52840909 | O75: =AVERAGE('Monthly Headcount'!O204,'Monthly Headcount'!O235,'Monthly Headcount'!O266) -> 8 | P75: =O75/O65 -> 0.25
B76: Total New hires | C76: =SUM(E76,G76,I76,K76,M76,O76) -> 28.666667 | D76: =SUM(D77:D79) -> 1 | E76: =SUM(E77:E79) -> 12.833333 | F76: =SUM(F77:F79) -> 1 | G76: =SUM(G77:G79) -> 9.6666667 | H76: =SUM(H77:H79) -> 1 | I76: =SUM(I77:I79) -> 5.6666667 | J76: =SUM(J77:J79) -> 1 | K76: =SUM(K77:K79) -> 0 | ... P76: =SUM(P77:P79) -> 0
B77: New hires at EXCO | C77: =SUM(E77,G77,I77,K77,M77,O77) -> 0 | D77: =C77/C76 -> 0 | E77: =AVERAGE('Monthly Headcount'!E206,'Monthly Headcount'!E237,'Monthly Headcount'!E268) -> 0 | F77: =E77/E76 -> 0 | G77: =AVERAGE('Monthly Headcount'!G206,'Monthly Headcount'!G237,'Monthly Headcount'!G268) -> 0 | H77: 0 | I77: =AVERAGE('Monthly Headcount'!I206,'Monthly Headcount'!I237,'Monthly Headcount'!I268) -> 0 | J77: 0 | K77: =AVERAGE('Monthly Headcount'!K206,'Monthly Headcount'!K237,'Monthly Headcount'!K268) -> 0 | L77: 0 | M77: =AVERAGE('Monthly Headcount'!M206,'Monthly Headcount'!M237,'Monthly Headcount'!M268) -> 0 | N77: 0 | O77: =AVERAGE('Monthly Headcount'!O206,'Monthly Headcount'!O237,'Monthly Headcount'!O268) -> 0 | P77: 0
B78: New hires at EXCO - 1&2 | C78: =SUM(E78,G78,I78,K78,M78,O78) -> 0.5 | D78: =C78/C76 -> 0.01744186 | E78: =AVERAGE('Monthly Headcount'!E207,'Monthly Headcount'!E238,'Monthly Headcount'!E269) -> 0.5 | F78: =E78/E76 -> 0.038961039 | G78: =AVERAGE('Monthly Headcount'!G207,'Monthly Headcount'!G238,'Monthly Headcount'!G269) -> 0 | H78: =G78/G76 -> 0 | I78: =AVERAGE('Monthly Headcount'!I207,'Monthly Headcount'!I238,'Monthly Headcount'!I269) -> 0 | J78: =I78/I76 -> 0 | K78: =AVERAGE('Monthly Headcount'!K207,'Monthly Headcount'!K238,'Monthly Headcount'!K269) -> 0 | L78: - | M78: =AVERAGE('Monthly Headcount'!M207,'Monthly Headcount'!M238,'Monthly Headcount'!M269) -> 0 | N78: =M78/M76 -> 0 | O78: =AVERAGE('Monthly Headcount'!O207,'Monthly Headcount'!O238,'Monthly Headcount'!O269) -> 0
B79: New hires at Other Levels | C79: =SUM(E79,G79,I79,K79,M79,O79) -> 28.166667 | D79: =C79/C76 -> 0.98255814 | E79: =AVERAGE('Monthly Headcount'!E208,'Monthly Headcount'!E239,'Monthly Headcount'!E270) -> 12.333333 | F79: =E79/E76 -> 0.96103896 | G79: =AVERAGE('Monthly Headcount'!G208,'Monthly Headcount'!G239,'Monthly Headcount'!G270) -> 9.6666667 | H79: =G79/G76 -> 1 | I79: =AVERAGE('Monthly Headcount'!I208,'Monthly Headcount'!I239,'Monthly Headcount'!I270) -> 5.6666667 | J79: =I79/I76 -> 1 | K79: =AVERAGE('Monthly Headcount'!K208,'Monthly Headcount'!K239,'Monthly Headcount'!K270) -> 0 | M79: =AVERAGE('Monthly Headcount'!M208,'Monthly Headcount'!M239,'Monthly Headcount'!M270) -> 0.5 | N79: =M79/M76 -> 1 | O79: =AVERAGE('Monthly Headcount'!O208,'Monthly Headcount'!O239,'Monthly Headcount'!O270) -> 0
B80: Total Exits | C80: =SUM(E80,G80,I80,K80,M80,O80) -> 23.166667 | D80: =SUM(D81:D83) -> 0.019273433 | E80: =SUM(E81:E83) -> 11.833333 | F80: =SUM(F81:F83) -> 0.019189189 | G80: =SUM(G81:G83) -> 6.6666667 | H80: =SUM(H81:H83) -> 0.029455081 | I80: =SUM(I81:I83) -> 4.6666667 | J80: =SUM(J81:J83) -> 0.020618557 | K80: =SUM(K81:K83) -> 0 | ... P80: =SUM(P81:P83) -> 0
B81: Exits at EXCO | C81: =SUM(E81,G81,I81,K81,M81,O81) -> 0 | D81: =C81/$C$6 -> 0 | E81: =AVERAGE('Monthly Headcount'!E210,'Monthly Headcount'!E241,'Monthly Headcount'!E268) -> 0 | F81: =E81/$E$6 -> 0 | G81: =AVERAGE('Monthly Headcount'!G210,'Monthly Headcount'!G241,'Monthly Headcount'!G268) -> 0 | H81: =G81/$G$6 -> 0 | I81: =AVERAGE('Monthly Headcount'!I210,'Monthly Headcount'!I241,'Monthly Headcount'!I268) -> 0 | J81: =I81/$I$6 -> 0 | K81: =AVERAGE('Monthly Headcount'!K210,'Monthly Headcount'!K241,'Monthly Headcount'!K268) -> 0 | L81: =K81/$K$6 -> 0 | M81: =AVERAGE('Monthly Headcount'!M210,'Monthly Headcount'!M241,'Monthly Headcount'!M268) -> 0 | N81: =M81/$M$6 -> 0 | O81: =AVERAGE('Monthly Headcount'!O210,'Monthly Headcount'!O241,'Monthly Headcount'!O268) -> 0 | P81: =O81/$O$6 -> 0
B82: Exits at EXCO - 1&2 | C82: =SUM(E82,G82,I82,K82,M82,O82) -> 1.5 | D82: =C82/$C$6 -> 0.0012479201 | E82: =AVERAGE('Monthly Headcount'!E211,'Monthly Headcount'!E242,'Monthly Headcount'!E269) -> 1.5 | F82: =E82/$E$6 -> 0.0024324324 | G82: =AVERAGE('Monthly Headcount'!G211,'Monthly Headcount'!G242,'Monthly Headcount'!G269) -> 0 | H82: =G82/$G$6 -> 0 | I82: =AVERAGE('Monthly Headcount'!I211,'Monthly Headcount'!I242,'Monthly Headcount'!I269) -> 0 | J82: =I82/$I$6 -> 0 | K82: =AVERAGE('Monthly Headcount'!K211,'Monthly Headcount'!K242,'Monthly Headcount'!K269) -> 0 | L82: =K82/$K$6 -> 0 | M82: =AVERAGE('Monthly Headcount'!M211,'Monthly Headcount'!M242,'Monthly Headcount'!M269) -> 0 | N82: =M82/$M$6 -> 0 | O82: =AVERAGE('Monthly Headcount'!O211,'Monthly Headcount'!O242,'Monthly Headcount'!O269) -> 0 | P82: =O82/$O$6 -> 0
B83: Exits at Other Levels | C83: =SUM(E83,G83,I83,K83,M83,O83) -> 21.666667 | D83: =C83/$C$6 -> 0.018025513 | E83: =AVERAGE('Monthly Headcount'!E212,'Monthly Headcount'!E243,'Monthly Headcount'!E270) -> 10.333333 | F83: =E83/$E$6 -> 0.016756757 | G83: =AVERAGE('Monthly Headcount'!G212,'Monthly Headcount'!G243,'Monthly Headcount'!G270) -> 6.6666667 | H83: =G83/$G$6 -> 0.029455081 | I83: =AVERAGE('Monthly Headcount'!I212,'Monthly Headcount'!I243,'Monthly Headcount'!I270) -> 4.6666667 | J83: =I83/$I$6 -> 0.020618557 | K83: =AVERAGE('Monthly Headcount'!K212,'Monthly Headcount'!K243,'Monthly Headcount'!K270) -> 0 | L83: =K83/$K$6 -> 0 | N83: =M83/$M$6 -> 0 | O83: =AVERAGE('Monthly Headcount'!O212,'Monthly Headcount'!O243,'Monthly Headcount'!O270) -> 0 | P83: =O83/$O$6 -> 0
B84: Total Internal Movements | C84: =SUM(E84,G84,I84,K84,M84,O84) -> 6.6666667 | E84: =SUM(E85:E86) -> 3.6666667 | F84: =SUM(F85:F86) -> 0 | G84: =SUM(G85:G86) -> 2 | H84: =SUM(H85:H86) -> 0 | I84: =SUM(I85:I86) -> 1 | J84: =SUM(J85:J86) -> 0 | K84: =SUM(K85:K86) -> 0 | L84: =SUM(L85:L86) -> 0 | ... P84: =SUM(P85:P86) -> 0
B85: Promotions | C85: =SUM(E85,G85,I85,K85,M85,O85) -> 3.6666667 | E85: =AVERAGE('Monthly Headcount'!E214,'Monthly Headcount'!E245,'Monthly Headcount'!E276) -> 1.6666667 | G85: =AVERAGE('Monthly Headcount'!G214,'Monthly Headcount'!G245,'Monthly Headcount'!G276) -> 2 | I85: =AVERAGE('Monthly Headcount'!I214,'Monthly Headcount'!I245,'Monthly Headcount'!I276) -> 0 | K85: =AVERAGE('Monthly Headcount'!K214,'Monthly Headcount'!K245,'Monthly Headcount'!K276) -> 0 | M85: =AVERAGE('Monthly Headcount'!M214,'Monthly Headcount'!M245,'Monthly Headcount'!M276) -> 0 | O85: =AVERAGE('Monthly Headcount'!O214,'Monthly Headcount'!O245,'Monthly Headcount'!O276) -> 0
B86: Transfers | C86: =SUM(E86,G86,I86,K86,M86,O86) -> 3 | E86: =AVERAGE('Monthly Headcount'!E215,'Monthly Headcount'!E246,'Monthly Headcount'!E277) -> 2 | G86: =AVERAGE('Monthly Headcount'!G215,'Monthly Headcount'!G246,'Monthly Headcount'!G277) -> 0 | I86: =AVERAGE('Monthly Headcount'!I215,'Monthly Headcount'!I246,'Monthly Headcount'!I277) -> 1 | K86: =AVERAGE('Monthly Headcount'!K215,'Monthly Headcount'!K246,'Monthly Headcount'!K277) -> 0 | M86: =AVERAGE('Monthly Headcount'!L215,'Monthly Headcount'!M246,'Monthly Headcount'!M277) -> 0 | O86: =AVERAGE('Monthly Headcount'!O215,'Monthly Headcount'!O246,'Monthly Headcount'!O277) -> 0
B87: Principals | C87: =SUM(E87,G87,I87,K87,M87,O87) -> 420 | D87: =C87/C64 -> 0.17976887 | E87: =E88+E89 -> 338 | F87: =E87/C87 -> 0.8047619 | G87: =G88+G89 -> 0 | H87: =G87/C87 -> 0 | I87: =I88+I89 -> 33.333333 | J87: =I87/C87 -> 0.079365079 | K87: =K88+K89 -> 34.666667 | L87: =K87/E87 -> 0.1025641 | M87: =M88+M89 -> 4 | N87: =M87/C87 -> 0.0095238095 | O87: =O88+O89 -> 10 | P87: =O87/C87 -> 0.023809524
B88: Female | C88: =SUM(E88,G88,I88,K88,M88,O88) -> 135.33333 | D88: =C88/C87 -> 0.32222222 | E88: =AVERAGE('Monthly Headcount'!E217,'Monthly Headcount'!E248,'Monthly Headcount'!E279) -> 103.66667 | F88: =E88/E87 -> 0.30670611 | G88: =AVERAGE('Monthly Headcount'!G217,'Monthly Headcount'!G248,'Monthly Headcount'!G279) -> 0 | H88: 0 | I88: =AVERAGE('Monthly Headcount'!I217,'Monthly Headcount'!I248,'Monthly Headcount'!I279) -> 10.333333 | J88: =I88/I87 -> 0.31 | K88: =AVERAGE('Monthly Headcount'!K217,'Monthly Headcount'!K248,'Monthly Headcount'!K279) -> 14.333333 | L88: =K88/K87 -> 0.41346154 | M88: =AVERAGE('Monthly Headcount'!M217,'Monthly Headcount'!M248,'Monthly Headcount'!M279) -> 1 | N88: =M88/M87 -> 0.25 | O88: =AVERAGE('Monthly Headcount'!O217,'Monthly Headcount'!O248,'Monthly Headcount'!O279) -> 6 | P88: 0
B89: Male | C89: =SUM(E89,G89,I89,K89,M89,O89) -> 284.66667 | D89: =C89/C87 -> 0.67777778 | E89: =AVERAGE('Monthly Headcount'!E218,'Monthly Headcount'!E249,'Monthly Headcount'!E280) -> 234.33333 | F89: =E89/E87 -> 0.69329389 | G89: =AVERAGE('Monthly Headcount'!G218,'Monthly Headcount'!G249,'Monthly Headcount'!G280) -> 0 | H89: 0 | I89: =AVERAGE('Monthly Headcount'!I218,'Monthly Headcount'!I249,'Monthly Headcount'!I280) -> 23 | J89: =I89/I87 -> 0.69 | K89: =AVERAGE('Monthly Headcount'!K218,'Monthly Headcount'!K249,'Monthly Headcount'!K280) -> 20.333333 | L89: =K89/K87 -> 0.58653846 | M89: =AVERAGE('Monthly Headcount'!M218,'Monthly Headcount'!M249,'Monthly Headcount'!M280) -> 3 | N89: =M89/M87 -> 0.75 | O89: =AVERAGE('Monthly Headcount'!O218,'Monthly Headcount'!O249,'Monthly Headcount'!O280) -> 4 | P89: 0
B90: Casuals/Contractors | C90: =SUM(E90,G90,I90,K90,M90,O90) -> 697.33333 | D90: =C90/C64 -> 0.29847339 | E90: =E91+E92 -> 42.333333 | F90: =E90/C90 -> 0.060707457 | G90: =G91+G92 -> 655 | H90: =G90/C90 -> 0.93929254 | I90: =I91+I92 -> 0 | J90: 0 | K90: =K91+K92 -> 0 | L90: =K90/C90 -> 0 | M90: =M91+M92 -> 0 | N90: 0 | O90: =O91+O92 -> 0 | P90: 0
B91: Female | C91: =SUM(E91,G91,I91,K91,M91,O91) -> 285 | D91: =C91/C90 -> 0.40869981 | E91: =AVERAGE('Monthly Headcount'!E220,'Monthly Headcount'!E251,'Monthly Headcount'!E282) -> 6 | F91: =E91/E90 -> 0.14173228 | G91: =AVERAGE('Monthly Headcount'!G220,'Monthly Headcount'!G251,'Monthly Headcount'!G282) -> 279 | H91: =G91/G90 -> 0.4259542 | I91: =AVERAGE('Monthly Headcount'!I220,'Monthly Headcount'!I251,'Monthly Headcount'!I282) -> 0 | J91: 0 | K91: =AVERAGE('Monthly Headcount'!K220,'Monthly Headcount'!K251,'Monthly Headcount'!K282) -> 0 | L91: 0 | M91: =AVERAGE('Monthly Headcount'!M220,'Monthly Headcount'!M251,'Monthly Headcount'!M282) -> 0 | N91: 0 | O91: =AVERAGE('Monthly Headcount'!O220,'Monthly Headcount'!O251,'Monthly Headcount'!O282) -> 0 | P91: 0
B92: Male | C92: =SUM(E92,G92,I92,K92,M92,O92) -> 412.33333 | D92: =C92/C90 -> 0.59130019 | E92: =AVERAGE('Monthly Headcount'!E221,'Monthly Headcount'!E252,'Monthly Headcount'!E283) -> 36.333333 | F92: =E92/E90 -> 0.85826772 | G92: =AVERAGE('Monthly Headcount'!G221,'Monthly Headcount'!G252,'Monthly Headcount'!G283) -> 376 | H92: =G92/G90 -> 0.5740458 | I92: =AVERAGE('Monthly Headcount'!I221,'Monthly Headcount'!I252,'Monthly Headcount'!I283) -> 0 | J92: 0 | K92: =AVERAGE('Monthly Headcount'!K221,'Monthly Headcount'!K252,'Monthly Headcount'!K283) -> 0 | L92: 0 | M92: =AVERAGE('Monthly Headcount'!M221,'Monthly Headcount'!M252,'Monthly Headcount'!M283) -> 0 | N92: 0 | O92: =AVERAGE('Monthly Headcount'!O221,'Monthly Headcount'!O252,'Monthly Headcount'!O283) -> 0 | P92: 0
A93: Q4 | B93: Overall Headcount | C93: =SUM(E93,G93,I93,K93,M93,O93) -> 2268.3333 | D93: =SUM(F93,H93,J93,L93,N93,P93) -> 1 | E93: =SUM(E94,E116,E119) -> 965 | F93: =E93/C93 -> 0.42542248 | G93: =SUM(G94,G116,G119) -> 868.33333 | H93: =G93/C93 -> 0.38280676 | I93: =SUM(I94,I116,I119) -> 258 | J93: =I93/C93 -> 0.1137399 | K93: =SUM(K94,K116,K119) -> 74 | L93: =K93/C93 -> 0.032623071 | M93: =SUM(M94,M116,M119) -> 62 | N93: =M93/C93 -> 0.027332843 | O93: =SUM(O94,O116,O119) -> 41 | P93: =O93/C93 -> 0.018074945
B94: Direct Staff | C94: =SUM(E94,G94,I94,K94,M94,O94) -> 1181 | D94: =C94/C93 -> 0.52064658 | E94: =E95+E96 -> 596 | F94: =E94/C94 -> 0.50465707 | G94: =G95+G96 -> 231 | H94: =G94/C94 -> 0.19559695 | I94: =I95+I96 -> 225 | J94: =I94/C94 -> 0.19051651 | K94: =K95+K96 -> 39 | L94: =K94/C94 -> 0.033022862 | M94: =M95+M96 -> 58 | N94: =M94/C94 -> 0.049110923 | O94: =O95+O96 -> 32 | P94: =O94/C94 -> 0.027095682
B95: Female | C95: =SUM(E95,G95,I95,K95,M95,O95) -> 295 | D95: =C95/C94 -> 0.24978831 | E95: ='Monthly Headcount'!E164 -> 134 | F95: =E95/E94 -> 0.22483221 | G95: ='Monthly Headcount'!G164 -> 48 | H95: =G95/G94 -> 0.20779221 | I95: ='Monthly Headcount'!I164 -> 64 | J95: =I95/I94 -> 0.28444444 | K95: ='Monthly Headcount'!K164 -> 16 | L95: =K95/K94 -> 0.41025641 | M95: ='Monthly Headcount'!M164 -> 16 | N95: =M95/M94 -> 0.27586207 | O95: ='Monthly Headcount'!O164 -> 17 | P95: =O95/O94 -> 0.53125
B96: Male | C96: =SUM(E96,G96,I96,K96,M96,O96) -> 886 | D96: =C96/C94 -> 0.75021169 | E96: ='Monthly Headcount'!E165 -> 462 | F96: =E97/E94 -> 0.86241611 | G96: ='Monthly Headcount'!G165 -> 183 | H96: =G96/G94 -> 0.79220779 | I96: ='Monthly Headcount'!I165 -> 161 | J96: =I96/I94 -> 0.71555556 | K96: ='Monthly Headcount'!K165 -> 23 | L96: =K96/K94 -> 0.58974359 | M96: ='Monthly Headcount'!M165 -> 42 | N96: =M96/M94 -> 0.72413793 | O96: ='Monthly Headcount'!O165 -> 15 | P96: =O96/O94 -> 0.46875
B97: Nationals | C97: =SUM(E97,G97,I97,K97,M97,O97) -> 1062 | D97: =C97/C94 -> 0.89923793 | E97: ='Monthly Headcount'!E166 -> 514 | F97: =E97/E94 -> 0.86241611 | G97: ='Monthly Headcount'!G166 -> 220 | H97: =G97/G94 -> 0.95238095 | I97: ='Monthly Headcount'!I166 -> 210 | J97: =I97/I94 -> 0.93333333 | K97: ='Monthly Headcount'!K166 -> 35 | L97: =K97/K94 -> 0.8974359 | M97: ='Monthly Headcount'!M166 -> 52 | N97: =M97/M94 -> 0.89655172 | O97: ='Monthly Headcount'!O166 -> 31 | P97: =O97/O94 -> 0.96875
B98: Expatriates | C98: =SUM(E98,G98,I98,K98,M98,O98) -> 119 | D98: =C98/C94 -> 0.10076207 | E98: ='Monthly Headcount'!E167 -> 82 | F98: =E98/E94 -> 0.13758389 | G98: ='Monthly Headcount'!G167 -> 11 | H98: =G98/G94 -> 0.047619048 | I98: ='Monthly Headcount'!I167 -> 15 | J98: =I98/I94 -> 0.066666667 | K98: ='Monthly Headcount'!K167 -> 4 | L98: =K98/K94 -> 0.1025641 | M98: ='Monthly Headcount'!M167 -> 6 | N98: =M98/M94 -> 0.10344828 | O98: ='Monthly Headcount'!O167 -> 1 | P98: =O98/O94 -> 0.03125
B99: Management | C99: =SUM(E99,G99,I99,K99,M99,O99) -> 253 | D99: =C99/C94 -> 0.21422523 | E99: ='Monthly Headcount'!E168 -> 121 | F99: =E99/E94 -> 0.20302013 | G99: ='Monthly Headcount'!G168 -> 56 | H99: =G99/G94 -> 0.24242424 | I99: ='Monthly Headcount'!I168 -> 42 | J99: =I99/I94 -> 0.18666667 | K99: ='Monthly Headcount'!K168 -> 11 | L99: =K99/K94 -> 0.28205128 | M99: ='Monthly Headcount'!M168 -> 16 | N99: =M99/M94 -> 0.27586207 | O99: ='Monthly Headcount'!O168 -> 7 | P99: =O99/O94 -> 0.21875
B100: Female in Management | C100: =SUM(E100,G100,I100,K100,M100,O100) -> 42 | D100: =C100/C99 -> 0.16600791 | E100: ='Monthly Headcount'!E169 -> 18 | F100: =E100/E99 -> 0.14876033 | G100: ='Monthly Headcount'!G169 -> 8 | H100: =G100/G99 -> 0.14285714 | I100: ='Monthly Headcount'!I169 -> 7 | J100: =I100/I99 -> 0.16666667 | K100: ='Monthly Headcount'!K169 -> 3 | L100: =K100/K99 -> 0.27272727 | M100: ='Monthly Headcount'!M169 -> 4 | N100: =M100/M99 -> 0.25 | O100: ='Monthly Headcount'!O169 -> 2 | P100: =O100/O99 -> 0.28571429
B101: Below 40 years of age | C101: =SUM(E101,G101,I101,K101,M101,O101) -> 925 | D101: =C101/C94 -> 0.78323455 | E101: ='Monthly Headcount'!E170 -> 459 | F101: =E101/E94 -> 0.77013423 | G101: ='Monthly Headcount'!G170 -> 174 | H101: =G101/G94 -> 0.75324675 | I101: ='Monthly Headcount'!I170 -> 186 | J101: =I101/I94 -> 0.82666667 | K101: ='Monthly Headcount'!K170 -> 34 | L101: =K101/K94 -> 0.87179487 | M101: ='Monthly Headcount'!M170 -> 47 | N101: =M101/M94 -> 0.81034483 | O101: ='Monthly Headcount'!O170 -> 25 | P101: =O101/O94 -> 0.78125
B102: Atleast 40 years of age | C102: =SUM(E102,G102,I102,K102,M102,O102) -> 256 | D102: =C102/C94 -> 0.21676545 | E102: ='Monthly Headcount'!E171 -> 137 | F102: =E102/E94 -> 0.22986577 | G102: ='Monthly Headcount'!G171 -> 57 | H102: =G102/G94 -> 0.24675325 | I102: ='Monthly Headcount'!I171 -> 39 | J102: =I102/I94 -> 0.17333333 | K102: ='Monthly Headcount'!K171 -> 5 | L102: =K102/K94 -> 0.12820513 | M102: ='Monthly Headcount'!M171 -> 11 | N102: =M102/M94 -> 0.18965517 | O102: ='Monthly Headcount'!O171 -> 7 | P102: =O102/O94 -> 0.21875
...

Sheet Copy YTD Headcount-Board
B1: Group | D1: Uganda | F1: APDL | H1: Tanzania | J1: Rwanda | L1: Burundi | N1: Kenya
B2: Number | C2: % | D2: Number | E2: % | F2: Number | G2: % | H2: Number | I2: % | J2: Number | K2: % | L2: Number | M2: % | N2: Number | O2: %
A4: Overall Headcount | B4: =SUM(D4,F4,H4,J4,L4,N4) -> 2149.6667 | C4: =SUM(E4,G4,I4,K4,M4,O4) -> 1 | D4: =SUM(D5,D27,D30) -> 996.66667 | E4: =D4/B$4 -> 0.46363777 | F4: =SUM(F5,F27,F30) -> 720.33333 | G4: =F4/B$4 -> 0.33509071 | H4: =SUM(H5,H27,H30) -> 248 | I4: =H4/B$4 -> 0.11536672 | J4: =SUM(J5,J27,J30) -> 76 | K4: =J4/B$4 -> 0.035354318 | L4: =SUM(L5,L27,L30) -> 65.666667 | M4: =L4/B$4 -> 0.030547372 | N4: =SUM(N5,N27,N30) -> 43 | O4: =N4/B$4 -> 0.020003101
A5: Direct Staff | B5: =SUM(D5,F5,H5,J5,L5,N5) -> 1202 | C5: =B5/B4 -> 0.55915646 | D5: =D6+D7 -> 616.66667 | E5: =D5/B5 -> 0.51303383 | F5: =F6+F7 -> 226.33333 | G5: =F5/B5 -> 0.18829728 | H5: =H6+H7 -> 226.33333 | I5: =H5/B5 -> 0.18829728 | J5: =J6+J7 -> 39.333333 | K5: =J5/B5 -> 0.032723239 | L5: =L6+L7 -> 59.666667 | M5: =L5/B5 -> 0.04963949 | N5: =N6+N7 -> 33.666667 | O5: =N5/B5 -> 0.028008874
A6: Female | B6: =SUM(D6,F6,H6,J6,L6,N6) -> 307.33333 | C6: =B6/B5 -> 0.25568497 | D6: =AVERAGE('Monthly Headcount'!E9,'Monthly Headcount'!E40,'Monthly Headcount'!E71) -> 146 | E6: =D6/D5 -> 0.23675676 | F6: =AVERAGE('Monthly Headcount'!G9,'Monthly Headcount'!G40,'Monthly Headcount'!G71) -> 45 | G6: =F6/F5 -> 0.1988218 | H6: =AVERAGE('Monthly Headcount'!I9,'Monthly Headcount'!I40,'Monthly Headcount'!I71) -> 67.333333 | I6: =H6/H5 -> 0.29749632 | J6: =AVERAGE('Monthly Headcount'!K9,'Monthly Headcount'!K40,'Monthly Headcount'!K71) -> 14 | K6: =J6/J5 -> 0.3559322 | L6: =AVERAGE('Monthly Headcount'!M9,'Monthly Headcount'!M40,'Monthly Headcount'!M71) -> 17.666667 | M6: =L6/L5 -> 0.29608939 | N6: =AVERAGE('Monthly Headcount'!O9,'Monthly Headcount'!O40,'Monthly Headcount'!O71) -> 17.333333 | O6: =N6/N5 -> 0.51485149
A7: Male | B7: =SUM(D7,F7,H7,J7,L7,N7) -> 894.66667 | C7: =B7/B5 -> 0.74431503 | D7: =AVERAGE('Monthly Headcount'!E10,'Monthly Headcount'!E41,'Monthly Headcount'!E72) -> 470.66667 | E7: =D8/D5 -> 0.86324324 | F7: =AVERAGE('Monthly Headcount'!G10,'Monthly Headcount'!G41,'Monthly Headcount'!G72) -> 181.33333 | G7: =F7/F5 -> 0.8011782 | H7: =AVERAGE('Monthly Headcount'!I10,'Monthly Headcount'!I41,'Monthly Headcount'!I72) -> 159 | I7: =H7/H5 -> 0.70250368 | J7: =AVERAGE('Monthly Headcount'!K10,'Monthly Headcount'!K41,'Monthly Headcount'!K72) -> 25.333333 | K7: =J7/J5 -> 0.6440678 | L7: =AVERAGE('Monthly Headcount'!M10,'Monthly Headcount'!M41,'Monthly Headcount'!M72) -> 42 | M7: =L7/L5 -> 0.70391061 | N7: =AVERAGE('Monthly Headcount'!O10,'Monthly Headcount'!O41,'Monthly Headcount'!O72) -> 16.333333 | O7: =N7/N5 -> 0.48514851
A8: Nationals | B8: =SUM(D8,F8,H8,J8,L8,N8) -> 1080.3333 | C8: =B8/B5 -> 0.89877981 | D8: =AVERAGE('Monthly Headcount'!E11,'Monthly Headcount'!E42,'Monthly Headcount'!E73) -> 532.33333 | E8: =D8/D5 -> 0.86324324 | F8: =AVERAGE('Monthly Headcount'!G11,'Monthly Headcount'!G42,'Monthly Headcount'!G73) -> 214.33333 | G8: =F8/F5 -> 0.94698085 | H8: =AVERAGE('Monthly Headcount'!I11,'Monthly Headcount'!I42,'Monthly Headcount'!I73) -> 211.33333 | I8: =H8/H5 -> 0.93372607 | J8: =AVERAGE('Monthly Headcount'!K11,'Monthly Headcount'!K42,'Monthly Headcount'!K73) -> 35 | K8: =J8/J5 -> 0.88983051 | L8: =AVERAGE('Monthly Headcount'!M11,'Monthly Headcount'!M42,'Monthly Headcount'!M73) -> 54.666667 | M8: =L8/L5 -> 0.91620112 | N8: =AVERAGE('Monthly Headcount'!O11,'Monthly Headcount'!O42,'Monthly Headcount'!O73) -> 32.666667 | O8: =N8/N5 -> 0.97029703
A9: Expatriates | B9: =SUM(D9,F9,H9,J9,L9,N9) -> 121.66667 | C9: =B9/B5 -> 0.10122019 | D9: =AVERAGE('Monthly Headcount'!E12,'Monthly Headcount'!E43,'Monthly Headcount'!E74) -> 84.333333 | E9: =D9/D5 -> 0.13675676 | F9: =AVERAGE('Monthly Headcount'!G12,'Monthly Headcount'!G43,'Monthly Headcount'!G74) -> 12 | G9: =F9/F5 -> 0.053019146 | H9: =AVERAGE('Monthly Headcount'!I12,'Monthly Headcount'!I43,'Monthly Headcount'!I74) -> 15 | I9: =H9/H5 -> 0.066273932 | J9: =AVERAGE('Monthly Headcount'!K12,'Monthly Headcount'!K43,'Monthly Headcount'!K74) -> 4.3333333 | K9: =J9/J5 -> 0.11016949 | L9: =AVERAGE('Monthly Headcount'!M12,'Monthly Headcount'!M43,'Monthly Headcount'!M74) -> 5 | M9: =L9/L5 -> 0.083798883 | N9: =AVERAGE('Monthly Headcount'!O12,'Monthly Headcount'!O43,'Monthly Headcount'!O74) -> 1 | O9: =N9/N5 -> 0.02970297
A10: Management | B10: =SUM(D10,F10,H10,J10,L10,N10) -> 266.33333 | C10: =B10/B5 -> 0.22157515 | D10: =AVERAGE('Monthly Headcount'!E13,'Monthly Headcount'!E44,'Monthly Headcount'!E75) -> 126.66667 | E10: =D10/D5 -> 0.20540541 | F10: =AVERAGE('Monthly Headcount'!G13,'Monthly Headcount'!G44,'Monthly Headcount'!G75) -> 64 | G10: =F10/F5 -> 0.28276878 | H10: =AVERAGE('Monthly Headcount'!I13,'Monthly Headcount'!I44,'Monthly Headcount'!I75) -> 41 | I10: =H10/H5 -> 0.18114875 | J10: =AVERAGE('Monthly Headcount'!K13,'Monthly Headcount'!K44,'Monthly Headcount'!K75) -> 11.333333 | K10: =J10/J5 -> 0.28813559 | L10: =AVERAGE('Monthly Headcount'!M13,'Monthly Headcount'!M44,'Monthly Headcount'!M75) -> 16.333333 | M10: =L10/L5 -> 0.27374302 | N10: =AVERAGE('Monthly Headcount'!O13,'Monthly Headcount'!O44,'Monthly Headcount'!O75) -> 7 | O10: =N10/N5 -> 0.20792079
A11: Female in Management | B11: =SUM(D11,F11,H11,J11,L11,N11) -> 44.666667 | C11: =B11/B10 -> 0.16770964 | D11: =AVERAGE('Monthly Headcount'!E14,'Monthly Headcount'!E45,'Monthly Headcount'!E76) -> 18.666667 | E11: =D11/D10 -> 0.14736842 | F11: =AVERAGE('Monthly Headcount'!G14,'Monthly Headcount'!G45,'Monthly Headcount'!G76) -> 9.3333333 | G11: =F11/F10 -> 0.14583333 | H11: =AVERAGE('Monthly Headcount'!I14,'Monthly Headcount'!I45,'Monthly Headcount'!I76) -> 8 | I11: =H11/H10 -> 0.19512195 | J11: =AVERAGE('Monthly Headcount'!K14,'Monthly Headcount'!K45,'Monthly Headcount'!K76) -> 2.6666667 | K11: =J11/J10 -> 0.23529412 | L11: =AVERAGE('Monthly Headcount'!M14,'Monthly Headcount'!M45,'Monthly Headcount'!M76) -> 4 | M11: =L11/L10 -> 0.24489796 | N11: =AVERAGE('Monthly Headcount'!O14,'Monthly Headcount'!O45,'Monthly Headcount'!O76) -> 2 | O11: =N11/N10 -> 0.28571429
A12: Below 40 years of age | B12: =SUM(D12,F12,H12,J12,L12,N12) -> 950.66667 | C12: =B12/B5 -> 0.79090405 | D12: =AVERAGE('Monthly Headcount'!E15,'Monthly Headcount'!E46,'Monthly Headcount'!E77) -> 473.66667 | E12: =D12/D5 -> 0.76810811 | F12: =AVERAGE('Monthly Headcount'!G15,'Monthly Headcount'!G46,'Monthly Headcount'!G77) -> 184.33333 | G12: =F12/F5 -> 0.81443299 | H12: =AVERAGE('Monthly Headcount'!I15,'Monthly Headcount'!I46,'Monthly Headcount'!I77) -> 184.33333 | I12: =H12/H5 -> 0.81443299 | J12: =AVERAGE('Monthly Headcount'!K15,'Monthly Headcount'!K46,'Monthly Headcount'!K77) -> 33.666667 | K12: =J12/J5 -> 0.8559322 | L12: =AVERAGE('Monthly Headcount'!M15,'Monthly Headcount'!M46,'Monthly Headcount'!M77) -> 48.666667 | M12: =L12/L5 -> 0.81564246 | N12: =AVERAGE('Monthly Headcount'!O15,'Monthly Headcount'!O46,'Monthly Headcount'!O77) -> 26 | O12: =N12/N5 -> 0.77227723
A13: Atleast 40 years of age | B13: =SUM(D13,F13,H13,J13,L13,N13) -> 251.33333 | C13: =B13/B5 -> 0.20909595 | D13: =AVERAGE('Monthly Headcount'!E16,'Monthly Headcount'!E47,'Monthly Headcount'!E78) -> 143 | E13: =D13/D5 -> 0.23189189 | F13: =AVERAGE('Monthly Headcount'!G16,'Monthly Headcount'!G47,'Monthly Headcount'!G78) -> 42 | G13: =F13/F5 -> 0.18556701 | H13: =AVERAGE('Monthly Headcount'!I16,'Monthly Headcount'!I47,'Monthly Headcount'!I78) -> 42 | I13: =H13/H5 -> 0.18556701 | J13: =AVERAGE('Monthly Headcount'!K16,'Monthly Headcount'!K47,'Monthly Headcount'!K78) -> 5.6666667 | K13: =J13/J5 -> 0.1440678 | L13: =AVERAGE('Monthly Headcount'!M16,'Monthly Headcount'!M47,'Monthly Headcount'!M78) -> 11 | M13: =L13/L5 -> 0.18435754 | N13: =AVERAGE('Monthly Headcount'!O16,'Monthly Headcount'!O47,'Monthly Headcount'!O78) -> 7.6666667 | O13: =N13/N5 -> 0.22772277
A14: Less than 5 years with Abacus | B14: =SUM(D14,F14,H14,J14,L14,N14) -> 685.66667 | C14: =B14/B5 -> 0.57043816 | D14: =AVERAGE('Monthly Headcount'!E17,'Monthly Headcount'!E48,'Monthly Headcount'!E79) -> 365.66667 | E14: =D14/D5 -> 0.59297297 | F14: =AVERAGE('Monthly Headcount'!G17,'Monthly Headcount'!G48,'Monthly Headcount'!G79) -> 92 | G14: =F14/F5 -> 0.40648012 | H14: =AVERAGE('Monthly Headcount'!I17,'Monthly Headcount'!I48,'Monthly Headcount'!I79) -> 143 | I14: =H14/H5 -> 0.63181149 | J14: =AVERAGE('Monthly Headcount'!K17,'Monthly Headcount'!K48,'Monthly Headcount'!K79) -> 29.333333 | K14: =J14/J5 -> 0.74576271 | L14: =AVERAGE('Monthly Headcount'!M17,'Monthly Headcount'!M48,'Monthly Headcount'!M79) -> 30.333333 | M14: =L14/L5 -> 0.50837989 | N14: =AVERAGE('Monthly Headcount'!O17,'Monthly Headcount'!O48,'Monthly Headcount'!O79) -> 25.333333 | O14: =N14/N5 -> 0.75247525
A15: Atleast 5 years with Abacus | B15: =SUM(D15,F15,H15,J15,L15,N15) -> 516.33333 | C15: =B15/B5 -> 0.42956184 | D15: =AVERAGE('Monthly Headcount'!E18,'Monthly Headcount'!E49,'Monthly Headcount'!E80) -> 251 | E15: =D15/D5 -> 0.40702703 | F15: =AVERAGE('Monthly Headcount'!G18,'Monthly Headcount'!G49,'Monthly Headcount'!G80) -> 134.33333 | G15: =F15/F5 -> 0.59351988 | H15: =AVERAGE('Monthly Headcount'!I18,'Monthly Headcount'!I49,'Monthly Headcount'!I80) -> 83.333333 | I15: =H15/H5 -> 0.36818851 | J15: =AVERAGE('Monthly Headcount'!K18,'Monthly Headcount'!K49,'Monthly Headcount'!K80) -> 10 | K15: =J15/J5 -> 0.25423729 | L15: =AVERAGE('Monthly Headcount'!M18,'Monthly Headcount'!M49,'Monthly Headcount'!M80) -> 29.333333 | M15: =L15/L5 -> 0.49162011 | N15: =AVERAGE('Monthly Headcount'!O18,'Monthly Headcount'!O49,'Monthly Headcount'!O80) -> 8.3333333 | O15: =N15/N5 -> 0.24752475
A16: Total New hires | B16: =SUM(D16,F16,H16,J16,L16,N16) -> 65.333333 | C16: =SUM(C17:C19) -> 0.054353855 | D16: =SUM(D17:D19) -> 20 | E16: =SUM(E17:E19) -> 0.032432432 | F16: =SUM(F17:F19) -> 7 | G16: =SUM(G17:G19) -> 0.0058236273 | H16: =SUM(H17:H19) -> 29.333333 | I16: =SUM(I17:I19) -> 0.024403771 | J16: =SUM(J17:J19) -> 2 | ... O16: =SUM(O17:O19) -> 0.0049916805
A17: New hires at EXCO | B17: =SUM(D17,F17,H17,J17,L17,N17) -> 1 | C17: =B17/$B$5 -> 0.00083194676 | D17: 1 | E17: =D17/$D$5 -> 0.0016216216 | F17: =AVERAGE('Monthly Headcount'!G20,'Monthly Headcount'!G51,'Monthly Headcount'!G82) -> 0 | G17: =F17/$B$5 -> 0 | H17: =AVERAGE('Monthly Headcount'!I20,'Monthly Headcount'!I51,'Monthly Headcount'!I82) -> 0 | I17: =H17/$B$5 -> 0 | J17: =AVERAGE('Monthly Headcount'!K20,'Monthly Headcount'!K51,'Monthly Headcount'!K82) -> 0 | K17: =J17/$B$5 -> 0 | L17: =AVERAGE('Monthly Headcount'!M20,'Monthly Headcount'!M51,'Monthly Headcount'!M82) -> 0 | M17: =L17/$B$5 -> 0 | N17: =AVERAGE('Monthly Headcount'!O20,'Monthly Headcount'!O51,'Monthly Headcount'!O82) -> 0 | O17: =N17/$B$5 -> 0
A18: New hires at EXCO - 1&2 | B18: =SUM(D18,F18,H18,J18,L18,N18) -> 2.3333333 | C18: =B18/$B$5 -> 0.0019412091 | D18: =AVERAGE('Monthly Headcount'!E21,'Monthly Headcount'!E52,'Monthly Headcount'!E83) -> 0 | E18: =D18/$D$5 -> 0 | F18: =AVERAGE('Monthly Headcount'!G21,'Monthly Headcount'!G52,'Monthly Headcount'!G83) -> 0 | G18: =F18/$B$5 -> 0 | H18: =AVERAGE('Monthly Headcount'!I21,'Monthly Headcount'!I52,'Monthly Headcount'!I83) -> 0.33333333 | I18: =H18/$B$5 -> 0.00027731559 | J18: 2 | K18: =J18/$B$5 -> 0.0016638935 | L18: =AVERAGE('Monthly Headcount'!M21,'Monthly Headcount'!M52,'Monthly Headcount'!M83) -> 0 | M18: =L18/$B$5 -> 0 | N18: =AVERAGE('Monthly Headcount'!O21,'Monthly Headcount'!O52,'Monthly Headcount'!O83) -> 0 | O18: =N18/$B$5 -> 0
A19: New hires at Other Levels | B19: =SUM(D19,F19,H19,J19,L19,N19) -> 62 | C19: =B19/$B$5 -> 0.051580699 | D19: 19 | E19: =D19/$D$5 -> 0.030810811 | F19: 7 | G19: =F19/$B$5 -> 0.0058236273 | H19: 29 | I19: =H19/$B$5 -> 0.024126456 | J19: 0 | K19: =J19/$B$5 -> 0 | L19: 1 | M19: =L19/$B$5 -> 0.00083194676 | N19: 6 | O19: =N19/$B$5 -> 0.0049916805
A20: Total Exits | B20: =SUM(D20,F20,H20,J20,L20,N20) -> 77 | C20: =SUM(C21:C23) -> 0.0640599 | D20: =SUM(D21:D23) -> 36 | E20: =SUM(E21:E23) -> 0.058378378 | F20: =SUM(F21:F23) -> 12 | G20: =SUM(G21:G23) -> 0.053019146 | H20: =SUM(H21:H23) -> 19 | I20: =SUM(I21:I23) -> 0.083946981 | J20: =SUM(J21:J23) -> 4 | ... O20: =SUM(O21:O23) -> 0.089108911
A21: Exits at EXCO | B21: =SUM(D21,F21,H21,J21,L21,N21) -> 0 | C21: =B21/$B$5 -> 0 | D21: =AVERAGE('Monthly Headcount'!E24,'Monthly Headcount'!E55,'Monthly Headcount'!E86) -> 0 | E21: =D21/$D$5 -> 0 | F21: =SUM('Monthly Headcount'!G24,'Monthly Headcount'!G55,'Monthly Headcount'!G86) -> 0 | G21: =F21/$F$5 -> 0 | H21: =AVERAGE('Monthly Headcount'!I24,'Monthly Headcount'!I55,'Monthly Headcount'!I86) -> 0 | I21: =H21/$H$5 -> 0 | J21: =AVERAGE('Monthly Headcount'!K24,'Monthly Headcount'!K55,'Monthly Headcount'!K86) -> 0 | K21: =J21/$J$5 -> 0 | L21: =AVERAGE('Monthly Headcount'!M24,'Monthly Headcount'!M55,'Monthly Headcount'!M86) -> 0 | M21: =L21/$L$5 -> 0 | N21: =AVERAGE('Monthly Headcount'!O24,'Monthly Headcount'!O55,'Monthly Headcount'!O86) -> 0 | O21: =N21/$N$5 -> 0
A22: Exits at EXCO - 1&2 | B22: =SUM(D22,F22,H22,J22,L22,N22) -> 9 | C22: =B22/$B$5 -> 0.0074875208 | D22: 4 | E22: =D22/$D$5 -> 0.0064864865 | F22: 2 | G22: =F22/$F$5 -> 0.0088365243 | H22: 1 | I22: =H22/$H$5 -> 0.0044182622 | J22: 2 | K22: =J22/$J$5 -> 0.050847458 | L22: =AVERAGE('Monthly Headcount'!M25,'Monthly Headcount'!M56,'Monthly Headcount'!M87) -> 0 | M22: =L22/$L$5 -> 0 | N22: =AVERAGE('Monthly Headcount'!O25,'Monthly Headcount'!O56,'Monthly Headcount'!O87) -> 0 | O22: =N22/$N$5 -> 0
A23: Exits at Other Levels | B23: =SUM(D23,F23,H23,J23,L23,N23) -> 68 | C23: =B23/$B$5 -> 0.056572379 | D23: 32 | E23: =D23/$D$5 -> 0.051891892 | F23: 10 | G23: =F23/$F$5 -> 0.044182622 | H23: 18 | I23: =H23/$H$5 -> 0.079528719 | J23: 2 | K23: =J23/$J$5 -> 0.050847458 | L23: 3 | M23: =L23/$L$5 -> 0.05027933 | N23: 3 | O23: =N23/$N$5 -> 0.089108911
A24: Total Internal Movements | B24: 31 | C24: =SUM(C25:C26) -> 0.025790349 | D24: =SUM(D25:D26) -> 16 | E24: =SUM(E25:E26) -> 0.013311148 | F24: =SUM(F25:F26) -> 2 | G24: =SUM(G25:G26) -> 0.0016638935 | H24: =SUM(H25:H26) -> 8 | I24: =SUM(I25:I26) -> 0.006655574 | J24: =SUM(J25:J26) -> 0 | ... M24: =SUM(M25:M26) -> 0.0024958403 | N24: =AVERAGE('Monthly Headcount'!O27,'Monthly Headcount'!O58,'Monthly Headcount'!O89) -> 0.66666667 | O24: =SUM(O25:O26) -> 0.0016638935
A25: Promotions | B25: =SUM(D25,F25,H25,J25,L25,N25) -> 29 | C25: =B25/$B$5 -> 0.024126456 | D25: 15 | E25: =D25/$B$5 -> 0.012479201 | F25: 2 | G25: =F25/$B$5 -> 0.0016638935 | H25: 7 | I25: =H25/$B$5 -> 0.0058236273 | J25: =AVERAGE('Monthly Headcount'!K28,'Monthly Headcount'!K59,'Monthly Headcount'!K90) -> 0 | K25: =J25/$B$5 -> 0 | L25: 3 | M25: =L25/$B$5 -> 0.0024958403 | N25: 2 | O25: =N25/$B$5 -> 0.0016638935
A26: Transfers | B26: =SUM(D26,F26,H26,J26,L26,N26) -> 2 | C26: =B26/$B$5 -> 0.0016638935 | D26: 1 | E26: =D26/$B$5 -> 0.00083194676 | F26: =AVERAGE('Monthly Headcount'!G29,'Monthly Headcount'!G60,'Monthly Headcount'!G91) -> 0 | G26: =F26/$B$5 -> 0 | H26: 1 | I26: =H26/$B$5 -> 0.00083194676 | J26: =AVERAGE('Monthly Headcount'!K29,'Monthly Headcount'!K60,'Monthly Headcount'!K91) -> 0 | K26: =J26/$B$5 -> 0 | L26: =AVERAGE('Monthly Headcount'!M29,'Monthly Headcount'!M60,'Monthly Headcount'!M91) -> 0 | M26: =L26/$B$5 -> 0 | N26: =AVERAGE('Monthly Headcount'!O29,'Monthly Headcount'!O60,'Monthly Headcount'!O91) -> 0 | O26: =N26/$B$5 -> 0
A27: Principals | B27: =SUM(D27,F27,H27,J27,L27,N27) -> 411 | C27: =B27/B4 -> 0.19119243 | D27: =D28+D29 -> 337.33333 | E27: =D27/B27 -> 0.82076237 | F27: =F28+F29 -> 0 | G27: =F27/B27 -> 0 | H27: =H28+H29 -> 21.666667 | I27: =H27/B27 -> 0.052716951 | J27: =J28+J29 -> 36.666667 | K27: =J27/D27 -> 0.10869565 | L27: =L28+L29 -> 6 | M27: =L27/B27 -> 0.01459854 | N27: =N28+N29 -> 9.3333333 | O27: =N27/B27 -> 0.02270884
A28: Female | B28: =SUM(D28,F28,H28,J28,L28,N28) -> 120.33333 | C28: =B28/B27 -> 0.29278183 | D28: =AVERAGE('Monthly Headcount'!E31,'Monthly Headcount'!E62,'Monthly Headcount'!E93) -> 95.333333 | E28: =D28/D27 -> 0.2826087 | F28: =AVERAGE('Monthly Headcount'!G31,'Monthly Headcount'!G62,'Monthly Headcount'!G93) -> 0 | G28: 0 | H28: =AVERAGE('Monthly Headcount'!I31,'Monthly Headcount'!I62,'Monthly Headcount'!I93) -> 6 | I28: =H28/H27 -> 0.27692308 | J28: =AVERAGE('Monthly Headcount'!K31,'Monthly Headcount'!K62,'Monthly Headcount'!K93) -> 14.666667 | K28: =J28/J27 -> 0.4 | L28: =AVERAGE('Monthly Headcount'!M31,'Monthly Headcount'!M62,'Monthly Headcount'!M93) -> 1 | M28: =L28/L27 -> 0.16666667 | N28: =AVERAGE('Monthly Headcount'!O31,'Monthly Headcount'!O62,'Monthly Headcount'!O93) -> 3.3333333 | O28: 0
A29: Male | B29: =SUM(D29,F29,H29,J29,L29,N29) -> 290.66667 | C29: =B29/B27 -> 0.70721817 | D29: =AVERAGE('Monthly Headcount'!E32,'Monthly Headcount'!E63,'Monthly Headcount'!E94) -> 242 | E29: =D29/D27 -> 0.7173913 | F29: =AVERAGE('Monthly Headcount'!G32,'Monthly Headcount'!G63,'Monthly Headcount'!G94) -> 0 | G29: 0 | H29: =AVERAGE('Monthly Headcount'!I32,'Monthly Headcount'!I63,'Monthly Headcount'!I94) -> 15.666667 | I29: =H29/H27 -> 0.72307692 | J29: =AVERAGE('Monthly Headcount'!K32,'Monthly Headcount'!K63,'Monthly Headcount'!K94) -> 22 | K29: =J29/J27 -> 0.6 | L29: =AVERAGE('Monthly Headcount'!M32,'Monthly Headcount'!M63,'Monthly Headcount'!M94) -> 5 | M29: =L29/L27 -> 0.83333333 | N29: =AVERAGE('Monthly Headcount'!O32,'Monthly Headcount'!O63,'Monthly Headcount'!O94) -> 6 | O29: 0
A30: Casuals/Contractors | B30: =SUM(D30,F30,H30,J30,L30,N30) -> 536.66667 | C30: =B30/B4 -> 0.24965111 | D30: =D31+D32 -> 42.666667 | E30: =D30/B30 -> 0.079503106 | F30: =F31+F32 -> 494 | G30: =F30/B30 -> 0.92049689 | H30: =H31+H32 -> 0 | I30: 0 | J30: =J31+J32 -> 0 | K30: =J30/B30 -> 0 | L30: =L31+L32 -> 0 | M30: 0 | N30: =AVERAGE('Monthly Headcount'!O33,'Monthly Headcount'!O64,'Monthly Headcount'!O95) -> 0 | O30: 0
A31: Female | B31: =SUM(D31,F31,H31,J31,L31,N31) -> 229.33333 | C31: =B31/B30 -> 0.42732919 | D31: =AVERAGE('Monthly Headcount'!E34,'Monthly Headcount'!E65,'Monthly Headcount'!E96) -> 6 | E31: =D31/D30 -> 0.140625 | F31: =AVERAGE('Monthly Headcount'!G34,'Monthly Headcount'!G65,'Monthly Headcount'!G96) -> 223.33333 | G31: =F31/F30 -> 0.45209177 | H31: =AVERAGE('Monthly Headcount'!I34,'Monthly Headcount'!I65,'Monthly Headcount'!I96) -> 0 | I31: 0 | J31: =AVERAGE('Monthly Headcount'!K34,'Monthly Headcount'!K65,'Monthly Headcount'!K96) -> 0 | K31: 0 | L31: =AVERAGE('Monthly Headcount'!M34,'Monthly Headcount'!M65,'Monthly Headcount'!M96) -> 0 | M31: 0 | N31: =AVERAGE('Monthly Headcount'!O34,'Monthly Headcount'!O65,'Monthly Headcount'!O96) -> 0 | O31: 0
A32: Male | B32: =SUM(D32,F32,H32,J32,L32,N32) -> 307.33333 | C32: =B32/B30 -> 0.57267081 | D32: =AVERAGE('Monthly Headcount'!E35,'Monthly Headcount'!E66,'Monthly Headcount'!E97) -> 36.666667 | E32: =D32/D30 -> 0.859375 | F32: =AVERAGE('Monthly Headcount'!G35,'Monthly Headcount'!G66,'Monthly Headcount'!G97) -> 270.66667 | G32: =F32/F30 -> 0.54790823 | H32: =AVERAGE('Monthly Headcount'!I35,'Monthly Headcount'!I66,'Monthly Headcount'!I97) -> 0 | I32: 0 | J32: =AVERAGE('Monthly Headcount'!K35,'Monthly Headcount'!K66,'Monthly Headcount'!K97) -> 0 | K32: 0 | L32: =AVERAGE('Monthly Headcount'!M35,'Monthly Headcount'!M66,'Monthly Headcount'!M97) -> 0 | M32: 0 | N32: =AVERAGE('Monthly Headcount'!O35,'Monthly Headcount'!O66,'Monthly Headcount'!O97) -> 0 | O32: 0
B34: Group | D34: Uganda | F34: APDL | H34: Tanzania | J34: Rwanda | L34: Burundi | N34: Kenya
B35: Number | C35: % | D35: Number | E35: % | F35: Number | G35: % | H35: Number | I35: % | J35: Number | K35: % | L35: Number | M35: % | N35: Number | O35: %
A36: Overall Headcount | B36: 2140 | C36: 1 | D36: 949.66667 | E36: 0.44376947 | F36: 760.33333 | G36: 0.35529595 | H36: 254.66667 | I36: 0.11900312 | J36: 71 | K36: 0.03317757 | L36: 62.666667 | M36: 0.029283489 | N36: 41.666667 | O36: 0.019470405
A37: Direct Staff | B37: 1173.3333 | C37: 0.5482866 | D37: 599.66667 | E37: 0.51107955 | F37: 223.66667 | G37: 0.190625 | H37: 222.33333 | I37: 0.18948864 | J37: 36.666667 | K37: 0.03125 | L37: 58 | M37: 0.049431818 | N37: 33 | O37: 0.028125
A38: Female | B38: 292.66667 | C38: 0.24943182 | D38: 134.33333 | E38: 0.22401334 | F38: 45.666667 | G38: 0.20417288 | H38: 64.666667 | I38: 0.29085457 | J38: 14.333333 | K38: 0.39090909 | L38: 16 | M38: 0.27586207 | N38: 17.666667 | O38: 0.53535354
A39: Male | B39: 880.66667 | C39: 0.75056818 | D39: 465.33333 | E39: 0.77598666 | F39: 178 | G39: 0.79582712 | H39: 157.66667 | I39: 0.70914543 | J39: 22.333333 | K39: 0.60909091 | L39: 42 | M39: 0.72413793 | N39: 15.333333 | O39: 0.46464646
A40: Nationals | B40: 1055.3333 | C40: 0.89943182 | D40: 517.33333 | E40: 0.8627015 | F40: 213 | G40: 0.95230999 | H40: 207.33333 | I40: 0.93253373 | J40: 33 | K40: 0.9 | L40: 52.666667 | M40: 0.90804598 | N40: 32 | O40: 0.96969697
A41: Expatriates | B41: 118.66667 | C41: 0.10113636 | D41: 82.333333 | E41: 0.1372985 | F41: 10.666667 | G41: 0.047690015 | H41: 15 | I41: 0.067466267 | J41: 3.6666667 | K41: 0.1 | L41: 6 | M41: 0.10344828 | N41: 1 | O41: 0.03030303
A42: Management | B42: 255.33333 | C42: 0.21761364 | D42: 122.33333 | E42: 0.20400222 | F42: 57.333333 | G42: 0.25633383 | H42: 41.666667 | I42: 0.1874063 | J42: 11 | K42: 0.3 | L42: 16 | M42: 0.27586207 | N42: 7 | O42: 0.21212121
A43: Female in Management | B43: 46 | C43: 0.18015666 | D43: 21 | E43: 0.17166213 | F43: 8.6666667 | G43: 0.15116279 | H43: 7.3333333 | I43: 0.176 | J43: 3 | K43: 0.27272727 | L43: 4 | M43: 0.25 | N43: 2 | O43: 0.28571429
A44: Below 40 years of age | B44: 927.33333 | C44: 0.79034091 | D44: 462 | E44: 0.77042802 | F44: 178.33333 | G44: 0.79731744 | H44: 182.33333 | I44: 0.82008996 | J44: 31.666667 | K44: 0.86363636 | L44: 47 | M44: 0.81034483 | N44: 26 | O44: 0.78787879
A45: Atleast 40 years of age | B45: 246 | C45: 0.20965909 | D45: 137.66667 | E45: 0.22957198 | F45: 45.333333 | G45: 0.20268256 | H45: 40 | I45: 0.17991004 | J45: 5 | K45: 0.13636364 | L45: 11 | M45: 0.18965517 | N45: 7 | O45: 0.21212121
A46: Less than 5 years with Abacus | B46: 693 | C46: 0.590625 | D46: 367.33333 | E46: 0.61256253 | F46: 98.666667 | G46: 0.44113264 | H46: 145 | I46: 0.65217391 | J46: 28 | K46: 0.76363636 | L46: 29 | M46: 0.5 | N46: 25 | O46: 0.75757576
A47: Atleast 5 years with Abacus | B47: 480.33333 | C47: 0.409375 | D47: 232.33333 | E47: 0.38743747 | F47: 125 | G47: 0.55886736 | H47: 77.333333 | I47: 0.34782609 | J47: 8.6666667 | K47: 0.23636364 | L47: 29 | M47: 0.5 | N47: 8 | O47: 0.24242424
... A49: New hires at EXCO | B49: 0 | C49: 0 | D49: 0 | E49: 0 | F49: 0 | G49: 0 | H49: 0 | I49: 0 | J49: 0 | K49: 0 | L49: 0 | M49: 0 | N49: 0 | O49: 0
A50: New hires at EXCO - 1&2 | B50: 9 | C50: 0.0074875208 | D50: 9 | E50: 0.48214286 | F50: 0 | G50: 0 | H50: 0 | I50: 0 | J50: 0 | K50: - | L50: 0 | M50: 0 | N50: 0 | O50: 0
A51: New hires at Other Levels | B51: 32.833333 | C51: 0.027315585 | D51: 9.6666667 | E51: 0.51785714 | F51: 11 | G51: 1 | H51: 8 | I51: 1 | J51: 2.6666667 | K51: 1 | L51: 0.5 | M51: 1 | N51: 1 | O51: 1
A52: Total Exits | B52: 24.333333 | C52: 0.020244038 | D52: 9.3333333 | E52: 0.015135135 | F52: 4.3333333 | G52: 0.019145803 | H52: 5.6666667 | I52: 0.025036819 | J52: 1.5 | K52: 0.038135593 | L52: 0.5 | M52: 0.0083798883 | N52: 3 | O52: 0.089108911
A53: Exits at EXCO | B53: 0.33333333 | C53: 0.00027731559 | D53: 0.33333333 | E53: 0.00054054054 | F53: 0 | G53: 0 | H53: 0 | I53: 0 | J53: 0 | K53: 0 | L53: 0 | M53: 0 | N53: 0 | O53: 0
A54: Exits at EXCO - 1&2 | B54: 0.66666667 | C54: 0.00055463117 | D54: 0.66666667 | E54: 0.0010810811 | F54: 0 | G54: 0 | H54: 0 | I54: 0 | J54: 0 | K54: 0 | L54: 0 | M54: 0 | N54: 0 | O54: 0
A55: Exits at Other Levels | B55: 23.333333 | C55: 0.019412091 | D55: 8.3333333 | E55: 0.013513514 | F55: 4.3333333 | G55: 0.019145803 | H55: 5.6666667 | I55: 0.025036819 | J55: 1.5 | K55: 0.038135593 | L55: 0.5 | M55: 0.0083798883 | N55: 3 | O55: 0.089108911
A56: Total Internal Movements | B56: 14.666667 | D56: 6 | E56: 0 | F56: 1.3333333 | G56: 0 | H56: 7.3333333 | I56: 0 | J56: 0 | K56: 0 | L56: 0 | M56: 0 | N56: 0 | O56: 0
A57: Promotions | B57: 8.3333333 | D57: 1 | F57: 1 | H57: 6.3333333 | J57: 0 | L57: 0 | N57: 0
A58: Transfers | B58: 6.3333333 | D58: 5 | F58: 0.33333333 | H58: 1 | J58: 0 | L58: 0 | N58: 0
A59: Principals | B59: 388 | C59: 0.32279534 | D59: 308 | E59: 0.79381443 | F59: 0 | G59: 0 | H59: 32.333333 | I59: 0.083333333 | J59: 34.333333 | K59: 0.11147186 | L59: 4.6666667 | M59: 0.012027491 | N59: 8.6666667 | O59: 0.02233677
A60: Female | B60: 98.666667 | C60: 0.25429553 | D60: 69.333333 | E60: 0.22510823 | F60: 0 | G60: 0 | H60: 10.333333 | I60: 0.31958763 | J60: 14 | K60: 0.40776699 | L60: 1 | M60: 0.21428571 | N60: 4 | O60: 0
A61: Male | B61: 289.33333 | C61: 0.74570447 | D61: 238.66667 | E61: 0.77489177 | F61: 0 | G61: 0 | H61: 22 | I61: 0.68041237 | J61: 20.333333 | K61: 0.59223301 | L61: 3.6666667 | M61: 0.78571429 | N61: 4.6666667 | O61: 0
A62: Casuals/Contractors | B62: 578.66667 | C62: 0.27040498 | D62: 42 | E62: 0.072580645 | F62: 536.66667 | G62: 0.92741935 | H62: 0 | I62: 0 | J62: 0 | K62: 0 | L62: 0 | M62: 0 | N62: 0 | O62: 0
A63: Female | B63: 242.66667 | C63: 0.41935484 | D63: 6 | E63: 0.14285714 | F63: 236.66667 | G63: 0.44099379 | H63: 0 | I63: 0 | J63: 0 | K63: 0 | L63: 0 | M63: 0 | N63: 0 | O63: 0
A64: Male | B64: 336 | C64: 0.58064516 | D64: 36 | E64: 0.85714286 | F64: 300 | G64: 0.55900621 | H64: 0 | I64: 0 | J64: 0 | K64: 0 | L64: 0 | M64: 0 | N64: 0 | O64: 0

Sheet Payroll - Monthly
AA1: GROUP PAYROLL UPDATE | AH1: GROUP PAYROLL UPDATE
A2: Month | C2: Group | F2: Uganda (3900) | I2: APDL (3900) | L2: Tanzania (2700) | O2: Rwanda (1300) | R2: Burundi (3000) | U2: Kenya (160) | AA2: Jan FY25 - Monthly Gross Payroll Costs | AH2: Jan FY24 - Monthly Gross Payroll Costs
B3: (Amount in USD) | C3: Budget | D3: Actual | E3: % Change | F3: Budget | G3: Actual | H3: % Change | I3: Budget | J3: Actual | K3: % Change | L3: Budget | M3: Actual | N3: % Change | O3: Budget | P3: Actual | Q3: % Change | R3: Budget | S3: Actual | T3: % Change | U3: Budget | V3: Actual | W3: % Change | AA3: Business Unit | AB3: FTEs | AC3: Casuals | AD3: Total | AE3: FX | AF3: USD | AH3: Business Unit | AI3: FTEs | AJ3: Casuals | AK3: Total | AL3: FX | AM3: USD
A4: 45292 | B4: Total Payroll Costs | C4: #REF! | D4: - | E4: #REF! | F4: #REF! | G4: - | H4: #REF! | I4: #REF! | J4: - | K4: #REF! | L4: #REF! | M4: - | N4: #REF! | O4: #REF! | P4: - | Q4: #REF! | R4: #REF! | S4: - | T4: #REF! | U4: #REF! | V4: - | W4: #REF! | AA4: Uganda | AB4: 2527360220 | AD4: =AB4+AC4 -> 2527360220 | AE4: 3800 | AF4: =AD4/AE4 -> 665094.79 | AH4: Uganda | AI4: 1925069899 | AJ4: 7899894 | AK4: =AI4+AJ4 -> 1932969793 | AL4: 3900 | AM4: =AK4/AL4 -> 495633.28
B5: Salary components - Direct staff | C5: - | D5: - | E5: #REF! | F5: - | G5: - | H5: #DIV/0! | I5: - | K5: #DIV/0! | L5: - | N5: #DIV/0! | O5: - | Q5: #DIV/0! | R5: - | T5: #DIV/0! | U5: - | W5: #DIV/0! | Z5: School fees | AA5: APDL | AB5: 819732311 | AC5: 182675617 | AD5: =AB5+AC5 -> 1002407928 | AE5: 3800 | AF5: =AD5/AE5 -> 263791.56 | AH5: APDL | AI5: 768398874 | AJ5: 165944896 | AK5: =AI5+AJ5 -> 934343770 | AL5: 3900 | AM5: =AK5/AL5 -> 239575.33
B6: Basic Salaries | C6: - | E6: #DIV/0! | H6: #DIV/0! | K6: #DIV/0! | N6: #DIV/0! | Q6: #DIV/0! | T6: #DIV/0! | W6: #DIV/0! | X6: =X5/AE4 -> 0 | AA6: Tanzania | AB6: 418207415 | AD6: =AB6+AC6 -> 418207415 | AE6: 2850 | AF6: =AD6/AE6 -> 146739.44 | AH6: Tanzania | AI6: 352644661 | AK6: =AI6+AJ6 -> 352644661 | AL6: 2700 | AM6: =AK6/AL6 -> 130609.13
B7: Over Time | C7: - | E7: #DIV/0! | H7: #DIV/0! | K7: #DIV/0! | N7: #DIV/0! | Q7: #DIV/0! | T7: #DIV/0! | W7: #DIV/0! | AA7: Kenya | AB7: 3523373 | AC7: 27500 | AD7: =AB7+AC7 -> 3550873 | AE7: 135 | AF7: =AD7/AE7 -> 26302.763 | AH7: Kenya | AI7: 3509674 | AK7: =AI7+AJ7 -> 3509674 | AL7: 160 | AM7: =AK7/AL7 -> 21935.463
B8: Housing Allowance | C8: - | E8: #DIV/0! | H8: #REF! | K8: #DIV/0! | N8: #DIV/0! | Q8: #DIV/0! | T8: #DIV/0! | W8: #DIV/0! | AA8: Rwanda | AB8: 32530864 | AD8: =AB8+AC8 -> 32530864 | AE8: 1475 | AF8: =AD8/AE8 -> 22054.823 | AH8: Rwanda | AI8: 33264863 | AK8: =AI8+AJ8 -> 33264863 | AL8: 1300 | AM8: =AK8/AL8 -> 25588.356
B9: Other Payroll components - Direct staff | C9: - | E9: #DIV/0! | F9: - | G9: - | H9: #DIV/0! | K9: #DIV/0! | N9: #DIV/0! | Q9: #DIV/0! | T9: #DIV/0! | W9: #DIV/0! | AA9: Burundi | AB9: 91168530 | AD9: =AB9+AC9 -> 91168530 | AE9: 3500 | AF9: =AD9/AE9 -> 26048.151 | AH9: Burundi | AI9: 85655956 | AK9: =AI9+AJ9 -> 85655956 | AL9: 3000 | AM9: =AK9/AL9 -> 28551.985
B10: Bonus | C10: - | E10: #DIV/0! | H10: #DIV/0! | K10: #DIV/0! | N10: #DIV/0! | Q10: #DIV/0! | T10: #DIV/0! | W10: #DIV/0! | AC10: Total | AF10: =SUM(AF4:AF9) -> 1150031.5 | AJ10: Total | AM10: =SUM(AM4:AM9) -> 941893.54
B11: Incentives | C11: - | E11: #DIV/0! | H11: #DIV/0! | K11: #DIV/0! | N11: #DIV/0! | Q11: #DIV/0! | T11: #DIV/0! | W11: #DIV/0! | X11: Business Unit | Y11: FTES | Z11: USD
B12: School Fees | C12: - | E12: #DIV/0! | H12: #DIV/0! | K12: #DIV/0! | N12: #DIV/0! | Q12: #DIV/0! | T12: #DIV/0! | W12: #DIV/0! | X12: Uganda | Y12: =AB4+AB16+AB28+AB40+AB52+AB64+AB76+AB88+AB100+AB113+AB125+AB138 -> 2.6822417e+10 | Z12: =Y12/AE16 -> 7058530.7
B13: Arrears | C13: - | E13: #DIV/0! | H13: #DIV/0! | K13: #DIV/0! | N13: #DIV/0! | Q13: #DIV/0! | T13: #DIV/0! | W13: #DIV/0! | X13: APDL | Y13: =(AB5+AB17+AB29+AB41+AB53+AB65+AB77+AB89+AB101+AB114+AB126+AB139)*0+3937617277 -> 3937617277 | Z13: =Y13/AE17 -> 1036215.1 | AA13: GROUP PAYROLL UPDATE | AH13: GROUP PAYROLL UPDATE
B14: Total Salaries - 'Principal Companies | C14: #REF! | E14: #REF! | F14: #REF! | H14: #REF! | I14: #REF! | K14: #REF! | L14: #REF! | N14: #REF! | O14: #REF! | Q14: #REF! | R14: #REF! | T14: #REF! | U14: #REF! | W14: #REF! | X14: Tanzania | Y14: =AB6+AB18+AB30+AB42+AB54+AB66+AB78+AB90+AB102+AB115+AB127+AB140 -> 5.6417888e+09 | Z14: =Y14/AE18 -> 1979575 | AA14: Feb FY25-Monthly Payroll Costs | AH14: Feb FY24-Monthly Payroll Costs
B15: Total Wages - 'Casuals/Contractors | C15: #REF! | E15: #REF! | F15: #REF! | H15: #REF! | I15: #REF! | K15: #REF! | L15: #REF! | N15: - | O15: #REF! | Q15: #REF! | R15: #REF! | T15: - | U15: #REF! | W15: - | X15: Kenya | Y15: =AB7+AB19+AB31+AB43+AB55+AB67+AB79+AB91+AB103+AB116+AB128+AB141 -> 39757073 | Z15: =Y15/AE19 -> 294496.84 | AA15: Business Unit | AB15: FTES | AC15: Casuals | AD15: Total | AE15: FX | AF15: USD | AH15: Business Unit | AI15: FTES | AJ15: Casuals | AK15: Total | AL15: FX | AM15: USD
A16: 45323 | B16: Total Payroll Costs | C16: #REF! | D16: - | E16: #REF! | F16: #REF! | G16: - | H16: #REF! | I16: #REF! | J16: - | K16: #REF! | L16: #REF! | M16: - | N16: #REF! | O16: #REF! | P16: - | Q16: #REF! | R16: #REF! | S16: - | T16: #REF! | U16: #REF! | V16: - | W16: #REF! | X16: Rwanda | Y16: =AB8+AB20+AB32+AB44+AB56+AB68+AB80+AB92+AB104+AB117+AB129+AB142 -> 544414067 | Z16: =Y16/AE20 -> 369094.28 | AA16: Uganda | AB16: 2482448390 | AD16: =AB16+AC16 -> 2482448390 | AE16: 3800 | AF16: =AD16/AE16 -> 653275.89 | AH16: Uganda | AI16: 2072195199 | AJ16: 7183909 | AK16: =AI16+AJ16 -> 2079379108 | AL16: 3900 | AM16: =AK16/AL16 -> 533174.13
B17: Salary components - Direct staff | C17: - | D17: - | E17: #REF! | F17: - | G17: - | H17: #DIV/0! | I17: - | K17: #DIV/0! | L17: - | N17: #DIV/0! | O17: - | Q17: #DIV/0! | R17: - | T17: #DIV/0! | U17: - | W17: #DIV/0! | X17: Burundi | Y17: =AB9+AB21+AB33+AB45+AB57+AB69+AB81+AB93+AB105+AB118+AB130+AB143 -> 1329045775 | Z17: =Y17/AE21 -> 379727.36 | AA17: APDL | AB17: 717623093 | AC17: 162671248 | AD17: =AB17+AC17 -> 880294341 | AE17: 3800 | AF17: =AD17/AE17 -> 231656.41 | AH17: APDL | AI17: 664825261 | AJ17: 159081998 | AK17: =AI17+AJ17 -> 823907259 | AL17: 3900 | AM17: =AK17/AL17 -> 211258.27
B18: Basic Salaries | C18: - | E18: #DIV/0! | H18: #DIV/0! | K18: #DIV/0! | N18: #DIV/0! | Q18: #DIV/0! | T18: #DIV/0! | W18: #DIV/0! | X18: AKLS | Z18: =(8528+8376)*12 -> 202848 | AA18: Tanzania | AB18: 476204671 | AC18: 0 | AD18: =AB18+AC18 -> 476204671 | AE18: 2850 | AF18: =AD18/AE18 -> 167089.36 | AH18: Tanzania | AI18: 367943763 | AJ18: 0 | AK18: =AI18+AJ18 -> 367943763 | AL18: 2700 | AM18: =AK18/AL18 -> 136275.47
B19: Over Time | C19: - | E19: #DIV/0! | H19: #DIV/0! | K19: #DIV/0! | N19: #DIV/0! | Q19: #DIV/0! | T19: #DIV/0! | W19: #DIV/0! | X19: Group | Z19: =SUM(Z12:Z18) -> 11320487 | AA19: Kenya | AB19: 3602939 | AC19: 27500 | AD19: =AB19+AC19 -> 3630439 | AE19: 135 | AF19: =AD19/AE19 -> 26892.141 | AH19: Kenya | AI19: 3666808 | AJ19: 97450 | AK19: =AI19+AJ19 -> 3764258 | AL19: 160 | AM19: =AK19/AL19 -> 23526.612
B20: Housing Allowance | C20: - | E20: #DIV/0! | H20: #REF! | K20: #DIV/0! | N20: #DIV/0! | Q20: #DIV/0! | T20: #DIV/0! | W20: #DIV/0! | AA20: Rwanda | AB20: 48942842 | AD20: =AB20+AC20 -> 48942842 | AE20: 1475 | AF20: =AD20/AE20 -> 33181.588 | AH20: Rwanda | AI20: 32498825 | AK20: =AI20+AJ20 -> 32498825 | AL20: 1300 | AM20: =AK20/AL20 -> 24999.096
B21: Other Payroll components - Direct staff | C21: - | E21: #DIV/0! | F21: - | G21: - | H21: #DIV/0! | K21: #DIV/0! | N21: #DIV/0! | Q21: #DIV/0! | T21: #DIV/0! | W21: #DIV/0! | AA21: Burundi | AB21: 97555934 | AC21: 0 | AD21: =AB21+AC21 -> 97555934 | AE21: 3500 | AF21: =AD21/AE21 -> 27873.124 | AH21: Burundi | AI21: 85896206 | AJ21: 0 | AK21: =AI21+AJ21 -> 85896206 | AL21: 3000 | AM21: =AK21/AL21 -> 28632.069
B22: Bonus | C22: - | E22: #DIV/0! | H22: #DIV/0! | K22: #DIV/0! | N22: #DIV/0! | Q22: #DIV/0! | T22: #DIV/0! | W22: #DIV/0! | AA22: Group | AE22: Total | AF22: =SUM(AF16:AF21) -> 1139968.5 | AH22: Group | AL22: Total | AM22: =SUM(AM16:AM21) -> 957865.65
B23: Incentives | C23: - | E23: #DIV/0! | H23: #DIV/0! | K23: #DIV/0! | N23: #DIV/0! | Q23: #DIV/0! | T23: #DIV/0! | W23: #DIV/0!
B24: School Fees | C24: - | E24: #DIV/0! | H24: #DIV/0! | K24: #DIV/0! | N24: #DIV/0! | Q24: #DIV/0! | T24: #DIV/0! | W24: #DIV/0!
B25: Arrears | C25: - | E25: #DIV/0! | H25: #DIV/0! | K25: #DIV/0! | N25: #DIV/0! | Q25: #DIV/0! | T25: #DIV/0! | W25: #DIV/0! | AA25: GROUP PAYROLL UPDATE | AH25: GROUP PAYROLL UPDATE
B26: Total Salaries - 'Principal Companies | C26: #REF! | E26: #REF! | F26: #REF! | H26: #REF! | I26: #REF! | K26: #REF! | L26: #REF! | N26: #REF! | O26: #REF! | Q26: #REF! | R26: #REF! | T26: #REF! | U26: #REF! | W26: #REF! | AA26: March FY25-Monthly Gross Payroll Costs | AH26: March FY24-Monthly Gross Payroll Costs
B27: Total Wages - 'Casuals/Contractors | C27: #REF! | E27: #REF! | F27: #REF! | H27: #REF! | I27: #REF! | K27: #REF! | L27: #REF! | N27: - | O27: #REF! | Q27: #REF! | R27: #REF! | T27: - | U27: #REF! | W27: - | AA27: Business Unit | AB27: FTES | AC27: Casuals | AD27: Total | AE27: FX | AF27: USD | AH27: Business Unit | AI27: FTES | AJ27: Casuals | AK27: Total | AL27: FX | AM27: USD
A28: 45352 | B28: Total Payroll Costs | C28: #REF! | D28: - | E28: #REF! | F28: #REF! | G28: - | H28: #REF! | I28: #REF! | J28: - | K28: #REF! | L28: #REF! | M28: - | N28: #REF! | O28: #REF! | P28: - | Q28: #REF! | R28: #REF! | S28: - | T28: #REF! | U28: #REF! | V28: - | W28: #REF! | AA28: Uganda | AB28: 2253821642 | AD28: =AB28+AC28 -> 2253821642 | AE28: 3800 | AF28: =AD28/AE28 -> 593110.96 | AH28: Uganda | AI28: 2422485038 | AJ28: 8639792 | AK28: =AI28+AJ28 -> 2431124830 | AL28: 3900 | AM28: =AK28/AL28 -> 623365.34
B29: Salary components - Direct staff | C29: - | D29: - | E29: #REF! | F29: - | G29: - | H29: #DIV/0! | I29: - | K29: #DIV/0! | L29: - | N29: #DIV/0! | O29: - | Q29: #DIV/0! | R29: - | T29: #DIV/0! | U29: - | W29: #DIV/0! | AA29: APDL | AB29: 752536334 | AC29: 202783555 | AD29: =AB29+AC29 -> 955319889 | AE29: 3800 | AF29: =AD29/AE29 -> 251399.97 | AH29: APDL | AI29: 767385515 | AJ29: 178894190 | AK29: =AI29+AJ29 -> 946279705 | AL29: 3900 | AM29: =AK29/AL29 -> 242635.82
B30: Basic Salaries | C30: - | E30: #DIV/0! | H30: #DIV/0! | K30: #DIV/0! | N30: #DIV/0! | Q30: #DIV/0! | T30: #DIV/0! | W30: #DIV/0! | Z30: Salary Increment | AA30: Tanzania | AB30: 700417000 | AD30: =AB30+AC30 -> 700417000 | AE30: 2850 | AF30: =AD30/AE30 -> 245760.35 | AH30: Tanzania | AI30: 462579298 | AJ30: 0 | AK30: =AI30+AJ30 -> 462579298 | AL30: 2700 | AM30: =AK30/AL30 -> 171325.67
B31: Over Time | C31: - | E31: #DIV/0! | H31: #DIV/0! | K31: #DIV/0! | N31: #DIV/0! | Q31: #DIV/0! | T31: #DIV/0! | W31: #DIV/0! | Z31: Red sea | AA31: Kenya | AB31: 3823250 | AC31: 11200 | AD31: =AB31+AC31 -> 3834450 | AE31: 135 | AF31: =AD31/AE31 -> 28403.333 | AH31: Kenya | AI31: 4818946 | AJ31: 91500 | AK31: =AI31+AJ31 -> 4910446 | AL31: 160 | AM31: =AK31/AL31 -> 30690.287
B32: Housing Allowance | C32: - | E32: #DIV/0! | H32: #REF! | K32: #DIV/0! | N32: #DIV/0! | Q32: #DIV/0! | T32: #DIV/0! | W32: #DIV/0! | AA32: Rwanda | AB32: 55403785 | AC32: 0 | AD32: =AB32+AC32 -> 55403785 | AE32: 1475 | AF32: =AD32/AE32 -> 37561.888 | AH32: Rwanda | AI32: 47277497 | AJ32: 0 | AK32: =AI32+AJ32 -> 47277497 | AL32: 1300 | AM32: =AK32/AL32 -> 36367.305
B33: Other Payroll components - Direct staff | C33: - | E33: #DIV/0! | F33: - | G33: - | H33: #DIV/0! | K33: #DIV/0! | N33: #DIV/0! | Q33: #DIV/0! | T33: #DIV/0! | W33: #DIV/0! | AA33: Burundi | AB33: 147457202 | AC33: 0 | AD33: =AB33+AC33 -> 147457202 | AE33: 3500 | AF33: =AD33/AE33 -> 42130.629 | AH33: Burundi | AI33: 106751957 | AJ33: 0 | AK33: =AI33+AJ33 -> 106751957 | AL33: 3000 | AM33: =AK33/AL33 -> 35583.986
B34: Bonus | C34: - | E34: #DIV/0! | H34: #DIV/0! | K34: #DIV/0! | N34: #DIV/0! | Q34: #DIV/0! | T34: #DIV/0! | W34: #DIV/0! | AA34: Group | AE34: Total | AF34: =SUM(AF28:AF33) -> 1198367.1 | AH34: Group | AL34: Total | AM34: =SUM(AM28:AM33) -> 1139968.4
B35: Incentives | C35: - | E35: #DIV/0! | H35: #DIV/0! | K35: #DIV/0! | N35: #DIV/0! | Q35: #DIV/0! | T35: #DIV/0! | W35: #DIV/0!
B36: School Fees | C36: - | E36: #DIV/0! | H36: #DIV/0! | K36: #DIV/0! | N36: #DIV/0! | Q36: #DIV/0! | T36: #DIV/0! | W36: #DIV/0!
B37: Arrears | C37: - | E37: #DIV/0! | H37: #DIV/0! | K37: #DIV/0! | N37: #DIV/0! | Q37: #DIV/0! | T37: #DIV/0! | W37: #DIV/0! | AA37: GROUP PAYROLL UPDATE DIRECT STAFF | AH37: GROUP PAYROLL UPDATE DIRECT STAFF
B38: Total Salaries - 'Principal Companies | C38: #REF! | E38: #REF! | F38: #REF! | H38: #REF! | I38: #REF! | K38: #REF! | L38: #REF! | N38: #REF! | O38: #REF! | Q38: #REF! | R38: #REF! | T38: #REF! | U38: #REF! | W38: #REF! | AA38: April FY25-Monthly Gross Payroll Costs | AH38: April FY24-Monthly Gross Payroll Costs
B39: Total Wages - 'Casuals/Contractors | C39: #REF! | E39: #REF! | F39: #REF! | H39: #REF! | I39: #REF! | K39: #REF! | L39: #REF! | N39: - | O39: #REF! | Q39: #REF! | R39: #REF! | T39: - | U39: #REF! | W39: - | AA39: Business Unit | AB39: FTES | AC39: Casuals | AD39: Total | AE39: FX | AF39: USD | AH39: Business Unit | AI39: FTES | AJ39: Casuals | AK39: Total | AL39: FX | AM39: USD
A40: 45383 | B40: Total Payroll Costs | C40: #REF! | D40: - | E40: #REF! | F40: #REF! | G40: - | H40: #REF! | I40: #REF! | J40: - | K40: #REF! | L40: #REF! | M40: - | N40: #REF! | O40: #REF! | P40: - | Q40: #REF! | R40: #REF! | S40: - | T40: #REF! | U40: #REF! | V40: - | W40: #REF! | AA40: Uganda | AB40: 2934134126 | AC40: 15294786 | AD40: =AB40+AC40 -> 2949428912 | AE40: 3800 | AF40: =AD40/AE40 -> 776165.5 | AH40: Uganda | AI40: 2016267514 | AJ40: 7260649 | AK40: 2023528163 | AL40: 3900 | AM40: 518853
B41: Salary components - Direct staff | C41: - | D41: - | E41: #REF! | F41: - | G41: - | H41: #DIV/0! | I41: - | K41: #DIV/0! | L41: - | N41: #DIV/0! | O41: - | Q41: #DIV/0! | R41: - | T41: #DIV/0! | U41: - | W41: #DIV/0! | AA41: APDL | AB41: 751624086 | AC41: 207927241 | AD41: =AB41+AC41 -> 959551327 | AE41: 3800 | AF41: =AD41/AE41 -> 252513.51 | AH41: APDL | AI41: 709805502 | AJ41: 190469437 | AK41: 900274939 | AL41: 3900 | AM41: 230840
B42: Basic Salaries | C42: - | E42: #DIV/0! | H42: #DIV/0! | K42: #DIV/0! | N42: #DIV/0! | Q42: #DIV/0! | T42: #DIV/0! | W42: #DIV/0! | AA42: Tanzania | AB42: 434062193 | AC42: 0 | AD42: =AB42+AC42 -> 434062193 | AE42: 2850 | AF42: =AD42/AE42 -> 152302.52 | AH42: Tanzania | AI42: 410328647 | AJ42: 0 | AK42: 410328647 | AL42: 2700 | AM42: 151974
B43: Over Time | C43: - | E43: #DIV/0! | H43: #DIV/0! | K43: #DIV/0! | N43: #DIV/0! | Q43: #DIV/0! | T43: #DIV/0! | W43: #DIV/0! | AA43: Kenya | AB43: 3575549 | AC43: 16500 | AD43: =AB43+AC43 -> 3592049 | AE43: 135 | AF43: =AD43/AE43 -> 26607.77 | AH43: Kenya | AI43: 4509920 | AJ43: 72300 | AK43: 4582220 | AL43: 160 | AM43: 28639
B44: Housing Allowance | C44: - | E44: #DIV/0! | H44: #REF! | K44: #DIV/0! | N44: #DIV/0! | Q44: #DIV/0! | T44: #DIV/0! | W44: #DIV/0! | AA44: Rwanda | AB44: 50144988 | AC44: 0 | AD44: =AB44+AC44 -> 50144988 | AE44: 1250 | AF44: =AD44/AE44 -> 40115.99 | AH44: Rwanda | AI44: 41287929 | AJ44: 0 | AK44: 41287929 | AL44: 1300 | AM44: 31760
B45: Other Payroll components - Direct staff | C45: - | E45: #DIV/0! | F45: - | G45: - | H45: #DIV/0! | K45: #DIV/0! | N45: #DIV/0! | Q45: #DIV/0! | T45: #DIV/0! | W45: #DIV/0! | AA45: Burundi | AB45: 113454326 | AC45: 0 | AD45: =AB45+AC45 -> 113454326 | AE45: 3000 | AF45: =AD45/AE45 -> 37818.109 | AH45: Burundi | AI45: 99177165 | AJ45: 0 | AK45: 99177165 | AL45: 3000 | AM45: 33059
B46: Bonus | C46: - | E46: #DIV/0! | H46: #DIV/0! | K46: #DIV/0! | N46: #DIV/0! | Q46: #DIV/0! | T46: #DIV/0! | W46: #DIV/0! | AA46: Group | AE46: Total | AF46: =SUM(AF40:AF45) -> 1285523.4 | AH46: Group | AL46: Total | AM46: =SUM(AM40:AM45) -> 995125
B47: Incentives | C47: - | E47: #DIV/0! | H47: #DIV/0! | K47: #DIV/0! | N47: #DIV/0! | Q47: #DIV/0! | T47: #DIV/0! | W47: #DIV/0!
B48: School Fees | C48: - | E48: #DIV/0! | H48: #DIV/0! | K48: #DIV/0! | N48: #DIV/0! | Q48: #DIV/0! | T48: #DIV/0! | W48: #DIV/0!
B49: Arrears | C49: - | E49: #DIV/0! | H49: #DIV/0! | K49: #DIV/0! | N49: #DIV/0! | Q49: #DIV/0! | T49: #DIV/0! | W49: #DIV/0! | AA49: GROUP PAYROLL UPDATE DIRECT STAFF | AH49: GROUP PAYROLL UPDATE DIRECT STAFF DIRECT STAFF
B50: Total Salaries - 'Principal Companies | C50: #REF! | E50: #REF! | F50: #REF! | H50: #REF! | I50: #REF! | K50: #REF! | L50: #REF! | N50: #REF! | O50: #REF! | Q50: #REF! | R50: #REF! | T50: #REF! | U50: #REF! | W50: #REF! | AA50: May FY25-Monthly Gross Payroll Costs | AH50: May FY24-Monthly Gross Payroll Costs
B51: Total Wages - 'Casuals/Contractors | C51: #REF! | E51: #REF! | F51: #REF! | H51: #REF! | I51: #REF! | K51: #REF! | L51: #REF! | N51: - | O51: #REF! | Q51: #REF! | R51: #REF! | T51: - | U51: #REF! | W51: - | AA51: Business Unit | AB51: FTES | AC51: Casuals | AD51: Total | AE51: FX | AF51: USD | AH51: Business Unit | AI51: FTES | AJ51: Casuals | AK51: Total | AL51: FX | AM51: USD
A52: 45413 | B52: Total Payroll Costs | C52: #REF! | D52: - | E52: #REF! | F52: #REF! | G52: - | H52: #REF! | I52: #REF! | J52: - | K52: #REF! | L52: #REF! | M52: - | N52: #REF! | O52: #REF! | P52: - | Q52: #REF! | R52: #REF! | S52: - | T52: #REF! | U52: #REF! | V52: - | W52: #REF! | AA52: Uganda | AB52: 2213197619 | AC52: 17500810 | AD52: =AB52+AC52 -> 2230698429 | AE52: 3800 | AF52: =AD52/AE52 -> 587025.9 | AH52: Uganda | AI52: 2923740308 | AJ52: 6454571 | AK52: 2930194879 | AL52: 3900 | AM52: 751332
B53: Salary components - Direct staff | C53: - | D53: - | E53: #REF! | F53: =SUM(F54:F56) -> 0 | G53: =SUM(G54:G56) -> 0 | H53: #DIV/0! | I53: - | K53: #DIV/0! | L53: - | N53: #DIV/0! | O53: - | Q53: #DIV/0! | R53: - | T53: #DIV/0! | U53: - | W53: #DIV/0! | AA53: APDL | AB53: 670470162 | AC53: 208676663 | AD53: =AB53+AC53 -> 879146825 | AE53: 3800 | AF53: =AD53/AE53 -> 231354.43 | AH53: APDL | AI53: 767385515 | AJ53: 169945454 | AK53: 937330969 | AL53: 3900 | AM53: 240341
B54: Basic Salaries | C54: - | E54: #DIV/0! | H54: #DIV/0! | K54: #DIV/0! | N54: #DIV/0! | Q54: #DIV/0! | T54: #DIV/0! | W54: #DIV/0! | AA54: Tanzania | AB54: 478593369 | AC54: 0 | AD54: =AB54+AC54 -> 478593369 | AE54: 2850 | AF54: =AD54/AE54 -> 167927.5 | AH54: Tanzania | AI54: 545856052 | AJ54: 0 | AK54: 545856052 | AL54: 2700 | AM54: 202169
B55: Over Time | C55: - | E55: #DIV/0! | H55: #DIV/0! | K55: #DIV/0! | N55: #DIV/0! | Q55: #DIV/0! | T55: #DIV/0! | W55: #DIV/0! | AA55: Kenya | AB55: 3336626 | AC55: 7020 | AD55: =AB55+AC55 -> 3343646 | AE55: 135 | AF55: =AD55/AE55 -> 24767.748 | AH55: Kenya | AI55: 4637756 | AJ55: 45200 | AK55: 4682956 | AL55: 160 | AM55: 29268
B56: Housing Allowance | C56: - | E56: #DIV/0! | H56: #REF! | K56: #DIV/0! | N56: #DIV/0! | Q56: #DIV/0! | T56: #DIV/0! | W56: #DIV/0! | AA56: Rwanda | AB56: 60696250 | AC56: 0 | AD56: =AB56+AC56 -> 60696250 | AE56: 1475 | AF56: =AD56/AE56 -> 41150 | AH56: Rwanda | AI56: 45836140 | AJ56: 0 | AK56: 45836140 | AL56: 1300 | AM56: 35259
B57: Other Payroll components - Direct staff | C57: - | E57: #DIV/0! | F57: =SUM(F58:F60) -> 0 | G57: =SUM(G58:G60) -> 0 | H57: #DIV/0! | K57: #DIV/0! | N57: #DIV/0! | Q57: #DIV/0! | T57: #DIV/0! | W57: #DIV/0! | AA57: Burundi | AB57: 116166557 | AC57: 0 | AD57: =AB57+AC57 -> 116166557 | AE57: 3500 | AF57: =AD57/AE57 -> 33190.445 | AH57: Burundi | AI57: 98649845 | AJ57: 0 | AK57: 98649845 | AL57: 3000 | AM57: 32883
B58: Bonus | C58: - | E58: #DIV/0! | H58: #DIV/0! | K58: #DIV/0! | N58: #DIV/0! | Q58: #DIV/0! | T58: #DIV/0! | W58: #DIV/0! | AA58: Group | AE58: Total | AF58: =SUM(AF52:AF57) -> 1085416 | AH58: Group | AL58: Total | AM58: =SUM(AM52:AM57) -> 1291252
B59: Incentives | C59: - | E59: #DIV/0! | H59: #DIV/0! | K59: #DIV/0! | N59: #DIV/0! | Q59: #DIV/0! | T59: #DIV/0! | W59: #DIV/0!
B60: School Fees | C60: - | E60: #DIV/0! | H60: #DIV/0! | K60: #DIV/0! | N60: #DIV/0! | Q60: #DIV/0! | T60: #DIV/0! | W60: #DIV/0!
B61: Arrears | C61: - | E61: #DIV/0! | H61: #DIV/0! | K61: #DIV/0! | N61: #DIV/0! | Q61: #DIV/0! | T61: #DIV/0! | W61: #DIV/0! | AA61: GROUP PAYROLL UPDATE DIRECT STAFF | AH61: GROUP PAYROLL UPDATE DIRECT STAFF
B62: Total Salaries - 'Principal Companies | C62: #REF! | E62: #REF! | H62: #REF! | I62: #REF! | K62: #REF! | L62: #REF! | N62: #REF! | O62: #REF! | Q62: #REF! | R62: #REF! | T62: #REF! | U62: #REF! | W62: #REF! | AA62: June FY25-Monthly Gross Payroll Costs | AH62: June FY24-Monthly Gross Payroll Costs
B63: Total Wages - 'Casuals/Contractors | C63: #REF! | E63: #REF! | H63: #REF! | I63: #REF! | K63: #REF! | L63: #REF! | N63: - | O63: #REF! | Q63: #REF! | R63: #REF! | T63: - | U63: #REF! | W63: - | AA63: Business Unit | AB63: FTES | AC63: Casuals | AD63: Total | AE63: FX | AF63: USD | AH63: Business Unit | AI63: FTES | AJ63: Casuals | AK63: Total | AL63: FX | AM63: USD
A64: 45444 | B64: Total Payroll Costs | C64: #REF! | D64: - | E64: #REF! | F64: #REF! | G64: - | H64: #REF! | I64: #REF! | J64: - | K64: #REF! | L64: #REF! | M64: - | N64: #REF! | O64: #REF! | P64: - | Q64: #REF! | R64: #REF! | S64: - | T64: #REF! | U64: #REF! | V64: - | W64: #REF! | AA64: Uganda | AB64: 2269638096 | AC64: 15446498 | AD64: =AB64+AC64 -> 2285084594 | AE64: 3800 | AF64: =AD64/AE64 -> 601338.05 | AH64: Uganda | AI64: 2239793267 | AJ64: 6455631 | AK64: 2246248898 | AL64: 3900 | AM64: 575961
B65: Salary components - Direct staff | C65: - | D65: - | E65: #REF! | F65: - | G65: - | H65: #DIV/0! | I65: - | K65: #DIV/0! | L65: - | N65: #DIV/0! | O65: - | Q65: #DIV/0! | R65: - | T65: #DIV/0! | U65: - | W65: #DIV/0! | AA65: APDL | AB65: 671025975 | AC65: 217347040 | AD65: =AB65+AC65 -> 888373015 | AE65: 3800 | AF65: =AD65/AE65 -> 233782.37 | AH65: APDL | AI65: 733361043 | AJ65: 185846557 | AK65: 919207600 | AL65: 3900 | AM65: 235694
B66: Basic Salaries | C66: - | E66: #DIV/0! | H66: #DIV/0! | K66: #DIV/0! | N66: #DIV/0! | Q66: #DIV/0! | T66: #DIV/0! | W66: #DIV/0! | AA66: Tanzania | AB66: 432160254 | AC66: 0 | AD66: =AB66+AC66 -> 432160254 | AE66: 2850 | AF66: =AD66/AE66 -> 151635.18 | AH66: Tanzania | AI66: 444635119 | AJ66: 0 | AK66: 444635119 | AL66: 2700 | AM66: 164680
B67: Over Time | C67: - | E67: #DIV/0! | H67: #DIV/0! | K67: #DIV/0! | N67: #DIV/0! | Q67: #DIV/0! | T67: #DIV/0! | W67: #DIV/0! | AA67: Kenya | AB67: 3146482 | AC67: 1480 | AD67: =AB67+AC67 -> 3147962 | AE67: 135 | AF67: =AD67/AE67 -> 23318.237 | AH67: Kenya | AI67: 4720813 | AJ67: 39800 | AK67: 4760613 | AL67: 160 | AM67: 29754
B68: Housing Allowance | C68: - | E68: #DIV/0! | H68: #REF! | K68: #DIV/0! | N68: #DIV/0! | Q68: #DIV/0! | T68: #DIV/0! | W68: #DIV/0! | AA68: Rwanda | AB68: 42689242 | AC68: 0 | AE68: 1475 | AF68: =AD68/AE68 -> 0 | AH68: Rwanda | AI68: 53922018 | AJ68: 0 | AL68: 1300 | AM68: 0
B69: Other Payroll components - Direct staff | C69: - | E69: #DIV/0! | F69: - | G69: - | H69: #DIV/0! | K69: #DIV/0! | N69: #DIV/0! | Q69: #DIV/0! | T69: #DIV/0! | W69: #DIV/0! | AA69: Burundi | AB69: 115075823 | AC69: 0 | AD69: =AB69+AC69 -> 115075823 | AE69: 3500 | AF69: =AD69/AE69 -> 32878.807 | AH69: Burundi | AI69: 84270026 | AJ69: 0 | AK69: 84270026 | AL69: 3000 | AM69: 28090
B70: Bonus | C70: - | E70: #DIV/0! | H70: #DIV/0! | K70: #DIV/0! | N70: #DIV/0! | Q70: #DIV/0! | T70: #DIV/0! | W70: #DIV/0! | AA70: Group | AE70: Total | AF70: =SUM(AF64:AF69) -> 1042952.6 | AH70: Group | AL70: Total | AM70: =SUM(AM64:AM69) -> 1034179
B71: Incentives | C71: - | E71: #DIV/0! | H71: #DIV/0! | K71: #DIV/0! | N71: #DIV/0! | Q71: #DIV/0! | T71: #DIV/0! | W71: #DIV/0!
B72: School Fees | C72: - | E72: #DIV/0! | H72: #DIV/0! | K72: #DIV/0! | N72: #DIV/0! | Q72: #DIV/0! | T72: #DIV/0! | W72: #DIV/0!
B73: Arrears | C73: - | E73: #DIV/0! | H73: #DIV/0! | K73: #DIV/0! | N73: #DIV/0! | Q73: #DIV/0! | T73: #DIV/0! | W73: #DIV/0! | AA73: GROUP PAYROLL UPDATE DIRECT STAFF | AH73: GROUP PAYROLL UPDATE DIRECT STAFF
B74: Total Salaries - 'Principal Companies | C74: #REF! | E74: #REF! | F74: #REF! | H74: #REF! | I74: #REF! | K74: #REF! | L74: #REF! | N74: #REF! | O74: #REF! | Q74: #REF! | R74: #REF! | T74: #REF! | U74: #REF! | W74: #REF! | AA74: July FY25-Monthly Gross Payroll Costs | AH74: July FY24-Monthly Gross Payroll Costs
B75: Total Wages - 'Casuals/Contractors | C75: #REF! | E75: #REF! | F75: #REF! | H75: #REF! | I75: #REF! | K75: #REF! | L75: #REF! | N75: - | O75: #REF! | Q75: #REF! | R75: #REF! | T75: - | U75: #REF! | W75: - | AA75: Business Unit | AB75: FTES | AC75: Casuals | AD75: Total | AE75: FX | AF75: USD | AH75: Business Unit | AI75: FTES | AJ75: Casuals | AK75: Total | AL75: FX | AM75: USD
A76: 45474 | B76: Total Payroll Costs | C76: #REF! | D76: - | E76: #REF! | F76: #REF! | G76: - | H76: #REF! | I76: #REF! | J76: - | K76: #REF! | L76: #REF! | M76: - | N76: #REF! | O76: #REF! | P76: - | Q76: #REF! | R76: #REF! | S76: - | T76: #REF! | U76: #REF! | V76: - | W76: #REF! | AA76: Uganda | AB76: 2026648520 | AC76: 18131279 | AD76: =AB76+AC76 -> 2044779799 | AE76: 3800 | AF76: =AD76/AE76 -> 538099.95 | AH76: Uganda | AI76: 2822834172 | AJ76: 6622402 | AK76: =AI76+AJ76 -> 2829456574 | AL76: 3900 | AM76: =AK76/AL76 -> 725501.69
B77: Salary components - Direct staff | C77: - | D77: - | E77: #REF! | F77: - | G77: - | H77: #DIV/0! | I77: - | K77: #DIV/0! | L77: - | N77: #DIV/0! | O77: - | Q77: #DIV/0! | R77: - | T77: #DIV/0! | U77: - | W77: #DIV/0! | AA77: APDL | AB77: 6.7613741e+08 | AC77: 221672091 | AD77: =AB77+AC77 -> 8.978095e+08 | AE77: 3800 | AF77: =AD77/AE77 -> 236265.66 | AH77: APDL | AI77: 680847542 | AJ77: 177841143 | AK77: =AI77+AJ77 -> 858688685 | AL77: 3900 | AM77: =AK77/AL77 -> 220176.59
B78: Basic Salaries | C78: - | E78: #DIV/0! | H78: #DIV/0! | K78: #DIV/0! | N78: #DIV/0! | Q78: #DIV/0! | T78: #DIV/0! | W78: #DIV/0! | AA78: Tanzania | AB78: 501265247 | AD78: =AB78+AC78 -> 501265247 | AE78: 2850 | AF78: =AD78/AE78 -> 175882.54 | AH78: Tanzania | AI78: 690298714 | AK78: =AI78+AJ78 -> 690298714 | AL78: 2700 | AM78: =AK78/AL78 -> 255666.19
B79: Over Time | C79: - | E79: #DIV/0! | H79: #DIV/0! | K79: #DIV/0! | N79: #DIV/0! | Q79: #DIV/0! | T79: #DIV/0! | W79: #DIV/0! | AA79: Kenya | AB79: 3154482 | AC79: 8140 | AD79: =AB79+AC79 -> 3162622 | AE79: 135 | AF79: =AD79/AE79 -> 23426.83 | AH79: Kenya | AI79: 4393637 | AJ79: 38900 | AK79: =AI79+AJ79 -> 4432537 | AL79: 160 | AM79: =AK79/AL79 -> 27703.356
B80: Housing Allowance | C80: - | E80: #DIV/0! | H80: #REF! | K80: #DIV/0! | N80: #DIV/0! | Q80: #DIV/0! | T80: #DIV/0! | W80: #DIV/0! | AA80: Rwanda | AB80: 41500071 | AD80: =AB80+AC80 -> 41500071 | AE80: 1475 | AF80: =AD80/AE80 -> 28135.641 | AH80: Rwanda | AI80: 126298174 | AK80: =AI80+AJ80 -> 126298174 | AL80: 1300 | AM80: =AK80/AL80 -> 97152.442
B81: Other Payroll components - Direct staff | C81: - | E81: #DIV/0! | F81: - | G81: - | H81: #DIV/0! | K81: #DIV/0! | N81: #DIV/0! | Q81: #DIV/0! | T81: #DIV/0! | W81: #DIV/0! | AA81: Burundi | AB81: 115328341 | AD81: =AB81+AC81 -> 115328341 | AE81: 3500 | AF81: =AD81/AE81 -> 32950.955 | AH81: Burundi | AI81: 83877460 | AK81: =AI81+AJ81 -> 83877460 | AL81: 3000 | AM81: =AK81/AL81 -> 27959.153
B82: Bonus | C82: - | E82: #DIV/0! | H82: #DIV/0! | K82: #DIV/0! | N82: #DIV/0! | Q82: #DIV/0! | T82: #DIV/0! | W82: #DIV/0! | AA82: Group | AE82: Total | AF82: =SUM(AF76:AF81) -> 1034761.6 | AH82: Group | AL82: Total | AM82: =SUM(AM76:AM81) -> 1354159.4
B83: Incentives | C83: - | E83: #DIV/0! | H83: #DIV/0! | K83: #DIV/0! | N83: #DIV/0! | Q83: #DIV/0! | T83: #DIV/0! | W83: #DIV/0!
B84: School Fees | C84: - | E84: #DIV/0! | H84: #DIV/0! | K84: #DIV/0! | N84: #DIV/0! | Q84: #DIV/0! | T84: #DIV/0! | W84: #DIV/0!
B85: Arrears | C85: - | E85: #DIV/0! | H85: #DIV/0! | K85: #DIV/0! | N85: #DIV/0! | Q85: #DIV/0! | T85: #DIV/0! | W85: #DIV/0! | AA85: GROUP PAYROLL UPDATE DIRECT STAFF | AH85: GROUP PAYROLL UPDATE DIRECT STAFF
B86: Total Salaries - 'Principal Companies | C86: #REF! | E86: #REF! | F86: #REF! | H86: #REF! | I86: #REF! | K86: #REF! | L86: #REF! | N86: #REF! | O86: #REF! | Q86: #REF! | R86: #REF! | T86: #REF! | U86: #REF! | W86: #REF! | AA86: Aug FY25-Monthly Gross Payroll Costs | AH86: Aug FY24-Monthly Gross Payroll Costs
B87: Total Wages - 'Casuals/Contractors | C87: #REF! | E87: #REF! | F87: #REF! | H87: #REF! | I87: #REF! | K87: #REF! | L87: #REF! | N87: - | O87: #REF! | Q87: #REF! | R87: #REF! | T87: - | U87: #REF! | W87: - | AA87: Business Unit | AB87: FTES | AC87: Casuals | AD87: Total | AE87: FX | AF87: USD | AH87: Business Unit | AI87: FTES | AJ87: Casuals | AK87: Total | AL87: FX | AM87: USD
A88: 45505 | B88: Total Payroll Costs | C88: #REF! | D88: - | E88: #REF! | F88: #REF! | G88: - | H88: #REF! | I88: #REF! | J88: - | K88: #REF! | L88: #REF! | M88: - | N88: #REF! | O88: #REF! | P88: - | Q88: #REF! | R88: #REF! | S88: - | T88: #REF! | U88: #REF! | V88: - | W88: #REF! | AA88: Uganda | AB88: 1.9226131e+09 | AC88: 17447922 | AD88: =AB88+AC88 -> 1.940061e+09 | AE88: 3800 | AF88: =AD88/AE88 -> 510542.37 | AH88: Uganda | AI88: 2359084774 | AJ88: 10823805 | AK88: =AI88+AJ88 -> 2369908579 | AL88: 3900 | AM88: =AK88/AL88 -> 607668.87
B89: Salary components - Direct staff | C89: - | D89: - | E89: #REF! | F89: - | G89: - | H89: #DIV/0! | I89: - | K89: #DIV/0! | L89: - | N89: #DIV/0! | O89: - | Q89: #DIV/0! | R89: - | T89: #DIV/0! | U89: - | W89: #DIV/0! | AA89: APDL | AB89: 7.4539098e+08 | AC89: 231822134 | AD89: =AB89+AC89 -> 9.7721312e+08 | AE89: 3800 | AF89: =AD89/AE89 -> 257161.35 | AH89: APDL | AI89: 805537572 | AJ89: 162874421 | AK89: =AI89+AJ89 -> 968411993 | AL89: 3900 | AM89: =AK89/AL89 -> 248310.77
B90: Basic Salaries | C90: - | E90: #DIV/0! | H90: #DIV/0! | K90: #DIV/0! | N90: #DIV/0! | Q90: #DIV/0! | T90: #DIV/0! | W90: #DIV/0! | AA90: Tanzania | AB90: 415321246 | AD90: =AB90+AC90 -> 415321246 | AE90: 2850 | AF90: =AD90/AE90 -> 145726.75 | AH90: Tanzania | AI90: 352019670 | AK90: =AI90+AJ90 -> 352019670 | AL90: 2700 | AM90: =AK90/AL90 -> 130377.66
B91: Over Time | C91: - | E91: #DIV/0! | H91: #DIV/0! | K91: #DIV/0! | N91: #DIV/0! | Q91: #DIV/0! | T91: #DIV/0! | W91: #DIV/0! | AA91: Kenya | AB91: 3405468 | AC91: 4500 | AD91: =AB91+AC91 -> 3409968 | AE91: 135 | AF91: =AD91/AE91 -> 25259.022 | AH91: Kenya | AI91: 8752244 | AJ91: 38535 | AK91: =AI91+AJ91 -> 8790779 | AL91: 160 | AM91: =AK91/AL91 -> 54942.369
B92: Housing Allowance | C92: - | E92: #DIV/0! | H92: #REF! | K92: #DIV/0! | N92: #DIV/0! | Q92: #DIV/0! | T92: #DIV/0! | W92: #DIV/0! | AA92: Rwanda | AB92: 41909283 | AD92: =AB92+AC92 -> 41909283 | AE92: 1475 | AF92: =AD92/AE92 -> 28413.073 | AH92: Rwanda | AI92: 39286183 | AK92: =AI92+AJ92 -> 39286183 | AL92: 1300 | AM92: =AK92/AL92 -> 30220.141
B93: Other Payroll components - Direct staff | C93: - | E93: #DIV/0! | F93: - | G93: - | H93: #DIV/0! | K93: #DIV/0! | N93: #DIV/0! | Q93: #DIV/0! | T93: #DIV/0! | W93: #DIV/0! | AA93: Burundi | AB93: 115783118 | AD93: =AB93+AC93 -> 115783118 | AE93: 3500 | AF93: =AD93/AE93 -> 33080.891 | AH93: Burundi | AI93: 93309537 | AK93: =AI93+AJ93 -> 93309537 | AL93: 3000 | AM93: =AK93/AL93 -> 31103.179
B94: Bonus | C94: - | E94: #DIV/0! | H94: #DIV/0! | K94: #DIV/0! | N94: #DIV/0! | Q94: #DIV/0! | T94: #DIV/0! | W94: #DIV/0! | AA94: Group | AE94: Total | AF94: =SUM(AF88:AF93) -> 1000183.5 | AH94: Group | AL94: Total | AM94: =SUM(AM88:AM93) -> 1102623
B95: Incentives | C95: - | E95: #DIV/0! | H95: #DIV/0! | K95: #DIV/0! | N95: #DIV/0! | Q95: #DIV/0! | T95: #DIV/0! | W95: #DIV/0!
B96: School Fees | C96: - | E96: #DIV/0! | H96: #DIV/0! | K96: #DIV/0! | N96: #DIV/0! | Q96: #DIV/0! | T96: #DIV/0! | W96: #DIV/0!
B97: Arrears | C97: - | E97: #DIV/0! | H97: #DIV/0! | K97: #DIV/0! | N97: #DIV/0! | Q97: #DIV/0! | T97: #DIV/0! | W97: #DIV/0! | AA97: GROUP PAYROLL UPDATE DIRECT STAFF | AH97: GROUP PAYROLL UPDATE DIRECT STAFF
B98: Total Salaries - 'Principal Companies | C98: #REF! | E98: #REF! | F98: #REF! | H98: #REF! | I98: #REF! | K98: #REF! | L98: #REF! | N98: #REF! | O98: #REF! | Q98: #REF! | R98: #REF! | T98: #REF! | U98: #REF! | W98: #REF! | AA98: Sept FY25-Monthly Gross Payroll Costs | AH98: Sept FY24-Monthly Gross Payroll Costs
B99: Total Wages - 'Casuals/Contractors | C99: #REF! | E99: #REF! | F99: #REF! | H99: #REF! | I99: #REF! | K99: #REF! | L99: #REF! | N99: - | O99: #REF! | Q99: #REF! | R99: #REF! | T99: - | U99: #REF! | W99: - | AA99: Business Unit | AB99: FTES | AC99: Casuals | AD99: Total | AE99: FX | AF99: USD | AH99: Business Unit | AI99: FTES | AJ99: Casuals | AK99: Total | AL99: FX | AM99: USD
A100: 45536 | B100: Total Payroll Costs | C100: #REF! | D100: - | E100: #REF! | F100: #REF! | G100: - | H100: #REF! | I100: #REF! | J100: - | K100: #REF! | L100: #REF! | M100: - | N100: #REF! | O100: #REF! | P100: - | Q100: #REF! | R100: #REF! | S100: - | T100: #REF! | U100: #REF! | V100: - | W100: #REF! | AA100: Uganda | AB100: 2131426071 | AC100: 17166486 | AD100: =AB100+AC100 -> 2148592557 | AE100: 3800 | AF100: =AD100/AE100 -> 565419.09 | AH100: Uganda | AI100: 2487577626 | AJ100: 10994027 | AK100: =AI100+AJ100 -> 2498571653 | AL100: 3900 | AM100: =AK100/AL100 -> 640659.4
...

Sheet Quarterly Recruitment Summary
B2: Summary Planned/Budgeted Recruitments as at Mar FY25
B3: Business Unit | C3: Planned Hires | D3: Actual Hires | E3: Variance | F3: Pending
B4: Uganda | C4: 31 | D4: 6 | E4: =C4-D4 -> 25 | F4: 25 positions 21 positions in commercial; 6 medical reps on hold because of red sea, 1 sales manager/debt collections, 4 sales reps(HO), 2 branch store attendant, 2 counter sales reps, 1 delivery, 4 sales reps (order booking branch), 1 sales manager pushed to Q2. 4 positions in support; 3 positions in supply chain, 1Assistant Warehouse Manager, 1 logistics officer, 1 local purchase assistant, 1 Group IT Manager
B5: APDL | C5: 6 | D5: 0 | E5: =C5-D5 -> 6 | F5: 6 positions 1 dispatch clerk, 1 forklift operator, 1 purchase assistant, 3 medical representatives pushed to Q2.
B6: Tanzania | C6: 19 | D6: 11 | E6: =C6-D6 -> 8 | F6: 8 positions 2 medical reps, 1 delivery driver, 1 BM(local), 2 FTP/ABM, 1 RBDM, 1 Business Analyst Q2
B7: Rwanda | C7: 7 | D7: 0 | E7: =C7-D7 -> 7 | F7: 7 positions 1 Asst sales manager, 3 delivery associate 1 counter sales and accounts assistant, 1 field sales rep, 1 warehouse assitant pushed to Q2
B8: Kenya | C8: 6 | D8: 2 | E8: =C8-D8 -> 4 | F8: 4 positions 4 medical representatives pushed to Q2.
B9: Burundi | C9: 7 | D9: 0 | E9: =C9-D9 -> 7 | F9: 7 positions 1 sales rep, 5 medical reps, 1 procurement and logistics officer pushed to Q2
B10: Group | C10: =SUM(C4:C9) -> 76 | D10: =SUM(D4:D9) -> 19 | E10: =SUM(E4:E9) -> 57
B13: Summary Unplanned/Unbudgeted Recruitments as at Mar FY25
B14: Business Unit | C14: Vacant Positions | D14: Filled Positions | E14: Variance | F14: Remarks
B15: Uganda | C15: 14 | D15: 14 | E15: 0
B16: APDL | C16: 7 | D16: 7 | E16: 0
B17: Tanzania | C17: 18 | D17: 18 | E17: 0
B18: Rwanda | C18: 2 | D18: 2 | E18: 0
B19: Kenya | C19: 1 | D19: 1 | E19: 0
B20: Burundi | C20: 4 | D20: 4 | E20: 0
B21: Group | C21: =SUM(C15:C20) -> 46 | D21: =SUM(D15:D20) -> 46 | E21: =SUM(E15:E20) -> 0
B24: Summary Planned/Budgeted Recruitments as at Jun FY25
B25: Business Unit | C25: Planned Hires | D25: Actual Hires | E25: Variance | F25: Pending
B26: Uganda | C26: 26 | D26: 13 | E26: 13 | F26: 12 positions in commercial; 1 field sales rep, 6 medical reps, 1 sales manager/debt collections, 4 sales reps (order booking-branch) 1 position in supply chain; 1 logistics officer
B27: APDL | C27: 6 | D27: 1 | E27: 5 | F27: 5 positions 1 dispatch clerk, 1 purchase assistant, 3 medical reps
B28: Tanzania | C28: 8 | D28: 6 | E28: 2 | F28: 2 positions 1 delivery driver the vechile has not yet been bought, 1 RBDM on hold
B29: Rwanda | C29: 7 | D29: 0 | E29: 7 | F29: 7 positions 1 Asst sales manager, 3 delivery associate 1 counter sales and accounts assistant, 1 field sales rep, 1 warehouse assitant pushed to Q3
B30: Kenya | C30: 5 | D30: 1 | E30: 4 | F30: 4 positions 4 medical representatives pushed to Q3
B31: Burundi | C31: 7 | D31: 1 | E31: 6 | F31: 6 positions 1 sales rep, 5 medical reps
B32: Group | C32: =SUM(C26:C31) -> 59 | D32: =SUM(D26:D31) -> 22 | E32: =SUM(E26:E31) -> 37
B35: Summary Unplanned/Unbudgeted Recruitments as at Jun FY25
B36: Business Unit | C36: Vacant Positions | D36: Filled Positions | E36: Variance | F36: Remarks
B37: Uganda | C37: 16 | D37: 16 | E37: 0
B38: APDL | C38: 32 | D38: 32 | E38: 0
B39: Tanzania | C39: 18 | D39: 18 | E39: 0
B40: Rwanda | C40: 8 | D40: 8 | E40: 0
B41: Kenya | C41: 1 | D41: 1 | E41: 0
B42: Burundi | C42: 0 | D42: 0 | E42: 0
B43: Group | C43: =SUM(C37:C42) -> 75 | D43: =SUM(D37:D42) -> 75 | E43: =SUM(E37:E42) -> 0
B46: Summary Planned/Budgeted Recruitments as at Sept FY25
B47: Business Unit | C47: Planned Hires | D47: Actual Hires | E47: Variance | F47: Pending
B48: Uganda | C48: 18 | D48: 7 | E48: =C48-D48 -> 11 | F48: 10 positions in commercial; 1 field supervisor on hold, 6 medical reps on hold, 3 sales reps (order booking-branch) pushed to Q4 1 position in supply chain; 1 logistics officer
B49: APDL | C49: 20 | D49: 15 | E49: =C49-D49 -> 5 | F49: 5 positions 1 dispatch clerk, 1 purchase assistant, 3 medical reps
B50: Tanzania | C50: 4 | D50: 2 | E50: =C50-D50 -> 2 | F50: 2 positions 1 delivery driver the vechile has not yet been bought, 1 RBDM on hold
B51: Rwanda | C51: 7 | D51: 0 | E51: =C51-D51 -> 7 | F51: 7 positions 1 Asst sales manager, 3 delivery associate 1 counter sales and accounts assistant, 1 field sales rep, 1 warehouse assistant all recruitments were put on hold
B52: Kenya | C52: 4 | D52: 0 | E52: =C52-D52 -> 4 | F52: 4 positions 4 medical representatives all recruitments have been put on hold
B53: Burundi | C53: 6 | D53: 0 | E53: =C53-D53 -> 6 | F53: 6 positions 1 sales rep, 5 medical reps
B54: Group | C54: =SUM(C48:C53) -> 59 | D54: =SUM(D48:D53) -> 24 | E54: =SUM(E48:E53) -> 35
B57: Summary Unplanned/Unbudgeted Recruitments as at Sept FY25
B58: Business Unit | C58: Vacant Positions | D58: Filled Positions | E58: Variance | F58: Remarks
B59: Uganda | C59: 37 | D59: 31 | E59: =C59-D59 -> 6 | F59: Asst Financial Accountant, Data Analytis, Asst. Branch Manager, Counter Sales Rep, Medical Rep, Branch Store Attendant
B60: APDL | C60: 17 | D60: 14 | E60: =C60-D60 -> 3 | F60: Production Officer, QA Officer, BFS Officer
B61: Tanzania | C61: 17 | D61: 15 | E61: =C61-D61 -> 2 | F61: Logistics Officer, Pharmaceutical Technicians
B62: Rwanda | C62: 1 | D62: 0 | E62: =C62-D62 -> 1 | F62: Medical Reps
B63: Kenya | C63: 0 | D63: 0 | E63: =C63-D63 -> 0
B64: Burundi | C64: 1 | D64: 1 | E64: =C64-D64 -> 0
B65: Group | C65: =SUM(C59:C64) -> 73 | D65: =SUM(D59:D64) -> 61 | E65: =SUM(E59:E64) -> 12
B68: Summary Planned/Budgeted Recruitments as at Dec FY25
B69: Business Unit | C69: Planned Hires | D69: Actual Hires | E69: Variance | F69: Pending
B70: Uganda | C70: 11 | D70: 1 | E70: 10 | F70: 10 positions in commercial; 1 field supervisor on hold, 6 medical reps on hold, 3 sales reps (order booking-branch) on hold
B71: APDL | C71: 5 | D71: 0 | E71: =C71-D71 -> 5 | F71: 5 positions 1 dispatch clerk on hold, 1 purchase assistant on hold, 3 medical reps there was no need
B72: Tanzania | C72: 1 | D72: 0 | E72: =C72-D72 -> 1 | F72: 1 delivery driver the vechile was not bought, 1 RBDM was promoted internally
B73: Rwanda | C73: 7 | D73: 0 | E73: =C73-D73 -> 7 | F73: 7 positions 1 Asst sales manager, 3 delivery associate 1 counter sales and accounts assistant, 1 field sales rep, 1 warehouse assistant all recruitments were put on hold
B74: Kenya | C74: 4 | D74: 0 | E74: =C74-D74 -> 4 | F74: 4 positions 4 medical representatives all recruitments have been put on hold
B75: Burundi | C75: 6 | D75: 0 | E75: =C75-D75 -> 6 | F75: 6 positions 1 sales rep, 5 medical reps
B76: Group | C76: =SUM(C70:C75) -> 34 | D76: =SUM(D70:D75) -> 1 | E76: =SUM(E70:E75) -> 33
B79: Summary Unplanned/Unbudgeted Recruitments as at Dec FY25
B80: Business Unit | C80: Pending | D80: Actual Hires | E80: Total positions | F80: Remarks
B81: Uganda | C81: 22 | D81: 22 | E81: =C81-D81 -> 0
B82: APDL | C82: 7 | D82: 7 | E82: =C82-D82 -> 0
B83: Tanzania | C83: 19 | D83: 19 | E83: =C83-D83 -> 0
B84: Rwanda | C84: 2 | D84: 2 | E84: =C84-D84 -> 0
B85: Kenya | C85: 2 | D85: 2 | E85: =C85-D85 -> 0
B86: Burundi | C86: 1 | D86: 1 | E86: =C86-D86 -> 0
B87: Group | C87: =SUM(C81:C86) -> 53 | D87: =SUM(D81:D86) -> 53 | E87: =SUM(E81:E86) -> 0
B89: Y2D Planned hires | C89: =76+2+22 -> 100
B90: Y2D Unplanned hires | C90: =C21+C43+C65+C87 -> 247
B91: Total | C91: =C89+C90 -> 347
B92: Positions on hold | C92: 33
B93: New Total | C93: =C91-C92 -> 314 | F93: FY25 = 301/314*100=96%
B94: Y2D planned actual hires | C94: =D10+D32+D54+D76 -> 66
B95: Y2D unplanned actual hires | C95: =D21+D43+D65+D87 -> 235
B96: Total | C96: =C94+C95 -> 301
B98: Positions on hold | C98: 10 | F98: Uganda 3 sales reps (order booking-branch), 1 field supervisor on hold, 6 medical reps on hold, 1 Data Analyst
C99: 5 | F99: APDL 1 dispatch clerk, 1 purchase assistant, 3 medical reps
C100: 1 | F100: Tanzania 1 delivery driver the vechile was not bought bought
C101: 7 | F101: Rwanda 1 Asst sales manager, 3 delivery associate 1 counter sales and accounts assistant, 1 field sales rep, 1 warehouse assistant
C102: 4 | F102: Kenya 4 medical representatives all recruitments have been put on hold
C103: 6 | F103: Burundi 1 sales rep, 5 medical reps
C104: =SUM(C98:C103) -> 33

Sheet New Hires Update
B1: GROUP RECRUITMENT TRACKER 2025
B2: S/N | C2: Business Unit | D2: Position | E2: Department | F2: Person Replaced (Name) | G2: Person Hired (Name) | H2: Level | I2: Date of Joining (Month-Date) | J2: Reason for Hire | K2: Budget | L2: Actual | M2: Saving (Amount) | N2: Saving (%) | O2: Comment
B3: 1 | C3: APL UGANDA | D3: Medical Representative | E3: Commercial | F3: Ndayambazi Amis | G3: Makosa Bornface | H3: STL 1&2 | I3: 45670 | J3: Replacement | K3: 249 | L3: 211 | M3: =K3-L3 -> 38 | N3: =M3/K3 -> 0.15261044
B4: 2 | D4: Medical Representative | E4: Commercial | F4: N/A | G4: Wooki Trevor | H4: STL 1&2 | I4: 45673 | J4: Expansion | K4: 211 | L4: 211 | M4: =K4-L4 -> 0 | N4: =M4/K4 -> 0 | Q4: Group Recruitment Summary YTD FY25
B5: 3 | D5: Delivery Clerk | E5: Commercial | F5: Peter Muwonge | G5: Tumusiime Geofrey | H5: STL 1&2 | I5: 45677 | J5: Replacement | K5: 121 | L5: 103 | M5: =K5-L5 -> 18 | N5: =M5/K5 -> 0.14876033 | R5: Group | S5: Uganda | T5: APDL | U5: Tanzania | V5: Rwanda | W5: Kenya | X5: Burundi
B6: 4 | D6: Branch Store Attedant | E6: Commercial | F6: Acidri Amule | G6: Adriko Paul | H6: STL 1&2 | I6: 45674 | J6: Replacement | K6: 116 | L6: 103 | M6: =K6-L6 -> 13 | N6: =M6/K6 -> 0.11206897 | Q6: Planned | R6: =SUM(S6,T6,U6,V6,W6,X6) -> 0
B7: 5 | D7: Field Sales Representative | E7: Commercial | F7: Inocent Saddam | G7: Oloya Geoffrey | H7: STL 1&2 | I7: 45693 | J7: Replacement | K7: 115 | L7: 132 | M7: =K7-L7 -> -17 | N7: =M7/K7 -> -0.14782609 | Q7: Unplanned | R7: =SUM(S7,T7,U7,V7,W7,X7) -> 0
B8: 6 | D8: Warehouse Attedant | E8: Commercial | F8: N/A | G8: Musana Joshua Oliimi | H8: STL 1&2 | I8: 45705 | J8: Expansion | K8: 103 | L8: 103 | M8: =K8-L8 -> 0 | N8: =M8/K8 -> 0 | Q8: Total Positions (Planned and Unplanned) | R8: =SUM(S8,T8,U8,V8,W8,X8) -> 0 | S8: =S6+S7 -> 0 | T8: =T6+T7 -> 0 | U8: =U6+U7 -> 0 | V8: =V6+V7 -> 0 | W8: =W6+W7 -> 0 | X8: =X6+X7 -> 0
B9: 7 | D9: Warehouse Attedant | E9: Commercial | F9: N/A | G9: Kalema Leo | H9: STL 1&2 | I9: 45705 | J9: Expansion | K9: 103 | L9: 103 | M9: =K9-L9 -> 0 | N9: =M9/K9 -> 0 | Q9: On hold & Not yet started | R9: =SUM(S9,T9,U9,V9,W9,X9) -> 0
B10: 8 | D10: Warehouse Attedant | E10: Commercial | F10: N/A | G10: Muhindo Neckson | H10: STL 1&2 | I10: 45705 | J10: Expansion | K10: 103 | L10: 103 | M10: =K10-L10 -> 0 | N10: =M10/K10 -> 0
B11: 9 | D11: Warehouse Attedant | E11: Commercial | F11: N/A | G11: Ekadu Emmanuel | H11: STL 1&2 | I11: 45705 | J11: Expansion | K11: 103 | L11: 103 | M11: =K11-L11 -> 0 | N11: =M11/K11 -> 0 | Q11: Total positions expected to be filled YTD | R11: =SUM(S11,T11,U11,V11,W11,X11) -> 248 | S11: 100 | T11: 41 | U11: 84 | V11: =V8-V9 -> 0 | W11: 12 | X11: =11 -> 11
B12: 10 | D12: Warehouse Attedant | E12: Commercial | F12: N/A | G12: Adomati Denish | H12: STL 1&2 | I12: 45712 | J12: Expansion | K12: 103 | L12: 103 | M12: =K12-L12 -> 0 | N12: =M12/K12 -> 0 | Q12: Filled positions | R12: =SUM(S12,T12,U12,V12,W12,X12) -> 198 | S12: 81 | T12: 40 | U12: 42 | V12: 20 | W12: 10 | X12: 5
B13: 11 | D13: Assistant Branch Manager | E13: Commercial | F13: Kasumba Emmanuel Monday | G13: Mohsin Khan | H13: ML 1&2 | I13: 45691 | J13: Replacement | K13: 1707 | L13: 1175 | M13: =K13-L13 -> 532 | N13: =M13/K13 -> 0.31165788 | Q13: % Performance | R13: =R12/R11 -> 0.7983871 | S13: =S12/S11 -> 0.81 | T13: =T12/T11 -> 0.97560976 | U13: =U12/U11 -> 0.5 | V13: =V12/V11 -> #DIV/0! | W13: =W12/W11 -> 0.83333333 | X13: =X12/X11 -> 0.45454545
B14: 12 | D14: Assistant Branch Manager | E14: Commercial | F14: Mohameed Aneez Hamza | G14: Irfan Khan | H14: ML 1&2 | I14: 45694 | J14: Replacement | K14: 1747 | L14: 1175 | M14: =K14-L14 -> 572 | N14: =M14/K14 -> 0.32741843
B15: 13 | D15: Group Head Internal Audit | E15: Internal Audit | F15: Maria Francesca | G15: Brian Nuwamanya | H15: EXCO | I15: 45691 | J15: Replacement | K15: 5916 | L15: 11053 | M15: =K15-L15 -> -5137 | N15: =M15/K15 -> -0.86832319
B16: 14 | D16: Nurse | E16: Commercial | F16: Mbambu Roset | G16: Masika Cathreen Kisubi | H16: STL 1&2 | I16: 45712 | J16: Replacement | K16: 138 | L16: 132 | M16: =K16-L16 -> 6 | N16: =M16/K16 -> 0.043478261
B17: 15 | D17: Counter Sales Representative | E17: Commercial | F17: Wamala William | G17: Kalyesubula Edrine | H17: STL 1&2 | I17: 45712 | J17: Replacement | K17: 169 | L17: 132 | M17: =K17-L17 -> 37 | N17: =M17/K17 -> 0.21893491
B18: 16 | D18: Assistant Branch Manager | E18: Commercial | F18: Patel Mehulkumar Kanubhai | G18: Kupparla Suneel Kumar | H18: ML 1&2 | I18: 45712 | J18: Replacement | K18: 1801 | L18: 1175 | M18: =K18-L18 -> 626 | N18: =M18/K18 -> 0.34758468
B19: 17 | D19: Branch Store Attedant | E19: Commercial | F19: Ojara Bob Kennedy | G19: Onyinge Nixson | H19: STL 1&2 | I19: 45733 | J19: Replacement | K19: 126 | L19: 103 | M19: =K19-L19 -> 23 | N19: =M19/K19 -> 0.18253968
B20: 18 | D20: Counter Sales Representative | E20: Commercial | F20: Ruhume Ronald | G20: Matison Moris | H20: STL 1&2 | I20: 45733 | J20: Replacement | K20: 257 | L20: 132 | M20: =K20-L20 -> 125 | N20: =M20/K20 -> 0.48638132
B21: 19 | D21: Branch Manager | E21: Commercial | F21: Patel Mehulkumar Kanubhai | G21: Vamankumar Nitinbhai | H21: ML 1&2 | I21: 45719 | J21: Replacement | K21: 1801 | L21: 1579 | M21: =K21-L21 -> 222 | N21: =M21/K21 -> 0.12326485
B22: 20 | D22: Medical Representative | E22: Commercial | F22: Nyamurangwa David | G22: Ashaba Collins | H22: STL 1&2 | I22: 45719 | J22: Replacement | K22: 197 | L22: 211 | M22: =K22-L22 -> -14 | N22: =M22/K22 -> -0.07106599
B23: 21 | D23: Assistant Warehouse Manager | E23: Supply Chain | F23: N/A | G23: Tanveer Allam | H23: ML 1&2 | I23: 45748 | J23: Expansion | K23: 1580 | L23: 1580 | M23: =K23-L23 -> 0 | N23: =M23/K23 -> 0
B24: 22 | D24: Assistant Warehouse Manager | E24: Supply Chain | F24: N/A | G24: Rajeev Summan | H24: ML 1&2 | I24: 45748 | J24: Expansion | K24: 1782 | L24: 1782 | M24: =K24-L24 -> 0 | N24: =M24/K24 -> 0
B25: 23 | D25: logistics Graduate Trainee | E25: Supply Chain | F25: Amanya Joshua | G25: Muhekyi Talent | H25: STL 1&2 | I25: 45749 | J25: Replacement | K25: 211 | L25: 211 | M25: =K25-L25 -> 0 | N25: =M25/K25 -> 0
... B95: 93 | D95: Driver | E95: Human Resource/OHSE | F95: N/A | G95: Okello James | H95: STL 1&2 | I95: 45952 | J95: Expansion | K95: 158 | L95: 158 | M95: =K95-L95 -> 0 | N95: =M95/K95 -> 0
B96: 94 | D96: Assistant Branch Manager | E96: Commercial | F96: Rajani Kumar | G96: Imran Mirza | H96: ML 1&2 | I96: 45964 | J96: Replacement | K96: =7689537/3800 -> 2023.5624 | L96: =4464700/3800 -> 1174.9211 | M96: =K96-L96 -> 848.64132 | N96: =M96/K96 -> 0.41937987
B97: 95 | D97: Branch Stores Attendant | E97: Commercial | F97: Olinga Joseph | G97: Elanda Abdul Hakimu | H97: STL 1&2 | I97: 45965 | J97: Replacement | K97: 102 | L97: 132 | M97: =K97-L97 -> -30 | N97: =M97/K97 -> -0.29411765
B98: 96 | D98: Branch Stores Attendant | E98: Commercial | F98: N/A | G98: Wandera Sam | H98: STL 1&2 | I98: 45965 | J98: Expansion | K98: 102 | L98: 102 | M98: =K98-L98 -> 0 | N98: =M98/K98 -> 0
B99: 97 | D99: Medical Representative | E99: Commercial | F99: Wooki Trevor | G99: Atati David | H99: STL 1&2 | I99: 45973 | J99: Replacement | K99: 211 | L99: 211 | M99: =K99-L99 -> 0 | N99: =M99/K99 -> 0
B100: 98 | D100: Graduate Trainee-Regulatory | E100: Regulatory | F100: N/A | G100: Kyebungya Friday Didas | H100: STL 1&2 | I100: 45978 | J100: Expansion | K100: 211 | L100: 211 | M100: =K100-L100 -> 0 | N100: =M100/K100 -> 0
B101: 99 | D101: Assistant Branch Manager | E101: Commercial | F101: Patel Krunalkumar Pravinbhai | G101: Seku Syed Bava Abuthalif | H101: ML 1&2 | I101: 45985 | J101: Replacement | K101: 1174 | L101: 1174 | M101: =K101-L101 -> 0 | N101: =M101/K101 -> 0
B102: 100 | D102: Assistant Branch Manager | E102: Commercial | F102: Chandrakant Ramanbhai | G102: Farhan Sayed | H102: ML 1&2 | I102: 45987 | J102: Replacement | K102: 1174 | L102: 1174 | M102: =K102-L102 -> 0 | N102: =M102/K102 -> 0
B103: 101 | D103: Counter Sales Representative | E103: Commercial | F103: Muhindo Edgar | G103: Kyadhuba Susan | H103: STL 1&2 | I103: 45992 | J103: Replacement | K103: 147.62 | L103: 132 | M103: =K103-L103 -> 15.62 | N103: =M103/K103 -> 0.10581222
B104: 102 | D104: Assistant Branch Manager | E104: Commercial | F104: Twebaze Ambrose | G104: Patel Dhruvikkumar Ravindrabhai | H104: ML 1&2 | I104: 45992 | J104: Replacement | K104: 1174 | L104: 1174 | M104: =K104-L104 -> 0 | N104: =M104/K104 -> 0
B105: 103 | D105: Assistant Branch Manager | E105: Commercial | F105: Rahul Patil | G105: Mohd Irfan Ansari | H105: ML 1&2 | I105: 45994 | J105: Replacement | K105: 1621.4 | L105: 1300 | M105: =K105-L105 -> 321.4 | N105: =M105/K105 -> 0.19822376
B106: 104 | D106: Assistant Branch Manager | E106: Commercial | F106: Kennet Franklin | G106: Tanishq Kapoor’s | H106: ML 1&2 | I106: 45999 | J106: Replacement | K106: 2334.62 | L106: 1300 | M106: =K106-L106 -> 1034.62 | N106: =M106/K106 -> 0.4431642
B107: 105 | D107: Branch Store Attedant | E107: Commercial | F107: Enos Edonyu | G107: Ainembababazi Expedito | H107: STL 1&2 | I107: 45999 | J107: Replacement | K107: 169.55 | L107: 132 | M107: =K107-L107 -> 37.55 | N107: =M107/K107 -> 0.22146859
B108: 106 | D108: Nurse | E108: Commercial | F108: Mweisgwa Samuel | G108: Beinobwengye Herman | H108: STL 1&2 | I108: 46006 | J108: Replacement | K108: 150.48 | L108: 132 | M108: =K108-L108 -> 18.48 | N108: =M108/K108 -> 0.12280702
... B112: 110 | D112: Branch Sales Representative | E112: Commercial | F112: Muhamed Katongole | G112: Kyambadde Abdu Shakuluh | H112: STL 1&2 | I112: 46014 | J112: Replacement | K112: 222.94 | L112: 132 | M112: =K112-L112 -> 90.94 | N112: =M112/K112 -> 0.40791244
B113: 1 | C113: APDL | D113: Production Officer | E113: Production | F113: Nuwabiine Elnest | G113: Okello Benard | H113: STL 1&2 | I113: 45659 | J113: Replacement | K113: 343 | L113: 197 | M113: =K113-L113 -> 146 | N113: =M113/K113 -> 0.42565598
B114: 2 | D114: Production Officer | E114: Production | F114: Oluka James Joel | G114: Sserunjogi Raymond | H114: STL 1&2 | I114: 45659 | J114: Replacement | K114: 244 | L114: 197 | M114: =K114-L114 -> 47 | N114: =M114/K114 -> 0.19262295
B115: 3 | D115: Quality Assurance Officer | E115: Quality | F115: Mugenyi Nathan | G115: Wankya Max | H115: STL 1&2 | I115: 45659 | J115: Replacement | K115: 210 | L115: 197 | M115: =K115-L115 -> 13 | N115: =M115/K115 -> 0.061904762
B116: 4 | D116: Production Officer | E116: Production | F116: Baguma Henry | G116: Edrine Katamba | H116: STL 1&2 | I116: 45691 | J116: Replacement | K116: 253 | L116: 197 | M116: =K116-L116 -> 56 | N116: =M116/K116 -> 0.22134387
B117: 5 | D117: Quality Assurance Officer | E117: Quality | F117: Osebart Atwongyeire | G117: Onan Tumuhimbise | H117: STL 1&2 | I117: 45691 | J117: Replacement | K117: 248 | L117: 197 | M117: =K117-L117 -> 51 | N117: =M117/K117 -> 0.20564516
B118: 6 | D118: Quality Assurance Officer | E118: Quality | F118: N/A | G118: Nabbaale Gloria Martha | H118: STL 1&2 | I118: 45719 | J118: Expansion | K118: 197 | L118: 197 | M118: =K118-L118 -> 0 | N118: =M118/K118 -> 0
B119: 7 | D119: Quality Assurance Officer | E119: Quality | F119: Barigye Edward | G119: Mugisa Friday Moses | H119: STL 1&2 | I119: 45719 | J119: Replacement | K119: 197 | L119: 197 | M119: =K119-L119 -> 0 | N119: =M119/K119 -> 0
B120: 8 | D120: Quality Control Analyst | E120: Quality | F120: Wanyana Valeria | G120: Naliggo Olivia | H120: STL 1&2 | I120: 45748 | J120: Replacement | K120: 256.44 | L120: 197 | M120: =K120-L120 -> 59.44 | N120: =M120/K120 -> 0.23178911
B121: 9 | D121: Quality Control Analyst | E121: Quality | F121: Laker Faith Oruni | G121: Nshizirungu Alforce | H121: STL 1&2 | I121: 45748 | J121: Replacement | K121: 353 | L121: 197 | M121: =K121-L121 -> 156 | N121: =M121/K121 -> 0.44192635
B122: 10 | D122: Quality Assurance Officer | E122: Quality | F122: N/A | G122: Basaalirwa Joel Frebase | H122: STL 1&2 | I122: 45775 | J122: Expansion | K122: 197 | L122: 197 | M122: =K122-L122 -> 0 | N122: =M122/K122 -> 0
B123: 11 | D123: Quality Assurance Officer | E123: Quality | F123: Aijuka Gilbert | G123: Kantono Mildred | H123: STL 1&2 | I123: 45775 | J123: Replacement | K123: 335 | L123: 316 | M123: =K123-L123 -> 19 | N123: =M123/K123 -> 0.056716418
B124: 12 | D124: Stores Officer | E124: Supply Chain | F124: Bayati Babirye | G124: Kirya Nicholas | H124: STL 1&2 | I124: 45775 | J124: Replacement | K124: 536 | L124: 197 | M124: =K124-L124 -> 339 | N124: =M124/K124 -> 0.63246269
B125: 13 | D125: Quality Control Analyst | E125: Quality | F125: Opio Ronald | G125: Nuwasasira Lilian | H125: STL 1&2 | I125: 45775 | J125: Replacement | K125: 254 | L125: 197 | M125: =K125-L125 -> 57 | N125: =M125/K125 -> 0.22440945
... B171: 59 | D171: Maintenance Engineer EEI | E171: Engineering | F171: N/A | G171: Muyomba Hussein | H171: ML 1&2 | I171: 45883 | J171: Expansion | K171: 1000 | L171: 1000 | M171: =K171-L171 -> 0 | N171: =M171/K171 -> 0
B172: 60 | D172: Electrical Technician | E172: Engineering | G172: Walyamboga John | H172: STL 1&2 | I172: 45883 | K172: 342 | L172: 342 | M172: =K172-L172 -> 0 | N172: =M172/K172 -> 0
B173: 61 | D173: Quality Assurance officer | E173: Quality | F173: N/A | G173: Tembuli Sabath | H173: STL 1&2 | I173: 45887 | J173: Expansion | K173: 197 | L173: 197 | M173: =K173-L173 -> 0 | N173: =M173/K173 -> 0
B174: 62 | D174: Production Officer | E174: Production | F174: Mugalu Julius Ntulume | G174: Ddamba Elijah | H174: STL 1&2 | I174: 45901 | J174: Replacement | K174: 197 | L174: 197 | M174: =K174-L174 -> 0 | N174: =M174/K174 -> 0
B175: 63 | D175: Production Officer | E175: Production | F175: Musubo Ronald | G175: Waiswa Sowedi | H175: STL 1&2 | I175: 45901 | J175: Replacement | K175: 197 | L175: 197 | M175: =K175-L175 -> 0 | N175: =M175/K175 -> 0
B176: 64 | D176: Production Officer | E176: Production | F176: Nantinda Calton | G176: Kyanda Mark | H176: STL 1&2 | I176: 45901 | J176: Replacement | K176: 197 | L176: 197 | M176: =K176-L176 -> 0 | N176: =M176/K176 -> 0
B177: 65 | D177: Quality Assurance Manager | E177: Quality | F177: Manikandan Ramaraj | G177: Murinzi Joseph Karara | H177: EXCO 1&2 | I177: 45901 | J177: Replacement | K177: 4781 | L177: 3684 | M177: =K177-L177 -> 1097 | N177: =M177/K177 -> 0.22944991
B178: 66 | D178: Shift Leader | E178: Production | F178: N/A | G178: Mujuni Moses | H178: ML 1&2 | I178: 45915 | J178: Expansion | K178: 789 | L178: 658 | M178: =K178-L178 -> 131 | N178: =M178/K178 -> 0.16603295
B179: 67 | D179: Human Resource Supervisor | E179: Human Resource/OHSE | F179: Ronald Nuwe Kaija | G179: Lemi Martin | H179: ML 1&2 | I179: 45922 | J179: Replacement | K179: 921 | L179: 1395 | M179: =K179-L179 -> -474 | N179: =M179/K179 -> -0.51465798
B180: 68 | D180: Quality Control analyst | E180: Quality | F180: Jamellah Nankiga | G180: Oruni Laker Faith | H180: STL 1&2 | I180: 45929 | J180: Replacement | K180: 395 | L180: 395 | M180: =K180-L180 -> 0 | N180: =M180/K180 -> 0
B181: 69 | D181: Production Officer | E181: Production | F181: Oming Solomon | G181: Kyobe Andrew | H181: STL 1&2 | I181: 45929 | J181: Replacement | K181: 197 | L181: 197 | M181: =K181-L181 -> 0 | N181: =M181/K181 -> 0
B182: 70 | D182: Production Officer | E182: Production | F182: Wilson Damulira | G182: Mutatwala Puis | H182: STL 1&2 | I182: 45936 | J182: Replacement | K182: 197 | L182: 197 | M182: =K182-L182 -> 0 | N182: =M182/K182 -> 0
B183: 71 | D183: Production Officer | E183: Production | F183: Muganzi Micheal | G183: Ssentamu Arnold Raymond | H183: STL 1&2 | I183: 45936 | J183: Replacement | K183: 246 | L183: 316 | M183: =K183-L183 -> -70 | N183: =M183/K183 -> -0.28455285
B184: 72 | D184: Engineering Store Keeper | E184: Engineering | F184: N/A | G184: Aton Khabale | H184: STL 1&2 | I184: 45964 | J184: Expansion | K184: 246 | L184: 316 | M184: =K184-L184 -> -70 | N184: =M184/K184 -> -0.28455285
... B188: 76 | D188: BFS Operator | E188: Production | F188: Nuwarimpa Aine | G188: Ainomugisha Samuel Baker | H188: STL 1&2 | I188: 46020 | J188: Replacement | K188: 197 | L188: 197 | M188: =K188-L188 -> 0 | N188: =M188/K188 -> 0
B189: 1 | C189: APL TANZANIA | D189: Sales Representative | E189: Commercial | F189: N/A | G189: Brighton Theobald Mbakile | H189: STL 1&2 | I189: 45658 | J189: Expansion | K189: 239 | L189: 239 | M189: =K189-L189 -> 0 | N189: =M189/K189 -> 0 | P189: 0
B190: 2 | D190: Sales Representative | E190: Commercial | F190: Norbert Mbunda | G190: Hamida Hassani Juma | H190: STL 1&2 | I190: 45658 | J190: Replacement | K190: 376 | L190: 185 | M190: =K190-L190 -> 191 | N190: =M190/K190 -> 0.50797872
B191: 3 | D191: Sales Representative | E191: Commercial | F191: Paulina Samson Mtao | G191: Nobert Bazili Ricardo | H191: STL 1&2 | I191: 45658 | J191: Replacement | K191: 323 | L191: 285 | M191: =K191-L191 -> 38 | N191: =M191/K191 -> 0.11764706
B192: 4 | D192: Procurement Officer | E192: Finance | F192: Japhet Kanyenye | G192: Victor Rwabukoba Sylivand | H192: STL 1&2 | I192: 45658 | J192: Replacement | K192: 1383 | L192: 556 | M192: =K192-L192 -> 827 | N192: =M192/K192 -> 0.59797542
B193: 5 | D193: Driver | E193: Commercial | F193: N/A | G193: Gabriel Joseph Gabriel | H193: STL 1&2 | I193: 45658 | J193: Expansion | K193: 137 | L193: 137 | M193: =K193-L193 -> 0 | N193: =M193/K193 -> 0
B194: 6 | D194: Store Attendant | E194: Commercial | F194: N/A | G194: Amri Jumanne Hussein | H194: STL 1&2 | I194: 45658 | J194: Expansion | K194: 137 | L194: 137 | M194: =K194-L194 -> 0 | N194: =M194/K194 -> 0
B195: 7 | D195: Sales Representative | E195: Commercial | F195: N/A | G195: Elisia Genes Assey | H195: STL 1&2 | I195: 45663 | J195: Expansion | K195: 241 | L195: 223 | M195: =K195-L195 -> 18 | N195: =M195/K195 -> 0.074688797
B196: 8 | D196: Sales Representative | E196: Commercial | F196: N/A | G196: Jackson Aloyce Mwizarubi | H196: STL 1&2 | I196: 45663 | J196: Expansion | K196: 241 | L196: 223 | M196: =K196-L196 -> 18 | N196: =M196/K196 -> 0.074688797
B197: 9 | D197: Pharmaceutical Technician | E197: Commercial | F197: N/A | G197: Rachel Timothy Sosoma | H197: STL 1&2 | I197: 45663 | J197: Expansion | K197: 278 | L197: 223 | M197: =K197-L197 -> 55 | N197: =M197/K197 -> 0.19784173
B198: 10 | D198: Human Resource Officer | E198: Human Resource/OHSE | F198: Lucy Mugeta Jandwa | G198: Paulo Siafu | H198: STL 1&2 | I198: 45664 | J198: Replacement | K198: 1576 | L198: 926 | M198: =K198-L198 -> 650 | N198: =M198/K198 -> 0.41243655
B199: 11 | D199: Branch Manager | E199: Commercial | F199: Ayub Benedict Mdetele | G199: Aswaneesh Chackalaparamb Shaji | H199: ML 1&2 | I199: 45666 | J199: Replacement | K199: 2333 | L199: 1920 | M199: =K199-L199 -> 413 | N199: =M199/K199 -> 0.17702529
B200: 12 | D200: Sales Representative | E200: Commercial | F200: Joseph Ndumbaro | G200: David Noah Yongolo | H200: STL 1&2 | I200: 45667 | J200: Replacement | K200: 250 | L200: 239 | M200: =K200-L200 -> 11 | N200: =M200/K200 -> 0.044
B201: 13 | D201: Sales Representative | E201: Commercial | F201: Nishan Idd Misanya | G201: Ntalagane Keneth Christopher | H201: STL 1&2 | I201: 45672 | J201: Replacement | K201: 329 | L201: 223 | M201: =K201-L201 -> 106 | N201: =M201/K201 -> 0.32218845
... B277: 89 | D277: Pharmaceutical Technician | E277: Supply Chain | F277: Mariam Jakson Mangu | G277: John Patrick Mlacha | H277: STL 1&2 | I277: 46001 | J277: Replacement | K277: 257 | L277: 277 | M277: =K277-L277 -> -20 | N277: =M277/K277 -> -0.077821012
B278: 1 | C278: APL BURUNDI | D278: Counter Sales Assistant | E278: Commercial | F278: Ndihokubwayo Josephine | G278: Kaze Emmanuel | H278: STL 1&2 | I278: 45659 | J278: Replacement | K278: 139.83 | L278: 139.83 | M278: =K278-L278 -> 0 | N278: =M278/K278 -> 0
B279: =B278+1 -> 2 | D279: Logistics Officer | E279: Supply Chain | F279: Sinzinkayo Emery Diallo | G279: Amanya Joshua | H279: STL 1&2 | I279: 45764 | J279: Replacement | K279: 108.09 | L279: 594 | M279: =K279-L279 -> -485.91 | N279: =M279/K279 -> -4.4954205
B280: =B279+1 -> 3 | D280: Counter Sales Asst & Cashier | E280: Commercial | F280: Digne Alda | G280: Ingabire Digne Alda | H280: STL 1&2 | I280: 45870 | J280: Replacement | K280: 116.43 | L280: 116.43 | M280: =K280-L280 -> 0 | N280: =M280/K280 -> 0
B281: =B280+1 -> 4 | D281: Team Leader of Med Repr/ALC | E281: Commercial | F281: Manirakiza Fabrice | G281: Muhimpundu Corneille | H281: STL 1&2 | I281: 45945 | J281: Replacement | K281: 128 | L281: =448138/3500 -> 128.03943 | M281: =K281-L281 -> -0.039428571 | N281: =M281/K281 -> -0.00030803571
B282: 1 | C282: KENYA | D282: Medical Representative | E282: Commercial | F282: Christina Mrunde Sasaka | G282: Getrude Jeptoo | H282: STL 1&2 | I282: 45663 | J282: Replacement | K282: 538.46 | L282: 423.08 | M282: =K282-L282 -> 115.38 | N282: =M282/K282 -> 0.21427776
B283: 2 | D283: Medical Representative | E283: Commercial | F283: Joakim Mutuku | G283: Faith Mwende | H283: STL 1&2 | I283: 45663 | J283: Replacement | K283: 538.46 | L283: 538.46 | M283: =K283-L283 -> 0 | N283: =M283/K283 -> 0
B284: 3 | D284: Sales Representative | E284: Commercial | F284: N/A | G284: Grace Mwende Mutilangi | H284: STL 1&2 | I284: 45664 | J284: Expansion | K284: 269.23 | L284: 230.77 | M284: =K284-L284 -> 38.46 | N284: =M284/K284 -> 0.14285184
B285: 4 | D285: Financial Accountant | E285: Finance | F285: Patrick Wafula | G285: Cynthia Trufena Jomo | H285: ML 1&2 | I285: 45677 | J285: Replacement | K285: 923.08 | L285: 1076.92 | M285: =K285-L285 -> -153.84 | N285: =M285/K285 -> -0.16665944
B286: 5 | D286: Sales Representative | E286: Commercial | F286: Seifuddin Mohamedali | G286: Rose Nyambura Maina | H286: STL 1&2 | I286: 45705 | J286: Replacement | K286: 269.23 | L286: 269.23 | M286: =K286-L286 -> 0 | N286: =M286/K286 -> 0
B287: 6 | D287: Sales Representative | E287: Commercial | F287: N/A | G287: Mary Nzasi Ngei | H287: STL 1&2 | I287: 45717 | J287: Expansion | K287: 269.23 | L287: 269.23 | M287: =K287-L287 -> 0 | N287: =M287/K287 -> 0
B288: 7 | D288: Medical Representative | E288: Commercial | F288: Grace Njuguna | G288: Divina Wanjigu | H288: STL 1&2 | I288: 45764 | J288: Replacement | K288: 269.23 | L288: 269.23 | M288: =K288-L288 -> 0 | N288: =M288/K288 -> 0
B289: 8 | D289: Supply Chain Executive | E289: Supply Chain | F289: N/A | G289: John Kilungu | H289: STL 1&2 | I289: 45817 | J289: Expansion | K289: 230.77 | L289: 230.77 | M289: =K289-L289 -> 0 | N289: =M289/K289 -> 0
B290: 9 | D290: Receptionist | E290: Administration | F290: N/A | G290: Jacinta Muringe | H290: STL 1&2 | I290: 45936 | J290: Expansion | K290: 230.77 | L290: 230.77 | M290: =K290-L290 -> 0 | N290: =M290/K290 -> 0
B291: 10 | D291: Senior Medical Representative | E291: Commercial | F291: Victor Mnallah | G291: Stanslous Onyango Okhonjo | H291: STL 1&2 | I291: 45985 | J291: Replacement | K291: =70000/135 -> 518.51852 | L291: 518.52 | M291: =K291-L291 -> -0.0014814815 | N291: =M291/K291 -> -2.8571429e-06
B292: 1 | C292: APL RWANDA | D292: Head of Finance | E292: Finance | F292: Naomi Muthoni Ndungu | G292: Ssesimba Hamuza | H292: EXCO 1&2 | I292: 45677 | J292: Replacement | K292: =4070629/1475 -> 2759.7485 | L292: =6492537/1475 -> 4401.72 | M292: =K292-L292 -> -1641.9715 | N292: =M292/K292 -> -0.59497144
B293: 2 | D293: Country Head | E293: Commercial | F293: Saifi Alarm | G293: Hingu Ankitkumar Dhirajlal | H293: EXCO 1&2 | I293: 45705 | J293: Replacement | K293: =8548357/1475 -> 5795.4963 | L293: =11404250/1475 -> 7731.6949 | M293: =K293-L293 -> -1936.1986 | N293: =M293/K293 -> -0.33408677
B294: 3 | D294: Human Resource Business Partner | E294: Human Resource/OHSE | F294: Joseph Mugwaneza | G294: Mpano Divine | H294: ML 1&2 | I294: 45748 | J294: Replacement | K294: =2248675.4222651/1475 -> 1524.5257 | L294: =1836800/1475 -> 1245.2881 | M294: =K294-L294 -> 279.23757 | N294: =M294/K294 -> 0.18316357
B295: 4 | D295: Medical Representative | E295: Commercial | F295: Shingiro Rodrigue | G295: Uwineza Gisele | H295: STL 1&2 | I295: 45761 | J295: Replacement | K295: =217248.5/1475 -> 147.28712 | L295: =811246/1475 -> 549.99729 | M295: =K295-L295 -> -402.71017 | N295: =M295/K295 -> -2.7341846
...

Sheet Transfers & Promotion
A2: PROMOTIONS
A3: Business Unit | B3: Employee ID | C3: Full Name | D3: Gender | E3: Current Department | F3: Current Unit/Branch | G3: Current Job Title | H3: New Department | I3: New Unit/Branch | J3: New Job Title | K3: Effective date of Promotion | L3: Costs Incurred
A4: APL - Uganda | B4: EXP-0178 | C4: Chowdhury Sourabh Barua | D4: Male | E4: Commercial | F4: Branches - Bwaise | G4: Assistant Branch Manager | H4: Commercial | I4: Branches - Bwaise | J4: Branch Manager | K4: 45658 | L4: =394710/3800 -> 103.87105
B5: APL-1368 | C5: Atino Carmen Obuku | D5: Female | E5: Commercial | F5: Branches - Nateete | G5: Assistant Branch Manager | H5: Commercial | I5: Branches - Nateete | J5: Branch Manager | K5: 45658 | L5: =530334/3800 -> 139.56158
B6: EXP-0162 | C6: Patel Krunalkumar Pravinbhai | D6: Male | E6: Commercial | F6: Branches -Soroti | G6: Assistant Branch Manager | H6: Commercial | I6: Branches -Soroti | J6: Branch Manager | K6: 45658 | L6: =393177/3800 -> 103.46763
B7: EXP-0193 | C7: Krishnam Sai Vamsi | D7: Male | E7: Commercial | F7: Branches-Ishaka | G7: Assistant Branch Manager | H7: Commercial | I7: Branches-Ishaka | J7: Branch Manager | K7: 45658 | L7: =294954/3800 -> 77.619474
B8: APL-2222 | C8: Mansuur Muwereza | D8: Male | E8: Finance | F8: Head Office | G8: Management Accountant | H8: Finance | I8: Head Office | J8: Chief Accountant | K8: 45658 | L8: =309225/3800 -> 81.375
B9: APL-196 | C9: Katusiime Agnes | D9: Female | E9: Human Resource | F9: Head Office | G9: Welfare Assistant-Catering | H9: Human Resource | I9: Head Office | J9: Catering Supervisor | K9: 45658 | L9: =54051/3800 -> 14.223947
B10: APL-1294 | C10: Oyeny Joseph Owen | D10: Male | E10: Supply Chain | F10: Head Office | G10: Logistics Officer | H10: Supply Chain | I10: Head Office | J10: Assistant Logistics Manager | K10: 45658 | L10: =157661/3800 -> 41.489737
B11: APL-1711 | C11: Ambrose Ongelech Levi | D11: Male | E11: Supply Chain | F11: Ware House | G11: Ware House Attendant | H11: Supply Chain | I11: Ware House | J11: Warehouse Supervisor | K11: 45658 | L11: =23601/3800 -> 6.2107895
B12: APL-1260 | C12: Kintu Mark | D12: Male | E12: Supply Chain | F12: Ware House | G12: Warehouse Ass. - Store Mgt | H12: Supply Chain | I12: Ware House | J12: Warehouse Supervisor | K12: 45658 | L12: =28759/3800 -> 7.5681579
B13: APL-1123 | C13: Ochom Benard | D13: Male | E13: Supply Chain | F13: Ware House | G13: Warehouse Ass. - Store Mgt | H13: Supply Chain | I13: Ware House | J13: Warehouse Supervisor | K13: 45658 | L13: =27322/3800 -> 7.19
B14: APL-1122 | C14: Okuni Moses | D14: Male | E14: Supply Chain | F14: Ware House | G14: Warehouse Ass. - Store Mgt | H14: Supply Chain | I14: Ware House | J14: Warehouse Supervisor | K14: 45658 | L14: =37474/3800 -> 9.8615789
B15: EXP-0173 | C15: Praveen Prasannakumar | D15: Male | E15: Supply Chain | F15: Ware House | G15: Assistant Manager- Warehouse | H15: Supply Chain | I15: Ware House | J15: Warehouse Manager | K15: 45658 | L15: =625551/3800 -> 164.61868
B16: APL-1222 | C16: Ssekamate John Paul | D16: Male | E16: Supply Chain | F16: Ware House | G16: Warehouse Ass. - Store Mgt | H16: Supply Chain | I16: Ware House | J16: Warehouse Supervisor | K16: 45658 | L16: =28619/3800 -> 7.5313158
B17: EXP-112 | C17: Harsh Indravadanbhai Mistry | D17: Male | E17: Commercial | F17: Warehouse - Sales | G17: Sales Executive - Company Sales | H17: Commercial | I17: Warehouse - Sales | J17: Sales Manager | K17: 45658 | L17: =765134/3800 -> 201.35105
B18: APL-2251 | C18: Yvonne Nakimuli | D18: Female | E18: Legal and Compliance | F18: Legal | G18: Legal and Compliance Manager | H18: Legal and Compliance | I18: Legal | J18: Group Legal and Compliance Manager | K18: 45658 | L18: 0
C19: Fredrick Ssanyu Lyamuzadde | D19: Male | E19: Finance | F19: Head Office | G19: Graduate Trainee-Accounts | H19: Finance | I19: Head Office | J19: Accounts Assistant | K19: 45748 | L19: =750000/3800 -> 197.36842
C20: Acidri Ayadi Amule | D20: Male | E20: Commercial | F20: Koboko Branch | G20: Branch Store Attedant | H20: Commercial | I20: Koboko Branch | J20: Counter Sales Representative | K20: 45778 | L20: =70173/3800 -> 18.466579
B21: APL-336 | C21: Babona Enock | D21: Male | E21: Commercial | F21: Entebbe Branch | G21: Branch Store Attedant | H21: Commercial | I21: Entebbe Branch | J21: Counter Sales Representative | K21: 45870 | L21: 29.25
B22: APL-2344 | C22: Naiwungu Elvis | D22: Male | E22: Commercial | F22: Busia Branch | G22: Branch Store Attedant | H22: Commercial | I22: Busia Branch | J22: Counter Sales Representative | K22: 45870 | L22: 131.57895
B23: EXP-097 | C23: Robert Kennet Franklin | D23: Male | E23: Commercial | F23: Namirembe-1 | G23: Branch Manager | H23: Commercial | I23: Head Office | J23: Regional Branch Manager | K23: 45901 | L23: =1157162/3800 -> 304.51632
B24: APL-2430 | C24: Musana Oliimi Joshua | D24: Male | E24: Supply Chain | F24: Warehouse | G24: Warehouse Attedant | H24: Supply Chain | I24: Warehouse | J24: Driver | K24: 45901 | L24: =210000/3800 -> 55.263158
B25: APL-2431 | C25: Ekadu Emmanuel | D25: Male | E25: Supply Chain | F25: Warehouse | G25: Warehouse Attedant | H25: Supply Chain | I25: Ware House | J25: Local Purchase Assistant- Invoicing | K25: 45901 | L25: =382307/3800 -> 100.60711
B26: APL-440 | C26: Enos Edonyu | D26: Male | E26: Commercial | F26: Mukwano Branch | G26: Branch Store Attedant | H26: Commercial | I26: Mukwano Branch | J26: Counter Sales Representative | K26: 45992 | L26: =96643/3800 -> 25.432368
B27: APL-267 | C27: Otim John | D27: Male | E27: Commercial | F27: Lira Branch | G27: Branch Store Attedant | H27: Commercial | I27: Lira Branch | J27: Counter Sales Representative | K27: 45992 | L27: =971766/3800 -> 255.72789
B28: EXP-0239 | C28: Moshin Khan | D28: Male | E28: Commercial | F28: Jinja Branch | G28: Assistant Branch Manager | H28: Commercial | I28: Soroti | J28: Branch Manager | K28: 46003 | L28: 0
A29: APL - Tanzania | B29: APL-0379 | C29: Joseph Michael Gingilyan | D29: Male | E29: Commercial | F29: Abacus Life Care | G29: Sales Representative | H29: Commercial | I29: Abacus Life Care | J29: Field Supervisor | K29: 45658
B30: APL-0430 | C30: Heri Nestor Mauki | D30: Male | E30: Commercial | F30: Kariakoo 1 Branch | G30: Ass. Branch Manager/Ftp | H30: Commercial | I30: Mpanda Branch | J30: Branch Manager | K30: 45658
B31: APL-0397 | C31: Doreen Mapenzi Yonah | D31: Female | E31: Commercial | F31: Kariakoo 2 Branch | G31: Ass. Branch Manager/Ftp | H31: Commercial | I31: Kariakoo 2 Branch | J31: Branch Manager/Ftp | K31: 45658
B32: APL-0432 | C32: Liberati Gabriael Masumbuko | D32: Male | E32: Commercial | F32: Kigoma Branch | G32: Ass. Branch Manager/Ftp | H32: Commercial | I32: Kigoma Branch | J32: Branch Manager/Ftp | K32: 45658
B33: APL-0459 | C33: Wilson Wilhelim Mariki | D33: Male | E33: Commercial | F33: Mbagala Branch | G33: Ass. Branch Manager/Ftp | H33: Commercial | I33: Mbagala Branch | J33: Branch Manager/Ftp | K33: 45658
B34: APL-0403 | C34: Athuman Masondole Madaraka | D34: Male | E34: Commercial | F34: Mbeya Branch | G34: Ass. Branch Manager/Ftp | H34: Commercial | I34: Ifakara Branch | J34: Branch Manager/Ftp | K34: 45658
B35: APL-0202 | C35: Ashraf Yusuph Roomy | D35: Male | E35: Commercial | F35: Mwanza Branch | G35: Asst. Branch Manager | H35: Commercial | I35: Kahama Branch | J35: Branch Manager | K35: 45658
B36: EXP-0030 | C36: Pranay Raj Alishetty | D36: Male | E36: Commercial | F36: Mwanza Branch | G36: Branch Manager | H36: Commercial | I36: Branches | J36: Assistant Regional Branch Development Manager | K36: 45962
A37: APL - Burundi | B37: APL-049 | C37: Manirakiza Micheline | D37: Female | E37: Commercial | F37: Head office | G37: Counter Sales Assistant | H37: Commercial | I37: Head office | J37: Assistant Branch Manager | K37: 45658
B38: APL-009 | C38: Sindaharaye Dieudonne | D38: Male | E38: Commercial | F38: Head office | G38: Tender Representative | H38: Commercial | I38: Head office | J38: Tender Manager | K38: 45658
B39: APL-0319 | C39: Manirakiza Fabrice | D39: Male | E39: Commercial | F39: Head office | G39: Medical Reprentative/ALC | H39: Commercial | I39: Head office | J39: Team Leader of Med Repr/ALC | K39: 45658
A40: APL - Kenya | B40: APL-0007 | C40: Gladys Anyango Owino | D40: Female | E40: Commercial | F40: APL Kenya | G40: Medical Representative | H40: Commercial | I40: APL Kenya | J40: Snr Medical Representative | K40: 45660 | L40: 92.31
B41: APL-0012 | C41: David J Ojwang | D41: Male | E41: Supply Chain | F41: APL Kenya | G41: Store Keeper/Deliveries | H41: Supply Chain | I41: APL Kenya | J41: Warehouse Assistant | K41: 45660 | L41: 46.15
A42: APDL | B42: APDL-01044 | C42: Kakooza Noah | D42: Male | E42: Quality | F42: Mukono | G42: Quality Control Analyst | H42: Quality | I42: Mukono | J42: Team Leader-Documentation | K42: 45664 | L42: 145
B43: APDL-01021 | C43: Asiimwe Grace | D43: Female | E43: Supply Chain | F43: Mukono | G43: Stores Chemist | H43: Supply Chain | I43: Mukono | J43: Asst Warehouse Manager | K43: 45691 | L43: 158
B44: APDL-00928 | C44: Ashok Kumar | D44: Male | E44: Information Technology | F44: Mukono | G44: Group Software Development Manager | H44: Information Technology | I44: Mukono | J44: Group ICT Manager | K44: 45779 | L44: 2092
B45: APDL-00934 | C45: Dennis Kabuye Donozio | D45: Male | E45: Production | F45: Mukono | G45: Production Officer | H45: Production | I45: Mukono | J45: Team Leader-Manufacturing | K45: 45810 | L45: 79
B46: APDL-854 | C46: Gumisiriza Nicholas | D46: Male | E46: Production | F46: Mukono | G46: Team Leader-Sterlization | H46: Production | I46: Mukono | J46: Shift Leader | K46: 45915 | L46: 238
B47: APDL-602 | C47: Bakasiima Abdallah | D47: Male | E47: Production | F47: Mukono | G47: Team Leader-BFS | H47: Production | I47: Mukono | J47: Shift Leader | K47: 45915 | L47: 176
B48: APDL-1031 | C48: Mugalu Julius Ntulume | D48: Male | E48: Production | F48: Mukono | G48: Production Officer | H48: Production | I48: Mukono | J48: Shift Leader | K48: 45915 | L48: 419
B49: APDL-554 | C49: Wampande Faisal | D49: Male | E49: Quality | F49: Mukono | G49: Team Leader-Ipqa | H49: Quality | I49: Mukono | J49: Quality Control Specialist | K49: 45923
